Workbook

Sheet Industry & Competitor Analysis
A1: Rasio-Rasio Keuangan Perusahaan Pupuk di Indonesia
B3: Rasio Keuangan Tahunan 2021-2025 (Berdasarkan 3 Perusahaan Pupuk di Indonesia) | I3: Rasio Keuangan 2021-2025 (Berdasarkan 4 Perusahaan Pupuk di Indonesia) | P3: Rasio Keuangan 2021-2025 (Berdasarkan 4 Perusahaan Pupuk di Indonesia) | W3: Rasio Keuangan 2021-2025 PT Pupuk Kalimatan Timur | AD3: Rasio Keuangan 2021-2025 PT Pupuk Kalimatan Timur | AK3: Rasio Keuangan 2021-2025 PT Pupuk Kalimatan Timur | AR3: Rasio Keuangan 2021-2025 PT Saraswati Anugerah Makmur Tbk | AY3: Rasio Keuangan 2021-2025 PT Saraswati Anugerah Makmur Tbk | BF3: Rasio Keuangan 2021-2025 PT Saraswati Anugerah Makmur Tbk | BM3: Rasio Keuangan 2021-2025 PT Delta Giri Wacana Tbk | BT3: Rasio Keuangan 2021-2025 PT Delta Giri Wacana Tbk | CA3: Rasio Keuangan 2021-2025 PT Delta Giri Wacana Tbk | CH3: Rasio Keuangan 2021-2025 PT Nusa Palapa Gemilang Tbk | CO3: Rasio Keuangan 2021-2025 PT Nusa Palapa Gemilang Tbk | CV3: Rasio Keuangan 2021-2025 PT Nusa Palapa Gemilang Tbk
B4: Metric | C4: Min | D4: Q1 / Lower Benchmark | E4: Median | F4: Q3 / Upper Benchmark | G4: Max | I4: Metric | J4: Min | K4: Q1 / Lower Benchmark | L4: Median | M4: Q3 / Upper Benchmark | N4: Max | P4: Metric | Q4: Min | R4: Q1 / Lower Benchmark | S4: Median | T4: Q3 / Upper Benchmark | U4: Max | W4: Metric | X4: Min | Y4: Q1 / Lower Benchmark | Z4: Median | AA4: Q3 / Upper Benchmark | AB4: Max | AD4: Metric | AE4: Min | AF4: Q1 / Lower Benchmark | AG4: Median | AH4: Q3 / Upper Benchmark | AI4: Max | AK4: Metric | AL4: Min | AM4: Q1 / Lower Benchmark | AN4: Median | AO4: Q3 / Upper Benchmark | AP4: Max | AR4: Metric | AS4: Min | AT4: Q1 / Lower Benchmark | AU4: Median | AV4: Q3 / Upper Benchmark | AW4: Max | AY4: Metric | AZ4: Min | BA4: Q1 / Lower Benchmark | BB4: Median | BC4: Q3 / Upper Benchmark | BD4: Max | BF4: Metric | BG4: Min | BH4: Q1 / Lower Benchmark | BI4: Median | BJ4: Q3 / Upper Benchmark | BK4: Max | BM4: Metric | BN4: Min | BO4: Q1 / Lower Benchmark | BP4: Median | BQ4: Q3 / Upper Benchmark | BR4: Max | BT4: Metric | BU4: Min | BV4: Q1 / Lower Benchmark | BW4: Median | BX4: Q3 / Upper Benchmark | BY4: Max | CA4: Metric | CB4: Min | CC4: Q1 / Lower Benchmark | CD4: Median | CE4: Q3 / Upper Benchmark | CF4: Max | CH4: Metric | CI4: Min | CJ4: Q1 / Lower Benchmark | CK4: Median | CL4: Q3 / Upper Benchmark | CM4: Max | CO4: Metric | CP4: Min | CQ4: Q1 / Lower Benchmark | CR4: Median | CS4: Q3 / Upper Benchmark | CT4: Max | CV4: Metric | CW4: Min | CX4: Q1 / Lower Benchmark | CY4: Median | CZ4: Q3 / Upper Benchmark | DA4: Max
B5: Gross Profit Margin (GPM) | C5: {=MIN(TOCOL(C15:G17,1))} -> -0.0077 | D5: {=_xlfn.QUARTILE.INC(TOCOL(C15:G17,1),1)} -> 0.2194 | E5: {=MEDIAN(TOCOL(C15:G17,1))} -> 0.2402 | F5: {=_xlfn.QUARTILE.INC(TOCOL(C15:G17,1),3)} -> 0.24855 | G5: {=MAX(TOCOL(C14:G17,1))} -> 0.2766 | I5: Current Ratio | J5: {=MIN(TOCOL(C42:G44,1))} -> 0.83 | K5: {=_xlfn.QUARTILE.INC(TOCOL(C42:G44,1),1)} -> 1.185 | L5: {=MEDIAN(TOCOL(C42:G44,1))} -> 1.39 | M5: {=_xlfn.QUARTILE.INC(TOCOL(C42:G44,1),3)} -> 2.015 | N5: {=MAX(TOCOL(C42:G44,1))} -> 5.18 | P5: DIO | Q5: {=MIN(TOCOL(C56:F59,1))} -> #REF! | R5: {=_xlfn.QUARTILE.INC(TOCOL(C56:F59,1),1)} -> #REF! | S5: {=MEDIAN(TOCOL(C56:F59,1))} -> #REF! | T5: {=_xlfn.QUARTILE.INC(TOCOL(C56:F59,1),3)} -> #REF! | U5: {=MAX(TOCOL(C56:F59,1))} -> #REF! | W5: Gross Profit Margin (GPM) | X5: =MIN(C14:G14) -> 0 | Y5: {=_xlfn.QUARTILE.INC(TOCOL(C14:G14,1),1)} -> #NUM! | Z5: {=MEDIAN(TOCOL(C14:G14,1))} -> #NUM! | AA5: {=_xlfn.QUARTILE.INC(TOCOL(C14:G14,1),3)} -> #NUM! | AB5: {=MAX(TOCOL(C14:G14,1))} -> 0 | AD5: Current Ratio | AE5: {=MIN(TOCOL(C41:G41,1))} -> 163 | AF5: {=_xlfn.QUARTILE.INC(TOCOL(C41:G41,1),1)} -> 204 | AG5: {=MEDIAN(TOCOL(C41:G41,1))} -> 245 | AH5: {=_xlfn.QUARTILE.INC(TOCOL(C41:G41,1),3)} -> 302 | AI5: {=MAX(TOCOL(C41:G41,1))} -> 310 | AK5: DIO | AL5: {=MIN(TOCOL(C56:G56,1))} -> 163 | AM5: {=_xlfn.QUARTILE.INC(TOCOL(C56:G56,1),1)} -> 204 | AN5: {=MEDIAN(TOCOL(C56:G56,1))} -> 245 | AO5: {=_xlfn.QUARTILE.INC(TOCOL(C56:G56,1),3)} -> 302 | AP5: {=MAX(TOCOL(C56:G56,1))} -> 310 | AR5: Gross Profit Margin (GPM) | AS5: {=MIN(TOCOL(C15:G15,1))} -> 0.2125 | AT5: {=_xlfn.QUARTILE.INC(TOCOL(C15:G15,1),1)} -> 0.2402 | AU5: {=MEDIAN(TOCOL(C15:G15,1))} -> 0.2452 | AV5: {=_xlfn.QUARTILE.INC(TOCOL(C15:G15,1),3)} -> 0.246 | AW5: {=MAX(TOCOL(C15:G15,1))} -> 0.2559 | AY5: Current Ratio | AZ5: {=MIN(TOCOL(C42:G42,1))} -> 1.39 | BA5: {=_xlfn.QUARTILE.INC(TOCOL(C42:G42,1),1)} -> 1.6 | BB5: {=MEDIAN(TOCOL(C42:G42,1))} -> 1.76 | BC5: {=_xlfn.QUARTILE.INC(TOCOL(C42:G42,1),3)} -> 1.98 | BD5: {=MAX(TOCOL(C42:G42,1))} -> 2.05 | BF5: DIO | BG5: {=MIN(TOCOL(C57:G57,1))} -> #REF! | BH5: {=_xlfn.QUARTILE.INC(TOCOL(C57:G57,1),1)} -> #REF! | BI5: {=MEDIAN(TOCOL(C57:G57,1))} -> #REF! | BJ5: {=_xlfn.QUARTILE.INC(TOCOL(C57:G57,1),3)} -> #REF! | BK5: {=MAX(TOCOL(C57:G57,1))} -> #REF! | BM5: Gross Profit Margin (GPM) | BN5: {=MIN(TOCOL(C16:G16,1))} -> 0.2263 | BO5: {=_xlfn.QUARTILE.INC(TOCOL(C16:G16,1),1)} -> 0.2321 | BP5: {=MEDIAN(TOCOL(C16:G16,1))} -> 0.2511 | BQ5: {=_xlfn.QUARTILE.INC(TOCOL(C16:G16,1),3)} -> 0.2675 | BR5: {=MAX(TOCOL(C16:G16,1))} -> 0.2766 | BT5: Current Ratio | BU5: {=MIN(TOCOL(C43:G43,1))} -> 1.02 | BV5: {=_xlfn.QUARTILE.INC(TOCOL(C43:G43,1),1)} -> 1.14 | BW5: {=MEDIAN(TOCOL(C43:G43,1))} -> 1.15 | BX5: {=_xlfn.QUARTILE.INC(TOCOL(C43:G43,1),3)} -> 1.22 | BY5: {=MAX(TOCOL(C43:G43,1))} -> 1.27 | CA5: DIO | CB5: {=MIN(TOCOL(C58:G58,1))} -> #REF! | CC5: {=_xlfn.QUARTILE.INC(TOCOL(C58:G58,1),1)} -> #REF! | CD5: {=MEDIAN(TOCOL(C58:G58,1))} -> #REF! | CE5: {=_xlfn.QUARTILE.INC(TOCOL(C58:G58,1),3)} -> #REF! | CF5: {=MAX(TOCOL(C58:G58,1))} -> #REF! | CH5: Gross Profit Margin (GPM) | CI5: {=MIN(TOCOL(C17:G17,1))} -> -0.0077 | CJ5: {=_xlfn.QUARTILE.INC(TOCOL(C17:G17,1),1)} -> 0.0318 | CK5: {=MEDIAN(TOCOL(C17:G17,1))} -> 0.1629 | CL5: {=_xlfn.QUARTILE.INC(TOCOL(C17:G17,1),3)} -> 0.2401 | CM5: {=MAX(TOCOL(C17:G17,1))} -> 0.2453 | CO5: Current Ratio | CP5: {=MIN(TOCOL(C44:G44,1))} -> 0.83 | CQ5: {=_xlfn.QUARTILE.INC(TOCOL(C44:G44,1),1)} -> 1.26 | CR5: {=MEDIAN(TOCOL(C44:G44,1))} -> 2.2 | CS5: {=_xlfn.QUARTILE.INC(TOCOL(C44:G44,1),3)} -> 2.99 | CT5: {=MAX(TOCOL(C44:G44,1))} -> 5.18 | CV5: DIO | CW5: {=MIN(TOCOL(C59:G59,1))} -> #REF! | CX5: {=_xlfn.QUARTILE.INC(TOCOL(C59:G59,1),1)} -> #REF! | CY5: {=MEDIAN(TOCOL(C59:G59,1))} -> #REF! | CZ5: {=_xlfn.QUARTILE.INC(TOCOL(C59:G59,1),3)} -> #REF! | DA5: {=MAX(TOCOL(C59:G59,1))} -> #REF!
B6: Operating Profit Margin (OPM) | C6: {=MIN(TOCOL(H15:L17,1))} -> -0.5802 | D6: {=_xlfn.QUARTILE.INC(TOCOL(H15:L17,1),1)} -> 0.05385 | E6: {=MEDIAN(TOCOL(H15:L17,1))} -> 0.0827 | F6: {=_xlfn.QUARTILE.INC(TOCOL(H15:L17,1),3)} -> 0.112 | G6: {=MAX(TOCOL(I14:L17,1))} -> 0.1394 | I6: Quick Ratio | J6: {=MIN(TOCOL(J42:N44,1))} -> 0.47 | K6: {=_xlfn.QUARTILE.INC(TOCOL(J42:N44,1),1)} -> 0.535 | L6: {=MEDIAN(TOCOL(J42:N44,1))} -> 0.72 | M6: {=_xlfn.QUARTILE.INC(TOCOL(J42:N44,1),3)} -> 1.195 | N6: {=MAX(TOCOL(J42:N44,1))} -> 2.58 | P6: DSO | Q6: {=MIN(TOCOL(J56:M59,1))} -> #REF! | R6: {=_xlfn.QUARTILE.INC(TOCOL(J56:M59,1),1)} -> #REF! | S6: {=MEDIAN(TOCOL(J56:M59,1))} -> #REF! | T6: {=_xlfn.QUARTILE.INC(TOCOL(J56:M59,1),3)} -> #REF! | U6: {=MAX(TOCOL(J56:M59,1))} -> #REF! | W6: Operating Profit Margin (OPM) | X6: {=MIN(TOCOL(H14:L14,1))} -> 0 | Y6: {=_xlfn.QUARTILE.INC(TOCOL(H14:L14,1),1)} -> #NUM! | Z6: {=MEDIAN(TOCOL(H14:L14,1))} -> #NUM! | AA6: {=_xlfn.QUARTILE.INC(TOCOL(H14:L14,1),3)} -> #NUM! | AB6: {=MAX(TOCOL(H14:L14,1))} -> 0 | AD6: Quick Ratio | AE6: {=MIN(TOCOL(J41:N41,1))} -> 163 | AF6: {=_xlfn.QUARTILE.INC(TOCOL(J41:N41,1),1)} -> 204 | AG6: {=MEDIAN(TOCOL(J41:N41,1))} -> 245 | AH6: {=_xlfn.QUARTILE.INC(TOCOL(J41:N41,1),3)} -> 302 | AI6: {=MAX(TOCOL(J41:N41,1))} -> 310 | AK6: DSO | AL6: {=MIN(TOCOL(J56:N56,1))} -> 163 | AM6: {=_xlfn.QUARTILE.INC(TOCOL(J56:N56,1),1)} -> 204 | AN6: {=MEDIAN(TOCOL(J56:N56,1))} -> 245 | AO6: {=_xlfn.QUARTILE.INC(TOCOL(J56:N56,1),3)} -> 302 | AP6: {=MAX(TOCOL(J56:N56,1))} -> 310 | AR6: Operating Profit Margin (OPM) | AS6: {=MIN(TOCOL(H15:L15,1))} -> 0.0998 | AT6: {=_xlfn.QUARTILE.INC(TOCOL(H15:L15,1),1)} -> 0.1242 | AU6: {=MEDIAN(TOCOL(H15:L15,1))} -> 0.1299 | AV6: {=_xlfn.QUARTILE.INC(TOCOL(H15:L15,1),3)} -> 0.1352 | AW6: {=MAX(TOCOL(H15:L15,1))} -> 0.1394 | AY6: Quick Ratio | AZ6: {=MIN(TOCOL(J42:N42,1))} -> 0.47 | BA6: {=_xlfn.QUARTILE.INC(TOCOL(J42:N42,1),1)} -> 0.68 | BB6: {=MEDIAN(TOCOL(J42:N42,1))} -> 0.72 | BC6: {=_xlfn.QUARTILE.INC(TOCOL(J42:N42,1),3)} -> 1.19 | BD6: {=MAX(TOCOL(J42:N42,1))} -> 1.2 | BF6: DSO | BG6: {=MIN(TOCOL(J57:N57,1))} -> #REF! | BH6: {=_xlfn.QUARTILE.INC(TOCOL(J57:N57,1),1)} -> #REF! | BI6: {=MEDIAN(TOCOL(J57:N57,1))} -> #REF! | BJ6: {=_xlfn.QUARTILE.INC(TOCOL(J57:N57,1),3)} -> #REF! | BK6: {=MAX(TOCOL(J57:N57,1))} -> #REF! | BM6: Operating Profit Margin (OPM) | BN6: {=MIN(TOCOL(H16:L16,1))} -> 0.0344 | BO6: {=_xlfn.QUARTILE.INC(TOCOL(H16:L16,1),1)} -> 0.0726 | BP6: {=MEDIAN(TOCOL(H16:L16,1))} -> 0.0827 | BQ6: {=_xlfn.QUARTILE.INC(TOCOL(H16:L16,1),3)} -> 0.0837 | BR6: {=MAX(TOCOL(H16:L16,1))} -> 0.0969 | BT6: Quick Ratio | BU6: {=MIN(TOCOL(J43:N43,1))} -> 0.48 | BV6: {=_xlfn.QUARTILE.INC(TOCOL(J43:N43,1),1)} -> 0.51 | BW6: {=MEDIAN(TOCOL(J43:N43,1))} -> 0.52 | BX6: {=_xlfn.QUARTILE.INC(TOCOL(J43:N43,1),3)} -> 0.59 | BY6: {=MAX(TOCOL(J43:N43,1))} -> 0.85 | CA6: DSO | CB6: {=MIN(TOCOL(J58:N58,1))} -> #REF! | CC6: {=_xlfn.QUARTILE.INC(TOCOL(J58:N58,1),1)} -> #REF! | CD6: {=MEDIAN(TOCOL(J58:N58,1))} -> #REF! | CE6: {=_xlfn.QUARTILE.INC(TOCOL(J58:N58,1),3)} -> #REF! | CF6: {=MAX(TOCOL(J58:N58,1))} -> #REF! | CH6: Operating Profit Margin (OPM) | CI6: {=MIN(TOCOL(H17:L17,1))} -> -0.5802 | CJ6: {=_xlfn.QUARTILE.INC(TOCOL(H17:L17,1),1)} -> -0.2039 | CK6: {=MEDIAN(TOCOL(H17:L17,1))} -> 0.047 | CL6: {=_xlfn.QUARTILE.INC(TOCOL(H17:L17,1),3)} -> 0.0607 | CM6: {=MAX(TOCOL(H17:L17,1))} -> 0.0658 | CO6: Quick Ratio | CP6: {=MIN(TOCOL(J44:N44,1))} -> 0.55 | CQ6: {=_xlfn.QUARTILE.INC(TOCOL(J44:N44,1),1)} -> 0.83 | CR6: {=MEDIAN(TOCOL(J44:N44,1))} -> 1.39 | CS6: {=_xlfn.QUARTILE.INC(TOCOL(J44:N44,1),3)} -> 1.68 | CT6: {=MAX(TOCOL(J44:N44,1))} -> 2.58 | CV6: DSO | CW6: {=MIN(TOCOL(J59:N59,1))} -> #REF! | CX6: {=_xlfn.QUARTILE.INC(TOCOL(J59:N59,1),1)} -> #REF! | CY6: {=MEDIAN(TOCOL(J59:N59,1))} -> #REF! | CZ6: {=_xlfn.QUARTILE.INC(TOCOL(J59:N59,1),3)} -> #REF! | DA6: {=MAX(TOCOL(J59:N59,1))} -> #REF!
B7: Net Profit Margin (NPM) | C7: {=MIN(TOCOL(M15:Q17,1))} -> -0.2477 | D7: {=_xlfn.QUARTILE.INC(TOCOL(M15:Q16,1),1)} -> 0.0544 | E7: {=MEDIAN(TOCOL(N15:Q17,1))} -> 0.0688 | F7: {=_xlfn.QUARTILE.INC(TOCOL(M15:Q17,1),3)} -> 0.0868 | G7: {=MAX(TOCOL(M14:Q17,1))} -> 1.1501 | I7: Inventory Turnover | J7: {=MIN(TOCOL(C50:G52,1))} -> 0.68 | K7: {=_xlfn.QUARTILE.INC(TOCOL(C50:G52,1),1)} -> 2.195 | L7: {=MEDIAN(TOCOL(C50:G52,1))} -> 2.395 | M7: {=_xlfn.QUARTILE.INC(TOCOL(C50:G52,1),3)} -> 2.55 | N7: {=MAX(TOCOL(C50:G52,1))} -> 4.1 | P7: DPO | Q7: {=MIN(TOCOL(C63:F66,1))} -> #REF! | R7: {=_xlfn.QUARTILE.INC(TOCOL(C63:F66,1),1)} -> #REF! | S7: {=MEDIAN(TOCOL(C63:F66,1))} -> #REF! | T7: {=_xlfn.QUARTILE.INC(TOCOL(C63:F66,1),3)} -> #REF! | U7: {=MAX(TOCOL(C63:F66,1))} -> #REF! | W7: Net Profit Margin (NPM) | X7: {=MIN(TOCOL(M14:Q14,1))} -> 0 | Y7: {=_xlfn.QUARTILE.INC(TOCOL(M14:Q14,1),1)} -> #NUM! | Z7: {=MEDIAN(TOCOL(M14:Q14,1))} -> #NUM! | AA7: {=_xlfn.QUARTILE.INC(TOCOL(M14:Q14,1),3)} -> #NUM! | AB7: {=MAX(TOCOL(M14:Q14,1))} -> 0 | AD7: Inventory Turnover | AE7: {=MIN(TOCOL(C49:G49,1))} -> 163 | AF7: {=_xlfn.QUARTILE.INC(TOCOL(C49:G49,1),1)} -> 204 | AG7: {=MEDIAN(TOCOL(C49:G49,1))} -> 245 | AH7: {=_xlfn.QUARTILE.INC(TOCOL(C49:G49,1),3)} -> 302 | AI7: {=MAX(TOCOL(C49:G49,1))} -> 310 | AK7: DPO | AL7: {=MIN(TOCOL(C63:G63,1))} -> 163 | AM7: {=_xlfn.QUARTILE.INC(TOCOL(C63:G63,1),1)} -> 204 | AN7: {=MEDIAN(TOCOL(C63:G63,1))} -> 245 | AO7: {=_xlfn.QUARTILE.INC(TOCOL(C63:G63,1),3)} -> 302 | AP7: {=MAX(TOCOL(C63:G63,1))} -> 310 | AR7: Net Profit Margin (NPM) | AS7: {=MIN(TOCOL(M15:Q15,1))} -> 0.0627 | AT7: {=_xlfn.QUARTILE.INC(TOCOL(M15:Q15,1),1)} -> 0.079 | AU7: {=MEDIAN(TOCOL(M15:Q15,1))} -> 0.0893 | AV7: {=_xlfn.QUARTILE.INC(TOCOL(M15:Q15,1),3)} -> 0.0906 | AW7: {=MAX(TOCOL(M15:Q15,1))} -> 0.091 | AY7: Inventory Turnover | AZ7: {=MIN(TOCOL(C50:G50,1))} -> 2.3 | BA7: {=_xlfn.QUARTILE.INC(TOCOL(C50:G50,1),1)} -> 2.31 | BB7: {=MEDIAN(TOCOL(C50:G50,1))} -> 2.42 | BC7: {=_xlfn.QUARTILE.INC(TOCOL(C50:G50,1),3)} -> 3.37 | BD7: {=MAX(TOCOL(C50:G50,1))} -> 3.6 | BF7: DPO | BG7: {=MIN(TOCOL(C64:G64,1))} -> #REF! | BH7: {=_xlfn.QUARTILE.INC(TOCOL(C64:G64,1),1)} -> #REF! | BI7: {=MEDIAN(TOCOL(C64:G64,1))} -> #REF! | BJ7: {=_xlfn.QUARTILE.INC(TOCOL(C64:G64,1),3)} -> #REF! | BK7: {=MAX(TOCOL(C64:G64,1))} -> #REF! | BM7: Net Profit Margin (NPM) | BN7: {=MIN(TOCOL(M16:Q16,1))} -> 0.005 | BO7: {=_xlfn.QUARTILE.INC(TOCOL(M16:Q16,1),1)} -> 0.0528 | BP7: {=MEDIAN(TOCOL(M16:Q16,1))} -> 0.053 | BQ7: {=_xlfn.QUARTILE.INC(TOCOL(M16:Q16,1),3)} -> 0.0586 | BR7: {=MAX(TOCOL(M16:Q16,1))} -> 0.0843 | BT7: Inventory Turnover | BU7: {=MIN(TOCOL(C51:G51,1))} -> 2.16 | BV7: {=_xlfn.QUARTILE.INC(TOCOL(C51:G51,1),1)} -> 2.3175 | BW7: {=MEDIAN(TOCOL(C51:G51,1))} -> 2.415 | BX7: {=_xlfn.QUARTILE.INC(TOCOL(C51:G51,1),3)} -> 2.49 | BY7: {=MAX(TOCOL(C51:G51,1))} -> 2.58 | CA7: DPO | CB7: {=MIN(TOCOL(C65:G65,1))} -> #REF! | CC7: {=_xlfn.QUARTILE.INC(TOCOL(C65:G65,1),1)} -> #REF! | CD7: {=MEDIAN(TOCOL(C65:G65,1))} -> #REF! | CE7: {=_xlfn.QUARTILE.INC(TOCOL(C65:G65,1),3)} -> #REF! | CF7: {=MAX(TOCOL(C65:G65,1))} -> #REF! | CH7: Net Profit Margin (NPM) | CI7: {=MIN(TOCOL(M17:Q17,1))} -> -0.2477 | CJ7: {=_xlfn.QUARTILE.INC(TOCOL(M17:Q17,1),1)} -> 0.0122 | CK7: {=MEDIAN(TOCOL(M17:Q17,1))} -> 0.0178 | CL7: {=_xlfn.QUARTILE.INC(TOCOL(M17:Q17,1),3)} -> 0.0192 | CM7: {=MAX(TOCOL(M17:Q17,1))} -> 1.1501 | CO7: Inventory Turnover | CP7: {=MIN(TOCOL(C52:G52,1))} -> 0.68 | CQ7: {=_xlfn.QUARTILE.INC(TOCOL(C52:G52,1),1)} -> 1.29 | CR7: {=MEDIAN(TOCOL(C52:G52,1))} -> 1.87 | CS7: {=_xlfn.QUARTILE.INC(TOCOL(C52:G52,1),3)} -> 2.42 | CT7: {=MAX(TOCOL(C52:G52,1))} -> 4.1 | CV7: DPO | CW7: {=MIN(TOCOL(C66:G66,1))} -> #REF! | CX7: {=_xlfn.QUARTILE.INC(TOCOL(C66:G66,1),1)} -> #REF! | CY7: {=MEDIAN(TOCOL(C66:G66,1))} -> #REF! | CZ7: {=_xlfn.QUARTILE.INC(TOCOL(C66:G66,1),3)} -> #REF! | DA7: {=MAX(TOCOL(C66:G66,1))} -> #REF!
B8: EBITDA Margin | C8: {=MIN(TOCOL(C78:G80,1))} -> -0.5108 | D8: {=_xlfn.QUARTILE.INC(TOCOL(C78:G80,1),1)} -> 0.07305 | E8: {=MEDIAN(TOCOL(C78:G80,1))} -> 0.0896 | F8: {=_xlfn.QUARTILE.INC(TOCOL(C78:G80,1),3)} -> 0.12095 | G8: {=MAX(TOCOL(C77:G80,1))} -> 55.01 | I8: Debt to Equity Ratio (DER) | J8: {=MIN(TOCOL(J50:N52,1))} -> 0.12 | K8: {=_xlfn.QUARTILE.INC(TOCOL(J50:N52,1),1)} -> 0.5 | L8: {=MEDIAN(TOCOL(J50:N52,1))} -> 0.66 | M8: {=_xlfn.QUARTILE.INC(TOCOL(J50:N52,1),3)} -> 0.975 | N8: {=MAX(TOCOL(J50:N52,1))} -> 1.45 | P8: CCC | Q8: {=MIN(TOCOL(J63:M66,1))} -> #REF! | R8: {=_xlfn.QUARTILE.INC(TOCOL(J63:M66,1),1)} -> #REF! | S8: {=MEDIAN(TOCOL(J63:M66,1))} -> #REF! | T8: {=_xlfn.QUARTILE.INC(TOCOL(J63:M66,1),3)} -> #REF! | U8: {=MAX(TOCOL(I63:N66,1))} -> #REF! | W8: EBITDA Margin | X8: {=MIN(TOCOL(C77:G77,1))} -> 24.45 | Y8: {=_xlfn.QUARTILE.INC(TOCOL(C77:G77,1),1)} -> 28 | Z8: {=MEDIAN(TOCOL(C77:G77,1))} -> 32.02 | AA8: {=_xlfn.QUARTILE.INC(TOCOL(C77:G77,1),3)} -> 38.21 | AB8: {=MAX(TOCOL(X77:AB80,1))} -> 0.1958 | AD8: Debt to Equity Ratio (DER) | AE8: {=MIN(TOCOL(J49:N49,1))} -> 163 | AF8: {=_xlfn.QUARTILE.INC(TOCOL(J49:N49,1),1)} -> 204 | AG8: {=MEDIAN(TOCOL(J49:N49,1))} -> 245 | AH8: {=_xlfn.QUARTILE.INC(TOCOL(J49:N49,1),3)} -> 302 | AI8: {=MAX(TOCOL(J49:N49,1))} -> 310 | AK8: CCC | AL8: {=MIN(TOCOL(J63:N63,1))} -> 163 | AM8: {=_xlfn.QUARTILE.INC(TOCOL(J63:N63,1),1)} -> 204 | AN8: {=MEDIAN(TOCOL(J63:N63,1))} -> 245 | AO8: {=_xlfn.QUARTILE.INC(TOCOL(J63:N63,1),3)} -> 302 | AP8: {=MAX(TOCOL(J63:N63,1))} -> 310 | AR8: EBITDA Margin | AS8: {=MIN(TOCOL(C78:G78,1))} -> 0.1103 | AT8: {=_xlfn.QUARTILE.INC(TOCOL(C78:G78,1),1)} -> 0.1316 | AU8: {=MEDIAN(TOCOL(C78:G78,1))} -> 0.1417 | AV8: {=_xlfn.QUARTILE.INC(TOCOL(C78:G78,1),3)} -> 0.1426 | AW8: {=MAX(TOCOL(C78:G78,1))} -> 0.146 | AY8: Debt to Equity Ratio (DER) | AZ8: {=MIN(TOCOL(J50:N50,1))} -> 0.41 | BA8: {=_xlfn.QUARTILE.INC(TOCOL(J50:N50,1),1)} -> 0.5 | BB8: {=MEDIAN(TOCOL(J50:N50,1))} -> 0.57 | BC8: {=_xlfn.QUARTILE.INC(TOCOL(J50:N50,1),3)} -> 0.62 | BD8: {=MAX(TOCOL(J50:N50,1))} -> 0.74 | BF8: CCC | BG8: {=MIN(TOCOL(J64:N64,1))} -> #REF! | BH8: {=_xlfn.QUARTILE.INC(TOCOL(J64:N64,1),1)} -> #REF! | BI8: {=MEDIAN(TOCOL(J64:N64,1))} -> #REF! | BJ8: {=_xlfn.QUARTILE.INC(TOCOL(J64:N64,1),3)} -> #REF! | BK8: {=MAX(TOCOL(J64:N64,1))} -> #REF! | BM8: EBITDA Margin | BN8: {=MIN(TOCOL(C79:G79,1))} -> 0.0404 | BO8: {=_xlfn.QUARTILE.INC(TOCOL(C79:G79,1),1)} -> 0.0783 | BP8: {=MEDIAN(TOCOL(C79:G79,1))} -> 0.0893 | BQ8: {=_xlfn.QUARTILE.INC(TOCOL(C79:G79,1),3)} -> 0.0896 | BR8: {=MAX(TOCOL(C79:G79,1))} -> 0.1043 | BT8: Debt to Equity Ratio (DER) | BU8: {=MIN(TOCOL(J51:N51,1))} -> 0.8 | BV8: {=_xlfn.QUARTILE.INC(TOCOL(J51:N51,1),1)} -> 1.03 | BW8: {=MEDIAN(TOCOL(J51:N51,1))} -> 1.14 | BX8: {=_xlfn.QUARTILE.INC(TOCOL(J51:N51,1),3)} -> 1.28 | BY8: {=MAX(TOCOL(J51:N51,1))} -> 1.45 | CA8: CCC | CB8: {=MIN(TOCOL(J65:N65,1))} -> #REF! | CC8: {=_xlfn.QUARTILE.INC(TOCOL(J65:N65,1),1)} -> #REF! | CD8: {=MEDIAN(TOCOL(J65:N65,1))} -> #REF! | CE8: {=_xlfn.QUARTILE.INC(TOCOL(J65:N65,1),3)} -> #REF! | CF8: {=MAX(TOCOL(J65:N65,1))} -> #REF! | CH8: EBITDA Margin | CI8: {=MIN(TOCOL(C80:G80,1))} -> -0.5108 | CJ8: {=_xlfn.QUARTILE.INC(TOCOL(C80:G80,1),1)} -> -0.1457 | CK8: {=MEDIAN(TOCOL(C80:G80,1))} -> 0.0678 | CL8: {=_xlfn.QUARTILE.INC(TOCOL(C80:G80,1),3)} -> 0.0845 | CM8: {=MAX(TOCOL(C80:G80,1))} -> 0.0944 | CO8: Debt to Equity Ratio (DER) | CP8: {=MIN(TOCOL(J52:N52,1))} -> 0.12 | CQ8: {=_xlfn.QUARTILE.INC(TOCOL(J52:N52,1),1)} -> 0.31 | CR8: {=MEDIAN(TOCOL(J52:N52,1))} -> 0.5 | CS8: {=_xlfn.QUARTILE.INC(TOCOL(J52:N52,1),3)} -> 0.66 | CT8: {=MAX(TOCOL(J52:N52,1))} -> 0.92 | CV8: CCC | CW8: {=MIN(TOCOL(J66:N66,1))} -> #REF! | CX8: {=_xlfn.QUARTILE.INC(TOCOL(J66:N66,1),1)} -> #REF! | CY8: {=MEDIAN(TOCOL(J66:N66,1))} -> #REF! | CZ8: {=_xlfn.QUARTILE.INC(TOCOL(J66:N66,1),3)} -> #REF! | DA8: {=MAX(TOCOL(J66:N66,1))} -> #REF!
B9: ROA | C9: {=MIN(TOCOL(R15:V17,1))} -> -0.0592 | D9: {=_xlfn.QUARTILE.INC(TOCOL(R15:V17,1),1)} -> 0.0215 | E9: {=MEDIAN(TOCOL(R15:V17,1))} -> 0.0481 | F9: {=_xlfn.QUARTILE.INC(TOCOL(R15:V17,1),3)} -> 0.09105 | G9: {=MAX(TOCOL(R14:V17,1))} -> 0.1335 | P9: NWC | Q9: {=MIN(TOCOL(C70:F73,1))} -> #REF! | R9: {=_xlfn.QUARTILE.INC(TOCOL(C70:F73,1),1)} -> #REF! | S9: {=MEDIAN(TOCOL(C70:F73,1))} -> #REF! | T9: {=_xlfn.QUARTILE.INC(TOCOL(C70:F73,1),3)} -> #REF! | U9: {=MAX(TOCOL(C70:F73,1))} -> #REF! | W9: ROA | X9: {=MIN(TOCOL(R14:V14,1))} -> 0 | Y9: {=_xlfn.QUARTILE.INC(TOCOL(R14:V14,1),1)} -> #NUM! | Z9: {=MEDIAN(TOCOL(R14:V14,1))} -> #NUM! | AA9: {=_xlfn.QUARTILE.INC(TOCOL(R14:V14,1),3)} -> #NUM! | AB9: {=MAX(TOCOL(R14:V14,1))} -> 0 | AK9: NWC | AL9: {=MIN(TOCOL(C70:G70,1))} -> #REF! | AM9: {=_xlfn.QUARTILE.INC(TOCOL(C70:G70,1),1)} -> #REF! | AN9: {=MEDIAN(TOCOL(C70:G70,1))} -> #REF! | AO9: {=_xlfn.QUARTILE.INC(TOCOL(C70:G70,1),3)} -> #REF! | AP9: {=MAX(TOCOL(C70:G70,1))} -> #REF! | AR9: ROA | AS9: {=MIN(TOCOL(R15:V15,1))} -> 0.0852 | AT9: {=_xlfn.QUARTILE.INC(TOCOL(R15:V15,1),1)} -> 0.0969 | AU9: {=MEDIAN(TOCOL(R15:V15,1))} -> 0.128 | AV9: {=_xlfn.QUARTILE.INC(TOCOL(R15:V15,1),3)} -> 0.1323 | AW9: {=MAX(TOCOL(R15:V15,1))} -> 0.1335 | BF9: NWC | BG9: {=MIN(TOCOL(C71:G71,1))} -> #REF! | BH9: {=_xlfn.QUARTILE.INC(TOCOL(C71:G71,1),1)} -> #REF! | BI9: {=MEDIAN(TOCOL(C71:G71,1))} -> #REF! | BJ9: {=_xlfn.QUARTILE.INC(TOCOL(C71:G71,1),3)} -> #REF! | BK9: {=MAX(TOCOL(C71:G71,1))} -> #REF! | BM9: ROA | BN9: {=MIN(TOCOL(R16:V16,1))} -> 0 | BO9: {=_xlfn.QUARTILE.INC(TOCOL(R16:V16,1),1)} -> 0.0283 | BP9: {=MEDIAN(TOCOL(R16:V16,1))} -> 0.0481 | BQ9: {=_xlfn.QUARTILE.INC(TOCOL(R16:V16,1),3)} -> 0.0654 | BR9: {=MAX(TOCOL(R16:V16,1))} -> 0.0722 | CA9: NWC | CB9: {=MIN(TOCOL(C72:F72,1))} -> #REF! | CC9: {=_xlfn.QUARTILE.INC(TOCOL(C72:F72,1),1)} -> #REF! | CD9: {=MEDIAN(TOCOL(C72:F72,1))} -> #REF! | CE9: {=_xlfn.QUARTILE.INC(TOCOL(C72:F72,1),3)} -> #REF! | CF9: {=MAX(TOCOL(C72:F72,1))} -> #REF! | CH9: ROA | CI9: {=MIN(TOCOL(R17:V17,1))} -> -0.0592 | CJ9: {=_xlfn.QUARTILE.INC(TOCOL(R17:V17,1),1)} -> -0.0513 | CK9: {=MEDIAN(TOCOL(R17:V17,1))} -> 0.0195 | CL9: {=_xlfn.QUARTILE.INC(TOCOL(R17:V17,1),3)} -> 0.0235 | CM9: {=MAX(TOCOL(R17:V17,1))} -> 0.0373 | CV9: NWC | CW9: {=MIN(TOCOL(C73:G73,1))} -> #REF! | CX9: {=_xlfn.QUARTILE.INC(TOCOL(C73:G73,1),1)} -> #REF! | CY9: {=MEDIAN(TOCOL(C73:G73,1))} -> #REF! | CZ9: {=_xlfn.QUARTILE.INC(TOCOL(C73:G73,1),3)} -> #REF! | DA9: {=MAX(TOCOL(C73:G73,1))} -> #REF!
B10: ROE | C10: {=MIN(TOCOL(W15:AA17,1))} -> -0.1998 | D10: {=_xlfn.QUARTILE.INC(TOCOL(W15:AA17,1),1)} -> 0.0212 | E10: {=MEDIAN(TOCOL(W15:AA17,1))} -> 0.208 | F10: {=_xlfn.QUARTILE.INC(TOCOL(W15:AA17,1),3)} -> 0.2835 | G10: {=MAX(TOCOL(W14:AA17,1))} -> 0.3527 | W10: ROE | X10: {=MIN(TOCOL(W14:AA14,1))} -> 0 | Y10: {=_xlfn.QUARTILE.INC(TOCOL(W14:AA14,1),1)} -> #NUM! | Z10: {=MEDIAN(TOCOL(W14:AA14,1))} -> #NUM! | AA10: {=_xlfn.QUARTILE.INC(TOCOL(W14:AA14,1),3)} -> #NUM! | AB10: {=MAX(TOCOL(W14:AA14,1))} -> 0 | AR10: ROE | AS10: {=MIN(TOCOL(W14:AA14,1))} -> 0 | AT10: {=_xlfn.QUARTILE.INC(TOCOL(W14:AA14,1),1)} -> #NUM! | AU10: {=MEDIAN(TOCOL(W14:AA14,1))} -> #NUM! | AV10: {=_xlfn.QUARTILE.INC(TOCOL(W14:AA14,1),3)} -> #NUM! | AW10: {=MAX(TOCOL(W14:AA14,1))} -> 0 | BM10: ROE | BN10: {=MIN(TOCOL(W16:AA16,1))} -> 0 | BO10: {=_xlfn.QUARTILE.INC(TOCOL(W16:AA16,1),1)} -> 0.0316 | BP10: {=MEDIAN(TOCOL(W16:AA16,1))} -> 0.2393 | BQ10: {=_xlfn.QUARTILE.INC(TOCOL(W16:AA16,1),3)} -> 0.242 | BR10: {=MAX(TOCOL(W16:AA16,1))} -> 0.3527 | CH10: ROE | CI10: {=MIN(TOCOL(W17:AA17,1))} -> -0.1998 | CJ10: {=_xlfn.QUARTILE.INC(TOCOL(W17:AA17,1),1)} -> 0.0128 | CK10: {=MEDIAN(TOCOL(W17:AA17,1))} -> 0.0183 | CL10: {=_xlfn.QUARTILE.INC(TOCOL(W17:AA17,1),3)} -> 0.0241 | CM10: {=MAX(TOCOL(W17:AA17,1))} -> 0.2972
B12: Profitability Ratio
B13: Competitor Name | C13: GPM 2025 | D13: GPM 2024 | E13: GPM 2023 | F13: GPM 2022 | G13: GPM 2021 | H13: OPM 2025 | I13: OPM 2024 | J13: OPM 2023 | K13: OPM 2022 | L13: OPM 2021 | M13: NPM 2025 | N13: NPM 2024 | O13: NPM 2023 | P13: NPM 2022 | Q13: NPM 2021 | R13: ROA 2025 | S13: ROA 2024 | T13: ROA 2023 | U13: ROA 2022 | V13: ROA 2021 | W13: ROE 2025 | X13: ROE 2024 | Y13: ROE 2023 | Z13: ROE 2022 | AA13: ROE 2021
B14: PT Pupuk Kalimatan Timur
B15: PT Saraswati Anugerah Makmur Tbk | C15: =D118 -> 0.2125 | D15: =E118 -> 0.246 | E15: =F118 -> 0.2452 | F15: =G118 -> 0.2402 | G15: =H118 -> 0.2559 | H15: =D119 -> 0.0998 | I15: =E119 -> 0.1242 | J15: =F119 -> 0.1352 | K15: =G119 -> 0.1394 | L15: =H119 -> 0.1299 | M15: =D120 -> 0.0627 | N15: =E120 -> 0.079 | O15: =F120 -> 0.091 | P15: =G120 -> 0.0906 | Q15: =H120 -> 0.0893 | R15: =AB112 -> 0.0852 | S15: =AC112 -> 0.1335 | T15: =AD112 -> 0.128 | U15: =AE112 -> 0.1323 | V15: =AF112 -> 0.0969 | W15: =AB111 -> 0.1551 | X15: =AC111 -> 0.2698 | Y15: =AD111 -> 0.336 | Z15: =AE111 -> 0.349 | AA15: =AF111 -> 0.208
B16: PT Delta Giri Wacana Tbk | C16: =D256 -> 0.2675 | D16: =E256 -> 0.2766 | E16: =F256 -> 0.2321 | F16: =G256 -> 0.2263 | G16: =H256 -> 0.2511 | H16: =D257 -> 0.0969 | I16: =E257 -> 0.0827 | J16: =F257 -> 0.0344 | K16: =G257 -> 0.0726 | L16: =H257 -> 0.0837 | M16: =D258 -> 0.0528 | N16: =E258 -> 0.053 | O16: =F258 -> 0.005 | P16: =G258 -> 0.0843 | Q16: =H258 -> 0.0586 | R16: =AB246 -> 0.0722 | S16: =AC246 -> 0.0654 | T16: =AD246 -> 0.0283 | U16: =AE246 -> 0.0481 | V16: 0 | W16: =AB245 -> 0.2393 | X16: =AC245 -> 0.242 | Y16: =AD245 -> 0.0316 | Z16: =AE245 -> 0.3527 | AA16: 0
B17: PT Nusa Palapa Gemilang Tbk | C17: =D431 -> 0.2401 | D17: =E431 -> 0.2453 | E17: =F431 -> 0.0318 | F17: =G431 -> -0.0077 | G17: =H431 -> 0.1629 | H17: =D432 -> 0.047 | I17: =E432 -> 0.0658 | J17: =F432 -> -0.5802 | K17: =G432 -> -0.2039 | L17: =H432 -> 0.0607 | M17: =D433 -> 0.0192 | N17: =E433 -> 0.0178 | O17: =F433 -> 1.1501 | P17: =G433 -> -0.2477 | Q17: =H433 -> 0.0122 | R17: =AB424 -> 0.0195 | S17: =AC424 -> 0.0235 | T17: =AD424 -> -0.0592 | U17: =AE424 -> -0.0513 | V17: =AF424 -> 0.0373 | W17: =AB423 -> 0.0183 | X17: =AC423 -> 0.0128 | Y17: =AD423 -> 0.2972 | Z17: =AE423 -> -0.1998 | AA17: =AF423 -> 0.0241
B19: Rasio Keuangan Quartal 2023-2026 (Berdasarkan 3 Perusahaan Pupuk di Indonesia) | I19: Rasio Keuangan Quartal 2023-2026 (Berdasarkan 3 Perusahaan Pupuk di Indonesia) | P19: Rasio Keuangan Quartal 2023-2026 (Berdasarkan 3 Perusahaan Pupuk di Indonesia) | W19: Rasio Keuangan Quartal 2023-2026 (PT Pupuk Kalimatan Timur) | AD19: Rasio Keuangan Quartal 2023-2026 (PT Pupuk Kalimatan Timur) | AK19: Rasio Keuangan Quartal 2023-2026 (PT Pupuk Kalimatan Timur) | AR19: Rasio Keuangan Quartal 2023-2026 (PT Saraswati Anugerah Makmur Tbk) | AY19: Rasio Keuangan Quartal 2023-2026 (PT Saraswati Anugerah Makmur Tbk) | BF19: Rasio Keuangan Quartal 2023-2026 (PT Saraswati Anugerah Makmur Tbk) | BM19: Rasio Keuangan Quartal 2023-2026 (PT Delta Giri Wacana Tbk) | BT19: Rasio Keuangan Quartal 2023-2026 (PT Delta Giri Wacana Tbk) | CA19: Rasio Keuangan Quartal 2023-2026 (PT Delta Giri Wacana Tbk) | CH19: Rasio Keuangan Quartal 2023-2026 (PT Nusa Palapa Gemilang Tbk) | CO19: Rasio Keuangan Quartal 2023-2026 (PT Nusa Palapa Gemilang Tbk) | CV19: Rasio Keuangan Quartal 2023-2026 (PT Nusa Palapa Gemilang Tbk)
B20: Metric | C20: Min | D20: Q1 / Lower Benchmark | E20: Median | F20: Q3 / Upper Benchmark | G20: Max | I20: Metric | J20: Min | K20: Q1 / Lower Benchmark | L20: Median | M20: Q3 / Upper Benchmark | N20: Max | P20: Metric | Q20: Min | R20: Q1 / Lower Benchmark | S20: Median | T20: Q3 / Upper Benchmark | U20: Max | W20: Metric | X20: Min | Y20: Q1 / Lower Benchmark | Z20: Median | AA20: Q3 / Upper Benchmark | AB20: Max | AD20: Metric | AE20: Min | AF20: Q1 / Lower Benchmark | AG20: Median | AH20: Q3 / Upper Benchmark | AI20: Max | AK20: Metric | AL20: Min | AM20: Q1 / Lower Benchmark | AN20: Median | AO20: Q3 / Upper Benchmark | AP20: Max | AR20: Metric | AS20: Min | AT20: Q1 / Lower Benchmark | AU20: Median | AV20: Q3 / Upper Benchmark | AW20: Max | AY20: Metric | AZ20: Min | BA20: Q1 / Lower Benchmark | BB20: Median | BC20: Q3 / Upper Benchmark | BD20: Max | BF20: Metric | BG20: Min | BH20: Q1 / Lower Benchmark | BI20: Median | BJ20: Q3 / Upper Benchmark | BK20: Max | BM20: Metric | BN20: Min | BO20: Q1 / Lower Benchmark | BP20: Median | BQ20: Q3 / Upper Benchmark | BR20: Max | BT20: Metric | BU20: Min | BV20: Q1 / Lower Benchmark | BW20: Median | BX20: Q3 / Upper Benchmark | BY20: Max | CA20: Metric | CB20: Min | CC20: Q1 / Lower Benchmark | CD20: Median | CE20: Q3 / Upper Benchmark | CF20: Max | CH20: Metric | CI20: Min | CJ20: Q1 / Lower Benchmark | CK20: Median | CL20: Q3 / Upper Benchmark | CM20: Max | CO20: Metric | CP20: Min | CQ20: Q1 / Lower Benchmark | CR20: Median | CS20: Q3 / Upper Benchmark | CT20: Max | CV20: Metric | CW20: Min | CX20: Q1 / Lower Benchmark | CY20: Median | CZ20: Q3 / Upper Benchmark | DA20: Max
B21: Gross Profit Margin (GPM) | C21: {=MIN(TOCOL(C31:P33,1))} -> 0.0435 | D21: {=_xlfn.QUARTILE.INC(TOCOL(C31:P33,1),1)} -> 0.2307 | E21: {=MEDIAN(TOCOL(C31:P33,1))} -> 0.2476 | F21: {=_xlfn.QUARTILE.INC(TOCOL(C31:P33,1),3)} -> 0.2789 | G21: {=MAX(TOCOL(C31:P33,1))} -> 4.5584 | I21: Current Ratio | J21: {=MIN(TOCOL(R42:AE44,1))} -> 1.02 | K21: {=_xlfn.QUARTILE.INC(TOCOL(R42:AE44,1),1)} -> 1.23 | L21: {=MEDIAN(TOCOL(R42:AE44,1))} -> 1.77 | M21: {=_xlfn.QUARTILE.INC(TOCOL(R42:AE44,1),3)} -> 2.515 | N21: {=MAX(TOCOL(R42:AE44,1))} -> 6.11 | P21: DIO | Q21: {=MIN(TOCOL(R57:AE60,1))} -> #REF! | R21: {=_xlfn.QUARTILE.INC(TOCOL(R57:AE60,1),1)} -> #REF! | S21: {=MEDIAN(TOCOL(R57:AE60,1))} -> #REF! | T21: {=_xlfn.QUARTILE.INC(TOCOL(R57:AE60,1),3)} -> #REF! | U21: {=MAX(TOCOL(R57:AE60,1))} -> #REF! | W21: Gross Profit Margin (GPM) | AD21: Current Ratio | AK21: DIO | AR21: Gross Profit Margin (GPM) | AS21: {=MIN(TOCOL(C31:P31,1))} -> 0.1825 | AT21: {=_xlfn.QUARTILE.INC(TOCOL(C31:P31,1),1)} -> 0.2211 | AU21: {=MEDIAN(TOCOL(C31:P31,1))} -> 0.2325 | AV21: {=_xlfn.QUARTILE.INC(TOCOL(C31:P31,1),3)} -> 0.2503 | AW21: {=MAX(TOCOL(C31:P31,1))} -> 0.292 | AY21: Current Ratio | AZ21: {=MIN(TOCOL(R42:AE42,1))} -> 1.47 | BA21: {=_xlfn.QUARTILE.INC(TOCOL(R42:AE42,1),1)} -> 1.5875 | BB21: {=MEDIAN(TOCOL(R42:AE42,1))} -> 1.675 | BC21: {=_xlfn.QUARTILE.INC(TOCOL(R42:AE42,1),3)} -> 1.795 | BD21: {=MAX(TOCOL(R42:AE42,1))} -> 2.05 | BF21: DIO | BG21: {=MIN(TOCOL(R57:AE57,1))} -> #REF! | BH21: {=_xlfn.QUARTILE.INC(TOCOL(R57:AE57,1),1)} -> #REF! | BI21: {=MEDIAN(TOCOL(R57:AE57,1))} -> #REF! | BJ21: {=_xlfn.QUARTILE.INC(TOCOL(R57:AE57,1),3)} -> #REF! | BK21: {=MAX(TOCOL(R57:AE57,1))} -> #REF! | BM21: Gross Profit Margin (GPM) | BN21: {=MIN(TOCOL(C32:P32,1))} -> 0.1852 | BO21: {=_xlfn.QUARTILE.INC(TOCOL(C32:P32,1),1)} -> 0.24715 | BP21: {=MEDIAN(TOCOL(C32:P32,1))} -> 0.27505 | BQ21: {=_xlfn.QUARTILE.INC(TOCOL(C32:P32,1),3)} -> 0.2831 | BR21: {=MAX(TOCOL(C32:P32,1))} -> 0.2946 | BT21: Current Ratio | BU21: {=MIN(TOCOL(R43:AE43,1))} -> 1.02 | BV21: {=_xlfn.QUARTILE.INC(TOCOL(R43:AE43,1),1)} -> 1.1025 | BW21: {=MEDIAN(TOCOL(R43:AE43,1))} -> 1.13 | BX21: {=_xlfn.QUARTILE.INC(TOCOL(R43:AE43,1),3)} -> 1.14 | BY21: {=MAX(TOCOL(R43:AE43,1))} -> 1.15 | CA21: DIO | CB21: {=MIN(TOCOL(R58:AE58,1))} -> #REF! | CC21: {=_xlfn.QUARTILE.INC(TOCOL(R58:AE58,1),1)} -> #REF! | CD21: {=MEDIAN(TOCOL(R58:AE58,1))} -> #REF! | CE21: {=_xlfn.QUARTILE.INC(TOCOL(R58:AE58,1),3)} -> #REF! | CF21: {=MAX(TOCOL(R58:AE58,1))} -> #REF! | CH21: Gross Profit Margin (GPM) | CI21: {=MIN(TOCOL(C33:P33,1))} -> 0.0435 | CJ21: {=_xlfn.QUARTILE.INC(TOCOL(C33:P33,1),1)} -> 0.2388 | CK21: {=MEDIAN(TOCOL(C33:P33,1))} -> 0.2476 | CL21: {=_xlfn.QUARTILE.INC(TOCOL(C33:P33,1),3)} -> 0.2583 | CM21: {=MAX(TOCOL(C33:P33,1))} -> 4.5584 | CO21: Current Ratio | CP21: {=MIN(TOCOL(R44:AE44,1))} -> 1.78 | CQ21: {=_xlfn.QUARTILE.INC(TOCOL(R44:AE44,1),1)} -> 2.305 | CR21: {=MEDIAN(TOCOL(R44:AE44,1))} -> 2.98 | CS21: {=_xlfn.QUARTILE.INC(TOCOL(R44:AE44,1),3)} -> 4.7425 | CT21: {=MAX(TOCOL(R44:AE44,1))} -> 6.11 | CV21: DIO | CW21: {=MIN(TOCOL(R59:AE59,1))} -> #REF! | CX21: {=_xlfn.QUARTILE.INC(TOCOL(R59:AE59,1),1)} -> #REF! | CY21: {=MEDIAN(TOCOL(R59:AE59,1))} -> #REF! | CZ21: {=_xlfn.QUARTILE.INC(TOCOL(R59:AE59,1),3)} -> #REF! | DA21: {=MAX(TOCOL(R59:AE59,1))} -> #REF!
B22: Operating Profit Margin (OPM) | C22: {=MIN(TOCOL(Q31:AD33,1))} -> -6.5618 | D22: {=_xlfn.QUARTILE.INC(TOCOL(Q31:AD33,1),1)} -> 0.064475 | E22: {=MEDIAN(TOCOL(Q31:AD33,1))} -> 0.091 | F22: {=_xlfn.QUARTILE.INC(TOCOL(Q31:AD33,1),3)} -> 0.119675 | G22: {=MAX(TOCOL(Q31:AD33,1))} -> 2.5808 | I22: Quick Ratio | J22: {=MIN(TOCOL(AI42:AV44,1))} -> 0.4 | K22: {=_xlfn.QUARTILE.INC(TOCOL(AI42:AV44,1),1)} -> 0.5825 | L22: {=MEDIAN(TOCOL(AI42:AV44,1))} -> 0.815 | M22: {=_xlfn.QUARTILE.INC(TOCOL(AI42:AV44,1),3)} -> 1.3425 | N22: {=MAX(TOCOL(AI42:AV44,1))} -> 3.01 | P22: DSO | Q22: {=MIN(TOCOL(AI57:AV59,1))} -> #REF! | R22: {=_xlfn.QUARTILE.INC(TOCOL(AI57:AV59,1),1)} -> #REF! | S22: {=MEDIAN(TOCOL(AI57:AV59,1))} -> #REF! | T22: {=_xlfn.QUARTILE.INC(TOCOL(AI57:AV59,1),3)} -> #REF! | U22: {=MAX(TOCOL(AI57:AV59,1))} -> #REF! | W22: Operating Profit Margin (OPM) | AD22: Quick Ratio | AK22: DSO | AR22: Operating Profit Margin (OPM) | AS22: {=MIN(TOCOL(Q31:AD31,1))} -> 0.0905 | AT22: {=_xlfn.QUARTILE.INC(TOCOL(Q31:AD31,1),1)} -> 0.09885 | AU22: {=MEDIAN(TOCOL(Q31:AD31,1))} -> 0.11385 | AV22: {=_xlfn.QUARTILE.INC(TOCOL(Q31:AD31,1),3)} -> 0.1335 | AW22: {=MAX(TOCOL(Q31:AD31,1))} -> 0.1491 | AY22: Quick Ratio | AZ22: {=MIN(TOCOL(AI42:AV42,1))} -> 0.72 | BA22: {=_xlfn.QUARTILE.INC(TOCOL(AI42:AV42,1),1)} -> 0.7625 | BB22: {=MEDIAN(TOCOL(AI42:AV42,1))} -> 0.815 | BC22: {=_xlfn.QUARTILE.INC(TOCOL(AI42:AV42,1),3)} -> 0.9175 | BD22: {=MAX(TOCOL(AI42:AV42,1))} -> 1.2 | BF22: DSO | BG22: {=MIN(TOCOL(AI57:AV57,1))} -> #REF! | BH22: {=_xlfn.QUARTILE.INC(TOCOL(AI57:AV57,1),1)} -> #REF! | BI22: {=MEDIAN(TOCOL(AI57:AV57,1))} -> #REF! | BJ22: {=_xlfn.QUARTILE.INC(TOCOL(AI57:AV57,1),3)} -> #REF! | BK22: {=MAX(TOCOL(AI57:AV57,1))} -> #REF! | BM22: Operating Profit Margin (OPM) | BN22: {=MIN(TOCOL(Q32:AD32,1))} -> -0.0168 | BO22: {=_xlfn.QUARTILE.INC(TOCOL(Q32:AD32,1),1)} -> 0.059975 | BP22: {=MEDIAN(TOCOL(Q32:AD32,1))} -> 0.08005 | BQ22: {=_xlfn.QUARTILE.INC(TOCOL(Q32:AD32,1),3)} -> 0.091175 | BR22: {=MAX(TOCOL(Q32:AD32,1))} -> 0.1318 | BT22: Quick Ratio | BU22: {=MIN(TOCOL(AI43:AV43,1))} -> 0.4 | BV22: {=_xlfn.QUARTILE.INC(TOCOL(AI43:AV43,1),1)} -> 0.48 | BW22: {=MEDIAN(TOCOL(AI43:AV43,1))} -> 0.485 | BX22: {=_xlfn.QUARTILE.INC(TOCOL(AI43:AV43,1),3)} -> 0.5175 | BY22: {=MAX(TOCOL(AI43:AV43,1))} -> 0.55 | CA22: DSO | CB22: {=MIN(TOCOL(AI58:AV58,1))} -> #REF! | CC22: {=_xlfn.QUARTILE.INC(TOCOL(AI58:AV58,1),1)} -> #REF! | CD22: {=MEDIAN(TOCOL(AI58:AV58,1))} -> #REF! | CE22: {=_xlfn.QUARTILE.INC(TOCOL(AI58:AV58,1),3)} -> #REF! | CF22: {=MAX(TOCOL(AI58:AV58,1))} -> #REF! | CH22: Operating Profit Margin (OPM) | CI22: {=MIN(TOCOL(Q33:AD33,1))} -> -6.5618 | CJ22: {=_xlfn.QUARTILE.INC(TOCOL(Q33:AD33,1),1)} -> 0.01085 | CK22: {=MEDIAN(TOCOL(Q33:AD33,1))} -> 0.0755 | CL22: {=_xlfn.QUARTILE.INC(TOCOL(Q33:AD33,1),3)} -> 0.09405 | CM22: {=MAX(TOCOL(Q33:AD33,1))} -> 2.5808 | CO22: Quick Ratio | CP22: {=MIN(TOCOL(AI44:AV44,1))} -> 0.68 | CQ22: {=_xlfn.QUARTILE.INC(TOCOL(AI44:AV44,1),1)} -> 1.1575 | CR22: {=MEDIAN(TOCOL(AI44:AV44,1))} -> 1.6 | CS22: {=_xlfn.QUARTILE.INC(TOCOL(AI44:AV44,1),3)} -> 2.655 | CT22: {=MAX(TOCOL(AI44:AV44,1))} -> 3.01 | CV22: DSO | CW22: {=MIN(TOCOL(AI59:AV59,1))} -> #REF! | CX22: {=_xlfn.QUARTILE.INC(TOCOL(AI59:AV59,1),1)} -> #REF! | CY22: {=MEDIAN(TOCOL(AI59:AV59,1))} -> #REF! | CZ22: {=_xlfn.QUARTILE.INC(TOCOL(AI59:AV59,1),3)} -> #REF! | DA22: {=MAX(TOCOL(AI59:AV59,1))} -> #REF!
B23: Net Profit Margin (NPM) | C23: {=MIN(TOCOL(AE31:AR33,1))} -> -0.0871 | D23: {=_xlfn.QUARTILE.INC(TOCOL(AE31:AR33,1),1)} -> 0.024625 | E23: {=MEDIAN(TOCOL(AE31:AR33,1))} -> 0.059 | F23: {=_xlfn.QUARTILE.INC(TOCOL(AE31:AR33,1),3)} -> 0.07785 | G23: {=MAX(TOCOL(AE31:AR33,1))} -> 3.1477 | I23: Inventory Turnover | J23: {=MIN(TOCOL(R50:AE52,1))} -> 0.71 | K23: {=_xlfn.QUARTILE.INC(TOCOL(R50:AE52,1),1)} -> 1.685 | L23: {=MEDIAN(TOCOL(R50:AE52,1))} -> 2.29 | M23: {=_xlfn.QUARTILE.INC(TOCOL(R50:AE52,1),3)} -> 3.1025 | N23: {=MAX(TOCOL(R50:AE52,1))} -> 3.66 | P23: DPO | Q23: {=MIN(TOCOL(R64:AE66,1))} -> #REF! | R23: {=_xlfn.QUARTILE.INC(TOCOL(R64:AE66,1),1)} -> #REF! | S23: {=MEDIAN(TOCOL(R64:AE66,1))} -> #REF! | T23: {=_xlfn.QUARTILE.INC(TOCOL(R64:AE66,1),3)} -> #REF! | U23: {=MAX(TOCOL(R64:AE66,1))} -> #REF! | W23: Net Profit Margin (NPM) | AD23: Inventory Turnover | AK23: DPO | AR23: Net Profit Margin (NPM) | AS23: {=MIN(TOCOL(AE31:AR31,1))} -> 0.0587 | AT23: {=_xlfn.QUARTILE.INC(TOCOL(AE31:AR31,1),1)} -> 0.06145 | AU23: {=MEDIAN(TOCOL(AE31:AR31,1))} -> 0.0723 | AV23: {=_xlfn.QUARTILE.INC(TOCOL(AE31:AR31,1),3)} -> 0.088375 | AW23: {=MAX(TOCOL(AE31:AR31,1))} -> 0.1028 | AY23: Inventory Turnover | AZ23: {=MIN(TOCOL(R50:AE50,1))} -> 1.59 | BA23: {=_xlfn.QUARTILE.INC(TOCOL(R50:AE50,1),1)} -> 2.4925 | BB23: {=MEDIAN(TOCOL(R50:AE50,1))} -> 3.075 | BC23: {=_xlfn.QUARTILE.INC(TOCOL(R50:AE50,1),3)} -> 3.44 | BD23: {=MAX(TOCOL(R50:AE50,1))} -> 3.66 | BF23: DPO | BG23: {=MIN(TOCOL(R64:AE64,1))} -> #REF! | BH23: {=_xlfn.QUARTILE.INC(TOCOL(R64:AE64,1),1)} -> #REF! | BI23: {=MEDIAN(TOCOL(R64:AE64,1))} -> #REF! | BJ23: {=_xlfn.QUARTILE.INC(TOCOL(R64:AE64,1),3)} -> #REF! | BK23: {=MAX(TOCOL(R64:AE64,1))} -> #REF! | BM23: Net Profit Margin (NPM) | BN23: {=MIN(TOCOL(AE32:AR32,1))} -> -0.0287 | BO23: {=_xlfn.QUARTILE.INC(TOCOL(AE32:AR32,1),1)} -> 0.024625 | BP23: {=MEDIAN(TOCOL(AE32:AR32,1))} -> 0.0405 | BQ23: {=_xlfn.QUARTILE.INC(TOCOL(AE32:AR32,1),3)} -> 0.049725 | BR23: {=MAX(TOCOL(AE32:AR32,1))} -> 0.0889 | BT23: Inventory Turnover | BU23: {=MIN(TOCOL(R51:AE51,1))} -> 2.02 | BV23: {=_xlfn.QUARTILE.INC(TOCOL(R51:AE51,1),1)} -> 2.105 | BW23: {=MEDIAN(TOCOL(R51:AE51,1))} -> 2.27 | BX23: {=_xlfn.QUARTILE.INC(TOCOL(R51:AE51,1),3)} -> 2.34 | BY23: {=MAX(TOCOL(R51:AE51,1))} -> 2.99 | CA23: DPO | CB23: {=MIN(TOCOL(R65:AE65,1))} -> #REF! | CC23: {=_xlfn.QUARTILE.INC(TOCOL(R65:AE65,1),1)} -> #REF! | CD23: {=MEDIAN(TOCOL(R65:AE65,1))} -> #REF! | CE23: {=_xlfn.QUARTILE.INC(TOCOL(R65:AE65,1),3)} -> #REF! | CF23: {=MAX(TOCOL(R65:AE65,1))} -> #REF! | CH23: Net Profit Margin (NPM) | CI23: {=MIN(TOCOL(AE33:AR33,1))} -> -0.0871 | CJ23: {=_xlfn.QUARTILE.INC(TOCOL(AE33:AR33,1),1)} -> 0.00965 | CK23: {=MEDIAN(TOCOL(AE33:AR33,1))} -> 0.03275 | CL23: {=_xlfn.QUARTILE.INC(TOCOL(AE33:AR33,1),3)} -> 0.0969 | CM23: {=MAX(TOCOL(AE33:AR33,1))} -> 3.1477 | CO23: Inventory Turnover | CP23: {=MIN(TOCOL(R52:AE52,1))} -> 0.71 | CQ23: {=_xlfn.QUARTILE.INC(TOCOL(R52:AE52,1),1)} -> 1.075 | CR23: {=MEDIAN(TOCOL(R52:AE52,1))} -> 1.67 | CS23: {=_xlfn.QUARTILE.INC(TOCOL(R52:AE52,1),3)} -> 2.095 | CT23: {=MAX(TOCOL(R52:AE52,1))} -> 3.48 | CV23: DPO | CW23: {=MIN(TOCOL(R66:AE66,1))} -> #REF! | CX23: {=_xlfn.QUARTILE.INC(TOCOL(R66:AE66,1),1)} -> #REF! | CY23: {=MEDIAN(TOCOL(R66:AE66,1))} -> #REF! | CZ23: {=_xlfn.QUARTILE.INC(TOCOL(R66:AE66,1),3)} -> #REF! | DA23: {=MAX(TOCOL(R66:AE66,1))} -> #REF!
B24: EBITDA Margin | C24: {=MIN(TOCOL(R78:AE80,1))} -> -0.3214 | D24: {=_xlfn.QUARTILE.INC(TOCOL(R78:AE80,1),1)} -> 0.0844 | E24: {=MEDIAN(TOCOL(R78:AE80,1))} -> 0.1052 | F24: {=_xlfn.QUARTILE.INC(TOCOL(R78:AE80,1),3)} -> 0.1281 | G24: {=MAX(TOCOL(R78:AE80,1))} -> 2.6303 | I24: Debt to Equity Ratio (DER) | J24: {=MIN(TOCOL(AI50:AV52,1))} -> 0.11 | K24: {=_xlfn.QUARTILE.INC(TOCOL(AI50:AV52,1),1)} -> 0.375 | L24: {=MEDIAN(TOCOL(AI50:AV52,1))} -> 0.685 | M24: {=_xlfn.QUARTILE.INC(TOCOL(AI50:AV52,1),3)} -> 1.035 | N24: {=MAX(TOCOL(AI50:AV52,1))} -> 1.45 | P24: CCC | Q24: {=MIN(TOCOL(AI64:AV66,1))} -> #REF! | R24: {=_xlfn.QUARTILE.INC(TOCOL(AI64:AV66,1),1)} -> #REF! | S24: {=MEDIAN(TOCOL(AI64:AV66,1))} -> #REF! | T24: {=_xlfn.QUARTILE.INC(TOCOL(AI64:AV66,1),3)} -> #REF! | U24: {=MAX(TOCOL(AI64:AV66,1))} -> #REF! | W24: EBITDA Margin | AD24: Debt to Equity Ratio (DER) | AK24: CCC | AR24: EBITDA Margin | AS24: {=MIN(TOCOL(R78:AE78,1))} -> 0.103 | AT24: {=_xlfn.QUARTILE.INC(TOCOL(R78:AE78,1),1)} -> 0.1111 | AU24: {=MEDIAN(TOCOL(R78:AE78,1))} -> 0.1213 | AV24: {=_xlfn.QUARTILE.INC(TOCOL(R78:AE78,1),3)} -> 0.138725 | AW24: {=MAX(TOCOL(R78:AE78,1))} -> 0.1616 | AY24: Debt to Equity Ratio (DER) | AZ24: {=MIN(TOCOL(AI50:AV50,1))} -> 0.41 | BA24: {=_xlfn.QUARTILE.INC(TOCOL(AI50:AV50,1),1)} -> 0.5125 | BB24: {=MEDIAN(TOCOL(AI50:AV50,1))} -> 0.625 | BC24: {=_xlfn.QUARTILE.INC(TOCOL(AI50:AV50,1),3)} -> 0.7575 | BD24: {=MAX(TOCOL(AI50:AV50,1))} -> 0.95 | BF24: CCC | BG24: {=MIN(TOCOL(AI64:AV64,1))} -> #REF! | BH24: {=_xlfn.QUARTILE.INC(TOCOL(AI64:AV64,1),1)} -> #REF! | BI24: {=MEDIAN(TOCOL(AI64:AV64,1))} -> #REF! | BJ24: {=_xlfn.QUARTILE.INC(TOCOL(AI64:AV64,1),3)} -> #REF! | BK24: {=MAX(TOCOL(AI64:AV64,1))} -> #REF! | BM24: EBITDA Margin | BN24: {=MIN(TOCOL(C79:G79,1))} -> 0.0404 | BO24: {=_xlfn.QUARTILE.INC(TOCOL(C79:G79,1),1)} -> 0.0783 | BP24: {=MEDIAN(TOCOL(C79:G79,1))} -> 0.0893 | BQ24: {=_xlfn.QUARTILE.INC(TOCOL(C79:G79,1),3)} -> 0.0896 | BR24: {=MAX(TOCOL(C79:G79,1))} -> 0.1043 | BT24: Debt to Equity Ratio (DER) | BU24: {=MIN(TOCOL(AI51:AV51,1))} -> 1.02 | BV24: {=_xlfn.QUARTILE.INC(TOCOL(AI51:AV51,1),1)} -> 1.05 | BW24: {=MEDIAN(TOCOL(AI51:AV51,1))} -> 1.13 | BX24: {=_xlfn.QUARTILE.INC(TOCOL(AI51:AV51,1),3)} -> 1.165 | BY24: {=MAX(TOCOL(AI51:AV51,1))} -> 1.45 | CA24: CCC | CB24: {=MIN(TOCOL(AI65:AV65,1))} -> #REF! | CC24: {=_xlfn.QUARTILE.INC(TOCOL(AI65:AV65,1),1)} -> #REF! | CD24: {=MEDIAN(TOCOL(AI65:AV65,1))} -> #REF! | CE24: {=_xlfn.QUARTILE.INC(TOCOL(AI65:AV65,1),3)} -> #REF! | CF24: {=MAX(TOCOL(AI65:AV65,1))} -> #REF! | CH24: EBITDA Margin | CI24: {=MIN(TOCOL(C80:G80,1))} -> -0.5108 | CJ24: {=_xlfn.QUARTILE.INC(TOCOL(C80:G80,1),1)} -> -0.1457 | CK24: {=MEDIAN(TOCOL(C80:G80,1))} -> 0.0678 | CL24: {=_xlfn.QUARTILE.INC(TOCOL(C80:G80,1),3)} -> 0.0845 | CM24: {=MAX(TOCOL(C80:G80,1))} -> 0.0944 | CO24: Debt to Equity Ratio (DER) | CP24: {=MIN(TOCOL(AI52:AV52,1))} -> 0.11 | CQ24: {=_xlfn.QUARTILE.INC(TOCOL(AI52:AV52,1),1)} -> 0.12 | CR24: {=MEDIAN(TOCOL(AI52:AV52,1))} -> 0.31 | CS24: {=_xlfn.QUARTILE.INC(TOCOL(AI52:AV52,1),3)} -> 0.375 | CT24: {=MAX(TOCOL(AI52:AV52,1))} -> 0.76 | CV24: CCC | CW24: {=MIN(TOCOL(AI66:AV66,1))} -> #REF! | CX24: {=_xlfn.QUARTILE.INC(TOCOL(AI66:AV66,1),1)} -> #REF! | CY24: {=MEDIAN(TOCOL(AI66:AV66,1))} -> #REF! | CZ24: {=_xlfn.QUARTILE.INC(TOCOL(AI66:AV66,1),3)} -> #REF! | DA24: {=MAX(TOCOL(AI66:AV66,1))} -> #REF!
B25: ROA | C25: {=MIN(TOCOL(AS31:BF33,1))} -> -0.369 | D25: {=_xlfn.QUARTILE.INC(TOCOL(AS31:BF33,1),1)} -> 0.0259 | E25: {=MEDIAN(TOCOL(AS31:BF33,1))} -> 0.061 | F25: {=_xlfn.QUARTILE.INC(TOCOL(AS31:BF33,1),3)} -> 0.1069 | G25: {=MAX(TOCOL(AS31:BF33,1))} -> 0.3004 | P25: NWC | Q25: {=MIN(TOCOL(R71:AE73,1))} -> #REF! | R25: {=_xlfn.QUARTILE.INC(TOCOL(R71:AE73,1),1)} -> #REF! | S25: {=MEDIAN(TOCOL(R71:AE73,1))} -> #REF! | T25: {=_xlfn.QUARTILE.INC(TOCOL(R71:AE73,1),3)} -> #REF! | U25: {=MAX(TOCOL(R71:AE73,1))} -> #REF! | W25: ROA | AK25: NWC | AR25: ROA | AS25: {=MIN(TOCOL(AS31:BF31,1))} -> 0.0456 | AT25: {=_xlfn.QUARTILE.INC(TOCOL(AS31:BF31,1),1)} -> 0.084775 | AU25: {=MEDIAN(TOCOL(AS31:BF31,1))} -> 0.10645 | AV25: {=_xlfn.QUARTILE.INC(TOCOL(AS31:BF31,1),3)} -> 0.136475 | AW25: {=MAX(TOCOL(AS31:BF31,1))} -> 0.1706 | BF25: NWC | BG25: {=MIN(TOCOL(R71:AE71,1))} -> #REF! | BH25: {=_xlfn.QUARTILE.INC(TOCOL(R71:AE71,1),1)} -> #REF! | BI25: {=MEDIAN(TOCOL(R71:AE71,1))} -> #REF! | BJ25: {=_xlfn.QUARTILE.INC(TOCOL(R71:AE71,1),3)} -> #REF! | BK25: {=MAX(TOCOL(R71:AE71,1))} -> #REF! | BM25: ROA | BN25: {=MIN(TOCOL(AS32:BF32,1))} -> 0.0407 | BO25: {=_xlfn.QUARTILE.INC(TOCOL(AS32:BF32,1),1)} -> 0.0517 | BP25: {=MEDIAN(TOCOL(AS32:BF32,1))} -> 0.06435 | BQ25: {=_xlfn.QUARTILE.INC(TOCOL(AS32:BF32,1),3)} -> 0.076025 | BR25: {=MAX(TOCOL(AS32:BF32,1))} -> 0.1261 | CA25: NWC | CB25: {=MIN(TOCOL(R72:AE72,1))} -> #REF! | CC25: {=_xlfn.QUARTILE.INC(TOCOL(R72:AE72,1),1)} -> #REF! | CD25: {=MEDIAN(TOCOL(R72:AE72,1))} -> #REF! | CE25: {=_xlfn.QUARTILE.INC(TOCOL(R72:AE72,1),3)} -> #REF! | CF25: {=MAX(TOCOL(R72:AE72,1))} -> #REF! | CH25: ROA | CI25: {=MIN(TOCOL(AS33:BF33,1))} -> -0.369 | CJ25: {=_xlfn.QUARTILE.INC(TOCOL(AS33:BF33,1),1)} -> -0.0004 | CK25: {=MEDIAN(TOCOL(AS33:BF33,1))} -> 0.0208 | CL25: {=_xlfn.QUARTILE.INC(TOCOL(AS33:BF33,1),3)} -> 0.0342 | CM25: {=MAX(TOCOL(AS33:BF33,1))} -> 0.3004 | CV25: NWC | CW25: {=MIN(TOCOL(R73:AE73,1))} -> #REF! | CX25: {=_xlfn.QUARTILE.INC(TOCOL(AI66:AV66,1),1)} -> #REF! | CY25: {=MEDIAN(TOCOL(AI66:AV66,1))} -> #REF! | CZ25: {=_xlfn.QUARTILE.INC(TOCOL(AI66:AV66,1),3)} -> #REF! | DA25: {=MAX(TOCOL(AI66:AV66,1))} -> #REF!
B26: ROE | C26: {=MIN(TOCOL(BG31:BT33,1))} -> -0.5819 | D26: {=_xlfn.QUARTILE.INC(TOCOL(BG31:BT33,1),1)} -> 0.04805 | E26: {=MEDIAN(TOCOL(BG31:BT33,1))} -> 0.1586 | F26: {=_xlfn.QUARTILE.INC(TOCOL(BG31:BT33,1),3)} -> 0.26275 | G26: {=MAX(TOCOL(BG31:BT33,1))} -> 0.6146 | W26: ROE | AR26: ROE | AS26: {=MIN(TOCOL(BG31:BT31,1))} -> 0.0814 | AT26: {=_xlfn.QUARTILE.INC(TOCOL(BG31:BT31,1),1)} -> 0.1707 | AU26: {=MEDIAN(TOCOL(BG31:BT31,1))} -> 0.24215 | AV26: {=_xlfn.QUARTILE.INC(TOCOL(BG31:BT31,1),3)} -> 0.343975 | AW26: {=MAX(TOCOL(BG31:BT31,1))} -> 0.4883 | BM26: ROE | BN26: {=MIN(TOCOL(BG32:BT32,1))} -> 0.0834 | BO26: {=_xlfn.QUARTILE.INC(TOCOL(BG32:BT32,1),1)} -> 0.108475 | BP26: {=MEDIAN(TOCOL(BG32:BT32,1))} -> 0.1463 | BQ26: {=_xlfn.QUARTILE.INC(TOCOL(BG32:BT32,1),3)} -> 0.185825 | BR26: {=MAX(TOCOL(BG32:BT32,1))} -> 0.4486 | CH26: ROE | CI26: {=MIN(TOCOL(BG33:BT33,1))} -> -0.5819 | CJ26: {=_xlfn.QUARTILE.INC(TOCOL(BG33:BT33,1),1)} -> 0.0026 | CK26: {=MEDIAN(TOCOL(BG33:BT33,1))} -> 0.0152 | CL26: {=_xlfn.QUARTILE.INC(TOCOL(BG33:BT33,1),3)} -> 0.052 | CM26: {=MAX(TOCOL(BG33:BT33,1))} -> 0.6146
B28: Profitability Ratio
B29: Competitor Name | C29: GPM Q2 2026 | D29: GPM Q1 2026 | E29: GPM Q4 2025 | F29: GPM Q3 2025 | G29: GPM Q2 2025 | H29: GPM Q1 2025 | I29: GPM Q4 2024 | J29: GPM Q3 2024 | K29: GPM Q2 2024 | L29: GPM Q1 2024 | M29: GPM Q4 2023 | N29: GPM Q3 2023 | O29: GPM Q2 2023 | P29: GPM Q1 2023 | Q29: OPM Q2 2026 | R29: OPM Q1 2026 | S29: OPM Q4 2025 | T29: OPM Q3 2025 | U29: OPM Q2 2025 | V29: OPM Q1 2025 | W29: OPM Q4 2024 | X29: OPM Q3 2024 | Y29: OPM Q2 2024 | Z29: OPM Q1 2024 | AA29: OPM Q4 2023 | AB29: OPM Q3 2023 | AC29: OPM Q2 2023 | AD29: OPM Q1 2023 | AE29: NPM Q2 2026 | AF29: NPM Q1 2026 | AG29: NPM Q4 2025 | AH29: NPM Q3 2025 | AI29: NPM Q2 2025 | AJ29: NPM Q1 2025 | AK29: NPM Q4 2024 | AL29: NPM Q3 2024 | AM29: NPM Q2 2024 | AN29: NPM Q1 2024 | AO29: NPM Q4 2023 | AP29: NPM Q3 2023 | AQ29: NPM Q2 2023 | AR29: NPM Q1 2023 | AS29: ROA Q2 2026 | AT29: ROA Q1 2026 | AU29: ROA Q4 2025 | AV29: ROA Q3 2025 | AW29: ROA Q2 2025 | AX29: ROA Q1 2025 | AY29: ROA Q4 2024 | AZ29: ROA Q3 2024 | BA29: ROA Q2 2024 | BB29: ROA Q1 2024 | BC29: ROA Q4 2023 | BD29: ROA Q3 2023 | BE29: ROA Q2 2023 | BF29: ROA Q1 2023 | BG29: ROE Q2 2026 | BH29: ROE Q1 2026 | BI29: ROE Q4 2025 | BJ29: ROE Q3 2025 | BK29: ROE Q2 2025 | BL29: ROE Q1 2025 | BM29: ROE Q4 2024 | BN29: ROE Q3 2024 | BO29: ROE Q2 2024 | BP29: ROE Q1 2024 | BQ29: ROE Q4 2023 | BR29: ROE Q3 2023 | BS29: ROE Q2 2023 | BT29: ROE Q1 2023
B30: PT Pupuk Kalimatan Timur
B31: PT Saraswati Anugerah Makmur Tbk | C31: =C172 -> 0.2025 | D31: =D172 -> 0.2307 | E31: =E172 -> 0.1825 | F31: =F172 -> 0.2309 | G31: =G172 -> 0.2072 | H31: =H172 -> 0.2355 | I31: =I172 -> 0.2341 | J31: =J172 -> 0.244 | ... P31: =P172 -> 0.2205 | Q31: =C180 -> 0.0966 | R31: =D180 -> 0.1011 | S31: =E180 -> 0.0981 | T31: =F180 -> 0.1117 | U31: =G180 -> 0.094 | V31: =H180 -> 0.0905 | W31: =I180 -> 0.1116 | X31: =J180 -> 0.1209 | ... AD31: =P180 -> 0.1356 | AE31: =C174 -> 0.0593 | AF31: =D174 -> 0.0625 | AG31: =E174 -> 0.0587 | AH31: =F174 -> 0.0697 | AI31: =G174 -> 0.0611 | AJ31: =H174 -> 0.0594 | AK31: =I174 -> 0.0689 | AL31: =J174 -> 0.0749 | ... AR31: =P174 -> 0.0918 | AS31: =AZ165 -> 0.0456 | AT31: =BA165 -> 0.0883 | AU31: =BB165 -> 0.1069 | AV31: =BC165 -> 0.0742 | AW31: =BD165 -> 0.0588 | AX31: =BE165 -> 0.1052 | AY31: =BF165 -> 0.1113 | AZ31: =BG165 -> 0.106 | ... BF31: =BM165 -> 0.143 | BG31: =AZ164 -> 0.0814 | BH31: =BA164 -> 0.1642 | BI31: =BB164 -> 0.2368 | BJ31: =BC164 -> 0.1586 | BK31: =BD164 -> 0.1174 | BL31: =BE164 -> 0.2127 | BM31: =BF164 -> 0.278 | BN31: =BG164 -> 0.2475 | ... BT31: =BM164 -> 0.443
B32: PT Delta Giri Wacana Tbk | C32: =C319 -> 0.2699 | D32: =D319 -> 0.2429 | E32: =E319 -> 0.2404 | F32: =F319 -> 0.2825 | G32: =G319 -> 0.2802 | H32: =H319 -> 0.2808 | I32: =I319 -> 0.2946 | J32: =J319 -> 0.2599 | ... P32: =P319 -> 0.1852 | Q32: =C320 -> 0.0915 | R32: =D320 -> 0.0888 | S32: =E320 -> 0.1264 | T32: =F320 -> 0.1051 | U32: =G320 -> 0.059 | V32: =H320 -> 0.0713 | W32: =I320 -> 0.1318 | X32: =J320 -> 0.0692 | ... AD32: =P320 -> -0.0168 | AE32: =C321 -> 0.0392 | AF32: =D321 -> 0.0447 | AG32: =E321 -> 0.0769 | AH32: =F321 -> 0.0514 | AI32: =G321 -> 0.031 | AJ32: =H321 -> 0.0322 | AK32: =I321 -> 0.0889 | AL32: =J321 -> 0.0663 | ... AR32: =P321 -> -0.0287 | AS32: =AZ323 -> 0.061 | AT32: =BA323 -> 0.1261 | AU32: =BB323 -> 0.0788 | AV32: =BC323 -> 0.0407 | AW32: =BD323 -> 0.0486 | AX32: =BE323 -> - | AY32: =BF323 -> - | AZ32: =BG323 -> - | ... BF32: =BM323 | BG32: =AZ322 -> 0.1783 | BH32: =BA322 -> 0.4486 | BI32: =BB322 -> 0.2084 | BJ32: =BC322 -> 0.1126 | BK32: =BD322 -> 0.1161 | BL32: =BE322 -> - | BM32: =BF322 -> - | BN32: =BG322 -> 0.0834 | ... BT32: =BM322
B33: PT Nusa Palapa Gemilang Tbk | C33: =C482 -> 0.2067 | D33: =D482 -> 0.2454 | E33: =E482 -> 0.2047 | F33: =F482 -> 0.2746 | G33: =G482 -> 0.256 | H33: =H482 -> 0.2583 | I33: =I482 -> 0.2388 | J33: =J482 -> 0.2541 | ... P33: =P482 -> - | Q33: =C483 -> 0.0526 | R33: =D483 -> 0.0962 | S33: =E483 -> 0.0011 | T33: =F483 -> 0.0734 | U33: =G483 -> 0.0876 | V33: =H483 -> 0.0828 | W33: =I483 -> 0.0401 | X33: =J483 -> 0.0776 | ... AD33: =P483 -> -6.5618 | AE33: =C484 -> 0.0072 | AF33: =D484 -> 0.0188 | AG33: =E484 -> 0.0032 | AH33: =F484 -> 0.0434 | AI33: =G484 -> 0.017 | AJ33: =H484 -> 0.0221 | AK33: =I484 -> -0.0057 | AL33: =J484 -> 0.0473 | ... AR33: =P484 -> 3.1477 | AS33: =AZ478 -> - | AT33: =BA478 -> 0.0008 | AU33: =BB478 -> 0.0342 | AV33: =BC478 -> 0.0208 | AW33: =BD478 -> 0.0259 | AX33: =BE478 -> 0.0231 | AY33: =BF478 -> 0.0354 | AZ33: =BG478 -> 0.0433 | ... BF33: =BM478 -> -0.1951 | BG33: =AZ477 -> - | BH33: =BA477 -> 0.005 | BI33: =BB477 -> 0.0441 | BJ33: =BC477 -> 0.0089 | BK33: =BD477 -> 0.0152 | BL33: =BE477 -> -0.0065 | BM33: =BF477 -> 0.0393 | BN33: =BG477 -> 0.052 | ... BT33: =BM477 -> -0.5819
C36: 2026 Kuartal I GPM | D36: OPM | E36: NPM
B37: 601660833660 | C37: =138844581061/601660833660 -> 0.23076885 | E37: =38810585879/B37 -> 0.064505754
B39: Current Ratio | C39: TAHUNAN | I39: Quick Ratio | J39: TAHUNAN | Q39: Current Ratio | R39: QUARTAL | AH39: Quick Ratio | AI39: QUARTAL
C40: FY 2025 | D40: FY 2024 | E40: FY 2023 | F40: FY 2022 | G40: FY 2021 | J40: FY 2025 | K40: FY 2024 | L40: FY 2023 | M40: FY 2022 | N40: FY 2021 | R40: Q2 2026 | S40: Q1 2026 | T40: Q4 2025 | U40: Q3 2025 | V40: Q2 2025 | W40: Q1 2025 | X40: Q4 2024 | Y40: Q3 2024 | Z40: Q2 2024 | AA40: Q1 2024 | AB40: Q4 2023 | AC40: Q3 2023 | AD40: Q2 2023 | AE40: Q1 2023 | AI40: Q2 2026 | AJ40: Q1 2026 | AK40: Q4 2025 | AL40: Q3 2025 | AM40: Q2 2025 | AN40: Q1 2025 | AO40: Q4 2024 | AP40: Q3 2024 | AQ40: Q2 2024 | AR40: Q1 2024 | AS40: Q4 2023 | AT40: Q3 2023 | AU40: Q2 2023 | AV40: Q1 2023
B41: PT Pupuk Kalimatan Timur | C41: 310 | D41: 302 | E41: 204 | F41: 245 | G41: 163 | I41: PT Pupuk Kalimatan Timur | J41: 310 | K41: 302 | L41: 204 | M41: 245 | N41: 163 | Q41: PT Pupuk Kalimatan Timur | AH41: PT Pupuk Kalimatan Timur
B42: PT Saraswati Anugerah Makmur Tbk | C42: =AB110 -> 1.98 | D42: =AC110 -> 2.05 | E42: =AD110 -> 1.76 | F42: =AE110 -> 1.39 | G42: =AF110 -> 1.6 | I42: PT Saraswati Anugerah Makmur Tbk | J42: =AB109 -> 1.2 | K42: =AC109 -> 1.19 | L42: =AD109 -> 0.72 | M42: =AE109 -> 0.47 | N42: =AF109 -> 0.68 | Q42: PT Saraswati Anugerah Makmur Tbk | R42: =AZ163 -> 1.47 | S42: =BA163 -> 1.8 | T42: =BB163 -> 1.98 | U42: =BC163 -> 1.7 | V42: =BD163 -> 1.64 | W42: =BE163 -> 1.97 | X42: =BF163 -> 2.05 | Y42: =BG163 -> 1.65 | ... AE42: =BM163 -> 1.55 | AH42: PT Saraswati Anugerah Makmur Tbk | AI42: =AZ162 -> 0.72 | AJ42: =BA162 -> 0.77 | AK42: =BB162 -> 1.2 | AL42: =BC162 -> 0.91 | AM42: =BD162 -> 0.75 | AN42: =BE162 -> 0.89 | AO42: =BF162 -> 1.19 | AP42: =BG162 -> 0.92 | ... AV42: =BM162 -> 0.76
B43: PT Delta Giri Wacana Tbk | C43: =AB244 -> 1.14 | D43: =AC244 -> 1.02 | E43: =AD244 -> 1.15 | F43: =AE244 -> 1.22 | G43: =AF244 -> 1.27 | I43: PT Delta Giri Wacana Tbk | J43: =AB243 -> 0.51 | K43: =AC243 -> 0.52 | L43: =AD243 -> 0.48 | M43: =AE243 -> 0.59 | N43: =AF243 -> 0.85 | Q43: PT Delta Giri Wacana Tbk | R43: =AZ321 -> 1.12 | S43: =BA321 -> 1.14 | T43: =BB321 -> 1.14 | U43: =BC321 -> 1.11 | V43: =BD321 -> 1.1 | W43: =BE321 -> 1.14 | X43: =BF321 -> 1.02 | Y43: =BG321 -> - | ... AE43: =BM321 -> - | AH43: PT Delta Giri Wacana Tbk | AI43: =AZ320 -> 0.4 | AJ43: =BA320 -> 0.48 | AK43: =BB320 -> 0.51 | AL43: =BC320 -> 0.45 | AM43: =BD320 -> 0.54 | AN43: =BE320 -> 0.55 | AO43: =BF320 -> 0.52 | AP43: =BG320 -> - | ... AV43: =BM320 -> -
B44: PT Nusa Palapa Gemilang Tbk | C44: =AB422 -> 2.2 | D44: =AC422 -> 2.99 | E44: =AD422 -> 5.18 | F44: =AE422 -> 0.83 | G44: =AF422 -> 1.26 | I44: PT Nusa Palapa Gemilang Tbk | J44: =AB421 -> 1.39 | K44: =AC421 -> 1.68 | L44: =AD421 -> 2.58 | M44: =AE421 -> 0.55 | N44: =AF421 -> 0.83 | Q44: PT Nusa Palapa Gemilang Tbk | R44: =AZ476 -> 1.78 | S44: =BA476 -> 1.79 | T44: =BB476 -> 2.2 | U44: =BC476 -> 2.67 | V44: =BD476 -> 2.97 | W44: =BE476 -> 2.62 | X44: =BF476 -> 2.99 | Y44: =BG476 -> 5.9 | ... AE44: =BM476 -> 3.43 | AH44: PT Nusa Palapa Gemilang Tbk | AI44: =AZ475 -> 1.07 | AJ44: =BA475 -> 1.08 | AK44: =BB475 -> 1.39 | AL44: =BC475 -> 1.54 | AM44: =BD475 -> 1.6 | AN44: =BE475 -> 1.6 | AO44: =BF475 -> 1.68 | AP44: =BG475 -> 2.68 | ... AW44: =BN475
B47: Inventory Turnover | C47: TAHUNAN | I47: Debt to Equity Ratio (DER) | J47: TAHUNAN | Q47: Inventory Turnover | R47: QUARTAL | AH47: Debt to Equity Ratio (DER) | AI47: QUARTAL
C48: FY 2025 | D48: FY 2024 | E48: FY 2023 | F48: FY 2022 | G48: FY 2021 | J48: FY 2025 | K48: FY 2024 | L48: FY 2023 | M48: FY 2022 | N48: FY 2021 | R48: Q2 2026 | S48: Q1 2026 | T48: Q4 2025 | U48: Q3 2025 | V48: Q2 2025 | W48: Q1 2025 | X48: Q4 2024 | Y48: Q3 2024 | Z48: Q2 2024 | AA48: Q1 2024 | AB48: Q4 2023 | AC48: Q3 2023 | AD48: Q2 2023 | AE48: Q1 2023 | AI48: Q2 2026 | AJ48: Q1 2026 | AK48: Q4 2025 | AL48: Q3 2025 | AM48: Q2 2025 | AN48: Q1 2025 | AO48: Q4 2024 | AP48: Q3 2024 | AQ48: Q2 2024 | AR48: Q1 2024 | AS48: Q4 2023 | AT48: Q3 2023 | AU48: Q2 2023 | AV48: Q1 2023
B49: PT Pupuk Kalimatan Timur | C49: 310 | D49: 302 | E49: 204 | F49: 245 | G49: 163 | I49: PT Pupuk Kalimatan Timur | J49: 310 | K49: 302 | L49: 204 | M49: 245 | N49: 163 | Q49: PT Pupuk Kalimatan Timur | AH49: PT Pupuk Kalimatan Timur
B50: PT Saraswati Anugerah Makmur Tbk | C50: =AB108 -> 3.6 | D50: =AC108 -> 3.37 | E50: =AD108 -> 2.3 | F50: =AE108 -> 2.31 | G50: =AF108 -> 2.42 | I50: PT Saraswati Anugerah Makmur Tbk | J50: =AB101 -> 0.41 | K50: =AC101 -> 0.5 | L50: =AD101 -> 0.57 | M50: =AE101 -> 0.74 | N50: =AF101 -> 0.62 | Q50: PT Saraswati Anugerah Makmur Tbk | R50: =AZ161 -> 3.06 | S50: =BA161 -> 1.64 | T50: =BB161 -> 3.66 | U50: =BC161 -> 3.05 | V50: =BD161 -> 2.41 | W50: =BE161 -> 2.16 | X50: =BF161 -> 3.6 | Y50: =BG161 -> 3.14 | ... AE50: =BM161 -> 3.35 | AH50: PT Saraswati Anugerah Makmur Tbk | AI50: =AZ154 -> 0.79 | AJ50: =BA154 -> 0.47 | AK50: =BB154 -> 0.41 | AL50: =BC154 -> 0.52 | AM50: =BD154 -> 0.76 | AN50: =BE154 -> 0.51 | AO50: =BF154 -> 0.5 | AP50: =BG154 -> 0.75 | ... AV50: =BM154 -> 0.84
B51: PT Delta Giri Wacana Tbk | C51: =AB242 -> 2.37 | D51: =AC242 -> 2.58 | E51: =AD242 -> 2.46 | F51: =AE242 -> 2.16 | I51: PT Delta Giri Wacana Tbk | J51: =AB235 -> 1.03 | K51: =AC235 -> 1.28 | L51: =AD235 -> 1.14 | M51: =AE235 -> 1.45 | N51: =AF235 -> 0.8 | Q51: PT Delta Giri Wacana Tbk | R51: =AZ319 -> 2.02 | S51: =BA319 -> 2.05 | T51: =BB319 -> 2.99 | U51: =BC319 -> 2.27 | V51: =BD319 -> 2.31 | W51: =BE319 -> 2.37 | X51: =BF319 -> - | Y51: =BG319 -> - | ... AE51: =BM319 -> - | AH51: PT Delta Giri Wacana Tbk | AI51: =AZ312 -> 1.05 | AJ51: =BA312 -> 1.05 | AK51: =BB312 -> 1.03 | AL51: =BC312 -> 1.12 | AM51: =BD312 -> 1.09 | AN51: =BE312 -> 1.02 | AO51: =BF312 -> 1.28 | AP51: =BG312 -> - | ... AV51: =BM312 -> 1.45
B52: PT Nusa Palapa Gemilang Tbk | C52: =AB420 -> 1.87 | D52: =AC420 -> 1.29 | E52: =AD420 -> 0.68 | F52: =AE420 -> 2.42 | G52: =AF420 -> 4.1 | I52: PT Nusa Palapa Gemilang Tbk | J52: =AB414 -> 0.5 | K52: =AC414 -> 0.31 | L52: =AD414 -> 0.12 | M52: =AE414 -> 0.92 | N52: =AF414 -> 0.66 | Q52: PT Nusa Palapa Gemilang Tbk | R52: =AZ474 -> 1.67 | S52: =BA474 -> - | T52: =BB474 -> 3.25 | U52: =BC474 -> 1.69 | V52: =BD474 -> 0.91 | W52: =BE474 -> 1.23 | X52: =BF474 -> 2.07 | Y52: =BG474 -> 1.49 | ... AE52: =BM474 -> 3.48 | AH52: PT Nusa Palapa Gemilang Tbk | AI52: =AZ467 -> 0.76 | AJ52: =BA467 -> 0.73 | AK52: =BB467 -> 0.5 | AL52: =BC467 -> 0.36 | AM52: =BD467 -> 0.31 | AN52: =BE467 -> 0.38 | AO52: =BF467 -> 0.31 | AP52: =BG467 -> 0.12 | ... AV52: =BM467 -> 0.33
B54: Days Inventory Outstanding | C54: TAHUNAN | I54: Days Sales Outstanding | J54: TAHUNAN | Q54: Days Inventory Outstanding | R54: QUARTAL | AH54: Days Sales Outstanding | AI54: QUARTAL
C55: FY 2025 | D55: FY 2024 | E55: FY 2023 | F55: FY 2022 | G55: FY 2021 | J55: FY 2025 | K55: FY 2024 | L55: FY 2023 | M55: FY 2022 | N55: FY 2021 | R55: Q2 2026 | S55: Q1 2026 | T55: Q4 2025 | U55: Q3 2025 | V55: Q2 2025 | W55: Q1 2025 | X55: Q4 2024 | Y55: Q3 2024 | Z55: Q2 2024 | AA55: Q1 2024 | AB55: Q4 2023 | AC55: Q3 2023 | AD55: Q2 2023 | AE55: Q1 2023 | AI55: Q2 2026 | AJ55: Q1 2026 | AK55: Q4 2025 | AL55: Q3 2025 | AM55: Q2 2025 | AN55: Q1 2025 | AO55: Q4 2024 | AP55: Q3 2024 | AQ55: Q2 2024 | AR55: Q1 2024 | AS55: Q4 2023 | AT55: Q3 2023 | AU55: Q2 2023 | AV55: Q1 2023
B56: PT Pupuk Kalimatan Timur | C56: 310 | D56: 302 | E56: 204 | F56: 245 | G56: 163 | I56: PT Pupuk Kalimatan Timur | J56: 310 | K56: 302 | L56: 204 | M56: 245 | N56: 163 | Q56: PT Pupuk Kalimatan Timur | R56: =CCC!Q115 -> #REF! | S56: =CCC!R115 -> #REF! | T56: =CCC!S115 -> #REF! | U56: =CCC!T115 -> #REF! | V56: =CCC!U115 -> #REF! | AH56: PT Pupuk Kalimatan Timur | AI56: =CCC!Q116 -> #REF! | AJ56: =CCC!R116 -> #REF! | AK56: =CCC!S116 -> #REF! | AL56: =CCC!T116 -> #REF! | AM56: =CCC!U116 -> #REF!
B57: PT Saraswati Anugerah Makmur Tbk | C57: =CCC!B79 -> #REF! | D57: =CCC!C79 -> #REF! | E57: =CCC!D79 -> #REF! | F57: =CCC!E79 -> #REF! | I57: PT Saraswati Anugerah Makmur Tbk | J57: =CCC!B80 -> #REF! | K57: =CCC!C80 -> #REF! | L57: =CCC!D80 -> #REF! | M57: =CCC!E80 -> #REF! | N57: =CCC!F80 -> #REF! | Q57: PT Saraswati Anugerah Makmur Tbk | R57: =CCC!I79 -> #REF! | S57: =CCC!J79 -> #REF! | T57: =CCC!K79 -> #REF! | U57: =CCC!L79 -> #REF! | V57: =CCC!M79 -> #REF! | W57: =CCC!N79 -> #REF! | X57: =CCC!O79 -> #REF! | Y57: =CCC!P79 -> #REF! | ... AE57: =CCC!V79 -> #REF! | AH57: PT Saraswati Anugerah Makmur Tbk | AI57: =CCC!I80 -> #REF! | AJ57: =CCC!J80 -> #REF! | AK57: =CCC!K80 -> #REF! | AL57: =CCC!L80 -> #REF! | AM57: =CCC!M80 -> #REF! | AN57: =CCC!N80 -> #REF! | AO57: =CCC!O80 -> #REF! | AP57: =CCC!P80 -> #REF! | ... AV57: =CCC!V80 -> #REF!
B58: PT Delta Giri Wacana Tbk | C58: =CCC!B97 -> #REF! | D58: =CCC!C97 -> #REF! | E58: =CCC!D97 -> #REF! | F58: =CCC!E97 -> #REF! | G58: =CCC!F97 -> #REF! | I58: PT Delta Giri Wacana Tbk | J58: =CCC!B98 -> #REF! | K58: =CCC!C98 -> #REF! | L58: =CCC!D98 -> #REF! | M58: =CCC!E98 -> #REF! | N58: =CCC!F98 -> #REF! | Q58: PT Delta Giri Wacana Tbk | R58: =CCC!I97 -> #REF! | S58: =CCC!J97 -> #REF! | T58: =CCC!K97 -> #REF! | U58: =CCC!L97 -> #REF! | V58: =CCC!M97 -> #REF! | W58: =CCC!N97 -> #REF! | X58: 0 | Y58: 0 | Z58: 0 | AA58: 0 | AB58: =CCC!S97 -> #REF! | AC58: 0 | AD58: 0 | AE58: 0 | AH58: PT Delta Giri Wacana Tbk | AI58: =CCC!I98 -> #REF! | AJ58: =CCC!J98 -> #REF! | AK58: =CCC!K98 -> #REF! | AL58: =CCC!L98 -> #REF! | AM58: =CCC!M98 -> #REF! | AN58: =CCC!N98 -> #REF! | AO58: 0 | AP58: 0 | AQ58: 0 | AR58: 0 | AS58: =CCC!S98 -> #REF! | AT58: 0 | AU58: 0 | AV58: 0
B59: PT Nusa Palapa Gemilang Tbk | C59: =CCC!B133 -> #REF! | D59: =CCC!C133 -> #REF! | E59: =CCC!D133 -> #REF! | F59: =CCC!E133 -> #REF! | G59: =CCC!F133 -> #REF! | I59: PT Nusa Palapa Gemilang Tbk | J59: =CCC!B134 -> #REF! | K59: =CCC!C134 -> #REF! | L59: =CCC!D134 -> #REF! | M59: =CCC!E134 -> #REF! | N59: =CCC!F134 -> #REF! | Q59: PT Nusa Palapa Gemilang Tbk | R59: =CCC!I133 -> #REF! | S59: =CCC!J133 -> #REF! | T59: =CCC!K133 -> #REF! | U59: =CCC!L133 -> #REF! | V59: =CCC!M133 -> #REF! | W59: =CCC!N133 -> #REF! | X59: =CCC!O133 -> #REF! | Y59: =CCC!P133 -> #REF! | ... AE59: =CCC!V133 -> #REF! | AH59: PT Nusa Palapa Gemilang Tbk | AI59: =CCC!I134 -> #REF! | AJ59: =CCC!J134 -> #REF! | AK59: =CCC!K134 -> #REF! | AL59: =CCC!L134 -> #REF! | AM59: =CCC!M134 -> #REF! | AN59: =CCC!N134 -> #REF! | AO59: =CCC!O134 -> #REF! | AP59: =CCC!P134 -> #REF! | ... AV59: =CCC!V134 -> #REF!
B61: Days Payable Outstanding | C61: TAHUNAN | I61: Cash Conversion Cycle (CCC) | J61: TAHUNAN | Q61: Days Payable Outstanding | R61: QUARTAL | AH61: Cash Conversion Cycle (CCC) | AI61: QUARTAL
C62: FY 2025 | D62: FY 2024 | E62: FY 2023 | F62: FY 2022 | G62: FY 2021 | J62: FY 2025 | K62: FY 2024 | L62: FY 2023 | M62: FY 2022 | N62: FY 2021 | R62: Q2 2026 | S62: Q1 2026 | T62: Q4 2025 | U62: Q3 2025 | V62: Q2 2025 | W62: Q1 2025 | X62: Q4 2024 | Y62: Q3 2024 | Z62: Q2 2024 | AA62: Q1 2024 | AB62: Q4 2023 | AC62: Q3 2023 | AD62: Q2 2023 | AE62: Q1 2023 | AI62: Q2 2026 | AJ62: Q1 2026 | AK62: Q4 2025 | AL62: Q3 2025 | AM62: Q2 2025 | AN62: Q1 2025 | AO62: Q4 2024 | AP62: Q3 2024 | AQ62: Q2 2024 | AR62: Q1 2024 | AS62: Q4 2023 | AT62: Q3 2023 | AU62: Q2 2023 | AV62: Q1 2023
B63: PT Pupuk Kalimatan Timur | C63: 310 | D63: 302 | E63: 204 | F63: 245 | G63: 163 | I63: PT Pupuk Kalimatan Timur | J63: 310 | K63: 302 | L63: 204 | M63: 245 | N63: 163 | Q63: PT Pupuk Kalimatan Timur | R63: =CCC!Q117 -> #REF! | S63: =CCC!R117 -> #REF! | T63: =CCC!S117 -> #REF! | U63: =CCC!T117 -> #REF! | V63: =CCC!U117 -> #REF! | AH63: PT Pupuk Kalimatan Timur | AI63: =CCC!Q118 -> #REF! | AJ63: =CCC!R118 -> #REF! | AK63: =CCC!S118 -> #REF! | AL63: =CCC!T118 -> #REF! | AM63: =CCC!U118 -> #REF!
B64: PT Saraswati Anugerah Makmur Tbk | C64: =CCC!B81 -> #REF! | D64: =CCC!C81 -> #REF! | E64: =CCC!D81 -> #REF! | F64: =CCC!E81 -> #REF! | G64: =CCC!F81 -> #REF! | I64: PT Saraswati Anugerah Makmur Tbk | J64: =CCC!B82 -> #REF! | K64: =CCC!C82 -> #REF! | L64: =CCC!D82 -> #REF! | M64: =CCC!E82 -> #REF! | N64: =CCC!F82 -> #REF! | Q64: PT Saraswati Anugerah Makmur Tbk | R64: =CCC!I81 -> #REF! | S64: =CCC!J81 -> #REF! | T64: =CCC!K81 -> #REF! | U64: =CCC!L81 -> #REF! | V64: =CCC!M81 -> #REF! | W64: =CCC!N81 -> #REF! | X64: =CCC!O81 -> #REF! | Y64: =CCC!P81 -> #REF! | ... AE64: =CCC!V81 -> #REF! | AH64: PT Saraswati Anugerah Makmur Tbk | AI64: =CCC!I82 -> #REF! | AJ64: =CCC!J82 -> #REF! | AK64: =CCC!K82 -> #REF! | AL64: =CCC!L82 -> #REF! | AM64: =CCC!M82 -> #REF! | AN64: =CCC!N82 -> #REF! | AO64: =CCC!O82 -> #REF! | AP64: =CCC!P82 -> #REF! | ... AV64: =CCC!V82 -> #REF!
B65: PT Delta Giri Wacana Tbk | C65: =CCC!B99 -> #REF! | D65: =CCC!C99 -> #REF! | E65: =CCC!D99 -> #REF! | F65: =CCC!E99 -> #REF! | G65: =CCC!F99 -> #REF! | I65: PT Delta Giri Wacana Tbk | J65: =CCC!B100 -> #REF! | K65: =CCC!C100 -> #REF! | L65: =CCC!D100 -> #REF! | M65: =CCC!E100 -> #REF! | N65: =CCC!F100 -> #REF! | Q65: PT Delta Giri Wacana Tbk | R65: =CCC!I99 -> #REF! | S65: =CCC!J99 -> #REF! | T65: =CCC!K99 -> #REF! | U65: 0 | V65: 0 | W65: =CCC!N99 -> #REF! | X65: 0 | Y65: 0 | Z65: 0 | AA65: 0 | AB65: =CCC!S99 -> #REF! | AC65: 0 | AD65: 0 | AE65: 0 | AH65: PT Delta Giri Wacana Tbk | AI65: =CCC!I100 -> #REF! | AJ65: =CCC!J100 -> #REF! | AK65: =CCC!K100 -> #REF! | AL65: 0 | AM65: 0 | AN65: =CCC!N100 -> #REF! | AO65: 0 | AP65: 0 | AQ65: 0 | AR65: 0 | AS65: =CCC!S100 -> #REF! | AT65: 0 | AU65: 0 | AV65: 0
B66: PT Nusa Palapa Gemilang Tbk | C66: =CCC!B135 -> #REF! | D66: =CCC!C135 -> #REF! | E66: =CCC!D135 -> #REF! | F66: =CCC!E135 -> #REF! | G66: =CCC!F135 -> #REF! | I66: PT Nusa Palapa Gemilang Tbk | J66: =CCC!B136 -> #REF! | K66: =CCC!C136 -> #REF! | L66: =CCC!D136 -> #REF! | M66: =CCC!E136 -> #REF! | N66: =CCC!F136 -> #REF! | Q66: PT Nusa Palapa Gemilang Tbk | R66: =CCC!I135 -> #REF! | S66: =CCC!J135 -> #REF! | T66: =CCC!K135 -> #REF! | U66: =CCC!L135 -> #REF! | V66: =CCC!M135 -> #REF! | W66: =CCC!N135 -> #REF! | X66: =CCC!O135 -> #REF! | Y66: =CCC!P135 -> #REF! | ... AE66: =CCC!V135 -> #REF! | AH66: PT Nusa Palapa Gemilang Tbk | AI66: =CCC!I136 -> #REF! | AJ66: =CCC!J136 -> #REF! | AK66: =CCC!K136 -> #REF! | AL66: =CCC!L136 -> #REF! | AM66: =CCC!M136 -> #REF! | AN66: =CCC!N136 -> #REF! | AO66: =CCC!O136 -> #REF! | AP66: =CCC!P136 -> #REF! | ... AV66: =CCC!V136 -> #REF!
B68: Net Working Capital | C68: TAHUNAN | Q68: Net Working Capital | R68: QUARTAL
C69: FY 2025 | D69: FY 2024 | E69: FY 2023 | F69: FY 2022 | G69: FY 2021 | R69: Q2 2026 | S69: Q1 2026 | T69: Q4 2025 | U69: Q3 2025 | V69: Q2 2025 | W69: Q1 2025 | X69: Q4 2024 | Y69: Q3 2024 | Z69: Q2 2024 | AA69: Q1 2024 | AB69: Q4 2023 | AC69: Q3 2023 | AD69: Q2 2023 | AE69: Q1 2023
B70: PT Pupuk Kalimatan Timur | C70: =CCC!B119 -> #REF! | D70: =CCC!C119 -> #REF! | E70: =CCC!D119 -> #REF! | F70: =CCC!E119 -> #REF! | G70: =CCC!F119 -> #REF! | Q70: PT Pupuk Kalimatan Timur | R70: =CCC!Q119 -> #REF! | S70: =CCC!R119 -> #REF! | T70: =CCC!S119 -> #REF! | U70: =CCC!T119 -> #REF! | V70: =CCC!U119 -> #REF!
B71: PT Saraswati Anugerah Makmur Tbk | C71: =CCC!B83 -> #REF! | D71: =CCC!C83 -> #REF! | E71: =CCC!D83 -> #REF! | F71: =CCC!E83 -> #REF! | G71: =CCC!F83 -> #REF! | Q71: PT Saraswati Anugerah Makmur Tbk | R71: =CCC!I83 -> #REF! | S71: =CCC!J83 -> #REF! | T71: =CCC!K83 -> #REF! | U71: =CCC!L83 -> #REF! | V71: =CCC!M83 -> #REF! | W71: =CCC!N83 -> #REF! | X71: =CCC!O83 -> #REF! | Y71: =CCC!P83 -> #REF! | ... AE71: =CCC!V83 -> #REF!
B72: PT Delta Giri Wacana Tbk | C72: =CCC!B101 -> #REF! | D72: =CCC!C101 -> #REF! | E72: =CCC!D101 -> #REF! | F72: =CCC!E101 -> #REF! | G72: =CCC!F101 -> #REF! | Q72: PT Delta Giri Wacana Tbk | R72: =CCC!I101 -> #REF! | S72: =CCC!J101 -> #REF! | T72: =CCC!K101 -> #REF! | U72: =CCC!L101 -> #REF! | V72: 0 | W72: =CCC!N101 -> #REF! | X72: =CCC!O101 -> #REF! | Y72: 0 | Z72: =CCC!Q101 -> #REF! | AA72: 0 | AB72: =CCC!S101 -> #REF! | AC72: =CCC!T101 -> #REF! | AD72: 0 | AE72: 0
B73: PT Nusa Palapa Gemilang Tbk | C73: =CCC!B137 -> #REF! | D73: =CCC!C137 -> #REF! | E73: =CCC!D137 -> #REF! | F73: =CCC!E137 -> #REF! | G73: =CCC!F137 -> #REF! | Q73: PT Nusa Palapa Gemilang Tbk | R73: =CCC!I137 -> #REF! | S73: =CCC!J137 -> #REF! | T73: =CCC!K137 -> #REF! | U73: =CCC!L137 -> #REF! | V73: =CCC!M137 -> #REF! | W73: =CCC!N137 -> #REF! | X73: =CCC!O137 -> #REF! | Y73: =CCC!P137 -> #REF! | ... AE73: =CCC!V137 -> #REF!
C75: TAHUNAN | Q75: EBITDA MARGIN | R75: QUARTAL
B76: EBITDA MARGIN | C76: FY 2025 | D76: FY 2024 | E76: FY 2023 | F76: FY 2022 | G76: FY 2021 | R76: Q2 2026 | S76: Q1 2026 | T76: Q4 2025 | U76: Q3 2025 | V76: Q2 2025 | W76: Q1 2025 | X76: Q4 2024 | Y76: Q3 2024 | Z76: Q2 2024 | AA76: Q1 2024 | AB76: Q4 2023 | AC76: Q3 2023 | AD76: Q2 2023 | AE76: Q1 2023
B77: PT Pupuk Kalimatan Timur | C77: 24.45 | D77: 28 | E77: 32.02 | F77: 55.01 | G77: 38.21 | Q77: PT Pupuk Kalimatan Timur
B78: PT Saraswati Anugerah Makmur Tbk | C78: =D123 -> 0.1103 | D78: =E123 -> 0.1316 | E78: =F123 -> 0.1417 | F78: =G123 -> 0.146 | G78: =H123 -> 0.1426 | Q78: PT Saraswati Anugerah Makmur Tbk | R78: =C177 -> 0.1052 | S78: =D177 -> 0.1211 | T78: =E177 -> 0.1082 | U78: =F177 -> 0.1212 | V78: =G177 -> 0.1045 | W78: =H177 -> 0.103 | X78: =I177 -> 0.1198 | Y78: =J177 -> 0.1281 | ... AE78: =P177 -> 0.1399
B79: PT Delta Giri Wacana Tbk | C79: =D261 -> 0.1043 | D79: =E261 -> 0.0896 | E79: =F261 -> 0.0404 | F79: =G261 -> 0.0783 | G79: =H261 -> 0.0893 | Q79: PT Delta Giri Wacana Tbk | R79: =C324 -> 0.099 | S79: =D324 -> 0.0965 | T79: =E324 -> 0.1332 | U79: =F324 -> 0.1137 | V79: =G324 -> 0.0725 | W79: =H324 -> 0.0856 | X79: =I324 -> 0.1379 | Y79: =J324 -> 0.0844 | ... AE79: =P324 -> 0.0044
B80: PT Nusa Palapa Gemilang Tbk | C80: =D436 -> 0.0678 | D80: =E436 -> 0.0944 | E80: =F436 -> -0.5108 | F80: =G436 -> -0.1457 | G80: =H436 -> 0.0845 | Q80: PT Nusa Palapa Gemilang Tbk | R80: =C487 -> 0.0703 | S80: =D487 -> 0.1133 | T80: =E487 -> 0.014 | U80: =F487 -> 0.0935 | V80: =G487 -> 0.125 | W80: =H487 -> 0.1112 | X80: =I487 -> 0.0573 | Y80: =J487 -> 0.1044 | ... AE80: =P487 -> -
B83: PT Saraswati Anugerah Makmur Tbk
B84: PT Saraswati Anugerah Makmur Tbk - INCOME STATEMENT | J84: PT Saraswati Anugerah Makmur Tbk - BALANCE SHEET | R84: PT Saraswati Anugerah Makmur Tbk - CASH FLOW | Z84: PT Saraswati Anugerah Makmur Tbk - RATIOS | AH84: Saraswati | AQ84: Keterangan | AR84: 2026 | AS84: 2025 | AT84: 2024 | AU84: 2023 | AV84: 2022 | AW84: 2021
B85: Fiscal Year | C85: TTM | D85: FY 2025 | E85: FY 2024 | F85: FY 2023 | G85: FY 2022 | H85: FY 2021 | J85: Fiscal Year | K85: TTM | L85: FY 2025 | M85: FY 2024 | N85: FY 2023 | O85: FY 2022 | P85: FY 2021 | R85: Fiscal Year | S85: TTM | T85: FY 2025 | U85: FY 2024 | V85: FY 2023 | W85: FY 2022 | X85: FY 2021 | Z85: Fiscal Year | AA85: Current | AB85: FY 2025 | AC85: FY 2024 | AD85: FY 2023 | AE85: FY 2022 | AF85: FY 2021 | AH85: Item | AI85: 2024 (Rp) Juni | AJ85: 2023 (Rp) Juni | AK85: 2022 (Rp) Juni | AL85: 2021 (Rp) Juni | AN85: Historical Beban Gaji Konsolidasi | AQ85: Bahan baku | AR85: 424055399013 | AS85: 409659037329 | AT85: 366553137250 | AU85: 820046808911 | AV85: 284510340637 | AW85: 95744376662 | BW85: 28943123990 | BX85: 6960129613 | BY85: 4232292850 | BZ85: 2862205525 | CA85: 2247025099 | CB85: 2114880447 | CC85: 242576716 | CD85: 190946431 | CF85: 217974631 | CG85: -42763491429 | CH85: -42763491429 | CI85: 0 | CJ85: 120000000 | CK85: 0 | CL85: 1924170512 | CM85: 5850307520 | CN85: 0 | CO85: -12697783981 | CQ85: -1903101
B86: Period Ending | C86: 46112 | D86: 46022 | E86: 45657 | F86: 45291 | G86: 44926 | H86: 44561 | J86: Period Ending | K86: 46112 | L86: 46022 | M86: 45657 | N86: 45291 | O86: 44926 | P86: 44561 | R86: Period Ending | S86: 46112 | T86: 46022 | U86: 45657 | V86: 45291 | W86: 44926 | X86: 44561 | Z86: Period Ending | AA86: 46205 | AB86: 46022 | AC86: 45657 | AD86: 45291 | AE86: 44926 | AF86: 44561 | AH86: Sales (Penjualan) | AI86: 4797559081178 | AJ86: 4463507984781 | AK86: 3689403867254 | AL86: 1852362345299 | AQ86: Bahan pembantu | AR86: 39162815079 | AS86: 17690272435 | AT86: 19268703692 | AU86: 16371503326 | AV86: 20555531649 | AW86: 15694531071 | BW86: 26793372513 | BX86: 8163918270 | BY86: 3569913694 | BZ86: 2917323830 | CA86: 1933466330 | CB86: 1601055726 | CC86: 231648220 | CD86: 314294689 | CF86: 464507711 | CG86: -35785047862 | CH86: -35785047862 | CI86: 418236043 | CJ86: 125000000 | CK86: 148298862 | CL86: 118316996 | CM86: 12441654047 | CN86: 1706066800 | CO86: -8238490913 | CQ86: -333711157
B87: Revenue | C87: 3933269 | D87: 4074971 | E87: 4797559 | F87: 4463508 | G87: 3689404 | H87: 1852362 | J87: Cash & Equivalents | K87: 72179 | L87: 104892 | M87: 63422 | N87: 165356 | O87: 311155 | P87: 99824 | R87: Net Income | S87: 248878 | T87: 255421 | U87: 378865 | V87: 406352 | W87: 334149 | X87: 165349 | Z87: Market Capitalization | AA87: 2870000 | AB87: 3157000 | AC87: 3971875 | AD87: 3818125 | AE87: 2408750 | AF87: 5611875 | AH87: Cost of Sales (Beban Pokok Penjualan) | AI87: 3616258016133 | AJ87: 3368353247154 | AK87: 2802447155031 | AL87: 1377675973614 | AO87: ="Bulan "&$C$3&"2026" -> Bulan 2026 | AQ87: Bahan baku | AR87: 2014496300965 | AS87: 1423755565845 | AT87: 1546558831061 | AU87: 1353948861099 | AV87: 1024444841095 | AW87: 588225859025
B88: Revenue Growth (YoY) | C88: -0.0655 | D88: -0.1506 | E88: 0.0748 | F88: 0.2098 | G88: 0.9917 | H88: 0.3145 | J88: Cash & Short-Term Investments | K88: 72179 | L88: 104892 | M88: 63422 | N88: 165356 | O88: 311155 | P88: 99824 | R88: Depreciation & Amortization | S88: 45397 | T88: 42701 | U88: 35490 | V88: 28906 | W88: 24441 | X88: 23427 | Z88: Market Cap Growth | AA88: -0.2 | AB88: -0.2052 | AC88: 0.0403 | AD88: 0.5851 | AE88: -0.5708 | AF88: 1.7513 | AH88: Gross Profit (Laba Bruto) | AI88: 1181301065045 | AJ88: 1095154737627 | AK88: 886956712223 | AL88: 474686371685 | AN88: Beban Gaji PHL | AQ88: Bahan pembantu | AR88: 40845835675 | AS88: 44475248418 | AT88: 34105968434 | AU88: 26116783041 | AV88: 22932125308 | AW88: 23398804900
B89: Cost of Revenue | C89: 3103616 | D89: 3209068 | E89: 3617256 | F89: 3369057 | G89: 2803100 | H89: 1378324 | J89: Cash Growth | K89: -0.074 | L89: 0.6539 | M89: -0.6165 | N89: -0.4686 | O89: 2.117 | P89: 1.1562 | R89: Other Operating Activities | S89: -138144 | T89: 14847 | U89: -99898 | V89: -357876 | W89: -265488 | X89: -222300 | Z89: Enterprise Value | AA89: 3769211 | AB89: 3921470 | AC89: 5048548 | AD89: 4656319 | AE89: 3347445 | AF89: 6123362 | AH89: Other Income (Pendapatan lain-lain) | AI89: 3045512843 | AJ89: 6370670689 | AK89: 3766766861 | AL89: 15923835588 | AN89: Beban Gaji Staff Pabrik | AQ89: Bahan baku | AR89: 100342207786 | AS89: 92787354345 | AT89: 90867416867 | AU89: 44674908951 | AV89: 49590303265 | AW89: 42393472168
B90: Gross Profit | C90: 829653 | D90: 865903 | E90: 1180303 | F90: 1094451 | G90: 886304 | H90: 474038 | J90: Accounts Receivable | K90: 1059597 | L90: 1295708 | M90: 1231426 | N90: 807444 | O90: 601000 | P90: 503574 | R90: Operating Cash Flow | S90: 156131 | T90: 312968 | U90: 314457 | V90: 77381 | W90: 93102 | X90: -33523 | Z90: Last Close Price | AA90: 280 | AB90: 296.85 | AC90: 353.42 | AD90: 320.79 | AE90: 194.34 | AF90: 437.27 | AH90: Finance Income (Pendapatan keuangan) | AI90: 2368584914 | AJ90: 4027970345 | AK90: 5267517470 | AL90: 3965961994 | AN90: Beban Gaji Staff Kantor | AQ90: Bahan baku | AR90: -747005537967 | AS90: -695217203791 | AT90: -532840140491 | AU90: -395416634638 | AV90: -171955267593 | AW90: -179751639255
B91: Selling, General & Admin | C91: 416893 | D91: 443910 | E91: 563856 | F91: 470299 | G91: 328619 | H91: 226439 | J91: Receivables | K91: 1059597 | L91: 1295708 | M91: 1231426 | N91: 807444 | O91: 601000 | P91: 503574 | R91: Operating Cash Flow Growth | S91: -0.6558 | T91: -0.0047 | U91: 3.0637 | V91: -0.1689 | W91: - | X91: - | Z91: PE Ratio | AA91: 11.53 | AB91: 12.36 | AC91: 10.48 | AD91: 9.4 | AE91: 7.21 | AF91: 33.94 | AH91: Selling Expenses (Beban penjualan) | AI91: 472608557127 | AJ91: 385866338362 | AK91: 267706201995 | AL91: 167832396021 | AN91: Beban Gaji BOD | AQ91: Bahan pembantu | AR91: -41886595103 | AS91: -28636562748 | AT91: -19422864016 | AU91: -15705946273 | AV91: -19810646562 | AW91: -17507117355
B92: Other Operating Expenses | C92: 12520 | D92: 15322 | E92: 20520 | F92: 20767 | G92: 43395 | H92: 6915 | J92: Inventory | K92: 1352094 | L92: 901180 | M92: 880544 | N92: 1263391 | O92: 1669639 | P92: 758517 | R92: Capital Expenditures | S92: -45368 | T92: -61832 | U92: -189779 | V92: -41803 | W92: -93947 | X92: -32039 | Z92: PS Ratio | AA92: 0.73 | AB92: 0.78 | AC92: 0.83 | AD92: 0.86 | AE92: 0.65 | AF92: 3.03 | AH92: General & Administrative Expenses (Beban umum & administrasi) | AI92: 92244983993 | AJ92: 85136872318 | AK92: 61565555321 | AL92: 59254610070 | AN92: Beban Gaji Principal | AQ92: Pemakaian bahan baku dan pembantu | AR92: 1830010425448 | AS92: 1264513711833 | AT92: 1505091052797 | AU92: 1850036284417 | AV92: 1210267227799 | AW92: 568198287216
B93: Operating Expenses | C93: 429413 | D93: 459232 | E93: 584376 | F93: 491066 | G93: 372015 | H93: 233354 | J93: Prepaid Expenses | K93: - | L93: - | M93: - | N93: - | O93: 10.42 | P93: 49.69 | R93: Sale of Property, Plant & Equipment | S93: 1032 | T93: 1000 | U93: 198.2 | V93: 536.94 | W93: 631.99 | X93: 80 | Z93: PB Ratio | AA93: 1.49 | AB93: 1.67 | AC93: 2.54 | AD93: 2.77 | AE93: 2.15 | AF93: 6.51 | AH93: Finance Expenses (Beban keuangan) | AI93: 92880640981 | AJ93: 76737481801 | AK93: 81776480705 | AL93: 42066844267 | AN93: Beban Gaji Managemen | AQ93: Pemakaian bahan baku | AR93: 1791888369797 | AS93: 1230984753728 | AT93: 1471139244687 | AU93: 1823253944323 | AV93: 1186590217404 | AW93: 546612068600
B94: Operating Income | C94: 400240 | D94: 406672 | E94: 595927 | F94: 603385 | G94: 514290 | H94: 240684 | J94: Other Current Assets | K94: 155396 | L94: 13186 | M94: 45072 | N94: 143699 | O94: 96480 | P94: 51960 | R94: Investment in Securities | S94: - | T94: - | U94: 13800 | V94: 20700 | W94: - | X94: - | Z94: P/TBV Ratio | AA94: 1.54 | AB94: 1.72 | AC94: 2.64 | AD94: 2.86 | AE94: 2.22 | AF94: 6.71 | AH94: Other Expenses (Beban lain-lain) | AI94: 20520287599 | AJ94: 20847345111 | AK94: 43395347916 | AL94: 6915042100 | AN94: Beban Tenaga Kerja Tidak Langsung | AQ94: Pemakaian bahan pembantu | AR94: 38122055651 | AS94: 33528958105 | AT94: 33951808110 | AU94: 26782340094 | AV94: 23677010395 | AW94: 21586218616
B95: Interest Expense | C95: -66822 | D95: -67456 | E95: -81501 | F95: -65778 | G95: -68763 | H95: -33786 | J95: Total Current Assets | K95: 2639265 | L95: 2314966 | M95: 2220463 | N95: 2379890 | O95: 2678284 | P95: 1413924 | R95: Investing Cash Flow | S95: -44336 | T95: -60832 | U95: -175781 | V95: -20566 | W95: -93315 | X95: -31959 | Z95: P/FCF Ratio | AA95: 25.91 | AB95: 12.57 | AC95: 31.86 | AD95: 107.32 | AE95: - | AF95: - | AH95: Profit Before Tax (Laba Sebelum Pajak) | AI95: 508460693102 | AJ95: 536965341069 | AK95: 441547410617 | AL95: 218507276809 | AN95: Beban Tenaga Kerja Langsung | AQ95: Jumlah (Catatan 6) | AR95: 1830010425448 | AS95: 1264513711833 | AT95: 1505091052797 | AU95: 1850036284417 | AV95: 1210267227799 | AW95: 568198287216
B96: Interest & Investment Income | C96: 655.09 | D96: 788.43 | E96: 2369 | F96: 4028 | G96: 5268 | H96: 3966 | J96: Property, Plant & Equipment | K96: 845501 | L96: 847651 | M96: 557170 | N96: 391554 | O96: 378737 | P96: 309525 | R96: Short-Term Debt Issued | S96: - | T96: - | U96: - | V96: 4009982 | W96: 3338042 | X96: 2542640 | Z96: P/OCF Ratio | AA96: 18.38 | AB96: 10.09 | AC96: 12.63 | AD96: 49.34 | AE96: 25.87 | AF96: - | AH96: Current Tax (Pajak kini) | AI96: 114442499600 | AJ96: 118865457260 | AK96: 96642393320 | AL96: 46878223480 | AN96: Beban Gaji Staff Laboratorium | AQ96: Pemakaian bahan baku dan pembantu | AR96: 1830010425448 | AS96: 1264513711833 | AT96: 1505091052797 | AU96: 1850036284417 | AV96: 1210267227799 | AW96: 568198287216
B97: Currency Exchange Gain (Loss) | C97: -178.24 | D97: -29.95 | E97: - | F97: - | G97: - | H97: - | J97: Long-Term Investments | K97: - | L97: - | M97: - | N97: 13800 | O97: 34500 | P97: 34500 | R97: Long-Term Debt Issued | S97: - | T97: 4154477 | U97: 4939538 | V97: 145098 | W97: 820826 | X97: 742.26 | Z97: EV/Sales Ratio | AA97: 0.96 | AB97: 0.96 | AC97: 1.05 | AD97: 1.04 | AE97: 0.91 | AF97: 3.31 | AH97: Deferred Tax (Pajak tangguhan) | AI97: 2797164982 | AJ97: 1977516849 | AK97: 1087294161 | AL97: 483013841 | AN97: Total Beban Gaji | AQ97: Gaji dan upah tenaga kerja | AR97: 62266843151 | AS97: 47644896693 | AT97: 59206305875 | AU97: 37564955048 | AV97: 28981053478 | AW97: 21294142329
B98: Other Non Operating Income (Expenses) | C98: -2350 | D98: 1395 | E98: -8532 | F98: -5365 | G98: -9585 | H98: 7563 | J98: Long-Term Deferred Tax Assets | K98: 12267 | L98: 12574 | M98: 10728 | N98: 8421 | O98: 6260 | P98: 5175 | R98: Total Debt Issued | S98: 4193971 | T98: 4154477 | U98: 4939538 | V98: 4155080 | W98: 4158868 | X98: 2543382 | Z98: EV/EBITDA Ratio | AA98: 8.46 | AB98: 8.73 | AC98: 8 | AD98: 7.36 | AE98: 6.21 | AF98: 23.19 | AH98: Income Tax Expense (Beban Pajak Penghasilan) | AI98: 111645334618 | AJ98: 116887940411 | AK98: 95555099159 | AL98: 47361237321 | AN98: Total Beban | AQ98: Penyusutan (Catatan 8) | AR98: 19930725937 | AS98: 15834696022 | AT98: 14211470347 | AU98: 11052379179 | AV98: 10418910422 | AW98: 10221563885
B99: EBT Excluding Unusual Items | C99: 331545 | D99: 341369 | E99: 508262 | F99: 536270 | G99: 441209 | H99: 218427 | J99: Total Assets | K99: 3497033 | L99: 3175191 | M99: 2788362 | N99: 2793665 | O99: 3097782 | P99: 1763124 | R99: Short-Term Debt Repaid | S99: - | T99: - | U99: - | V99: -4058915 | W99: -3847179 | X99: -2301340 | Z99: EV/EBIT Ratio | AA99: 9.42 | AB99: 9.64 | AC99: 8.47 | AD99: 7.72 | AE99: 6.51 | AF99: 25.44 | AH99: Profit for the Year (Laba Tahun Berjalan) | AI99: 396815358484 | AJ99: 420077400658 | AK99: 345992311458 | AL99: 171146039488 | AN99: % Beban Gaji terhadap Total Beban | AQ99: Biaya overhead pabrik | AR99: 93726806062 | AS99: 92973003315 | AT99: 91200982207 | AU99: 23805003770 | AV99: 42668822315 | AW99: 23377382926
B100: Gain (Loss) on Sale of Assets | C100: 956.9 | D100: 956.9 | E100: 198.2 | F100: 536.94 | G100: 338.26 | H100: 80 | J100: Accounts Payable | K100: 512392 | L100: 339600 | M100: 369394 | N100: 340374 | O100: 856188 | P100: 310219 | R100: Long-Term Debt Repaid | S100: - | T100: -4160248 | U100: -4963467 | V100: -139107 | W100: -14571 | X100: -33756 | Z100: EV/FCF Ratio | AA100: 34.03 | AB100: 15.62 | AC100: 40.49 | AD100: 130.87 | AE100: - | AF100: - | AN100: % Beban Gaji terhadap Revenue | AQ100: Jumlah biaya produksi | AR100: 2005934800598 | AS100: 1420966307863 | AT100: 1669709811226 | AU100: 1922458622414 | AV100: 1292336014015 | AW100: 623091376356
B101: Other Unusual Items | C101: - | D101: - | E101: - | F101: -80.54 | G101: - | H101: - | J101: Accrued Expenses | K101: 5500 | L101: 44563 | M101: 18984 | N101: 5379 | O101: 3028 | P101: 6480 | R101: Total Debt Repaid | S101: -4103488 | T101: -4160248 | U101: -4963467 | V101: -4198022 | W101: -3861750 | X101: -2335096 | Z101: Debt / Equity Ratio | AA101: 0.47 | AB101: 0.41 | AC101: 0.5 | AD101: 0.57 | AE101: 0.74 | AF101: 0.62 | AH101: Laba Operasi | AI101: =AI88+AI89-AI91-AI92 -> 619493036768 | AJ101: =AJ88+AJ89-AJ91-AJ92 -> 630522197636 | AK101: =AK88+AK89-AK91-AK92 -> 561451721768 | AL101: =AL88+AL89-AL91-AL92 -> 263523201182 | AN101: Total Beban Gaji (Milliar) | AQ101: Persediaan barang jadi awal tahun | AR101: 403555350857 | AS101: 423262090912 | AT101: 819102970668 | AU101: 768552539195 | AV101: 453450912773 | AW101: 269823324846
B102: Pretax Income | C102: 332502 | D102: 342326 | E102: 508461 | F102: 536965 | G102: 441547 | H102: 218507 | J102: Short-Term Debt | K102: 798263 | L102: 649221 | M102: 615529 | N102: 730455 | O102: 784886 | P102: 520118 | R102: Net Debt Issued (Repaid) | S102: 90482 | T102: -5771 | U102: -23930 | V102: -42943 | W102: 297118 | X102: 208286 | Z102: Debt / EBITDA Ratio | AA102: 2.05 | AB102: 1.72 | AC102: 1.22 | AD102: 1.24 | AE102: 1.54 | AF102: 2.01 | AH102: NPM | AI102: =AI99/AI86 -> 0.082711927 | AJ102: =AJ99/AJ86 -> 0.094113733 | AK102: =AK99/AK86 -> 0.093780005 | AL102: =AL99/AL86 -> 0.092393392 | AQ102: Persediaan barang jadi akhir tahun | AR102: -816515709656 | AS102: -514295696226 | AT102: -681417015518 | AU102: -534919521285 | AV102: -651194239135 | AW102: -360420968380
B103: Income Tax Expense | C103: 72737 | D103: 74827 | E103: 111645 | F103: 116888 | G103: 95555 | H103: 47361 | J103: Current Portion of Long-Term Debt | K103: 29869 | L103: 29869 | M103: 29869 | N103: 10315 | O103: 10315 | P103: 10198 | R103: Common Dividends Paid | S103: -204895 | T103: -204895 | U103: -216681 | V103: -159672 | W103: -85573 | X103: -89278 | Z103: Debt / FCF Ratio | AA103: 8.24 | AB103: 3.08 | AC103: 6.2 | AD103: 22.09 | AE103: - | AF103: - | AQ103: Angkut dan distribusi | AR103: 157367702235 | AS103: 153190270558 | AT103: 221883517448 | AU103: 187258078533 | AV103: 100777314135 | AW103: 66332384101
B104: Earnings From Continuing Operations | C104: 259765 | D104: 267499 | E104: 396815 | F104: 420077 | G104: 345992 | H104: 171146 | J104: Current Portion of Leases | K104: 5207 | L104: 6079 | M104: 7915 | N104: 5542 | O104: 1571 | P104: 969.63 | R104: Financing Cash Flow | S104: -114413 | T104: -210666 | U104: -240610 | V104: -202614 | W104: 211544 | X104: 119009 | Z104: Net Debt / Equity Ratio | AA104: 0.44 | AB104: 0.35 | AC104: 0.45 | AD104: 0.45 | AE104: 0.46 | AF104: 0.5 | AN104: Historical Beban Transport Konsolidasi | AQ104: Pemasaran | AR104: 9021323237 | AS104: 8688169321 | AT104: 9944898065 | AU104: 8918654837 | AV104: 7625500007 | AW104: 3478127956
B105: Minority Interest in Earnings | C105: -10886 | D105: -12078 | E105: -17951 | F105: -13726 | G105: -11843 | H105: -5797 | J105: Current Income Taxes Payable | K105: 26078 | L105: 13201 | M105: 34184 | N105: 35937 | O105: 17127 | P105: 20432 | R105: Net Cash Flow | S105: -2617 | T105: 41470 | U105: -101934 | V105: -145799 | W105: 211331 | X105: 53527 | Z105: Net Debt / EBITDA Ratio | AA105: 1.89 | AB105: 1.49 | AC105: 1.12 | AD105: 0.98 | AE105: 0.96 | AF105: 1.64 | AQ105: Penelitian dan pengembangan | AR105: 1369580100 | AS105: 964233649 | AT105: 1525649749 | AU105: 1314210411 | AV105: 339182108 | AW105: 449756651
B106: Net Income | C106: 248878 | D106: 255421 | E106: 378865 | F106: 406352 | G106: 334149 | H106: 165349 | J106: Current Unearned Revenue | K106: 85878 | L106: 88983 | M106: 9874 | N106: 226565 | O106: 256570 | P106: 15117 | R106: Free Cash Flow | S106: 110764 | T106: 251136 | U106: 124677 | V106: 35579 | W106: -845.16 | X106: -65562 | Z106: Net Debt / FCF Ratio | AA106: 7.59 | AB106: 2.66 | AC106: 5.69 | AD106: 17.44 | AE106: -612.35 | AF106: -6.58 | AO106: ="Bulan "&$C$3&" 2026" -> Bulan 2026 | AQ106: Analisa | AV106: 802549275 | AW106: 525756123
B107: Net Income to Common | C107: 248878 | D107: 255421 | E107: 378865 | F107: 406352 | G107: 334149 | H107: 165349 | J107: Other Current Liabilities | K107: - | L107: - | M107: - | N107: - | O107: 285.92 | P107: 918.82 | R107: Free Cash Flow Growth | S107: -0.5973 | T107: 1.0143 | U107: 2.5043 | V107: - | W107: - | X107: - | Z107: Asset Turnover | AA107: 1.22 | AB107: 1.37 | AC107: 1.72 | AD107: 1.52 | AE107: 1.52 | AF107: 1.19 | AN107: Beban Transportasi Produk Jadi | AQ107: Promosi | AV107: 5111057 | AW107: 38043493
B108: Net Income Growth | C108: -0.1714 | D108: -0.3258 | E108: -0.0676 | F108: 0.2161 | G108: 1.0209 | H108: 0.4526 | J108: Total Current Liabilities | K108: 1463188 | L108: 1171515 | M108: 1085748 | N108: 1354566 | O108: 1929971 | P108: 884452 | R108: Free Cash Flow Margin | S108: 0.0282 | T108: 0.0616 | U108: 0.026 | V108: 0.008 | W108: -0.0002 | X108: -0.0354 | Z108: Inventory Turnover | AA108: 2.41 | AB108: 3.6 | AC108: 3.37 | AD108: 2.3 | AE108: 2.31 | AF108: 2.42 | AN108: Beban Transportasi Bahan Baku | AQ108: Biaya gaji dan tunjangan | AR108: 28943123990 | AS108: 26793372513 | AT108: 23821689402 | AU108: 24904153929 | AV108: 24222506267 | AW108: 18962068120
B109: Shares Outstanding (Basic) | C109: 10250 | D109: 10250 | E109: 10250 | F109: 10250 | G109: 10250 | H109: 10250 | J109: Long-Term Debt | K109: 76959 | L109: 84426 | M109: 114294 | N109: 32239 | O109: 30474 | P109: - | R109: Free Cash Flow Per Share | S109: 10.81 | T109: 24.5 | U109: 12.16 | V109: 3.47 | W109: -0.08 | X109: -6.4 | Z109: Quick Ratio | AA109: 0.77 | AB109: 1.2 | AC109: 1.19 | AD109: 0.72 | AE109: 0.47 | AF109: 0.68 | AN109: Beban Transportasi Impor | AQ109: Biaya kantor dan umum | AR109: 6960129613 | AS109: 8163918270 | AT109: 9952830379 | AU109: 6733919712 | AV109: 4964257286 | AW109: 4377825782
B110: Shares Outstanding (Diluted) | C110: 10250 | D110: 10250 | E110: 10250 | F110: 10250 | G110: 10250 | H110: 10250 | J110: Long-Term Leases | K110: 2889 | L110: 4063 | M110: 5543 | N110: 7201 | O110: 1448 | P110: 290.47 | R110: Cash Interest Paid | S110: 80919 | T110: 81552 | U110: 92881 | V110: 76737 | W110: 81776 | X110: 42067 | Z110: Current Ratio | AA110: 1.8 | AB110: 1.98 | AC110: 2.05 | AD110: 1.76 | AE110: 1.39 | AF110: 1.6 | AN110: Beban Transportasi Lainnya | AQ110: Biaya penyusutan (Catatan 8) | AR110: 4232292850 | AS110: 3569913694 | AT110: 3038926903 | AU110: 2055964450 | AV110: 2754400161 | AW110: 1340182445
B111: EPS (Basic) | C111: 24.28 | D111: 24.92 | E111: 36.96 | F111: 39.64 | G111: 32.6 | H111: 16.13 | J111: Pension & Post-Retirement Benefits | K111: 26834 | L111: 26834 | M111: 20829 | N111: 19582 | O111: 15569 | P111: 16170 | R111: Cash Income Tax Paid | S111: 79505 | T111: 54672 | U111: 588.75 | V111: 139620 | W111: 155238 | X111: 69228 | Z111: Return on Equity (ROE) | AA111: 0.1469 | AB111: 0.1551 | AC111: 0.2698 | AD111: 0.336 | AE111: 0.349 | AF111: 0.208 | AN111: Total Biaya Transportasi | AQ111: Biaya profesional fee | AR111: 2862205525 | AS111: 2917323830 | AT111: 2981576171 | AU111: 2435814892 | AV111: 1574590915 | AW111: 1480073771
B112: EPS (Diluted) | C112: 24.28 | D112: 24.92 | E112: 36.96 | F112: 39.64 | G112: 32.6 | H112: 16.13 | J112: Total Liabilities | K112: 1569869 | L112: 1286837 | M112: 1226414 | N112: 1413588 | O112: 1977461 | P112: 900913 | R112: Levered Free Cash Flow | S112: 54755 | T112: 193756 | U112: 48900 | V112: -49241 | W112: -64049 | X112: -106029 | Z112: Return on Assets (ROA) | AA112: 0.0778 | AB112: 0.0852 | AC112: 0.1335 | AD112: 0.128 | AE112: 0.1323 | AF112: 0.0969 | AN112: % Beban Transportasi to Total Beban | AQ112: Biaya asuransi | AR112: 2247025099 | AS112: 1933466330 | AT112: 2261409556 | AU112: 2172934143 | AV112: 1379457491 | AW112: 1076250706
B113: EPS Growth | C113: -0.1714 | D113: -0.3258 | E113: -0.0676 | F113: 0.2159 | G113: 1.0211 | H113: 0.4525 | J113: Common Stock | K113: 512500 | L113: 512500 | M113: 512500 | N113: 512500 | O113: 512500 | P113: 512500 | R113: Unlevered Free Cash Flow | S113: 96519 | T113: 235916 | U113: 99838 | V113: -8130 | W113: -21072 | X113: -84912 | Z113: Return on Invested Capital (ROIC) | AA113: 0.1174 | AB113: 0.1316 | AC113: 0.2177 | AD113: 0.2595 | AE113: 0.2749 | AF113: 0.1601 | AN113: % Biaya Transportasi to Revenue | AQ113: Biaya perjalanan dinas | AR113: 2114880447 | AS113: 1601055726 | AT113: 1963177190 | AU113: 1654207557 | AV113: 981636390 | AW113: 374453599
B114: Free Cash Flow | C114: 110764 | D114: 251136 | E114: 124677 | F114: 35579 | G114: -845.16 | H114: -65562 | J114: Additional Paid-In Capital | K114: 12031 | L114: 12031 | M114: 12031 | N114: 12031 | O114: 12031 | P114: 12031 | Z114: Return on Capital Employed (ROCE) | AA114: 0.197 | AB114: 0.203 | AC114: 0.35 | AD114: 0.419 | AE114: 0.44 | AF114: 0.274 | AN114: Biaya Transport Produk Jadi per kg | AQ114: Biaya utilitas | AR114: 242576716 | AS114: 231648220 | AT114: 209351498 | AU114: 232518485 | AV114: 169110628 | AW114: 106941169
B115: Free Cash Flow Per Share | C115: 10.81 | D115: 24.5 | E115: 12.16 | F115: 3.47 | G115: -0.08 | H115: -6.4 | J115: Retained Earnings | K115: 1080806 | L115: 1043184 | M115: 982513 | N115: 813774 | O115: 561172 | P115: 312596 | Z115: Earnings Yield | AA115: 0.0867 | AB115: 0.0809 | AC115: 0.0954 | AD115: 0.1064 | AE115: 0.1387 | AF115: 0.0295 | AN115: Total Biaya Transportasi (Milliar) | AQ115: Biaya perawatan | AR115: 190946431 | AS115: 314294689 | AT115: 475846567 | AU115: 336988007 | AV115: 355000670 | AW115: 555342604
...
