Workbook

Sheet LK Summary Data
A1: SUMMARY LABA RUGI 2026
A2: KONSOL & STAND ALONE
A5: Monthly Laba Rugi Konsolidasi 2026 | AB5: Monthly Neraca Konsolidasi 2026 | CF5: Monthly Arus Kas Konsolidasi 2026 | DQ5: Monthly CALK Konsolidasi 2026
B6: Penjualan | C6: Harga Pokok Penjualan | D6: Laba Kotor | E6: Beban Usaha | F6: Beban Umum dan Administrasi | G6: Beban Penjualan dan Pemasaran | H6: Beban Analisa Lab | I6: Jumlah Beban Usaha | J6: Laba Usaha | K6: Pendapatan (Beban) Lain-lain | L6: Pendapatan Lain-lain | M6: Beban Diluar Usaha Lainnya | N6: Jumlah Pendapatan (Beban) Lain-lain | P6: Laba Sebelum Pajak | Q6: Beban Pajak Penghasilan | R6: Pajak tangguhan | S6: Jumlah Beban Pajak | T6: Laba Bersih Setelah Pajak | U6: Penghasilan Komprehensif Lain | V6: Keuntungan/Kerugian aktuarial | W6: atas liabilitas imbalan kerja | X6: Jumlah Penghasilan (Rugi) Komprehensif Lain | AB6: ASET | AC6: Aset Lancar | AD6: Kas dan Setara Kas | AE6: Piutang Usaha | AF6: Anjak Piutang | AG6: Cadangan Kerugian Piutang Tak Tertagih | AH6: Piutang Lain Pihak Terkait | AI6: Persediaan | AJ6: Persediaan dalam Proses | AK6: Persediaan Barang Dagang | AL6: Biaya Dibayar Dimuka | AM6: Pajak Dibayar Dimuka | AN6: Jumlah Aset Lancar | AO6: Aset Tidak Lancar | AP6: Investasi | AQ6: Aset Tetap | AR6: Aset Tidak Lancar Lainnya | AU6: Aset Pajak Tangguhan | AV6: Jumlah Aset Tidak Lancar | AW6: Jumlah Aset | AY6: LIABILITAS DAN EKUITAS | AZ6: Liabilitas Lancar | BA6: Hutang Usaha | BC6: Barang yang belum terinvoice | BD6: Persediaan Barang Diterima Belum di BAST (LPB) | BE6: Hutang Pajak | BF6: Uang Muka Penjualan | BI6: Hutang Lain-Lain | BJ6: Hutang Bunga Bank | BK6: Hutang Bank Jangka Pendek | BL6: Jumlah Liabilitas Lancar | BM6: Liabilitas Tidak Lancar | BN6: Hutang Bank Jangka Panjang | BO6: Hutang Leasing | BP6: Hutang Pemegang Saham | BQ6: Hutang Imbalan Pasca Kerja | BR6: Liabilitas pajak tangguhan | BS6: Jumlah Liabilitas Tidak Lancar | BT6: Jumlah Liabilitas | BU6: Ekuitas | BV6: Modal Disetor | BW6: Saldo Laba | BX6: Laba-Rugi Periode Berjalan | BY6: Laba-Rugi Ditahan | BZ6: Akumulasi penghasilan komprehensif lain | CA6: Kepentingan non pengendali - Rugi/Laba | CB6: Kepentingan non pengendali - Modal | CC6: Jumlah Ekuitas | CD6: Jumlah Liabilitas dan Ekuitas | CG6: Arus Kas dari Aktivitas Operasi | CH6: Laba (rugi) bersih | CI6: Penyesuaian : | CJ6: Penyusutan | CK6: Akumulasi Komprehensif Lain | CM6: Penurunan (Kenaikan) : | CN6: Piutang usaha | CO6: Anjak Piutang | CP6: Piutang Afiliasi & Lainnya | CQ6: Biaya dibayar dimuka | CR6: Pajak dibayar dimuka | CS6: Persediaan | CT6: Kenaikan (Penurunan) : | CU6: Utang Usaha | CV6: Hutang Afiliasi & Lainnya | CW6: Utang Pajak | CX6: Uang Muka Penjualan | CY6: Biaya yg masih harus dibayar | CZ6: Hutang jangka Panjang | DA6: Kas Bersih yang digunakan untuk Aktivitas Operasi | DB6: Arus Kas dari Aktivitas Investasi : | DC6: (Penambahan) Pengurangan Aset Tetap | DD6: (Penambahan) Pengurangan Investasi | DE6: (Penambahan) Pengurangan Konstruksi Dalam Pengerjaan | DF6: Kas Bersih yang diperoleh/ digunakan untuk Aktivitas Investasi | DG6: Arus Kas dari Aktivitas Pendanaan : | DH6: Utang Bank | DI6: Modal di setor | DJ6: Kas Bersih yang diperoleh/ digunakan untuk Aktivitas Pendanaan | DK6: Kenaikan Kas & Setara Kas | DL6: Kas & Setara Kas awal periode | DM6: Kas & Setara Kas akhir periode | DR6: Penjualan | DT6: Retur Penjualan | DU6: Diskon Penjualan | DV6: Jumlah Penjualan | DX6: BEBAN POKOK PENJUALAN | DY6: Harga Pokok Penjualan Afiliasi | DZ6: Harga Pokok Penjualan Non Afiliasi | EA6: Beban Bea Masuk Import | EE6: Beban Penyusutan Mesin | EF6: Beban Pemeliharaan Mesin Ew | EG6: Beban Pemeliharaan Mesin Line 1 | EH6: Beban Pemeliharaan Mesin Line 2 | EI6: Beban Pemeliharaan Mesin Line 3 | EJ6: Beban Pemeliharaan Mesin Line 4 | EK6: Beban Pemeliharaan Mesin Line 5 | EL6: Beban Pemeliharaan Mesin Copper Sulphate | EM6: Beban Penyusutan Peralatan Pabrik | EO6: Beban Sewa Kendaraan | EP6: Selisih Stock Opname | EQ6: Selisih Timbang | ER6: Beban Tenaga Kerja Langsung | ES6: Beban Transportasi Bahan Baku | ET6: Beban Transportasi Produk Jadi | EU6: Beban Transportasi Produk Jadi (Bonus dan Fee Marketing) | EV6: Beban Pemeliharaan Kendaraan Pabrik | EW6: Beban Pemeliharaan Aset Pabrik | EX6: Beban Rumah Tangga Pabrik | EY6: Beban Gaji Staff Pabrik | EZ6: Beban Tenaga Kerja Tidak Langsung | FA6: Beban Pemeliharaan Mesin Pramaterial | FC6: Beban Listrik Pabrik | FD6: Beban Listrik Pabrik (Gudang Timur) | FF6: Beban Transportasi Lainnya | FG6: Beban Perlengkapan Pabrik | FI6: Beban Bbm Pabrik | FJ6: Beban Bongkar | FK6: Beban Qc Produk | FL6: Beban Transportasi Impor | FM6: Beban Gudang Pelabuhan | FN6: Beban Administrasi Pabean | FO6: Beban Muat | FQ6: Beban Klaim | FR6: Beban Gaji PHL | FV6: Beban Asuransi Pengiriman | FW6: Beban Sample | FX6: Beban Demplot | FZ6: Beban Pemeliharaan Bangunan Pabrik | GA6: Beban Pemeliharaan Sarana Prasarana Pabrik | GB6: Beban Perlengkapan Mekanik | GC6: Beban Perlengkapan Elektrikal | GD6: Beban Pemeliharaan Mesin Crf | GE6: Beban Riset Dan Percobaan Lapangan | GF6: Beban Pemeliharaan Mesin Copper Sulphate Line 2 | GG6: Beban Pemeliharaan Aset Lab | GH6: Beban Operasional Gudang | GI6: Beban Uji Dosis (Internal) | GJ6: Beban Perlengkapan Lab | GK6: Beban Kerugian Bibit Afkir | GL6: Beban Pemeliharaan Mesin NPK | GM6: Jumlah Harga Pokok Penjualan | GO6: BEBAN UMUM DAN ADMINISTRASI | GQ6: Beban Pelatihan | GR6: Beban Pelatihan Internal | GS6: Beban Perlengkapan Kantor | GT6: Beban Hse | GU6: Beban Penyusutan Kendaraan | GV6: Beban Penyusutan Inventaris Kantor | GW6: Beban Amortisasi Ditangguhkan SHGB | GX6: Beban Penyusutan Bangunan | GY6: Beban Gaji BOD | GZ6: Beban Gaji Staff Kantor | HC6: Tunjangan Lembur | HF6: Tunjangan Hari Raya - THR | HG6: Beban Asuransi - BPJS KES | HH6: Beban Asuransi - BPJS TK | HI6: Beban Pemeliharaan Aset Kantor | HJ6: Beban Rumah Tangga Kantor | HK6: Beban Pengembangan System/Software | HL6: Beban Kompensasi Ganti Rugi | HM6: Beban Koreksi Fiskal | HN6: Beban Asuransi Kebakaran | HO6: Beban Pemeliharaan Kendaraan Kantor | HP6: Beban Bbm Kantor | HQ6: Beban Perjalanan Dinas Kantor | HR6: Beban Perjalanan Dinas Tamu | HS6: Beban Obat/Pengobatan | HT6: Beban Sewa | HU6: Biaya Legal Dan Perijinan | HV6: Beban Rakor | HW6: Beban Audit | HX6: Beban Perayaan Hari Besar | HY6: Beban Atk Kantor | HZ6: Beban Internet/Vsat | IA6: Beban Cetak/Fotocopy | IB6: Beban Air Minum Kantor | IC6: Beban Konsumsi Dan Oleh-Oleh Tamu | ID6: Beban Kirim Paket (Sampel/Dokumen) | IE6: Beban Listrik Kantor | IF6: Beban Telepon Kantor | IG6: Pajak Kendaraan & PBB | IH6: Beban Suka/Duka | IK6: Beban Pph 4 Ayat 2 | IL6: Beban Pph Pasal 23 | IM6: Beban Pph Pasal 21 | IN6: Beban Pph 25 | IO6: Beban Pinalti Pajak | IP6: Beban Pph Pasal 29 | IQ6: Beban Olahraga Dan Rekreasi | IR6: Biaya Kaizen | IS6: Beban Pemutusan Hubungan Kerja | IT6: Beban Apraisal | IU6: Beban Konsultan Keuangan | IV6: Beban Bphtb | IW6: Beban Kerugian Investasi | IX6: Beban Apresiasi Karyawan | IY6: Beban Imbalan Pasca Kerja | IZ6: Beban Notaris | JA6: Beban Gaji Staff Laboratorium | JB6: Beban Csr (Corporate Social Responsibility) | JC6: Beban Cadangan Kerugian Piutang Tak Tertagih | JD6: Beban Brand Development | JE6: Beban Ppn Tidak Bisa Dikreditkan | JH6: Beban Penyusutan Software | JI6: Beban Rekrutmen | JJ6: Beban Rups | JK6: Beban Aktuaria | JL6: Beban Riset Corporate & Strategy | JM6: Beban Gaji Managemen | JN6: Beban Gaji Principal | JO6: Beban Sarana Prasarana Kantor | JP6: Beban Outsourcing | JQ6: Biaya Pemeliharaan Bangunan Kantor | JR6: Beban Beasiswa | JS6: Beban Kesejahteraan Karyawan | JT6: Jumlah Beban Administrasi dan Umum | JV6: BEBAN PENJUALAN DAN PEMASARAN | JW6: Beban Operasional Pemasaran | JX6: Beban Relasi | JY6: Beban Promosi | JZ6: Jumlah Beban Penjualan dan Pemasaran | KB6: BEBAN ANALISA LAB | KC6: Beban Analisa Lab | KD6: Jumlah Analisa Lab | KF6: PENDAPATAN | KG6: Pendapatan Jasa Giro | KH6: Pendapatan Lain-Lain | KI6: Pendapatan Selisih Lebih Kurs | KJ6: Pendapatan Aval | KK6: Pendapatan Selisih Koma | KL6: Pendapatan Klaim | KM6: Pendapatan Jasa Maklon | KN6: Jumlah Pendapatan | KP6: BEBAN DILUAR USAHA | KQ6: Beban Adm Bank | KR6: Beban Marjin Pinjaman | KT6: Beban Administrasi Kredit - Mk | KV6: Beban Selisih Kurang Kurs | KW6: Beban Selisih Koma | KX6: Beban Market Place | KY6: Beban Lain-Lain | KZ6: Beban Zakat | LB6: Beban Qurban | LC6: Beban Administrasi Kredit - LC/SKBDN | LE6: Jumlah Beban Diluar Usaha | LG6: PAJAK PENGHASILAN | LH6: Beban Pajak Penghasilan | LI6: Jumlah Pajak Penghasilan | LJ6: Jumlah Beban | LK6: EBITDA
A7: January | B7: 22271442059 | C7: 14550282537 | D7: 7721159523 | F7: 2811522986 | G7: 689993629 | H7: 85297200 | I7: 3586813815 | J7: 4134345708 | L7: 14972802 | M7: 1999371672 | N7: -1984398870 | P7: 2149946838 | Q7: 686000 | S7: 686000 | T7: 2149260838 | W7: 0 | X7: 2149260838 | AD7: 44214340653 | AE7: 44331095704 | AG7: -325897486 | AH7: 10333743154 | AI7: 104300563162 | AJ7: - | AL7: 27470911203 | AM7: 12165949131 | AN7: 242490705521 | AP7: - | AQ7: 127315422381 | AR7: 6707849388 | AU7: 1712002768 | AV7: 135735274537 | AW7: 378225980058 | BA7: 21736710978 | BC7: - | BD7: - | BE7: 5705977764 | BF7: 9760447198 | BI7: 145767226 | BJ7: - | BK7: 198250150994 | BL7: 235599054161 | BN7: 10372247233 | BO7: - | BQ7: 5424840824 | BR7: - | BS7: 15797088057 | BT7: 251396142218 | BV7: 68245000000 | BW7: - | BX7: 2162513125 | BY7: 53985061075 | BZ7: -541805960 | CA7: - | CB7: 2979069600 | CC7: 126829837839 | CD7: 378225980058 | CF7: January | DQ7: January | DR7: 22321496113 | DT7: -49804054 | DU7: -250000 | DV7: 22271442059 | DZ7: 11233807019 | EA7: 419236000 | EE7: 222361613 | EF7: 175478 | EG7: 3802702 | EH7: 3154533 | EI7: 19358144 | EJ7: 328037 | EK7: 3330313 | EL7: 99249577 | EM7: 36077806 | EO7: 60150000 | EP7: 9103283 | ER7: 326841928 | ES7: 59495840 | ET7: 1256104694 | EV7: 527050 | EY7: 73522457 | EZ7: 161256537 | FA7: 10059662 | FC7: 78314507 | FD7: 22316357 | FF7: 5981156 | FG7: 214800 | FI7: 12000000 | FJ7: 22472770 | FO7: 13196810 | FR7: 117593000 | FV7: 53400200 | FW7: 23953018 | FZ7: 83382614 | GA7: 56657612 | GB7: 14957210 | GC7: 7356377 | GD7: 315543 | GE7: 15133876 | GF7: 437015 | GG7: 24510000 | GH7: 147000 | GM7: 14550282537 | GQ7: 33272500 | GR7: 59048061 | GS7: 155000 | GT7: 23945243 | GU7: 82255996 | GV7: 47123961 | GW7: 22118501 | GX7: 229723827 | GY7: 403465056 | GZ7: 453491678 | HC7: 40204681 | HG7: 29664522 | HH7: 61503254 | HI7: 225000 | HJ7: 48106641 | HK7: 712553 | HN7: 2502709 | HO7: 28181917 | HP7: 5290000 | HQ7: 116650988 | HR7: 8832900 | HT7: 54003207 | HU7: 59550000 | HV7: 49160000 | HX7: 124627563 | HY7: 1996000 | HZ7: 7520728 | IA7: 2529592 | IB7: 3316499 | IC7: 20354381 | ID7: 16661730 | IE7: 17158107 | IF7: 3178477 | IG7: 18466200 | IM7: 77824374 | IQ7: 380000 | JB7: 80200000 | JH7: 7339144 | JM7: 420042284 | JN7: 46928088 | JO7: 765000 | JP7: 41576967 | JQ7: 28962413 | JS7: 16440000 | JT7: 2797455742 | JW7: 491945849 | JX7: 147499000 | JY7: 50548780 | JZ7: 689993629 | KC7: 85297200 | KD7: 85297200 | KG7: 9971413 | KK7: 1389 | KN7: 14972802 | KQ7: 10483936 | KR7: 1612378407 | KT7: 103409480 | KV7: 217846340 | KW7: 2175 | LC7: 5933631 | LE7: 2000053970 | LH7: 818660 | LI7: 818660 | LJ7: =LE7+KD7+JZ7+JT7 -> 5572800541
A8: February | B8: 39926611384 | C8: 27445523058 | D8: 12481088327 | F8: 3136682077 | G8: 944187719 | H8: 5467002 | I8: 4086336797 | J8: 8394751529 | L8: 346889484 | M8: 2924246807 | N8: -2577357324 | P8: 5817394206 | Q8: 120515 | S8: 120515 | T8: 5817273691 | W8: 0 | X8: 5817273691 | AD8: 20099667310 | AE8: 49863908492 | AG8: -325897486 | AH8: 10184417154 | AI8: 119522871582 | AJ8: - | AL8: 9744087704 | AM8: 16589488907 | AN8: 225678543663 | AP8: - | AQ8: 130348634297 | AR8: 6678391743 | AU8: 1712002768 | AV8: 138739028808 | AW8: 364417572471 | BA8: 15356991892 | BC8: - | BD8: - | BE8: 8435842992 | BF8: 8132536607 | BI8: 211412619 | BJ8: - | BK8: 178095094338 | BL8: 210231878448 | BN8: 16131668617 | BO8: - | BQ8: 5420434399 | BR8: - | BS8: 21552103016 | BT8: 231783981464 | BV8: 68245000000 | BW8: - | BX8: 7966266292 | BY8: 53985061075 | BZ8: -541805960 | CA8: - | CB8: 2979069600 | CC8: 132633591006 | CD8: 364417572471 | CF8: February | DQ8: February | DR8: 40015918317 | DT8: -94261888 | DU8: - | DV8: 39921656429 | DZ8: 22392165850 | EA8: 565491000 | EE8: 222005363 | EF8: 1293465 | EG8: 2696948 | EH8: 9049778 | EI8: 1962777 | EJ8: 585879 | EK8: 151539 | EL8: 6637860 | EM8: 36369754 | EO8: 76200000 | EP8: 11241421 | ER8: 364107426 | ES8: 471516569 | ET8: 1997191395 | EV8: 6970489 | EX8: 7791915 | EY8: 84742190 | EZ8: 187134786 | FA8: 30650575 | FC8: 114452204 | FD8: 21982459 | FF8: 20197439 | FG8: 84378 | FI8: 24380000 | FJ8: 35225130 | FO8: 27952102 | FQ8: 82347618 | FR8: 184492750 | FS8: =FR8+FR7 -> 302085750 | FW8: 24500532 | FZ8: 4486900 | GA8: 19373805 | GB8: 9207729 | GC8: 1201085 | GD8: 12357289 | GE8: 31229661 | GF8: 1105871 | GG8: - | GH8: 20950373 | GI8: 250000000 | GM8: 2.7445523e+10 | GQ8: 4000000 | GR8: 56681061 | GS8: - | GT8: 18914000 | GU8: 82255996 | GV8: 48472243 | GW8: 22118501 | GX8: 229723827 | GY8: 481659168 | GZ8: 576797549 | HC8: 40136131 | HG8: 32968534 | HH8: 56737782 | HI8: - | HJ8: 37096158 | HK8: 7781025 | HN8: 2502709 | HO8: 35489846 | HP8: 4684000 | HQ8: 214327216 | HR8: 21534650 | HS8: 3231689 | HT8: 61822374 | HU8: 1400000 | HV8: 789750 | HW8: 112500000 | HX8: 91330954 | HY8: 9333482 | HZ8: 6572150 | IA8: 7373650 | IB8: 2434999 | IC8: 15796111 | ID8: 28890637 | IE8: 10281010 | IF8: 5205461 | IG8: 9486225 | IH8: 2550000 | IK8: 17500000 | IL8: 545613 | IM8: 101436998 | IO8: 500000 | IQ8: 160000 | IU8: 10256410 | JB8: 10000000 | JE8: 1100000 | JH8: 7339144 | JI8: 5780000 | JK8: 27600000 | JM8: 499749540 | JN8: 27556938 | JO8: 6302090 | JP8: 42861456 | JQ8: 5700000 | JR8: 4500000 | JS8: 24915000 | JT8: 3.1366821e+15 | JW8: 841310075 | JX8: 45296000 | JY8: 57581644000000 | JZ8: 944187719 | KC8: 5467002 | KD8: 5467002 | KG8: 10402432 | KH8: 7524000000000 | KI8: 328712547 | KJ8: 250000 | KK8: 505 | KM8: 4954955 | KN8: 351844439 | KQ8: 9113718 | KR8: 1735588517 | KT8: 93666662 | KV8: 632176029 | KW8: 1881 | KZ8: 450000000 | LC8: 3700000 | LE8: 2924246807 | LH8: 120515 | LI8: 120515 | LJ8: =LE8+KD8+JZ8+JT8 -> 3.13669e+15
A9: March | B9: 48178814422 | C9: 40934719757 | D9: 7244094665 | F9: 3260324202 | G9: 1314214864 | H9: 37721614 | I9: 4612260680 | J9: 2631833985 | L9: 168954351 | M9: 2176414214 | N9: -2007459863 | P9: 624374122 | Q9: 5800 | S9: 5800 | T9: 624368322 | W9: 0 | X9: 624368322 | AD9: 19442003776 | AE9: 51173068869 | AG9: -325897486 | AH9: 10482259154 | AI9: 92350283616 | AJ9: - | AL9: 20785426853 | AM9: 12225997754 | AN9: 206133142535 | AP9: - | AQ9: 130908524708 | AR9: 6648934098 | AU9: 1712002768 | AV9: 139269461574 | AW9: 345402604109 | BA9: 12535565229 | BC9: - | BD9: - | BE9: 5495911745 | BF9: 1887033524 | BI9: 123728456 | BJ9: - | BK9: 171105117438 | BL9: 191147356392 | BN9: 16098725935 | BO9: - | BP9: - | BQ9: 4874363998 | BR9: - | BS9: 20973089933 | BT9: 212120446325 | BV9: 68245000000 | BW9: - | BX9: 8614100314 | BY9: 53985793831 | BZ9: -541805960 | CA9: - | CB9: 2979069600 | CC9: 133282157785 | CD9: 345402604110 | CF9: March | DQ9: March | DR9: 48182107568 | DT9: -1115999 | DU9: -3600543 | DV9: 48177391026 | DZ9: 36906890058 | EA9: 31458000 | EE9: 215442863 | EF9: - | EG9: 5130400 | EH9: 398352 | EI9: 3630631 | EJ9: 5510499 | EK9: - | EL9: 9055099 | EM9: 36433869 | EO9: 78400000 | EP9: -2422384 | ER9: 330448692 | ES9: 563827103 | ET9: 1528774325 | EV9: 25221158 | EX9: 13299998 | EY9: 77156083 | EZ9: 170169077 | FA9: 3773210 | FC9: 157610005 | FD9: 22715808 | FF9: 32680371 | FG9: 45824 | FI9: 13200000 | FJ9: 20648075 | FO9: 19046250 | FQ9: 73863657 | FR9: 119704190 | FV9: 7693670 | FW9: 185886522 | FX9: 6500000 | FZ9: 2684750 | GA9: 72003354 | GB9: 5476718 | GC9: 224912 | GD9: 1129129 | GE9: 147272109 | GF9: 1870334 | GG9: - | GH9: 15311504 | GI9: - | GJ9: 2738184 | GM9: 40910902400 | GQ9: 188800 | GR9: 56681061 | GS9: 2055234 | GT9: 22576264 | GU9: 73328439 | GV9: 48404667 | GW9: 22118501 | GX9: 229723827 | GY9: 445721520 | GZ9: 501341795 | HC9: 41860616 | HF9: 235397436 | HG9: 31292115 | HH9: 58584781 | HI9: 570000 | HJ9: 30057426 | HK9: 40058503 | HN9: 2502709 | HO9: 29369114 | HP9: 2644500 | HQ9: 392268968 | HR9: 18255000 | HS9: 471200 | HT9: 39740733 | HU9: 37450000 | HV9: - | HW9: - | HX9: 14184500 | HY9: 2683373 | HZ9: 13066896 | IA9: 1665600 | IB9: 459000 | IC9: 24062775 | ID9: 28386565 | IE9: 11264468 | IF9: 4662225 | IG9: 20609000 | IH9: 3000000 | IK9: - | IL9: 1136720 | IM9: 145217360 | IO9: - | IQ9: - | IT9: 3153153 | IU9: - | JB9: 12150000 | JE9: - | JH9: 7339144 | JI9: - | JK9: - | JM9: 448420497 | JN9: 39472443000000 | JO9: 9443310 | JP9: 45879584 | JQ9: 44124797 | JR9: 9000000 | JS9: 8102500000000 | JT9: 3260147119 | JW9: 1112854406 | JX9: 144000000 | JY9: 57360458 | JZ9: 1314214864 | KC9: 37721614 | KD9: 37721614 | KG9: 10529676 | KH9: 6234595 | KI9: 152223945 | KJ9: - | KK9: 600 | KM9: 1388801 | KN9: 170377617 | KQ9: 9314146 | KR9: 1622930028 | KT9: 93666662 | KV9: - | KW9: 640203 | KY9: 400407 | KZ9: 450000000 | LC9: - | LE9: 2176951445 | LH9: 939175 | LI9: 939175 | LJ9: =LE9+KD9+JZ9+JT9 -> 6789035042
A10: April | B10: 29575707285 | C10: 22158325998 | D10: 7417381287 | F10: 3742450493 | G10: 512771636 | H10: 45975500 | I10: 4301197629 | J10: 3116183658 | L10: 466038804 | M10: 2337754847 | N10: -1871716042 | P10: 1244467616 | Q10: 7073168 | S10: 7073168 | T10: 1237394448 | W10: 0 | X10: 1237394448 | AD10: 22149448688 | AE10: 39387620234 | AG10: -726809713 | AH10: 8069303618 | AI10: 99484397378 | AJ10: - | AL10: 42184427546 | AM10: 13027126905 | AN10: 223575514655 | AP10: - | AQ10: 130729959005 | AR10: 7117825212 | AU10: 3097471000 | AV10: 140945255216 | AW10: 364520769872 | BA10: 13754261151 | BC10: - | BD10: - | BE10: 5190026785 | BF10: 2875451223 | BI10: 204767964 | BJ10: - | BK10: 186931451312 | BL10: 208955958435 | BN10: 15378310047 | BQ10: 10699500880 | BR10: - | BS10: 26077810927 | BT10: 235033769362 | BV10: 68245000000 | BW10: - | BX10: 9828369801 | BY10: 50176612716 | BZ10: -3110625307 | CA10: - | CB10: 4347643300 | CC10: 129487000509 | CD10: 364520769872 | CF10: April | DQ10: April | DR10: 29612451591 | DT10: -3070219 | DU10: -33674087 | DV10: 29575707285 | DZ10: 21523784259 | EA10: - | EE10: 239260219 | EF10: 1836691 | EG10: 2481691 | EH10: 7725793 | EI10: 879241 | EJ10: 312254 | EK10: 28846 | EL10: 4071356 | EM10: 35630504 | EO10: 49700000 | EP10: -19826732 | ER10: 324285484 | ES10: 307270932 | ET10: 1524741357 | EV10: 8997500 | EX10: 19511377 | EY10: 77483483 | EZ10: 156527580 | FA10: 7819930 | FC10: 78075299 | FD10: 20153339 | FF10: 684320 | FG10: 2286123 | FI10: 36480000 | FJ10: 31218950 | FN10: 660000 | FO10: 21235165 | FQ10: 5191495 | FR10: 267015399 | FV10: 23405000 | FW10: - | FX10: 15855186 | FZ10: 31200000 | GA10: 52362704 | GB10: 4800987 | GC10: 9545738 | GD10: -4498687 | GE10: 21637108 | GF10: 3371528 | GG10: 3100000 | GH10: 144510 | GI10: - | GJ10: 1479062 | GK10: 155839622 | GM10: 25053764614 | GQ10: 50395000 | GR10: 56681061 | GS10: 1096819 | GT10: 36840668 | GU10: 73328439 | GV10: 47894073 | GW10: 22118501 | GX10: 229723827 | GY10: 375241484 | GZ10: 492273124 | HC10: 32132452 | HF10: 186983075 | HG10: 31768205 | HH10: 57841930 | HI10: - | HJ10: 38906770 | HK10: 1871953 | HN10: 2502709 | HO10: 40696542 | HP10: 6577600 | HQ10: 367767840 | HR10: 7417000 | HS10: 2095000 | HT10: 254236581 | HU10: 2600000 | HV10: - | HW10: - | HX10: 23666755 | HY10: 12353040 | HZ10: 20116987 | IA10: 13879458 | IB10: 2493500 | IC10: 27819907 | ID10: 42647927 | IE10: 10217530 | IF10: 3257979 | IG10: 14755231 | IH10: 6850801 | IK10: - | IL10: - | IM10: 144930939 | IN10: 219782308 | IO10: - | IP10: 100201552 | IQ10: - | IS10: 20512326 | IT10: 14653153 | IU10: - | IX10: 17975000 | JB10: 5922000 | JE10: 330309 | JH10: 7339144000000 | JI10: - | JK10: 7175000 | JM10: 517391900 | JN10: - | JO10: 2127511000000 | JP10: 40902917 | JQ10: 10416666 | JR10: 4500000 | JS10: 31240000 | JT10: 3742450493 | JW10: 423608954 | JX10: 21000000 | JY10: 68162682 | JZ10: 512771636 | KC10: 45975500 | KD10: 45975500 | KG10: 14962478 | KH10: 5964500 | KI10: 443109689 | KJ10: 2000000 | KK10: 2137 | KM10: - | KN10: 466038804 | KQ10: 11342866 | KR10: 1666356554 | KT10: 99369633 | KV10: - | KW10: 2065 | KX10: 10611228 | KZ10: 550000000 | LC10: - | LE10: 2337682345 | LH10: 7073168 | LI10: 7073168 | LJ10: =LE10+KD10+JZ10+JT10 -> 6638879974
A11: May | B11: 28480547642 | C11: 19037629900 | D11: 9442917742 | F11: 4097901831 | G11: 424604784 | H11: 14616902 | I11: 4537123517 | J11: 4905794225 | L11: 935138038 | M11: 2473379589 | N11: -1538241551 | P11: 3367552675 | Q11: 3845 | S11: 3845 | T11: 3367548830 | W11: 0 | X11: 3367548830 | AD11: 25811037262 | AE11: 47008967012 | AG11: -726809713 | AH11: 7289928852 | AI11: 105118264727 | AJ11: - | AL11: 35666207828 | AM11: 14770319852 | AN11: 234937915819 | AP11: - | AQ11: 131006355933 | AR11: 7088722766 | AU11: 3097471000 | AV11: 141192549699 | AW11: 376130465518 | BA11: 22160497551 | BC11: - | BD11: - | BE11: 7273003713 | BF11: 1170365530 | BI11: 209126689 | BJ11: - | BK11: 201773311160 | BL11: 232586304644 | BN11: - | BQ11: 10689684037 | BR11: - | BS11: 10689684037 | BT11: 243275988681 | BV11: 68245000000 | BW11: - | BX11: 13195846129 | BY11: 50176612716 | BZ11: -3110625307 | CA11: - | CB11: 4347643300 | CC11: 132854476837 | CD11: 376130465518 | CF11: May | DQ11: May | DR11: 28705068315 | DT11: -3554196 | DU11: -220966477 | DV11: 28480547642 | DZ11: 15297472610 | EA11: 6335000 | EE11: 241470269 | EF11: 7893570 | EG11: 23588612 | EH11: 3967052 | EI11: 5338824 | EJ11: 12976311 | EK11: 13263163 | EL11: 11046185 | EM11: 36158762 | EO11: 46500000 | EP11: 53799097 | ER11: 331196306 | ES11: 73039394 | ET11: 1272103653 | EV11: 8752500 | EX11: 67119160 | EY11: 81128729 | EZ11: 166385566 | FA11: 51803988 | FC11: 143239832 | FD11: 27391726 | FF11: 3470445 | FG11: - | FI11: 12870000 | FJ11: 28346753 | FN11: - | FO11: 11362655 | FQ11: 10140738 | FR11: 180113477 | FV11: 60479625 | FW11: 132298674 | FX11: - | FZ11: 6254458 | GA11: 76165543 | GB11: 7421789 | GC11: 2440212 | GD11: 1547331 | GE11: 264207721 | GF11: 6630000 | GG11: - | GH11: - | GI11: 250500000 | GJ11: 1410168 | GK11: - | GM11: 19037629900 | GQ11: 49425481 | GR11: 620937378 | GS11: - | GT11: 34072300 | GU11: 73328439 | GV11: 48780029 | GW11: 22118501 | GX11: 229723827 | GY11: 424978646 | GZ11: 437607566 | HC11: 20723838 | HF11: 182483070 | HG11: 32401245 | HH11: 60872712 | HI11: 1495000 | HJ11: 38919265 | HK11: 153153 | HN11: 2502709 | HO11: 42962572 | HP11: 3092549 | HQ11: 387891565 | HR11: 4422601 | HS11: 6264262 | HT11: 98612811 | HU11: 23925000 | HV11: - | HW11: - | HX11: 77690444 | HY11: 10424848 | HZ11: 11335522 | IA11: 1271660 | IB11: 369200 | IC11: 7169400 | ID11: 10855249 | IE11: 13059808 | IF11: 5984394 | IG11: 24511000 | IH11: 13869351 | IK11: 2200000 | IL11: 425978 | IM11: 94163039 | IN11: 76673615 | IO11: - | IP11: 101178352 | IQ11: - | IS11: 3064288 | IT11: 11500000 | IU11: 110000000 | IX11: 8400000 | JB11: 20750000 | JE11: 1375000 | JH11: 7339144000000 | JI11: 3631104 | JK11: - | JM11: 506580138 | JN11: - | JO11: 11976274000000 | JP11: 43039505 | JQ11: 48307500 | JR11: 4500000 | JS11: 18562500 | JT11: 4097901831 | JW11: 333049075 | JX11: 17000000 | JY11: 74555709 | JZ11: 424604784 | KC11: 14616902 | KD11: 14616902 | KG11: 8597604 | KH11: 6489000 | KI11: 873214712 | KJ11: 46826500 | KK11: 10222 | KN11: 935138038 | KQ11: 9521123 | KR11: 1809093898 | KT11: 136745000 | KV11: 0 | KW11: 4866 | KY11: 2719701 | KZ11: 350000000 | LB11: 165295000 | LC11: - | LE11: 2473379589 | LH11: 3845 | LI11: 3845 | LJ11: =LE11+KD11+JZ11+JT11 -> 7010503106
A12: June | B12: 43859289220 | C12: 35299745158 | D12: 8559544062 | F12: 3914387840 | G12: 864961390 | H12: 80087700 | I12: 4859436930 | J12: 3700107132 | L12: 32493074 | M12: 2679452410 | N12: -2646959337 | P12: 1053147795 | Q12: 234133 | S12: 234133 | T12: 1052913662 | W12: 0 | X12: 1052913662 | AD12: 15936203293 | AE12: 63024226276 | AG12: -726809713 | AH12: 6595645696 | AI12: 107226471817 | AJ12: - | AL12: 38703370451 | AM12: 15350769281 | AN12: 246109877102 | AP12: - | AQ12: 130656345348 | AR12: 7059265121 | AU12: 3097471000 | AV12: 140813081470 | AW12: 386922958571 | BA12: 25476188216 | BC12: - | BD12: - | BE12: 8090627462 | BF12: 2283637018 | BI12: 215394159 | BJ12: - | BK12: 190885058208 | BL12: 226950905064 | BN12: 15399414819 | BQ12: 10665248189 | BR12: - | BS12: 26064663008 | BT12: 253015568072 | BV12: 68245000000 | BW12: - | BX12: 14248759791 | BY12: 50176612716 | BZ12: -3110625307 | CA12: - | CB12: 4347643300 | CC12: 133907390499 | CD12: 386922958571 | CF12: June | DQ12: June | DR12: 43875803190 | DT12: -10259733 | DU12: -6254236 | DV12: 43859289220 | DZ12: 27625035430 | EA12: 280808000 | EE12: 243995015 | EF12: 9016711 | EG12: 17625038 | EH12: 6193448 | EI12: 5720096 | EJ12: 8043401 | EK12: 992869 | EL12: 15764194 | EM12: 35768495 | EO12: 24000000 | EP12: 30140821 | ER12: 362932721 | ES12: 198159822 | ET12: 4841632676 | EV12: 21186500 | EX12: 41036519 | EY12: - | EZ12: 180899238 | FA12: 38614167 | FC12: 79502761 | FD12: 22991127 | FF12: 153693704 | FG12: - | FI12: 24299000 | FJ12: 35969640 | FN12: - | FO12: 15240780 | FQ12: 8184950 | FR12: 162238183 | FV12: 241525917 | FW12: 41643300 | FX12: - | FZ12: - | GA12: 83001413 | GB12: 14290078 | GC12: 2769738 | GD12: 11825996 | GE12: 25599080 | GF12: - | GG12: - | GH12: 11424493 | GI12: - | GJ12: - | GK12: - | GM12: 34921765318 | GQ12: 44802216 | GR12: 767671959 | GS12: 2826500 | GT12: 26933742 | GU12: 73510730 | GV12: 48642940 | GW12: 22118501 | GX12: 230603147 | GY12: 416873395 | GZ12: 493031932 | HC12: 44722423 | HF12: 182483070 | HG12: 31942268 | HH12: 71962120 | HI12: 850000 | HJ12: 31451175 | HK12: 750000 | HN12: 3985525 | HO12: 80430233 | HP12: 4980568 | HQ12: 268841798 | HR12: 4826207 | HS12: 3162199 | HT12: 102279477 | HU12: 27250000 | HV12: - | HW12: 87500000 | HX12: 17246000 | HY12: 9814528 | HZ12: 15096782 | IA12: 1948920 | IB12: 1197000 | IC12: 20102905 | ID12: 11214164 | IE12: 12549678 | IF12: 4027822 | IG12: 27666984 | IH12: 13801601 | IK12: - | IL12: 133329 | IM12: 138553424 | IN12: 32088251 | IO12: 24967315 | IP12: 100201552 | IQ12: 500000 | IS12: - | IT12: 42792793 | IU12: - | IX12: - | JB12: 20750000 | JE12: - | JH12: 7339144000000 | JI12: 5643250 | JK12: - | JM12: 516328291 | JN12: - | JO12: 11695317000000 | JP12: 43039505 | JQ12: 48307500 | JR12: - | JS12: 78929500 | JT12: 4280367681 | JW12: 802928692 | JX12: 19000000 | JY12: 43032698 | JZ12: 864961390 | KC12: 92087700 | KD12: 92087700 | KG12: 25381773 | KH12: 7097500 | KI12: 0 | KJ12: - | KK12: 13801 | KN12: 32493074 | KQ12: 8479013 | KR12: 1837214256 | KT12: 209500000 | KV12: 23996341 | KW12: 4139 | KX12: 5639102 | KZ12: 585245310 | LB12: 9374250 | LC12: - | LE12: 2679452410 | LH12: 234133 | LI12: 234133 | LJ12: =LE12+KD12+JZ12+JT12 -> 7916869181
A13: July | B13: 60848462285 | C13: 45952511554 | D13: 14895950731 | F13: 3979410847 | G13: 490049564 | H13: 106413011 | I13: 4575873422 | J13: 10320077309 | L13: 189156082 | M13: 1969173360 | N13: -1780017277 | P13: 8540060032 | Q13: 0 | S13: 0 | T13: 8540060032 | W13: 0 | X13: 8540060032 | AD13: 16228480826 | AE13: 82925685482 | AG13: -726809713 | AH13: 5825645696 | AI13: 99274743635 | AJ13: - | AL13: 33662234090 | AM13: 16997370821 | AN13: 254187350837 | AP13: - | AQ13: 132943952489 | AR13: 7029807476 | AU13: 3097471000 | AV13: 143071230966 | AW13: 397258581802 | BA13: 30921952568 | BC13: - | BD13: - | BE13: 11493763808 | BF13: 1395353998 | BI13: 214849468 | BJ13: - | BK13: 184742012601 | BL13: 228767932443 | BN13: 15401214441 | BQ13: 10641984387 | BR13: 0 | BS13: 26043198828 | BT13: 254811131271 | BV13: 68245000000 | BW13: 0 | BX13: 22788819822 | BY13: 50176612716 | BZ13: -3110625307 | CA13: - | CB13: 4347643300 | CC13: 117878613431 | CD13: 397258581802 | CF13: July | DQ13: July | DR13: 61121035296 | DT13: -29599501 | DU13: -242973510 | DV13: 60848462285 | DZ13: 38819880826 | EA13: 510959000 | EE13: 245695016 | EF13: 15656850 | EG13: 15026082 | EH13: 20455738 | EI13: 25428453 | EJ13: 23261444 | EK13: 1632153 | EL13: 6791720 | EM13: 35262639 | EO13: 48000000 | EP13: 233025586 | ER13: 392674443 | ES13: 498481549 | ET13: 3842897501 | EV13: 51100086 | EX13: 32132359 | EY13: 61109089 | EZ13: 188776392 | FA13: 15331056 | FC13: 114019783 | FD13: 21562472 | FF13: 45712333 | FG13: - | FI13: 12366000 | FJ13: 21126300 | FN13: - | FO13: 22645650 | FQ13: 1874378 | FR13: 164005615 | FV13: 15153000 | FW13: 578879 | FX13: - | FZ13: 6763904 | GA13: 261225465 | GB13: 17983486 | GC13: 23229831 | GD13: 3306549 | GE13: 6044978 | GF13: - | GG13: 7125000 | GH13: 15767450 | GI13: - | GJ13: - | GK13: - | GL13: 44012791 | GM13: 45888081847 | GQ13: 68901000 | GR13: 621585711 | GS13: 553118 | GT13: 5106056 | GU13: 73510730 | GV13: 49764655 | GW13: 22118501 | GX13: 230603147 | GY13: 413713990 | GZ13: 438948282 | HC13: 22691807 | HF13: 156942777 | HG13: 34237160 | HH13: 63910762 | HI13: - | HJ13: 16428627 | HK13: - | HN13: 2502709 | HO13: 58650022 | HP13: 5482740 | HQ13: 374057636 | HR13: 11397500 | HS13: 16962527 | HT13: 91112811 | HU13: 473795000 | HV13: - | HW13: 25000000 | HX13: - | HY13: 8223768 | HZ13: 23713013 | IA13: 8691664 | IB13: 3389900 | IC13: 11527700 | ID13: 26160402 | IE13: 12994102 | IF13: 3280525 | IG13: 9590200 | IH13: 12554802 | IK13: 1065709 | IL13: 8182769 | IM13: 139954990 | IN13: 56986631 | IO13: 23807888 | IP13: - | IQ13: 1500000 | IS13: 0 | IT13: 0 | IU13: 0 | IV13: 4250000 | IX13: - | JB13: 74686037 | JE13: 12949832 | JH13: 7339144 | JI13: - | JK13: - | JM13: 526248164 | JN13: - | JO13: 14990068 | JP13: 43039505 | JQ13: - | JR13: - | JS13: 35555000 | JT13: 4348659082 | JW13: 349172664 | JX13: 19000000 | JY13: 121876900 | JZ13: 490049564 | KC13: 106163011 | KD13: 106163011 | KG13: 21438602 | KH13: 16255418 | KI13: 150742199 | KJ13: - | KK13: 719864 | KN13: 189156082 | KQ13: 10020191 | KR13: 1809252863 | KT13: 94500000 | KV13: 0 | KW13: 23632 | KX13: 5376673 | KZ13: 50000000 | LB13: - | LC13: - | LE13: 2158329442 | LH13: 0 | LI13: 0 | LJ13: =LE13+KD13+JZ13+JT13 -> 7103201099
A14: August | B14: 54451094996 | C14: 42772596362 | D14: 11678498634 | F14: 3430273181 | G14: 429591314 | H14: 41150500 | I14: 3901014994 | J14: 7777483640 | L14: 554195179 | M14: 2479326566 | N14: -1925131386 | P14: 5852352253 | Q14: 0 | S14: 0 | T14: 5852352253 | X14: 5852352253 | AD14: 15146534221 | AE14: 95360939306 | AG14: -301516003 | AH14: 4937637296 | AI14: 102352653702 | AL14: 27357562602 | AM14: 16372616426 | AN14: 261226427550 | AP14: - | AQ14: 133732209029 | AR14: 7000349831 | AU14: 3097471000 | AV14: 143830029860 | AW14: 405056457410 | BA14: 26707978354 | BC14: - | BD14: - | BE14: 11154914765 | BF14: 1486038598 | BI14: 215511729 | BJ14: - | BK14: 191571541624 | BL14: 231135985071 | BN14: 15403011497 | BQ14: 10217658058 | BS14: 25620669555 | BT14: 256756654625 | BV14: 68245000000 | BX14: 28641172076 | BY14: 50176612716 | BZ14: -3110625307 | CA14: - | CB14: 4347643300 | CC14: 148299802784 | CD14: 405056457410 | CF14: August | DQ14: August | DR14: 54457721463 | DT14: -2135667 | DU14: -4490800 | DV14: 54451094996 | DZ14: 33668034218 | EA14: 1128546000 | EE14: 251397797 | EF14: 14854646 | EG14: 19894149 | EH14: 7620753 | EI14: 13332757 | EJ14: 100210109 | EK14: 2617095 | EL14: 4602982 | EM14: 46641517 | EO14: 36000000 | EP14: -61427224 | EQ14: 131712554 | ER14: 293098556 | ES14: 398141715 | ET14: 4745953221 | EV14: 4380765 | EX14: 424598482 | EY14: 99713118 | EZ14: 166689519 | FA14: 39358190 | FC14: 130045417 | FD14: 22849475 | FF14: 1936105 | FI14: 13112000 | FJ14: 34164045 | FN14: - | FO14: 23030050 | FQ14: 536884739 | FR14: 198843505 | FV14: 37439350 | FW14: 37102633 | FZ14: 42760219 | GA14: 99662488 | GB14: 4093220 | GC14: 418404 | GD14: 358050 | GE14: 5805170 | GF14: - | GG14: - | GH14: 23837500 | GI14: - | GJ14: - | GK14: - | GL14: 24283074 | GM14: 42772596362 | GQ14: 81273000 | GR14: 226897686 | GS14: - | GT14: 16697200 | GU14: 76213433 | GV14: 50660491 | GW14: 22118501 | GX14: 230603147 | GY14: 413713990 | GZ14: 498218892 | HC14: 29739111 | HF14: 182483070 | HG14: 32333729 | HH14: 63866902 | HI14: - | HJ14: 26383193 | HK14: - | HN14: - | HO14: 34865438 | HP14: 5418960 | HQ14: 192840410 | HR14: 14160340 | HS14: 1522000 | HT14: 86307533 | HU14: 38803136 | HV14: - | HW14: - | HX14: 22555000 | HY14: 5449101 | HZ14: 7972509 | IA14: 15507154 | IB14: 2037500 | IC14: 22754613 | ID14: 21196163 | IE14: 12824140 | IF14: 3803171 | IG14: 12177000 | IH14: 12252901 | IK14: - | IL14: 17534876 | IM14: 140834595 | IN14: 93548441 | IO14: 2019316 | IP14: - | IQ14: 750000 | IS14: - | IT14: 59459460 | IU14: - | IV14: - | IX14: - | JB14: 7800000 | JE14: 3995125 | JH14: 7339144 | JI14: - | JK14: - | JM14: 540948282 | JN14: - | JO14: 6151256 | JP14: 45082292 | JQ14: 5085000 | JR14: 4500000 | JS14: 31575980 | JT14: 3430273181 | JW14: 354467423 | JX14: 25500000 | JY14: 49623891 | JZ14: 429591314 | KC14: 41150500 | KD14: 41150500 | KG14: 22209512 | KH14: 5416500 | KI14: 0 | KJ14: 600000 | KK14: 3011 | KL14: 525966156 | KN14: 554195179 | KQ14: 11245904 | KR14: 1748764402 | KT14: 94500000 | KV14: 208466361 | KW14: 733 | KX14: 4708797 | KZ14: 411640368 | LB14: - | LC14: - | LE14: 3033521745 | LH14: 8123461 | LI14: 8123461 | LJ14: =LE14+KD14+JZ14+JT14 -> 6934536740
A15: September | B15: 73337840528 | C15: 64662165092 | D15: 8675675436 | F15: 3598035874 | G15: 772538953 | H15: 105153610 | I15: 4475728437 | J15: 4199946999 | L15: 247895233 | M15: 2081307655 | N15: -1833412422 | P15: 2366534577 | Q15: 0 | S15: 0 | T15: 2366534577 | X15: 2366534577 | AD15: 26449313884 | AE15: 114222708267 | AF15: 2493348844 | AG15: -135609003 | AH15: 3770977936 | AI15: 86952512893 | AL15: 14449173958 | AM15: 17263915379 | AN15: 265466342159 | AQ15: 135246210726 | AR15: 7089517186 | AU15: 3097471000 | AV15: 145433198911 | AW15: 410899541071 | BA15: 22607963166 | BE15: 12112195121 | BF15: 774032498 | BI15: 196895005 | BK15: 196058597022 | BL15: 231749682812 | BN15: 18272650705 | BQ15: 10210870193 | BS15: 28483520898 | BT15: 260233203709 | BV15: 68245000000 | BX15: 31007706653 | BY15: 50176612716 | BZ15: -3110625307 | CB15: 4347643300 | CC15: 150666337362 | CD15: 410899541071 | CF15: September | DQ15: September | DR15: 73347669895 | DT15: -9829367 | DU15: - | DV15: 73337840528 | DZ15: 56677498576 | EA15: 1036857000 | EE15: 251704392 | EF15: 23150721 | EG15: 25427892 | EH15: 21258556 | EI15: 2972007 | EJ15: 16387369 | EK15: 3465669 | EL15: 3922615 | EM15: 45934749 | EO15: 51300000 | EP15: -14779849 | EQ15: -154622342 | ER15: 400344914 | ES15: 164151853 | ET15: 3918492440 | EV15: 2251463 | EX15: 441686286 | EY15: 66118656 | EZ15: 193386598 | FA15: 26548102 | FC15: 161142952 | FD15: 17385132 | FF15: 12686228 | FG15: 19793750 | FI15: 25620000 | FJ15: 23021600 | FN15: - | FO15: 31838450 | FQ15: 26529465 | FR15: 327194523 | FV15: 31612500 | FW15: 211794735 | FX15: - | FZ15: - | GA15: 341903388 | GB15: 1123287 | GC15: 1852507 | GD15: 45868316 | GE15: 131448993 | GF15: 9251766 | GG15: 3000000 | GH15: 15723478 | GI15: - | GJ15: 783784 | GK15: - | GL15: 19132570 | GM15: 64662165092 | GQ15: 57307672 | GR15: 225503814 | GS15: 512160 | GT15: 16157500 | GU15: 76213433 | GV15: 50865801 | GW15: 22118501 | GX15: 231299121 | GY15: 413713990 | GZ15: 431916587 | HC15: 27674988 | HF15: 182483070 | HG15: 32887720 | HH15: 64016678 | HI15: 80000 | HJ15: 17559599 | HK15: - | HL15: 3750000 | HN15: - | HO15: 56732398 | HP15: 4424560 | HQ15: 222767892 | HR15: 9068265 | HS15: 39529492 | HT15: 84807533 | HU15: 12100000 | HV15: - | HW15: 5000000 | HX15: - | HY15: 9177029 | HZ15: 23926555 | IA15: 289750 | IB15: 782500 | IC15: 20408952 | ID15: 13942881 | IE15: 11586534 | IF15: 3597400 | IG15: 34455300 | IH15: - | IK15: - | IL15: 2091245 | IM15: 135116602 | IN15: 32088251 | IO15: 76500000 | IP15: - | IQ15: - | IS15: - | IT15: 23243244 | IU15: - | IV15: - | IX15: 261835000 | JB15: 14892216 | JE15: 0 | JH15: 7339144 | JK15: - | JM15: 528255203 | JN15: - | JO15: 22747845 | JP15: 47782450 | JQ15: - | JR15: 4500000 | JS15: 34987000 | JT15: 3598035874 | JW15: 535244435 | JX15: 121500000 | JY15: 115794518 | JZ15: 772538953 | KC15: 105153610 | KD15: 105153610 | KG15: 23675180 | KH15: 168562079 | KI15: 55013037 | KJ15: 600000 | KK15: 44937 | KL15: - | KN15: 247895233 | KQ15: 16354921 | KR15: 1896955018 | KT15: 94500000 | KV15: 0 | KW15: 1848 | KX15: 4137519 | KZ15: 50000000 | LB15: - | LC15: 19358348 | LE15: 2081307655 | LH15: 0 | LI15: 0 | LJ15: =LE15+KD15+JZ15+JT15 -> 6557036092
A16: October | CF16: October | DQ16: October | LJ16: =LE16+KD16+JZ16+JT16 -> 0
A17: November | CF17: November | DQ17: November | LJ17: =LE17+KD17+JZ17+JT17 -> 0
A18: December | CF18: December | DQ18: December | LJ18: =LE18+KD18+JZ18+JT18 -> 0
A21: Laba Rugi Konsolidasi up to month X in 2026 | AB21: Neraca Konsolidasi up to month x in 2026 | CF21: Arus Kas Konsolidasi up to month X in 2026 | DQ21: Monthly CALK Konsolidasi up to month X 2026
B22: Penjualan | C22: Harga Pokok Penjualan | D22: Laba Kotor | E22: Beban Usaha | F22: Beban Umum dan Administrasi | G22: Beban Penjualan dan Pemasaran | H22: Beban Analisa Lab | I22: Jumlah Beban Usaha | J22: Laba Usaha | K22: Pendapatan (Beban) Lain-lain | L22: Pendapatan Lain-lain | M22: Beban Diluar Usaha Lainnya | N22: Jumlah Pendapatan (Beban) Lain-lain | P22: Laba Sebelum Pajak | Q22: Beban Pajak Penghasilan | R22: Pajak tangguhan | S22: Jumlah Beban Pajak | T22: Laba Bersih Setelah Pajak | U22: Penghasilan Komprehensif Lain | V22: Keuntungan/Kerugian aktuarial | W22: atas liabilitas imbalan kerja | X22: Jumlah Penghasilan (Rugi) Komprehensif Lain | AB22: ASET | AC22: Aset Lancar | AD22: Kas dan Setara Kas | AE22: Piutang Usaha | AF22: Anjak Piutang | AG22: Cadangan Kerugian Piutang Tak Tertagih | AH22: Piutang Lain Pihak Terkait | AI22: Persediaan | AJ22: Persediaan dalam Proses | AK22: Persediaan Barang Dagang | AL22: Biaya Dibayar Dimuka | AM22: Pajak Dibayar Dimuka | AN22: Jumlah Aset Lancar | AO22: Aset Tidak Lancar | AP22: Investasi | AQ22: Aset Tetap | AR22: Aset Tidak Lancar Lainnya | AU22: Aset Pajak Tangguhan | AV22: Jumlah Aset Tidak Lancar | AW22: Jumlah Aset | AY22: LIABILITAS DAN EKUITAS | AZ22: Liabilitas Lancar | BA22: Hutang Usaha | BC22: Barang yang belum terinvoice | BD22: Persediaan Barang Diterima Belum di BAST (LPB) | BE22: Hutang Pajak | BF22: Uang Muka Penjualan | BI22: Hutang Lain-Lain | BJ22: Hutang Bunga Bank | BK22: Hutang Bank Jangka Pendek | BL22: Jumlah Liabilitas Lancar | BM22: Liabilitas Tidak Lancar | BN22: Hutang Bank Jangka Panjang | BO22: Hutang Leasing | BP22: Hutang Pemegang Saham | BQ22: Hutang Imbalan Pasca Kerja | BR22: Liabilitas pajak tangguhan | BS22: Jumlah Liabilitas Tidak Lancar | BT22: Jumlah Liabilitas | BU22: Ekuitas | BV22: Modal Disetor | BW22: Saldo Laba | BX22: Laba-Rugi Periode Berjalan | BY22: Laba-Rugi Ditahan | BZ22: Akumulasi penghasilan komprehensif lain | CA22: Kepentingan non pengendali - Rugi/Laba | CB22: Kepentingan non pengendali - Modal | CC22: Jumlah Ekuitas | CD22: Jumlah Liabilitas dan Ekuitas | CG22: Arus Kas dari Aktivitas Operasi | CH22: Laba (rugi) bersih | CI22: Penyesuaian : | CJ22: Penyusutan | CK22: Akumulasi Komprehensif Lain | CM22: Penurunan (Kenaikan) : | CN22: Piutang usaha | CO22: Anjak Piutang | CP22: Piutang Afiliasi & Lainnya | CQ22: Biaya dibayar dimuka | CR22: Pajak dibayar dimuka | CS22: Persediaan | CT22: Kenaikan (Penurunan) : | CU22: Utang Usaha | CV22: Hutang Afiliasi & Lainnya | CW22: Utang Pajak | CX22: Uang Muka Penjualan | CY22: Biaya yg masih harus dibayar | CZ22: Hutang jangka Panjang | DA22: Kas Bersih yang digunakan untuk Aktivitas Operasi | DB22: Arus Kas dari Aktivitas Investasi : | DC22: (Penambahan) Pengurangan Aset Tetap | DD22: (Penambahan) Pengurangan Investasi | DE22: (Penambahan) Pengurangan Konstruksi Dalam Pengerjaan | DF22: Kas Bersih yang diperoleh/ digunakan untuk Aktivitas Investasi | DG22: Arus Kas dari Aktivitas Pendanaan : | DH22: Utang Bank | DI22: Modal di setor | DJ22: Kas Bersih yang diperoleh/ digunakan untuk Aktivitas Pendanaan | DK22: Kenaikan Kas & Setara Kas | DL22: Kas & Setara Kas awal periode | DM22: Kas & Setara Kas akhir periode | DR22: Penjualan | DT22: Retur Penjualan | DU22: Diskon Penjualan | DV22: Jumlah Penjualan | DX22: BEBAN POKOK PENJUALAN | DY22: Harga Pokok Penjualan Afiliasi | DZ22: Harga Pokok Penjualan Non Afiliasi | EA22: Beban Bea Masuk Import | EE22: Beban Penyusutan Mesin | EF22: Beban Pemeliharaan Mesin Ew | EG22: Beban Pemeliharaan Mesin Line 1 | EH22: Beban Pemeliharaan Mesin Line 2 | EI22: Beban Pemeliharaan Mesin Line 3 | EJ22: Beban Pemeliharaan Mesin Line 4 | EK22: Beban Pemeliharaan Mesin Line 5 | EL22: Beban Pemeliharaan Mesin Copper Sulphate | EM22: Beban Penyusutan Peralatan Pabrik | EO22: Beban Sewa Kendaraan | EP22: Selisih Stock Opname | ER22: Beban Tenaga Kerja Langsung | ES22: Beban Transportasi Bahan Baku | ET22: Beban Transportasi Produk Jadi | EU22: Beban Transportasi Produk Jadi (Bonus dan Fee Marketing) | EV22: Beban Pemeliharaan Kendaraan Pabrik | EW22: Beban Pemeliharaan Aset Pabrik | EX22: Beban Rumah Tangga Pabrik | EY22: Beban Gaji Staff Pabrik | EZ22: Beban Tenaga Kerja Tidak Langsung | FA22: Beban Pemeliharaan Mesin Pramaterial | FC22: Beban Listrik Pabrik | FD22: Beban Listrik Pabrik (Gudang Timur) | FF22: Beban Transportasi Lainnya | FG22: Beban Perlengkapan Pabrik | FI22: Beban Bbm Pabrik | FJ22: Beban Bongkar | FK22: Beban Qc Produk | FL22: Beban Transportasi Impor | FM22: Beban Gudang Pelabuhan | FN22: Beban Administrasi Pabean | FO22: Beban Muat | FQ22: Beban Klaim | FR22: Beban Gaji PHL | FV22: Beban Asuransi Pengiriman | FW22: Beban Sample | FX22: Beban Demplot | FZ22: Beban Pemeliharaan Bangunan Pabrik | GA22: Beban Pemeliharaan Sarana Prasarana Pabrik | GB22: Beban Perlengkapan Mekanik | GC22: Beban Perlengkapan Elektrikal | GD22: Beban Pemeliharaan Mesin Crf | GE22: Beban Riset Dan Percobaan Lapangan | GF22: Beban Pemeliharaan Mesin Copper Sulphate Line 2 | GG22: Beban Pemeliharaan Aset Lab | GH22: Beban Operasional Gudang | GI22: Beban Uji Dosis (Internal) | GJ22: Beban Perlengkapan Lab | GK22: Beban Kerugian Bibit Afkir | GL22: Beban Pemeliharaan Mesin NPK | GM22: Jumlah Harga Pokok Penjualan | GO22: BEBAN UMUM DAN ADMINISTRASI | GQ22: Beban Pelatihan | GR22: Beban Pelatihan Internal | GS22: Beban Perlengkapan Kantor | GT22: Beban Hse | GU22: Beban Penyusutan Kendaraan | GV22: Beban Penyusutan Inventaris Kantor | GW22: Beban Amortisasi Ditangguhkan SHGB | GX22: Beban Penyusutan Bangunan | GY22: Beban Gaji BOD | GZ22: Beban Gaji Staff Kantor | HC22: Tunjangan Lembur | HF22: Tunjangan Hari Raya - THR | HG22: Beban Asuransi - BPJS KES | HH22: Beban Asuransi - BPJS TK | HI22: Beban Pemeliharaan Aset Kantor | HJ22: Beban Rumah Tangga Kantor | HK22: Beban Pengembangan System/Software | HL22: Beban Kompensasi Ganti Rugi | HM22: Beban Koreksi Fiskal | HN22: Beban Asuransi Kebakaran | HO22: Beban Pemeliharaan Kendaraan Kantor | HP22: Beban Bbm Kantor | HQ22: Beban Perjalanan Dinas Kantor | HR22: Beban Perjalanan Dinas Tamu | HS22: Beban Obat/Pengobatan | HT22: Beban Sewa | HU22: Biaya Legal Dan Perijinan | HV22: Beban Rakor | HW22: Beban Audit | HX22: Beban Perayaan Hari Besar | HY22: Beban Atk Kantor | HZ22: Beban Internet/Vsat | IA22: Beban Cetak/Fotocopy | IB22: Beban Air Minum Kantor | IC22: Beban Konsumsi Dan Oleh-Oleh Tamu | ID22: Beban Kirim Paket (Sampel/Dokumen) | IE22: Beban Listrik Kantor | IF22: Beban Telepon Kantor | IG22: Pajak Kendaraan & PBB | IH22: Beban Suka/Duka | IK22: Beban Pph 4 Ayat 2 | IL22: Beban Pph Pasal 23 | IM22: Beban Pph Pasal 21 | IN22: Beban Pph 25 | IO22: Beban Pinalti Pajak | IP22: Beban Pph Pasal 29 | IQ22: Beban Olahraga Dan Rekreasi | IR22: Biaya Kaizen | IS22: Beban Pemutusan Hubungan Kerja | IT22: Beban Apraisal | IU22: Beban Konsultan Keuangan | IV22: Beban Bphtb | IW22: Beban Kerugian Investasi | IX22: Beban Apresiasi Karyawan | IY22: Beban Imbalan Pasca Kerja | IZ22: Beban Notaris | JA22: Beban Gaji Staff Laboratorium | JB22: Beban Csr (Corporate Social Responsibility) | JC22: Beban Cadangan Kerugian Piutang Tak Tertagih | JD22: Beban Brand Development | JE22: Beban Ppn Tidak Bisa Dikreditkan | JH22: Beban Penyusutan Software | JI22: Beban Rekrutmen | JJ22: Beban Rups | JK22: Beban Aktuaria | JL22: Beban Riset Corporate & Strategy | JM22: Beban Gaji Managemen | JN22: Beban Gaji Principal | JO22: Beban Sarana Prasarana Kantor | JP22: Beban Outsourcing | JQ22: Biaya Pemeliharaan Bangunan Kantor | JR22: Beban Beasiswa | JS22: Beban Kesejahteraan Karyawan | JT22: Jumlah Beban Administrasi dan Umum | JV22: BEBAN PENJUALAN DAN PEMASARAN | JW22: Beban Operasional Pemasaran | JX22: Beban Relasi | JY22: Beban Promosi | JZ22: Jumlah Beban Penjualan dan Pemasaran | KB22: BEBAN ANALISA LAB | KC22: Beban Analisa Lab | KD22: Jumlah Analisa Lab | KF22: PENDAPATAN | KG22: Pendapatan Jasa Giro | KH22: Pendapatan Lain-Lain | KI22: Pendapatan Selisih Lebih Kurs | KJ22: Pendapatan Aval | KK22: Pendapatan Selisih Koma | KL22: Pendapatan Klaim | KM22: Pendapatan Jasa Maklon | KN22: Jumlah Pendapatan | KP22: BEBAN DILUAR USAHA | KQ22: Beban Adm Bank | KR22: Beban Marjin Pinjaman | KT22: Beban Administrasi Kredit - Mk | KV22: Beban Selisih Kurang Kurs | KW22: Beban Selisih Koma | KX22: Beban Market Place | KY22: Beban Lain-Lain | KZ22: Beban Zakat | LB22: Beban Qurban | LC22: Beban Administrasi Kredit - LC/SKBDN | LE22: Jumlah Beban Diluar Usaha | LG22: PAJAK PENGHASILAN | LH22: Beban Pajak Penghasilan | LI22: Jumlah Pajak Penghasilan | LJ22: Jumlah Beban | LK22: EBITDA
A23: January | B23: 22271442059 | C23: 14550282537 | D23: 7721159523 | F23: 2797455742 | G23: 689993629 | H23: 85297200 | I23: 3572746571 | J23: 4148412952 | L23: 14972802 | M23: 2000053969 | N23: -1985081168 | P23: 2163331785 | Q23: 818660 | S23: 818660 | T23: 2162513125 | W23: - | X23: 2162513125 | AD23: 44214340653 | AE23: 44331095704 | AG23: -325897486 | AH23: 10333743154 | AI23: 104300563162 | AJ23: - | AL23: 27470911203 | AM23: 12165949131 | AN23: 242490705521 | AP23: - | AQ23: 127315422381 | AR23: 6707849388 | AU23: 1712002768 | AV23: 135735274537 | AW23: 378225980058 | BA23: 21736710978 | BC23: - | BD23: - | BE23: 5705977764 | BF23: 9760447198 | BI23: 145767226 | BJ23: - | BK23: 198250150994 | BL23: 235599054161 | BN23: 10372247233 | BO23: - | BQ23: 5424840824 | BR23: - | BS23: 15797088057 | BT23: 251396142218 | BV23: 68245000000 | BW23: - | BX23: 2162513125 | BY23: 53985061075 | BZ23: -541805960 | CA23: - | CB23: 2979069600 | CC23: 126829837839 | CD23: 378225980058 | CF23: January | DQ23: January | DR23: 22321496113 | DT23: -49804054 | DU23: -250000 | DV23: 22271442059 | DZ23: 11233807019 | EA23: 419236000 | EE23: 222361613 | EF23: 175478 | EG23: 3802702 | EH23: 3154533 | EI23: 19358144 | EJ23: 328037 | EK23: 3330313 | EL23: 99249577 | EM23: 36077806 | EO23: 60150000 | EP23: 9103283 | ER23: 326841928 | ES23: 59495840 | ET23: 1256104694 | EV23: 527050 | EY23: 73522457 | EZ23: 161256537 | FA23: 10059662 | FC23: 78314507 | FD23: 22316357 | FF23: 5981156 | FG23: 214800 | FI23: 12000000 | FJ23: 22472770 | FO23: 13196810 | FR23: 117593000 | FV23: 53400200 | FW23: 23953018 | FZ23: 83382614 | GA23: 56657612 | GB23: 14957210 | GC23: 7356377 | GD23: 315543 | GE23: 15133876 | GF23: 437015 | GG23: 24510000 | GH23: 147000 | GM23: 14550282537 | GQ23: 33272500 | GR23: 59048061 | GS23: 155000 | GT23: 23945243 | GU23: 82255996 | GV23: 47123961 | GW23: 22118501 | GX23: 229723827 | GY23: 403465056 | GZ23: 453491678 | HC23: 40204681 | HG23: 29664522 | HH23: 61503254 | HI23: 225000 | HJ23: 48106641 | HK23: 712553 | HN23: 2502709 | HO23: 28181917 | HP23: 5290000 | HQ23: 116650988 | HR23: 8832900 | HT23: 54003207 | HU23: 59550000 | HV23: 49160000 | HX23: 124627563 | HY23: 1996000 | HZ23: 7520728 | IA23: 2529592 | IB23: 3316499 | IC23: 20354381 | ID23: 16661730 | IE23: 17158107 | IF23: 3178477 | IG23: 18466200 | IM23: 77824374 | IQ23: 380000 | JB23: 80200000 | JH23: 7339144 | JM23: 420042284 | JN23: 46928088 | JO23: 765000 | JP23: 41576967 | JQ23: 28962413 | JS23: 16440000 | JT23: 2797455742 | JW23: 491945849 | JX23: 147499000 | JY23: 50548780 | JZ23: 689993629 | KC23: 85297200 | KD23: 85297200 | KG23: 9971413 | KK23: 1389 | KN23: 14972802 | KQ23: 10483936 | KR23: 1612378407 | KT23: 103409480 | KV23: 217846340 | KW23: 2175 | LC23: 5933631 | LE23: 2000053970 | LH23: 818660 | LI23: 818660 | LJ23: =LE23+KD23+JZ23+JT23 -> 5572800541
A24: February | B24: 62193098489 | C24: 41995808416 | D24: 20197290073 | F24: 5948337818 | G24: 1634181348 | H24: 90764202 | I24: 7673283368 | J24: 12524006705 | L24: 366817240 | M24: 4923618479 | N24: -4556801239 | P24: 7967205467 | Q24: 939175 | S24: 939175 | T24: 7966266292 | W24: - | X24: 7966266292 | AD24: 20099667310 | AE24: 49863908492 | AG24: -325897486 | AH24: 10184417154 | AI24: 119522871582 | AJ24: - | AL24: 9744087704 | AM24: 16589488907 | AN24: 225678543663 | AP24: - | AQ24: 130348634297 | AR24: 6678391743 | AU24: 1712002768 | AV24: 138739028808 | AW24: 364417572471 | BA24: 15356991892 | BC24: - | BD24: - | BE24: 8435842992 | BF24: 8132536607 | BI24: 211412619 | BJ24: - | BK24: 178095094338 | BL24: 210231878448 | BN24: 16131668617 | BO24: - | BP24: 5420434399 | BQ24: - | BR24: 21552103016 | BS24: 231783981464 | BU24: 68245000000 | BV24: - | BW24: 7966266292 | BX24: 53985061075 | BY24: -541805960 | BZ24: - | CB24: 2979069600 | CC24: 132633591006 | CD24: 364417572471 | CF24: February | DQ24: February | DR24: 62337414430 | DT24: -144065941 | DU24: -250000 | DV24: 62193098489 | DZ24: 41995808416 | EA24: 984727000 | EE24: 444366975 | EF24: 1468944 | EG24: 6499650 | EH24: 12204311 | EI24: 21320922 | EJ24: 913916 | EK24: 3481852 | EL24: 105887437 | EM24: 72447560 | EO24: 136350000 | EP24: 20344703 | ER24: 690949354 | ES24: 531012409 | ET24: 3253296089 | EV24: 7497538 | EX24: 7791915 | EY24: 158264647 | EZ24: 348391323 | FA24: 40710236 | FC24: 192766711 | FD24: 44298816 | FF24: 26178595 | FG24: 299178 | FI24: 36380000 | FJ24: 57697900 | FO24: 41148912 | FQ24: 82347618 | FR24: 302085750 | FW24: 48453550 | FZ24: 87869514 | GA24: 76031417 | GB24: 24164940 | GC24: 8557462 | GD24: 12672832 | GE24: 46363537 | GF24: 1542886 | GG24: 24510000 | GH24: 21097373 | GI24: 250000000 | GM24: 4.1995806e+10 | GQ24: 37272500 | GR24: 115729122 | GS24: 155000 | GT24: 42859243 | GU24: 164511991 | GV24: 95596203 | GW24: 44237002 | GX24: 459447655 | GY24: 885124224 | GZ24: 1030289227 | HC24: 80340812 | HG24: 62633056 | HH24: 118241036 | HI24: 225000 | HJ24: 85202799 | HK24: 8493578 | HN24: 5005418 | HO24: 63671763 | HP24: 9974000 | HQ24: 330978204 | HR24: 30367550 | HS24: 3231689 | HT24: 115825581 | HU24: 75150000 | HV24: 49949750 | HW24: 112500000 | HX24: 215958517 | HY24: 11329482 | HZ24: 14092878 | IA24: 9903242 | IB24: 5751498 | IC24: 36150492 | ID24: 45552367 | IE24: 27439117 | IF24: 8383938 | IG24: 27952425 | IH24: 4550000 | IK24: 17500000 | IL24: 545613 | IM24: 179261372 | IO24: 500000 | IQ24: 540000 | IU24: 10256410 | JB24: 90200000 | JE24: 1100000 | JH24: 14678288 | JI24: 5780000 | JK24: 27600000 | JM24: 919791824 | JN24: 74485026 | JO24: 7067090 | JP24: 84438423 | JQ24: 34662413 | JR24: 4500000 | JS24: 41355000 | JT24: 594833781800 | JW24: 1333255924 | JX24: 192795000 | JY24: 108130424000000 | JZ24: 1634181348 | KC24: 90764202 | KD24: 90764202 | KG24: 20373845 | KH24: 12524000 | KI24: 328712547 | KJ24: 250000 | KK24: 1893 | KM24: 4954955 | KN24: 366817240 | KQ24: 19597654 | KR24: 3347966924 | KT24: 197076142 | KV24: 849340071 | KW24: 4056 | KZ24: 500000000 | LC24: 9633631 | LE24: 4923618479 | LH24: 939175 | LI24: 939175 | LJ24: =LE24+KD24+JZ24+JT24 -> 601482345829
A25: March | B25: 110370489515 | C25: 82906707994 | D25: 27463781520 | F25: 9208484937 | G25: 2948396212 | H25: 128485815 | I25: 12285366964 | J25: 15178414556 | L25: 537194857 | M25: 7100569924 | N25: -6563375067 | P25: 8615039489 | Q25: 939175 | S25: 939175 | T25: 8614100314 | W25: - | X25: 8614100314 | AD25: 19442003776 | AE25: 51173068869 | AG25: -325897486 | AH25: 10482259154 | AI25: 92350283616 | AJ25: - | AL25: 20785426853 | AM25: 12225997754 | AN25: 206133142535 | AP25: - | AQ25: 130908524708 | AR25: 6648934098 | AU25: 1712002768 | AV25: 139269461574 | AW25: 345402604109 | BA25: 12535565229 | BC25: - | BD25: - | BE25: 5495911745 | BF25: 1887033524 | BI25: 123728456 | BJ25: - | BK25: 171105117438 | BL25: 191147356392 | BN25: 16098725935 | BO25: - | BP25: - | BQ25: 4874363998 | BR25: - | BS25: 20973089933 | BT25: 212120446325 | BV25: 68245000000 | BW25: - | BX25: 8614100314 | BY25: 53985793831 | BZ25: -541805960 | CA25: - | CB25: 2979069600 | CC25: 133282157785 | CD25: 345402604110 | CF25: March | DQ25: March | DR25: 110519521998 | DT25: -145181940 | DU25: -3850543 | DV25: 110370489515 | DZ25: 70532863645 | EA25: 1016185000 | EE25: 659809838 | EF25: 1468944 | EG25: 11630050 | EH25: 12602663 | EI25: 24951552 | EJ25: 6424414 | EK25: 3481852 | EL25: 114942535 | EM25: 108881429 | EO25: 214750000 | EP25: 17922319 | ER25: 1021398046 | ES25: 1094839512 | ET25: 4782070414 | EV25: 32718697 | EX25: 21091913 | EY25: 235420730 | EZ25: 518560400 | FA25: 44483446 | FC25: 350376716 | FD25: 67014624 | FF25: 58858966 | FG25: 345003 | FI25: 49580000 | FJ25: 78345975 | FO25: 60195162 | FQ25: 156211275 | FR25: 421789940 | FV25: 145135445 | FW25: 234336533 | FX25: 6500000 | FZ25: 90554264 | GA25: 148034771 | GB25: 29641658 | GC25: 8782374 | GD25: 13801961 | GE25: 193635646 | GF25: 3413220 | GG25: 24510000 | GH25: 36408877 | GI25: 250000000 | GJ25: 2738184 | GM25: 82906707994 | GQ25: 37461300 | GR25: 172410183 | GS25: 2210234 | GT25: 65435507 | GU25: 237840430 | GV25: 144000870 | GW25: 66355503 | GX25: 689171482 | GY25: 1330845744 | GZ25: 1531631022 | HC25: 122201428 | HF25: 235397436 | HG25: 93925171 | HH25: 176825817 | HI25: 795000 | HJ25: 115260225 | HK25: 48552081 | HN25: 7508127 | HO25: 93040877 | HP25: 12618500 | HQ25: 723247172 | HR25: 48622550 | HS25: 3702889 | HT25: 155566314 | HU25: 112600000 | HV25: 49949750 | HW25: 112500000 | HX25: 230143017 | HY25: 14012855 | HZ25: 27159774 | IA25: 11568842 | IB25: 6210498 | IC25: 60213267 | ID25: 73938932 | IE25: 38703585 | IF25: 13046163 | IG25: 48561425 | IH25: 7550000 | IK25: 17500000 | IL25: 1682333 | IM25: 324478732 | IO25: 500000 | IQ25: 540000 | IT25: 3153153 | IU25: 10256410 | JB25: 102350000 | JE25: 1100000 | JH25: 22017432 | JI25: 5780000 | JK25: 27600000 | JM25: 1368212321 | JN25: 113957469000000 | JO25: 16510400 | JP25: 130318007 | JQ25: 78787210 | JR25: 13500000 | JS25: 49457500 | JT25: 9208484937 | JW25: 2446110330 | JX25: 336795000 | JY25: 165490882 | JZ25: 2948396212 | KC25: 128485815 | KD25: 128485815 | KG25: 30903520 | KH25: 18758595 | KI25: 480936493 | KJ25: 250000 | KK25: 2493 | KM25: 6343756 | KN25: 537194857 | KQ25: 28911800 | KR25: 4970896952 | KT25: 290742804 | KV25: 849340071 | KW25: 644259 | KY25: 400407 | KZ25: 950000000 | LC25: 9633631 | LE25: 7100569924 | LH25: 939175 | LI25: 939175 | LJ25: =LE25+KD25+JZ25+JT25 -> 19385936888
A26: April | B26: 139947620196 | C26: 105088851349 | D26: 34858768846 | F26: 12950979758 | G26: 3461167848 | H26: 174461315 | I26: 16586608921 | J26: 18272159926 | L26: 1001810395 | M26: 9437715037 | N26: -8435904642 | P26: 9836255284 | Q26: 7885483 | S26: 7885483 | T26: 9828369801 | W26: - | X26: 9828369801 | AD26: 22149448688 | AE26: 39387620234 | AG26: -726809713 | AH26: 8069303618 | AI26: 99484397378 | AJ26: - | AL26: 42184427546 | AM26: 13027126905 | AN26: 223575514655 | AP26: - | AQ26: 130729959005 | AR26: 7117825212 | AU26: 3097471000 | AV26: 140945255216 | AW26: 364520769872 | BA26: 13754261151 | BC26: - | BD26: - | BE26: 5190026785 | BF26: 2875451223 | BI26: 204767964 | BJ26: - | BK26: 186931451312 | BL26: 208955958435 | BN26: 15378310047 | BQ26: 10699500880 | BR26: - | BS26: 26077810927 | BT26: 235033769362 | BV26: 68245000000 | BW26: - | BX26: 9828369801 | BY26: 50176612716 | BZ26: -3110625307 | CA26: - | CB26: 4347643300 | CC26: 129487000509 | CD26: 364520769872 | CF26: April | DQ26: April | DR26: 140133396985 | DT26: -148252159 | DU26: -37524630 | DV26: 139947620196 | DZ26: 88927651287 | EA26: 1249743000 | EE26: 922887414 | EF26: 3305634 | EG26: 14111742 | EH26: 20328456 | EI26: 25830794 | EJ26: 6736668 | EK26: 3510698 | EL26: 119013891 | EM26: 144511933 | EO26: 264450000 | EP26: -1904413 | ER26: 1345683530 | ES26: 1402110444 | ET26: 6306811771 | EV26: 41716197 | EX26: 40603290 | EY26: 312904213 | EZ26: 675087980 | FA26: 52303376 | FC26: 428452015 | FD26: 87167963 | FF26: 59543286 | FG26: 2631125 | FI26: 86060000 | FJ26: 109564925 | FN26: 660000 | FO26: 81430327 | FQ26: 161402770 | FR26: 688805339 | FV26: 168540445 | FW26: 234336533 | FX26: 22355186 | FZ26: 121754264 | GA26: 200397475 | GB26: 34442645 | GC26: 18328113 | GD26: 9303274 | GE26: 215272754 | GF26: 6784749 | GG26: 27610000 | GH26: 36553387 | GI26: 250000000 | GJ26: 4217246 | GK26: 155839622 | GM26: 105088851349 | GQ26: 87856300 | GR26: 229091244 | GS26: 3307053 | GT26: 102276175 | GU26: 311168869 | GV26: 192072026 | GW26: 88474004 | GX26: 918895310 | GY26: 1706087228 | GZ26: 2023904146 | HC26: 154333880 | HF26: 422380511 | HG26: 125693376 | HH26: 234667747 | HI26: 795000 | HJ26: 124232921 | HK26: 50424034 | HN26: 10010836 | HO26: 133737419 | HP26: 19196100 | HQ26: 1091015012 | HR26: 56039550 | HS26: 5797889 | HT26: 409802895 | HU26: 115200000 | HV26: 49949750 | HW26: 112500000 | HX26: 253809772 | HY26: 26365895 | HZ26: 47276760 | IA26: 25448300 | IB26: 8703998 | IC26: 88033174 | ID26: 116586859 | IE26: 48921115 | IF26: 16304142 | IG26: 63316656 | IH26: 14400801 | IK26: 17500000 | IL26: 1682333 | IM26: 469276915 | IN26: 249716382 | IO26: 500000 | IP26: 100201552 | IQ26: 540000 | IS26: 20512326 | IT26: 17806306 | IU26: 10256410 | IX26: 17975000 | JB26: 108272000 | JE26: 1430309 | JH26: 29356576000000 | JI26: 5780000 | JK26: 34775000 | JM26: 1885604221 | JN26: 113957469 | JO26: 18637911000000 | JP26: 171220924 | JQ26: 89203876 | JR26: 18000000 | JS26: 80697500 | JT26: 12950979758 | JW26: 2869719284 | JX26: 357795000000000 | JY26: 233653564 | JZ26: 3461167848 | KC26: 174461315 | KD26: 174461315 | KG26: 45865998 | KH26: 24688500 | KI26: 924046182 | KJ26: 2250000 | KK26: 4760 | KM26: 6343756 | KN26: 1001810395 | KQ26: 40254666 | KR26: 6637253505 | KT26: 390112436 | KV26: 849340071 | KW26: 109093 | KX26: 11011635 | KZ26: 1500000000 | LC26: 9633631 | LE26: 9437715037 | LH26: 7885483 | LI26: 7885483 | LJ26: =LE26+KD26+JZ26+JT26 -> 26024323958
A27: May | B27: 168433122793 | C27: 124126481249 | D27: 44306641544 | F27: 17048881589 | G27: 3885772632 | H27: 189078217 | I27: 21123732437 | J27: 23182909106 | L27: 1931993478 | M27: 11911167128 | N27: -9979173650 | P27: 13203735457 | Q27: 7889328 | S27: 7889328 | T27: 13195846129 | W27: - | X27: 13195846129 | AD27: 25811037262 | AE27: 47008967012 | AG27: -726809713 | AH27: 7289928852 | AI27: 105118264727 | AJ27: - | AL27: 35666207828 | AM27: 14770319852 | AN27: 234937915819 | AP27: - | AQ27: 131006355933 | AR27: 7088722766 | AU27: 3097471000 | AV27: 141192549699 | AW27: 376130465518 | BA27: 22160497551 | BC27: - | BD27: - | BE27: 7273003713 | BF27: 1170365530 | BI27: 209126689 | BJ27: - | BK27: 201773311160 | BL27: 232586304644 | BN27: - | BQ27: 10689684037 | BR27: - | BS27: 10689684037 | BT27: 243275988681 | BV27: 68245000000 | BW27: - | BX27: 13195846129 | BY27: 50176612716 | BZ27: -3110625307 | CA27: - | CB27: 4347643300 | CC27: 132854476837 | CD27: 376130465518 | CF27: May | DQ27: May | DR27: 168843420255 | DT27: -151806356 | DU27: -258491107 | DV27: 168433122792 | DZ27: 104225123898 | EA27: 1256078000 | EE27: 1164357684 | EF27: 11199204 | EG27: 37700353 | EH27: 24295509 | EI27: 31169618 | EJ27: 19712980 | EK27: 16773861 | EL27: 130060076 | EM27: 180670695 | EO27: 310950000 | EP27: 51894684 | ER27: 1676879836 | ES27: 1475149838 | ET27: 7578915424 | EV27: 50468697 | EX27: 107722450 | EY27: 394032942 | EZ27: 841473546 | FA27: 104107364 | FC27: 571691847 | FD27: 114559689 | FF27: 63013731 | FG27: 2631125 | FI27: 98930000 | FJ27: 137911678 | FN27: 660000 | FO27: 92792982 | FQ27: 171543508 | FR27: 868918816 | FV27: 229020070 | FW27: 366635207 | FX27: 22355186 | FZ27: 128008722 | GA27: 276563018 | GB27: 41864434 | GC27: 20768324 | GD27: 10850605 | GE27: 479480476 | GF27: 13414749 | GG27: 27610000 | GH27: 36553387 | GI27: 500500000 | GJ27: 5627414 | GK27: 155839622 | GM27: 124126481249 | GQ27: 137281781 | GR27: 850028622 | GS27: 3307053 | GT27: 136348475 | GU27: 384497307 | GV27: 240852055 | GW27: 110592506 | GX27: 1148619137 | GY27: 2131065874 | GZ27: 2461511712 | HC27: 175057718 | HF27: 604863581 | HG27: 158094621 | HH27: 295540459 | HI27: 2290000 | HJ27: 163152186 | HK27: 50577187 | HN27: 12513545 | HO27: 176699991 | HP27: 22288649 | HQ27: 1478906577 | HR27: 60462151 | HS27: 12062151 | HT27: 508415706 | HU27: 139125000 | HV27: 49949750 | HW27: 112500000 | HX27: 331500216 | HY27: 36790743 | HZ27: 58612282 | IA27: 26719960 | IB27: 9073198 | IC27: 95202574 | ID27: 127442108 | IE27: 61980923 | IF27: 22288536 | IG27: 87827656 | IH27: 28270152 | IK27: 19700000 | IL27: 2108311 | IM27: 563439954 | IN27: 326389997 | IO27: 500000 | IP27: 201379904 | IQ27: 540000 | IS27: 23576614 | IT27: 29306306 | IU27: 120256410 | IX27: 26375000 | JB27: 129022000 | JE27: 2805309 | JH27: 36695720000000 | JI27: 9411104 | JK27: 34775000 | JM27: 2392184359 | JN27: 113957469 | JO27: 30614185000000 | JP27: 214260429 | JQ27: 137511376 | JR27: 22500000 | JS27: 99260000 | JT27: 17048881589 | JW27: 3202768359 | JX27: 374795000000000 | JY27: 308209273 | JZ27: 3885772632 | KC27: 189078217 | KD27: 189078217 | KG27: 54463602 | KH27: 31177500 | KI27: 1797260894 | KJ27: 49076500 | KK27: 14982 | KM27: 6343756 | KN27: 1931993478 | KQ27: 49848291 | KR27: 8446347403 | KT27: 526857436 | KV27: 849340071 | KW27: 113959 | KX27: 11011635 | KY27: 13731336 | KZ27: 1850000000 | LB27: 165295000 | LC27: 9633631 | LE27: 11911167128 | LH27: 7889328 | LI27: 7885483 | LJ27: =LE27+KD27+JZ27+JT27 -> 33034899566
A28: June | B28: 212292412013 | C28: 159048246567 | D28: 53244165446 | F28: 21329249270 | G28: 4750734022 | H28: 281165917 | I28: 26361149208 | J28: 26883016238 | L28: 1964486552 | M28: 14590619538 | N28: -12626132986 | P28: 14256883252 | Q28: 8123461 | S28: 8123461 | T28: 14248759791 | W28: - | X28: 14248759791 | AD28: 15936203293 | AE28: 63024226276 | AG28: -726809713 | AH28: 6595645696 | AI28: 107226471817 | AJ28: - | AL28: 38703370451 | AM28: 15350769281 | AN28: 246109877102 | AP28: - | AQ28: 130656345348 | AR28: 7059265121 | AU28: 3097471000 | AV28: 140813081470 | AW28: 386922958571 | BA28: 25476188216 | BC28: - | BD28: - | BE28: 8090627462 | BF28: 2283637018 | BI28: 215394159 | BJ28: - | BK28: 190885058208 | BL28: 226950905064 | BN28: 15399414819 | BQ28: 10665248189 | BR28: - | BS28: 26064663008 | BT28: 253015568072 | BV28: 68245000000 | BW28: - | BX28: 14248759791 | BY28: 50176612716 | BZ28: -3110625307 | CA28: - | CB28: 4347643300 | CC28: 133907390499 | CD28: 386922958571 | CF28: June | DQ28: June | DR28: 212719223445 | DT28: -162066089 | DU28: -264745343 | DV28: 212292412013 | DZ28: 131850159327 | EA28: 1536886000 | EE28: 1408352698 | EF28: 20215916 | EG28: 55325391 | EH28: 30488957 | EI28: 36889714 | EJ28: 27756380 | EK28: 17766730 | EL28: 145824270 | EM28: 216439190 | EO28: 334950000 | EP28: 82035505 | ER28: 2039812557 | ES28: 1673309660 | ET28: 12420548100 | EV28: 71655197 | EX28: 148758969 | EY28: 394032942 | EZ28: 1022372784 | FA28: 142721530 | FC28: 651194608 | FD28: 137550816 | FF28: 216707435 | FG28: 2631125 | FI28: 123229000 | FJ28: 173881318 | FN28: 660000 | FO28: 108033762 | FQ28: 179728458 | FR28: 1031156999 | FV28: 470545987 | FW28: 408278507 | FX28: 22355186 | FZ28: 128008722 | GA28: 359564431 | GB28: 56154512 | GC28: 23538062 | GD28: 22676602 | GE28: 505079555 | GF28: 13414749 | GG28: 27610000 | GH28: 47977880 | GI28: 500500000 | GJ28: 5627414 | GK28: 155839622 | GM28: 159048246567 | GQ28: 182083997 | GR28: 1617700581 | GS28: 6133553 | GT28: 163282217 | GU28: 458008038 | GV28: 289494996 | GW28: 132711007 | GX28: 1379222284 | GY28: 2547939269 | GZ28: 2954543644 | HC28: 219780141 | HF28: 787346651 | HG28: 190036889 | HH28: 367502579 | HI28: 3140000 | HJ28: 194603361 | HK28: 51327187 | HN28: 16499070 | HO28: 257130224 | HP28: 27269217 | HQ28: 1747748375 | HR28: 65288358 | HS28: 15224350 | HT28: 610695183 | HU28: 166375000 | HV28: 49949750 | HW28: 200000000 | HX28: 348746216 | HY28: 46605271 | HZ28: 73709064 | IA28: 28668880 | IB28: 10270198 | IC28: 115305479 | ID28: 138656272 | IE28: 74530601 | IF28: 26316358 | IG28: 115494640 | IH28: 42071753 | IK28: 19700000 | IL28: 2241640 | IM28: 701993378 | IN28: 358478248 | IO28: 25467315 | IP28: 301581456 | IQ28: 1040000 | IS28: 23576614 | IT28: 72099099 | IU28: 120256410 | IX28: 26375000 | JB28: 149772000 | JE28: 2805309 | JH28: 44034864000000 | JI28: 15054354 | JK28: 34775000 | JM28: 2908512650 | JN28: 113957469 | JO28: 42309502000000 | JP28: 257299934 | JQ28: 185818876 | JR28: 22500000 | JS28: 178189500 | JT28: 21329249270 | JW28: 4005697051 | JX28: 393795000000000 | JY28: 351241971 | JZ28: 4750734022 | KC28: 281165917 | KD28: 281165917 | KG28: 79845375 | KH28: 38275000 | KI28: 1797260895 | KJ28: 49076500 | KK28: 28783 | KM28: 6343756 | KN28: 1964486552 | KQ28: 58327304 | KR28: 10283561659 | KT28: 736357436 | KV28: 873336412 | KW28: 118098 | KX28: 19370438 | KZ28: 2435245310 | LB28: 174669250 | LC28: 9633631 | LE28: 14590619538 | LH28: 8123461 | LI28: 8123461 | LJ28: =LE28+KD28+JZ28+JT28 -> 40951768747
A29: July | B29: 273140874298 | C29: 204589533159 | D29: 68551341140 | F29: 25720135079 | G29: 5240783586 | H29: 387328928 | I29: 31348247593 | J29: 37203093547 | L29: 2153642634 | M29: 16559792898 | N29: -14406150264 | P29: 22796943283 | Q29: 8123461 | S29: =S28+S13 -> 8123461 | T29: =T28+T13 -> 22788819823 | X29: =X28+X13 -> 22788819823 | AD29: 16228480826 | AE29: 82925685482 | AG29: -726809713 | AH29: 5825645696 | AI29: 99274743635 | AJ29: - | AL29: 33662234090 | AM29: 16997370821 | AN29: 254187350837 | AP29: - | AQ29: 132943952489 | AR29: 7029807476 | AU29: 3097471000 | AV29: 143071230966 | AW29: 397258581802 | BA29: 30921952568 | BC29: - | BD29: - | BE29: 11493763808 | BF29: 1395353998 | BI29: 214849468 | BJ29: - | BK29: 184742012601 | BL29: 228767932443 | BN29: 15401214441 | BQ29: 10641984387 | BR29: 0 | BS29: 26043198828 | BT29: 254811131271 | BV29: 68245000000 | BW29: 0 | BX29: 22788819822 | BY29: 50176612716 | BZ29: -3110625307 | CA29: - | CB29: 4347643300 | CC29: 142447450531 | CD29: 397258581802 | CF29: July | DQ29: July | DR29: 273840258741 | DT29: -191665590 | DU29: -507718853 | DV29: 273140874298 | DZ29: 170670040154 | EA29: 2047845000 | EE29: 1654047714 | EF29: 35872766 | EG29: 70351473 | EH29: 50944695 | EI29: 62318167 | EJ29: 51017825 | EK29: 19398883 | EL29: 152615990 | EM29: 251701829 | EO29: 382950000 | EP29: 315061090 | ER29: 2432487000 | ES29: 2171791209 | ET29: 16059586073 | EV29: 122755283 | EX29: 180891328 | EY29: 514956120 | EZ29: 1211149176 | FA29: 158052586 | FC29: 765214391 | FD29: 159113288 | FF29: 262419768 | FG29: 2631125 | FI29: 135595000 | FJ29: 195007618 | FN29: 660000 | FO29: 130679412 | FQ29: 181602836 | FR29: 1195162614 | FV29: 282949170 | FW29: 408857386 | FX29: 22355186 | FZ29: 134772626 | GA29: 620789897 | GB29: 74137998 | GC29: 46767893 | GD29: 25983151 | GE29: 511124534 | GF29: 13414749 | GG29: 34735000 | GH29: 63745330 | GI29: 500500000 | GJ29: 5627414 | GK29: 155839622 | GL29: 44012791 | GM29: 204589533159 | GQ29: 250984997 | GR29: 2341327108 | GS29: 6686671 | GT29: 168388273 | GU29: 531518768 | GV29: 339259651 | GW29: 154829508 | GX29: 1609825431 | GY29: 2961653259 | GZ29: 3333677837 | HC29: 242471948 | HF29: 944289428 | HG29: 224274049 | HH29: 431413341 | HI29: 3140000 | HJ29: 211031988 | HK29: 51327187 | HN29: 19001779 | HO29: 315780246 | HP29: 32751957 | HQ29: 2121806011 | HR29: 76685858 | HS29: 32186877 | HT29: 701807994 | HU29: 640170000 | HV29: 49949750 | HW29: 225000000 | HX29: 348746216 | HY29: 54829039 | HZ29: 97422077 | IA29: 37360544 | IB29: 13660098 | IC29: 126833179 | ID29: 164816674 | IE29: 87524703 | IF29: 29596883 | IG29: 125084840 | IH29: 54626555 | IK29: 20765709 | IL29: 10424409 | IM29: 841948368 | IN29: 415464879 | IO29: 49275203 | IP29: 301581456 | IQ29: 2540000 | IS29: 23576614 | IT29: 72099099 | IU29: 120256410 | IV29: 4250000 | IX29: 26375000 | JB29: 224458037 | JE29: 15755141 | JH29: 51374009 | JI29: 15054354 | JK29: 34775000 | JM29: 3434760814 | JN29: 113957469 | JO29: 57299570 | JP29: 300339439 | JQ29: 185818876 | JR29: 22500000 | JS29: 213744500 | JT29: 25720135079 | JW29: 4354869715 | JX29: 412795000 | JY29: 473118871 | JZ29: 5240783586 | KC29: 387328928 | KD29: 387328928 | KG29: 101283976 | KH29: 54530417 | KI29: 1948003093 | KJ29: 49076500 | KK29: 748647 | KM29: 6343756 | KN29: 2153642634 | KQ29: 68347495 | KR29: 12092814522 | KT29: 830857436 | KV29: 873336413 | KW29: 141730 | KX29: 24747111 | KZ29: 2485245310 | LB29: 174669250 | LC29: 9633631 | LE29: 18713435533 | LH29: 8123461 | LI29: 8123461 | LJ29: =LE29+KD29+JZ29+JT29 -> 50061683126
A30: August | B30: 327591969294 | C30: 248151334323 | D30: 79440634971 | F30: 28372953456 | G30: 5670374900 | H30: 416729428 | I30: 34460057784 | J30: 44980577187 | L30: 2707837814 | M30: 19039119464 | N30: -16331281650 | P30: 28649295537 | Q30: 8123461 | S30: 8123461 | T30: 28641172076 | X30: 28641172076 | AD30: 15146534221 | AE30: 95360939306 | AG30: -301516003 | AH30: 4937637296 | AI30: 102352653702 | AL30: 27357562602 | AM30: 16372616426 | AN30: 261226427550 | AP30: - | AQ30: 133732209029 | AR30: 7000349831 | AU30: 3097471000 | AV30: 143830029860 | AW30: 405056457410 | BA30: 26707978354 | BC30: - | BD30: - | BE30: 11154914765 | BF30: 1486038598 | BI30: 215511729 | BJ30: - | BK30: 191571541624 | BL30: 231135985071 | BN30: 15403011497 | BQ30: 10217658058 | BS30: 25620669555 | BT30: 256756654625 | BV30: 68245000000 | BX30: 28641172076 | BY30: 50176612716 | BZ30: -3110625307 | CA30: - | CB30: 4347643300 | CC30: 148299802784 | CD30: 405056457410 | CF30: August | DQ30: August | DR30: 328297980204 | DT30: -193801257 | DU30: -512209653 | DV30: 327591969294 | DZ30: 204338074371 | EA30: 3176391000 | EE30: 1905445511 | EF30: 50727412 | EG30: 90245622 | EH30: 58565448 | EI30: 75650924 | EJ30: 151227934 | EK30: 22015978 | EL30: 157218972 | EM30: 298343346 | EO30: 430950000 | EP30: -23519148 | EQ30: 408865568 | ER30: 2725585556 | ES30: 2569932924 | ET30: 20902832994 | EV30: 127136047 | EX30: 1382944613 | EY30: 614669238 | EZ30: 1377838695 | FA30: 197410776 | FC30: 895259808 | FD30: 181962763 | FF30: 264355873 | FG30: 2631125 | FI30: 148707000 | FJ30: 229171663 | FN30: 660000 | FO30: 153709462 | FQ30: 718487575 | FR30: 1394006119 | FV30: 222844820 | FW30: 461815205 | FX30: 6500000 | FZ30: 177532845 | GA30: 720452385 | GB30: 78231218 | GC30: 47186297 | GD30: 26341201 | GE30: 516929704 | GF30: 13414749 | GG30: 34735000 | GH30: 87582830 | GI30: 500500000 | GJ30: 5627414 | GK30: 155839622 | GL30: 68295865 | GM30: 248151334323 | GQ30: 332257997 | GR30: 1790769991 | GS30: 6686671 | GT30: 185085473 | GU30: 607732201 | GV30: 389920142 | GW30: 176948009 | GX30: 1840428578 | GY30: 3439528473 | GZ30: 3788407453 | HC30: 272211059 | HF30: 1126772498 | HG30: 256607778 | HH30: 495280243 | HI30: 3140000 | HJ30: 222448144 | HK30: 51327187 | HN30: 19001779 | HO30: 350645684 | HP30: 38170917 | HQ30: 2314646421 | HR30: 90846198 | HS30: 33708877 | HT30: 788115527 | HU30: 678973136 | HV30: 49949750 | HW30: 225000000 | HX30: 371301216 | HY30: 60278140 | HZ30: 105394586 | IA30: 52867698 | IB30: 15697598 | IC30: 149587792 | ID30: 186012837 | IE30: 100348843 | IF30: 33400054 | IG30: 137261840 | IH30: 66879456 | IK30: 20765709 | IL30: 27959285 | IM30: 982782963 | IN30: 523980357 | IO30: 51294519 | IP30: 301581456 | IQ30: 3290000 | IS30: 23576614 | IT30: 131558559 | IU30: 120256410 | IV30: 4250000 | IX30: 26375000 | JB30: 232258037 | JE30: 19750266 | JH30: 58713153 | JI30: 15054354 | JK30: 34775000 | JM30: 3955037148 | JN30: 113957469 | JO30: 63450826 | JP30: 345421731 | JQ30: 190903876 | JR30: 36000000 | JS30: 236320480 | JT30: 28372953456 | JW30: 4709337138 | JX30: 438295000 | JY30: 522742762 | JZ30: 5670374900 | KC30: 416729428 | KD30: 416729428 | KG30: 123493489 | KH30: 59946917 | KI30: 1948713265 | KJ30: 49676500 | KK30: 41486 | KL30: 525966156 | KN30: 2707837813 | KQ30: 79593399 | KR30: 13841578924 | KT30: 925357436 | KV30: 1081802774 | KW30: 142463 | KX30: 29455908 | KZ30: 2896885678 | LB30: 174669250 | LC30: 9633631 | LE30: 21746957277 | LH30: 8123461 | LI30: 8123461 | LJ30: =LE30+KD30+JZ30+JT30 -> 56207015061
A31: September | B31: 400929809822 | C31: 312813499415 | D31: 88116310407 | F31: 31970989330 | G31: 6442913853 | H31: 521883037 | I31: 38935786221 | J31: 49180524186 | L31: 2955733046 | M31: 21120427118 | N31: -18164694072 | P31: 31015830114 | Q31: 8123461 | S31: 8123461 | T31: 31007706653 | X31: 31007706653 | AD31: 26449313884 | AE31: 114222708267 | AF31: 2493348844 | AG31: -135609003 | AH31: 3770977936 | AI31: 86952512893 | AL31: 14449173958 | AM31: 17263915379 | AN31: 265466342159 | AQ31: 135246210726 | AR31: 7089517186 | AU31: 3097471000 | AV31: 145433198911 | AW31: 410899541071 | BA31: 22607963166 | BE31: 12112195121 | BF31: 774032498 | BI31: 196895005 | BK31: 196058597022 | BL31: 231749682812 | BN31: 18272650705 | BQ31: 10210870193 | BS31: 28483520898 | BT31: 260233203709 | BV31: 68245000000 | BX31: 31007706653 | BY31: 50176612716 | BZ31: -3110625307 | CB31: 4347643300 | CC31: 150666337362 | CD31: 410899541071 | CF31: September | CG31: 31007706653 | CJ31: 5762210682 | CK31: -1366988488 | CN31: -61727828177 | CO31: -2493348844 | CP31: 6121227790 | CQ31: 14546755886 | CR31: -17241979967 | CS31: -17574582318 | CU31: 328139359 | CW31: 13144105386 | CX31: -5362757500 | CY31: -22419081 | DA31: -34879758619 | DC31: -14015383214 | DF31: -14015383214 | DH31: 25154781400 | DJ31: 25154781400 | DK31: -23740360433 | DL31: 50189674314 | DM31: 26449313881 | DQ31: September | DR31: 401645650098 | DT31: -203630624 | DU31: -512209653 | DV31: 400929809822 | DZ31: 261015572948 | EA31: 4213248000 | EE31: 2157149903 | EF31: 73878133 | EG31: 115673514 | EH31: 79824004 | EI31: 78622930 | EJ31: 167615302 | EK31: 25481648 | EL31: 161141587 | EM31: 344278095 | EO31: 482250000 | EP31: -38298997 | EQ31: 254243226 | ER31: 3125930470 | ES31: 2734084777 | ET31: 17133642663 | EU31: 7590489071 | EV31: 129387510 | EX31: 1824630899 | EY31: 680787894 | EZ31: 1571225293 | FA31: 223958878 | FC31: 1056402760 | FD31: 199347895 | FF31: 277042101 | FG31: 22424875 | FI31: 174327000 | FJ31: 252193263 | FN31: 660000 | FO31: 185547912 | FQ31: 745017040 | FR31: 1721200642 | FV31: 351651020 | FW31: 657754754 | FX31: 22355186 | FZ31: 177532845 | GA31: 1062355773 | GB31: 79354505 | GC31: 49038804 | GD31: 72209517 | GE31: 648378696 | GF31: 22666515 | GG31: 37735000 | GH31: 103306308 | GI31: 500500000 | GJ31: 6411198 | GK31: 155839622 | GL31: 87428434 | GM31: 312813499415 | GQ31: 389565669 | GR31: 2016273805 | GS31: 7198831 | GT31: 201242973 | GU31: 683945634 | GV31: 440785943 | GW31: 199066510 | GX31: 2071727699 | GY31: 3789081239 | GZ31: 4263813316 | HC31: 299886047 | HF31: 1309255568 | HG31: 289495498 | HH31: 559296921 | HI31: 3220000 | HJ31: 254974780 | HK31: 51327187 | HL31: 3750000 | HN31: 19001779 | HO31: 407378082 | HP31: 42595477 | HQ31: 2537414313 | HR31: 99914463 | HS31: 73238369 | HT31: 872923060 | HU31: 691073136 | HV31: 49949750 | HW31: 230000000 | HX31: 371301216 | HY31: 69455169 | HZ31: 129321140 | IA31: 53157448 | IB31: 16480098 | IC31: 169996744 | ID31: 199955718 | IE31: 111935377 | IF31: 36997454 | IG31: 171717140 | IH31: 66879456 | IK31: 20765709 | IL31: 30050530 | IM31: 1117899565 | IN31: 541101571 | IO31: 127794519 | IP31: 301581456 | IQ31: 3290000 | IS31: 23576614 | IT31: 154801803 | IU31: 120256410 | IV31: 4250000 | IX31: 288210000 | JB31: 247150253 | JE31: 19750266 | JH31: 66052297 | JI31: 15054354 | JK31: 34775000 | JM31: 4503964299 | JN31: 113957469 | JO31: 86198671 | JP31: 393204181 | JQ31: 190903876 | JR31: 40500000 | JS31: 271307480 | JT31: 31970989330 | JW31: 5244581573 | JX31: 559795000 | JY31: 638537280 | JZ31: 6442913853 | KC31: 521883037 | KD31: 521883037 | KG31: 147168669 | KH31: 228508997 | KI31: 2003016130 | KJ31: 50276500 | KK31: 796595 | KL31: 525966156 | KN31: 2955733046 | KQ31: 95948321 | KR31: 15738533942 | KT31: 1019857436 | KV31: 1081802774 | KW31: 144311 | KX31: 33593428 | KZ31: 2946885678 | LB31: 174669250 | LC31: 28991979 | LE31: 21120427118 | LH31: 8123461 | LI31: 8123461 | LJ31: =LE31+KD31+JZ31+JT31 -> 60056213338
A32: October | CF32: October | DQ32: October | LJ32: =LE32+KD32+JZ32+JT32 -> 0
A33: November | CF33: November | DQ33: November | LJ33: =LE33+KD33+JZ33+JT33 -> 0
A34: December | CF34: December | DQ34: December | LJ34: =LE34+KD34+JZ34+JT34 -> 0
A37: Laba Rugi Konsolidasi up to month X in 2025 | AB37: Neraca Konsolidasi up to month x in 2025 | CF37: Arus Kas Konsolidasi up to month X in 2025 | DQ37: Monthly CALK Konsolidasi up to month X 2025
B38: Penjualan | C38: Harga Pokok Penjualan | D38: Laba Kotor | E38: Beban Usaha | F38: Beban Umum dan Administrasi | G38: Beban Penjualan dan Pemasaran | H38: Beban Analisa Lab | I38: Jumlah Beban Usaha | J38: Laba Usaha | K38: Pendapatan (Beban) Lain-lain | L38: Pendapatan Lain-lain | M38: Beban Diluar Usaha Lainnya | N38: Jumlah Pendapatan (Beban) Lain-lain | P38: Laba Sebelum Pajak | Q38: Beban Pajak Penghasilan (Pajak Kini) | R38: Pajak tangguhan | S38: Jumlah Beban Pajak | T38: Laba Bersih Setelah Pajak | U38: Penghasilan Komprehensif Lain | V38: Keuntungan/Kerugian aktuarial | W38: atas liabilitas imbalan kerja | X38: Jumlah Penghasilan (Rugi) Komprehensif Lain | AB38: ASET | AC38: Aset Lancar | AD38: Kas dan Setara Kas | AE38: Piutang Usaha | AF38: Anjak Piutang | AG38: Cadangan Kerugian Piutang Tak Tertagih | AH38: Piutang Lain Pihak Terkait | AI38: Persediaan | AJ38: Persediaan dalam Proses | AK38: Persediaan Barang Dagang | AL38: Biaya Dibayar Dimuka | AM38: Pajak Dibayar Dimuka | AN38: Jumlah Aset Lancar | AO38: Aset Tidak Lancar | AP38: Investasi | AQ38: Aset Tetap | AR38: Aset Tidak Lancar Lainnya | AS38: Aset tidak berwujud - bersih | AT38: Pekerjaan dalam proses konstruksi | AU38: Aset Pajak Tangguhan | AV38: Jumlah Aset Tidak Lancar | AW38: Jumlah Aset | AY38: LIABILITAS DAN EKUITAS | AZ38: Liabilitas Lancar | BA38: Hutang Usaha | BC38: Barang yang belum terinvoice | BD38: Persediaan Barang Diterima Belum di BAST (LPB) | BE38: Hutang Pajak | BF38: Uang Muka Penjualan | BG38: Akrual | BH38: Pendapatan diterima dimuka | BI38: Hutang Lain-Lain | BJ38: Hutang Bunga Bank | BK38: Hutang Bank Jangka Pendek | BL38: Jumlah Liabilitas Lancar | BM38: Liabilitas Tidak Lancar | BN38: Hutang Bank Jangka Panjang | BO38: Hutang Leasing | BP38: Hutang Pemegang Saham | BQ38: Hutang Imbalan Pasca Kerja | BR38: Liabilitas pajak tangguhan | BS38: Jumlah Liabilitas Tidak Lancar | BT38: Jumlah Liabilitas | BU38: Ekuitas | BV38: Modal Disetor | BW38: Saldo Laba | BX38: Laba-Rugi Periode Berjalan | BY38: Laba-Rugi Ditahan | BZ38: Akumulasi penghasilan komprehensif lain | CA38: Kepentingan non pengendali - Rugi/Laba | CB38: Kepentingan non pengendali - Modal | CC38: Jumlah Ekuitas | CD38: Jumlah Liabilitas dan Ekuitas | CG38: Arus Kas dari Aktivitas Operasi | CH38: Laba (rugi) bersih | CI38: Penyesuaian : | CJ38: Penyusutan | CK38: Akumulasi Komprehensif Lain | CM38: Penurunan (Kenaikan) : | CN38: Piutang usaha | CO38: Anjak Piutang | CP38: Piutang Afiliasi & Lainnya | CQ38: Biaya dibayar dimuka | CR38: Pajak dibayar dimuka | CS38: Persediaan | CT38: Kenaikan (Penurunan) : | CU38: Utang Usaha | CV38: Hutang Afiliasi & Lainnya | CW38: Utang Pajak | CX38: Uang Muka Penjualan | CY38: Biaya yg masih harus dibayar | CZ38: Hutang jangka Panjang | DA38: Kas Bersih yang digunakan untuk Aktivitas Operasi | DB38: Arus Kas dari Aktivitas Investasi : | DC38: (Penambahan) Pengurangan Aset Tetap | DD38: (Penambahan) Pengurangan Investasi | DE38: (Penambahan) Pengurangan Konstruksi Dalam Pengerjaan | DF38: Kas Bersih yang diperoleh/ digunakan untuk Aktivitas Investasi | DG38: Arus Kas dari Aktivitas Pendanaan : | DH38: Utang Bank | DI38: Modal di setor | DJ38: Kas Bersih yang diperoleh/ digunakan untuk Aktivitas Pendanaan | DK38: Kenaikan Kas & Setara Kas | DL38: Kas & Setara Kas awal periode | DM38: Kas & Setara Kas akhir periode | DR38: Penjualan Afiliasi | DS38: Penjualan Non Afiliasi | DT38: Retur Penjualan | DU38: Diskon Penjualan | DV38: Jumlah Penjualan | DX38: BEBAN POKOK PENJUALAN | DY38: Harga Pokok Penjualan Afiliasi | DZ38: Harga Pokok Penjualan Non Afiliasi | EA38: Beban Bea Masuk Import | EB38: Beban Clearance Impor | EC38: Potongan Pembelian | ED38: Retur Pembelian | EE38: Beban Penyusutan Mesin | EF38: Beban Pemeliharaan Mesin Ew | EG38: Beban Pemeliharaan Mesin Line 1 | EH38: Beban Pemeliharaan Mesin Line 2 | EI38: Beban Pemeliharaan Mesin Line 3 | EJ38: Beban Pemeliharaan Mesin Line 4 | EK38: Beban Pemeliharaan Mesin Line 5 | EL38: Beban Pemeliharaan Mesin Copper Sulphate | EM38: Beban Penyusutan Peralatan Pabrik | EN38: Beban Pemeliharaan Mesin Mixing | EO38: Beban Sewa Kendaraan | EP38: Selisih Stock Opname | EQ38: Selisih Timbang | ER38: Beban Tenaga Kerja Langsung | ES38: Beban Transportasi Bahan Baku | ET38: Beban Transportasi Produk Jadi | EV38: Beban Pemeliharaan Kendaraan Pabrik | EW38: Beban Pemeliharaan Aset Pabrik | EX38: Beban Rumah Tangga Pabrik | EY38: Beban Gaji Staff Pabrik | EZ38: Beban Tenaga Kerja Tidak Langsung | FA38: Beban Pemeliharaan Mesin Pramaterial | FB38: Beban Operasional | FC38: Beban Listrik Pabrik | FD38: Beban Listrik Pabrik (Gudang Timur) | FE38: Beban Listrik Pabrik (Tengah) | FF38: Beban Transportasi Lainnya | FG38: Beban Perlengkapan Pabrik | FH38: Beban Telepon Pabrik | FI38: Beban Bbm Pabrik | FJ38: Beban Bongkar | FK38: Beban Qc Produk | FL38: Beban Transportasi Impor | FM38: Beban Gudang Pelabuhan | FN38: Beban Administrasi Pabean | FO38: Beban Muat | FP38: Beban Royalti Merk | FQ38: Beban Klaim | FR38: Beban Gaji PHL | FS38: Beban Operasional Kebun | FT38: Beban Perlengkapan Kebun | FU38: Beban Bbm Kebun | FV38: Beban Asuransi Pengiriman | FW38: Beban Sample | FX38: Beban Demplot | FY38: Beban Jasa Maklon | FZ38: Beban Pemeliharaan Bangunan Pabrik | GA38: Beban Pemeliharaan Sarana Prasarana Pabrik | GB38: Beban Perlengkapan Mekanik | GC38: Beban Perlengkapan Elektrikal | GD38: Beban Pemeliharaan Mesin Crf | GE38: Beban Riset Dan Percobaan Lapangan | GF38: Beban Pemeliharaan Mesin Copper Sulphate Line 2 | GG38: Beban Pemeliharaan Aset Lab | GH38: Beban Operasional Gudang | GI38: Beban Uji Dosis (Internal) | GJ38: Beban Perlengkapan Lab | GK38: Beban Kerugian Bibit Afkir | GL38: Beban Pemeliharaan Mesin NPK | GM38: Jumlah Harga Pokok Penjualan | GO38: BEBAN UMUM DAN ADMINISTRASI | GP38: Beban Administrasi Dan Umum | GQ38: Beban Pelatihan | GR38: Beban Pelatihan Internal | GS38: Beban Perlengkapan Kantor | GT38: Beban Hse | GU38: Beban Penyusutan Kendaraan | GV38: Beban Penyusutan Inventaris Kantor | GW38: Beban Amortisasi Ditangguhkan SHGB | GX38: Beban Penyusutan Bangunan | GY38: Beban Gaji BOD | GZ38: Beban Gaji Staff Kantor | HA38: Beban Tunjangan Keluarga | HB38: Bebang Tunjangan Kemahalan | HC38: Tunjangan Lembur | HD38: Beban Tunjangan Kinerja | HE38: Beban Bonus | HF38: Tunjangan Hari Raya - THR | HG38: Beban Asuransi - BPJS KES | HH38: Beban Asuransi - BPJS TK | HI38: Beban Pemeliharaan Aset Kantor | HJ38: Beban Rumah Tangga Kantor | HK38: Beban Pengembangan System/Software | HL38: Beban Kompensasi Ganti Rugi | HM38: Beban Koreksi Fiskal | HN38: Beban Asuransi Kebakaran | HO38: Beban Pemeliharaan Kendaraan Kantor | HP38: Beban Bbm Kantor | HQ38: Beban Perjalanan Dinas Kantor | HR38: Beban Perjalanan Dinas Tamu | HS38: Beban Obat/Pengobatan | HT38: Beban Sewa | HU38: Biaya Legal Dan Perijinan | HV38: Beban Rakor | HW38: Beban Audit | HX38: Beban Perayaan Hari Besar | HY38: Beban Atk Kantor | HZ38: Beban Internet/Vsat | IA38: Beban Cetak/Fotocopy | IB38: Beban Air Minum Kantor | IC38: Beban Konsumsi Dan Oleh-Oleh Tamu | ID38: Beban Kirim Paket (Sampel/Dokumen) | IE38: Beban Listrik Kantor | IF38: Beban Telepon Kantor | IG38: Pajak Kendaraan & PBB | IH38: Beban Suka/Duka | II38: Beban Bunga Imbalan Kerja | IJ38: Beban Kerugian Aktuaria | IK38: Beban Pph 4 Ayat 2 | IL38: Beban Pph Pasal 23 | IM38: Beban Pph Pasal 21 | IN38: Beban Pph 25 | IO38: Beban Pinalti Pajak | IP38: Beban Pph Pasal 29 | IQ38: Beban Olahraga Dan Rekreasi | IR38: Biaya Kaizen | IS38: Beban Pemutusan Hubungan Kerja | IT38: Beban Apraisal | IU38: Beban Konsultan Keuangan | IV38: Beban Bphtb | IW38: Beban Kerugian Investasi | IX38: Beban Apresiasi Karyawan | IY38: Beban Imbalan Pasca Kerja | IZ38: Beban Notaris | JA38: Beban Gaji Staff Laboratorium | JB38: Beban Csr (Corporate Social Responsibility) | JC38: Beban Cadangan Kerugian Piutang Tak Tertagih | JD38: Beban Brand Development | JE38: Beban Ppn Tidak Bisa Dikreditkan | JF38: Beban Operasional Direksi | JG38: Beban Asuransi Managemen | JH38: Beban Penyusutan Software | JI38: Beban Rekrutmen | JJ38: Beban Rups | JK38: Beban Aktuaria | JL38: Beban Riset Corporate & Strategy | JM38: Beban Gaji Managemen | JN38: Beban Gaji Principal | JO38: Beban Sarana Prasarana Kantor | JP38: Beban Outsourcing | JQ38: Biaya Pemeliharaan Bangunan Kantor | JR38: Beban Beasiswa | JS38: Beban Kesejahteraan Karyawan | JT38: Jumlah Beban Administrasi dan Umum | JV38: BEBAN PENJUALAN DAN PEMASARAN | JW38: Beban Operasional Pemasaran | JX38: Beban Relasi | JY38: Beban Promosi | JZ38: Jumlah Beban Penjualan dan Pemasaran | KB38: BEBAN ANALISA LAB | KC38: Beban Analisa Lab | KD38: Jumlah Analisa Lab | KF38: PENDAPATAN | KG38: Pendapatan Jasa Giro | KH38: Pendapatan Lain-Lain | KI38: Pendapatan Selisih Lebih Kurs | KJ38: Pendapatan Aval | KK38: Pendapatan Selisih Koma | KL38: Pendapatan Klaim | KM38: Pendapatan Jasa Maklon | KN38: Jumlah Pendapatan | KP38: BEBAN DILUAR USAHA | KQ38: Beban Adm Bank | KR38: Beban Marjin Pinjaman | KT38: Beban Administrasi Kredit - Mk | KU38: Beban Pengikatan Kredit | KV38: Beban Selisih Kurang Kurs | KW38: Beban Selisih Koma | KX38: Beban Market Place | KY38: Beban Lain-Lain | KZ38: Beban Zakat | LA38: Beban Infak | LB38: Beban Qurban | LC38: Beban Administrasi Kredit - LC/SKBDN | LD38: Beban Kerugian Penjualan Aset | LE38: Jumlah Beban Diluar Usaha | LG38: PAJAK PENGHASILAN | LH38: Beban Pajak Penghasilan | LI38: Jumlah Pajak Penghasilan | LJ38: Jumlah Beban
A39: January | B39: 1.6282247e+10 | C39: 1.0974216e+10 | D39: =B39-C39 -> 5308031773 | F39: 2.4710073e+09 | G39: 326990352 | H39: 104094850 | I39: =SUM(F39:H39) -> 2902092549 | J39: =D39-I39 -> 2405939224 | L39: 4.3551312e+08 | M39: 969651540 | N39: =L39-M39 -> -5.3413842e+08 | P39: =J39+N39 -> 1871800799 | T39: =P39-S39 -> 1871800799 | X39: =T39+W39 -> 1871800799 | AD39: 6934687663 | AE39: 24209033718 | AG39: -325897486 | AH39: 12907665333 | AI39: 64943539712 | AJ39: - | AL39: 15044199720 | AM39: 8452262420 | AN39: 132165491081 | AP39: - | AQ39: 118879140171 | AR39: 5795752389 | AU39: 1712002768 | AV39: 126386895329 | AW39: 258552386409 | BA39: 9703929204 | BC39: - | BD39: - | BE39: 3864906863 | BF39: 254960082 | BI39: 140564848 | BJ39: - | BK39: 116342758486 | BL39: 130307119483 | BN39: 7176083875 | BO39: 9929000 | BQ39: 7167318810 | BR39: - | BS39: 14353331685 | BT39: 144660451168 | BV39: 68245000000 | BW39: - | BX39: 1871800799 | BY39: 41337870802 | BZ39: -541805960 | CA39: - | CB39: 2979069600 | CC39: 113891935241 | CD39: 258552386409 | CF39: January | DQ39: January | DR39: 15971412502 | DS39: 16282305719 | DV39: 32253718221 | DZ39: 22664413951 | EA39: 164975000 | EB39: 5763600 | EE39: 189652120 | EF39: 29560887 | EG39: 6717372 | EH39: 6097054 | EI39: 940880 | EK39: 1011534 | EL39: 55613299 | EM39: 37058114 | EO39: 24000000 | EP39: -30 | ER39: 297725303 | ES39: 47315000 | ET39: 969196548 | EV39: 5422385 | EW39: 1500000 | EX39: 10530208 | EY39: 61856522 | EZ39: 143794547 | FA39: 22565985 | FC39: 146749818 | FD39: 11746599 | FF39: 1595018 | FG39: 28884764 | FI39: 5730000 | FJ39: 22642205 | FL39: 15911592 | FM39: 13465864 | FO39: 10752240 | FQ39: 15552523 | FR39: 12680000 | FV39: 9629500 | FW39: 15865007 | FZ39: 199970591 | GA39: 37135374 | GB39: 1351165 | GC39: 7539453 | GM39: 25302911992 | GQ39: 37481629 | GR39: 61201130 | GS39: 5724889 | GT39: 22827286 | GU39: 83296100 | GV39: 37660387 | GW39: 12183609 | GX39: 206127195 | GY39: 310801650 | GZ39: 362956973 | HC39: 36768081 | HG39: 35844110 | HH39: 49550351 | HJ39: 72851923 | HK39: 2959000 | HN39: 4145328 | HO39: 33283513 | HP39: 3958110 | HQ39: 57741363 | HR39: 5783000 | HS39: 600000 | HT39: 90389191 | HU39: 7069000 | HX39: 18335700 | HY39: 6532245 | HZ39: 4005474 | IA39: 8733300 | IB39: 3306696 | IC39: 12944177 | ID39: 16875512 | IE39: 12348714 | IF39: 5102461 | IG39: 15850399 | IH39: 2000000 | IK39: 7048400 | IL39: 208000 | IM39: 4194409 | IS39: 17601288 | IU39: 39767608 | JB39: 113559100 | JD39: 599250 | JE39: 51989503 | JH39: 8435833 | JI39: 11454629 | JK39: 32250000 | JM39: 554834189 | JN39: 34327610 | JO39: 245268 | JT39: 2523753583 | JW39: 304990352 | JX39: 22000000 | JZ39: 326990352 | KC39: 104094850 | KD39: 104094850 | KG39: 8189215 | KH39: 346167688 | KI39: 138211239 | KJ39: 1070500 | KK39: 720 | KN39: 493639362 | KQ39: 4982001000000 | KR39: 924627033 | KT39: 40041667 | KV39: 58126246 | KW39: 839 | LE39: 1.0277778e+15 | LJ39: =LE39+KD39+JZ39+JT39 -> 1.02778e+15
A40: February | B40: 4.5860255e+10 | C40: 3.3662331e+10 | D40: =B40-C40 -> 12197923967 | F40: 5.4845136e+09 | G40: 8.6142236e+08 | H40: 2.0965518e+08 | I40: =SUM(F40:H40) -> 6555591106 | J40: =D40-I40 -> 5642332860 | L40: 5.846629e+08 | M40: 2.2841221e+09 | N40: =L40-M40 -> -1699459238 | P40: =J40+N40 -> 3942873622 | T40: =P40-S40 -> 3942873622 | X40: =T40+W40 -> 3942873622 | AD40: 9785549424 | AE40: 39558334589 | AG40: -325897486 | AH40: 12292281333 | AI40: 68804860251 | AJ40: - | AL40: 12784452818 | AM40: 10071964680 | AN40: 152971545608 | AP40: - | AQ40: 119227963801 | AR40: 5790026052 | AU40: 1712002768 | AV40: 126729992622 | AW40: 279701538230 | BA40: 15636527900 | BC40: - | BD40: - | BE40: 4753827521 | BF40: 386816837 | BI40: 204103852 | BJ40: - | BK40: 128408920871 | BL40: 149390196980 | BN40: 7176083875 | BO40: 4930500 | BQ40: 7167318810 | BR40: - | BS40: 14348333185 | BT40: 163738530165 | BV40: 68245000000 | BW40: - | BX40: 3942873622 | BY40: 41337870802 | BZ40: -541805960 | CA40: - | CB40: 2979069600 | CC40: 115963008065 | CD40: 279701538230 | CF40: February | DQ40: February | DR40: 3442714095 | DS40: 29434220598 | DT40: -418018 | DV40: 65130234896 | DZ40: 44017225952 | EA40: 330702000 | EB40: 5763600 | EC40: -100000 | EE40: 380705282 | EF40: 41321330 | EG40: 11079209 | EH40: 10793737 | EI40: 1509270 | EJ40: 4833885 | EK40: 3434616 | EL40: 91160049 | EM40: 74104769 | EO40: 30448000 | EP40: -14669659 | ER40: 523134040 | ES40: 117985000 | ET40: 1640223686 | EV40: 5804243 | EW40: 3480005 | EX40: 16472712 | EY40: 129575720 | EZ40: 448907623 | FA40: 22805985 | FC40: 313446594 | FD40: 25050001 | FF40: 4849339 | FG40: 55302766 | FI40: 24502000 | FJ40: 38667305 | FL40: 15911592 | FM40: 13465864 | FO40: 29381290 | FQ40: 23540163 | FR40: 87778000 | FV40: 35265250 | FW40: 128662683 | FZ40: 200693778 | GA40: 43745346 | GB40: 14084123 | GC40: 10180508 | GD40: 1131714 | GM40: 48962359372 | GQ40: 15827500 | GR40: 122402260 | GS40: 14727775 | GT40: 44896235 | GU40: 166653658 | GV40: 78419170 | GW40: 24367219 | GX40: 412254390 | GY40: 624144697 | GZ40: 778016714 | HC40: 91142945 | HG40: 71858306 | HH40: 97512259 | HI40: 709000 | HJ40: 172972972 | HK40: 3866789 | HN40: 8290656 | HO40: 52252513 | HP40: 25589797 | HQ40: 344399172 | HR40: 5783000 | HS40: 53141050 | HT40: 161450049 | HU40: 18569000 | HV40: 40661254 | HW40: 92500000 | HX40: 18335700 | HY40: 15814351 | HZ40: 5653091 | IA40: 14563100 | IB40: 4504496 | IC40: 15431677 | ID40: 25357012 | IE40: 22920051 | IF40: 9625377 | IG40: 32112243 | IH40: 2000000 | IK40: 28179734 | IL40: 393460 | IM40: 132201512 | IO40: 1553360 | IS40: 17601288 | IU40: 79535216 | JB40: 157359100 | JD40: 1467455 | JE40: 52520803 | JH40: 17337477 | JI40: 11454629 | JK40: 32250000 | JL40: 38102760 | JM40: 1131295856 | JN40: 55073594 | JO40: 86888598 | JP40: 8459325 | JQ40: 2640250 | JT40: 5543039895 | JW40: 703322361 | JX40: 39000000 | JY40: 104100000 | JZ40: 846422361 | KC40: 209655185 | KD40: 209655185000000 | KG40: 10709247 | KH40: 358327210 | KI40: 500581036000000 | KJ40: 1070500 | KK40: 2798 | KN40: 870690791 | KQ40: 11202854 | KR40: 1.9397888e+09 | KT40: 80083334 | KV40: 286027888000000 | KW40: 3047106 | KZ40: 250000000 | LE40: 2570150029 | LH40: - | LI40: - | LJ40: =LE40+KD40+JZ40+JT40 -> 209664144612285
A41: March | B41: 8.3574841e+10 | C41: 6.3731126e+10 | D41: =B41-C41 -> 19843715079 | F41: 9.7710484e+09 | G41: 1.4179768e+09 | H41: 2.1373568e+08 | I41: =SUM(F41:H41) -> 11402760847 | J41: =D41-I41 -> 8440954232 | L41: 6.9836014e+08 | M41: 4.5260982e+09 | N41: =L41-M41 -> -3827738039 | P41: =J41+N41 -> 4613216192 | T41: =P41-S41 -> 4613216192 | X41: =T41+W41 -> 4613216192 | AD41: 10221166633 | AE41: 58777932663 | AG41: -325897486 | AH41: 12280196933 | AI41: 71302330279 | AJ41: - | AL41: 9258511443 | AM41: 10896944511 | AN41: 172411184975 | AP41: - | AQ41: 119191066037 | AR41: 5761940798 | AU41: 1712002768 | AV41: 126665009603 | AW41: 299076194578 | BA41: 17980333258 | BC41: - | BD41: - | BE41: 5079821953 | BF41: 2378666837 | BI41: 199464411 | BJ41: - | BK41: 142461154801 | BL41: 168099441259 | BN41: 7176083875 | BO41: - | BP41: - | BQ41: 7167318810 | BR41: - | BS41: 14343402685 | BT41: 182442843944 | BV41: 68245000000 | BW41: - | BX41: 4613216192 | BY41: 41337870802 | BZ41: -541805960 | CA41: - | CB41: 2979069600 | CC41: 116633350635 | CD41: 299076194579 | CF41: March | DQ41: March | DR41: -744921559 | DS41: 37719863154 | DT41: -4405405 | DU41: -875000 | DV41: 102099896086 | DZ41: 70336643267 | EA41: 740961000 | EB41: 67370000 | EC41: -100000 | EE41: 570486803 | EF41: 46819736 | EG41: 11938781 | EH41: 17423244 | EI41: 1667770 | EJ41: 4975077 | EK41: 4432045 | EL41: 135711726 | EM41: 110044997 | EO41: 81658000 | EP41: -73594924 | ER41: 869831731 | ES41: 392708250 | ET41: 2863036816 | EV41: 8502685 | EW41: 1500000 | EX41: 26552116 | EY41: 199660602 | EZ41: 601231797 | FA41: 23415117 | FC41: 464716871 | FD41: 38970619 | FF41: 13633783 | FG41: 66562322 | FI41: 43362000 | FJ41: 82518960 | FL41: 119319720 | FM41: 78274951 | FO41: 42839490 | FQ41: 17046366 | FR41: 143201202 | FV41: 59943325 | FW41: 177512047 | FZ41: 219484248 | GA41: 124453916 | GB41: 24168754 | GC41: 11849567 | GD41: 1131714 | GE41: 1644286 | GM41: 78773510777 | GQ41: 19157300 | GR41: 183603390 | GS41: 28334109 | GT41: 63848531 | GU41: 252599757 | GV41: 120197153 | GW41: 36550828 | GX41: 618794085 | GY41: 936217044 | GZ41: 1222426068 | HC41: 122992794 | HF41: 1610924588 | HG41: 99515911 | HH41: 142019606 | HI41: 759000 | HJ41: 256844265 | HK41: 4651364 | HL41: 775000 | HN41: 12435984 | HO41: 81093411 | HP41: 33608591 | HQ41: 470476695 | HR41: 25965964 | HS41: 55348050 | HT41: 259678607 | HU41: 15194750 | HV41: 40661254 | HW41: 92500000 | HX41: 23520500 | HY41: 25418916 | HZ41: 9422077 | IA41: 24520200 | IB41: 7808593 | IC41: 49962102 | ID41: 34758487 | IE41: 58755910 | IF41: 13492149 | IG41: 68117111 | IH41: 2553222 | IK41: 28621401 | IL41: 1267119 | IM41: 272999845 | IO41: 1553360 | IS41: 17601288 | IU41: 119302824 | JB41: 226967104 | JD41: 2392309 | JE41: 52520803 | JH41: 26239121 | JI41: 11454629 | JK41: 32250000 | JL41: 40989133 | JM41: 1.6671018e+15 | JN41: 94770717 | JO41: 87093852 | JP41: 20145705 | JQ41: 2694250 | JT41: 9831468664 | JW41: 1239538405 | JX41: 56000000 | JY41: 107438400 | JZ41: 1402976805 | KC41: 213735685000000 | KD41: 213735685 | KG41: 16114203 | KH41: 418473282 | KI41: 1043435424 | KJ41: 1070500 | KK41: 10955 | KN41: 1.4791044e+15 | KQ41: 21279003 | KR41: 3.1316225e+09 | KT41: 120125001 | KV41: 780744228 | KW41: 3071661 | KZ41: 1250000000 | LE41: 5306842403 | LH41: - | LI41: - | LJ41: =LE41+KD41+JZ41+JT41 -> 16755023557
A42: April | B42: 1.2587769e+11 | C42: 9.6832857e+10 | D42: =B42-C42 -> 29044834211 | F42: 1.301012e+10 | G42: 2.895428e+09 | H42: 1.6436498e+08 | I42: =SUM(F42:H42) -> 16069912727 | J42: =D42-I42 -> 12974921484 | L42: 9.1833482e+08 | M42: 6.8166209e+09 | N42: =L42-M42 -> -5898286130 | P42: =J42+N42 -> 7076635355 | T42: =P42-S42 -> 7076635355 | X42: =T42+W42 -> 7076635355 | AD42: 19477375518 | AE42: 60727478059 | AG42: -325897486 | AH42: 11521446933 | AI42: 63917210875 | AJ42: - | AL42: 7770366313 | AM42: 11564054446 | AN42: 174652034659 | AP42: - | AQ42: 119498475695 | AR42: 6104040045 | AU42: 1712002768 | AV42: 127314518508 | AW42: 301966553166 | BA42: 14868241050 | BC42: - | BD42: - | BE42: 6123642432 | BF42: 1073124107 | BI42: 158720135 | BJ42: - | BK42: 146302652962 | BL42: 168526380686 | BN42: 7176083875 | BO42: - | BP42: - | BQ42: 7167318810 | BR42: - | BS42: 14343402685 | BT42: 182869783371 | BV42: 68245000000 | BW42: - | BX42: 7076635355 | BY42: 41337870802 | BZ42: -541805960 | CA42: - | CB42: 2979069600 | CC42: 119096769797 | CD42: 301966553168 | CF42: April | DQ42: April | DR42: 15638749052 | DS42: 125756812283 | DT42: -53016135 | DU42: -875000 | DV42: 141341670200 | DZ42: 100524082026 | EA42: 917094000 | EB42: 110385600 | EC42: -100000 | ED42: - | EE42: 763685569 | EF42: 49748371 | EG42: 12826946 | EH42: 22193112 | EI42: 2340739 | EJ42: 5151347 | EK42: 6390092 | EL42: 209852014 | EM42: 144895509 | EN42: - | EO42: 201658000 | EP42: -67892830 | ER42: 1263104741 | ES42: 404358250 | ET42: 4861857032 | EV42: 14763000 | EW42: 1500000 | EX42: 32477086 | EY42: 268854406 | EZ42: 598050950 | FA42: 23981711 | FB42: - | FC42: 598474015 | FD42: 55008189 | FE42: - | FF42: 14554112 | FG42: 74009753 | FH42: - | FI42: 52662000 | FJ42: 98890445 | FK42: - | FL42: 136420466 | FM42: 93289611 | FN42: - | FO42: 63673690 | FP42: - | FQ42: 7023543 | FR42: 291065439 | FS42: - | FT42: - | FU42: - | FV42: 85975575 | FW42: 187287661 | FY42: - | FZ42: 254037688 | GA42: 155382667 | GB42: 38794083 | GC42: 11939546 | GD42: 1131714 | GE42: 25936063 | GH42: 13161280 | GM42: 109864522615 | GP42: - | GQ42: 20957300 | GR42: 244804520 | GS42: 30118238 | GT42: 80971431 | GU42: 338545857 | GV42: 160020702 | GW42: 76734438 | GX42: 825333780 | GY42: 1248289391 | GZ42: 1605899270 | HA42: - | HB42: - | HC42: 153889177 | HD42: - | HE42: - | HF42: 1610924588 | HG42: 128230818 | HH42: 157223846 | HI42: 969000 | HJ42: 323661768 | HK42: 41961792 | HL42: 775000 | HM42: - | HN42: 16581312 | HO42: 92325411 | HP42: 22702341 | HQ42: 522134718 | HR42: 25965964 | HS42: 55348050 | HT42: 261459557 | HU42: 18794750 | HV42: 44161254 | HW42: 92500000 | HX42: 38744625 | HY42: 33301421 | HZ42: 11558839 | IA42: 26263000 | IB42: 7831093000000 | IC42: 50111102 | ID42: 44890693 | IE42: 67928928 | IF42: 20754308 | IG42: 78001411 | IH42: 2553222 | II42: - | IJ42: - | IK42: 29063068 | IL42: 2071459000000 | IM42: 537497661 | IO42: 1553360 | IP42: - | IQ42: - | IR42: - | IS42: 17601288000000 | IT42: - | IU42: 159070432 | IV42: 736370000 | IW42: - | IX42: - | IY42: - | IZ42: - | JB42: 255167104 | JC42: - | JD42: 2392309 | JE42: 52520803 | JF42: - | JG42: - | JH42: 35140766 | JI42: 11454629 | JJ42: - | JK42: 32250000 | JL42: 40989133 | JM42: 2245881257 | JN42: 152824955 | JO42: 87093852 | JP42: 48776705 | JQ42: 2694250 | JT42: 13033635946 | JW42: 2696062520 | JX42: 80500000 | JY42: 118865466 | JZ42: 2895427986 | KC42: 164364985 | KD42: 164364985 | KG42: 21368625 | KH42: 474516782 | KI42: 421367207 | KJ42: 1070500 | KK42: 11705 | KM42: - | KN42: 918334820 | KQ42: 28057573 | KR42: 4.2524053e+09 | KT42: 918080249 | KU42: 365000000 | KV42: 1 | KW42: 3077807 | KY42: - | KZ42: 1250000000 | LA42: - | LB42: - | LD42: - | LE42: 6816620950 | LH42: - | LI42: - | LJ42: =LE42+KD42+JZ42+JT42 -> 22910049867
A43: May | B43: 148180899711 | C43: 112589116820 | D43: =B43-C43 -> 35591782891 | F43: 15164239255 | G43: 3260766640 | H43: 165293485 | I43: =SUM(F43:H43) -> 18590299380 | J43: =D43-I43 -> 17001483511 | L43: 945811943 | M43: 7741363917 | N43: =L43-M43 -> -6795551974 | P43: =J43+N43 -> 10205931537 | T43: 10205931537 | X43: =T43+W43 -> 10205931537 | AD43: 19423223388 | AE43: 61362306890 | AG43: -325897486 | AH43: 11588047624 | AI43: 70540866861 | AJ43: - | AL43: 8534900838 | AM43: 10742030687 | AN43: 181865478802 | AP43: - | AQ43: 120328488134 | AR43: 6809870225 | AU43: 1712002768 | AV43: 128850361127 | AW43: 310715839929 | BA43: 12598586360 | BC43: - | BD43: - | BE43: 4972814559 | BF43: 984652107 | BI43: 204443115 | BJ43: - | BK43: 155898147874 | BL43: 174658644015 | BN43: 7176083875 | BQ43: 6655046060 | BR43: - | BS43: 13831129935 | BT43: 188489773950 | BV43: 68245000000 | BW43: - | BX43: 10205931537 | BY43: 41337870802 | BZ43: -541805960 | CA43: - | CB43: 2979069600 | CC43: 122226065980 | CD43: 310715839929 | CF43: May | DQ43: May | DT43: -87982550 | DU43: -875000 | DV43: 167581582692 | DZ43: 110554492375 | EA43: 917094000 | EB43: 140612800 | EC43: -100000 | EE43: 9.5442764e+08 | EF43: 54311266 | EG43: 15014133 | EH43: 37577774 | EI43: 2340738.6 | EJ43: 8466705 | EK43: 11542232 | EL43: 2.4648325e+08 | EM43: 1.7972561e+08 | EO43: 237968000 | EP43: -58879865 | ER43: 1572214332 | ES43: 4.8754588e+08 | ET43: 5.9992234e+09 | EV43: 19470172 | EW43: 1500000.1 | EX43: 37013438 | EY43: 339190348 | EZ43: 748279827 | FA43: 30540331 | FC43: 730472985 | FD43: 69997044 | FF43: 19729912 | FG43: 76010744 | FI43: 83322000 | FJ43: 121504695 | FL43: 2.4251212e+08 | FM43: 1.8199963e+08 | FO43: 76814990 | FQ43: 7586375.9 | FR43: 417443047 | FV43: 110337775 | FW43: 2.0469772e+08 | FZ43: 69475188 | GA43: 2.1592893e+08 | GB43: 53874226 | GC43: 12217654 | GD43: 1131714 | GE43: 35626223 | GH43: 29077510 | GM43: 1.2529581e+11 | GQ43: 20957300 | GR43: 306588551 | KR43: 5.5014886e+09 | LJ43: =LE43+KD43+JZ43+JT43 -> 0
A44: June | B44: 1.7906721e+11 | C44: 1.4045875e+11 | D44: =B44-C44 -> 38608458150 | F44: 1.7912191e+10 | G44: 3.6850435e+09 | H44: 3.2762448e+08 | I44: =SUM(F44:H44) -> 21924859321 | J44: =D44-I44 -> 16683598829 | L44: 970597634 | M44: 9.2960583e+09 | N44: =L44-M44 -> -8325460705 | P44: =J44+N44 -> 8358138123 | T44: =P44-S44 -> 8358138123 | X44: =T44+W44 -> 8358138123 | AD44: 2.5086546e+10 | AE44: 66835123552 | AG44: -3.2589749e+08 | AH44: 1.1610544e+10 | AI44: 6.2808234e+10 | AJ44: - | AL44: 1.1052996e+10 | AM44: 8.6935457e+09 | AN44: 1.8576109e+11 | AP44: 0 | AQ44: 1.2104969e+11 | AR44: 6.9234279e+09 | AU44: 1712002768 | AV44: 1.2968512e+11 | AW44: 3.1544622e+11 | BA44: 1.0788683e+10 | BC44: 0 | BD44: 0 | BE44: 4.2136819e+09 | BF44: 8.93169e+08 | BI44: 216279034 | BJ44: 0 | BK44: 1.6524248e+11 | BL44: 1.8135429e+11 | BN44: 7176083875 | BQ44: 6537565029 | BR44: 0 | BS44: 13713648904 | BT44: 1.9506794e+11 | BV44: 68245000000 | BW44: 0 | BX44: 8.3581381e+09 | BY44: 4.1337871e+10 | BZ44: -5.4180596e+08 | CA44: 0 | CB44: 2979069600 | CC44: 1.2037827e+11 | CD44: 3.1544622e+11 | CF44: June | DQ44: June | DT44: -1.5870693e+08 | DU44: -875000 | DV44: 1.9153445e+11 | DZ44: 1.347398e+11 | EA44: 917094000 | EB44: 232100600 | EC44: -100000 | EE44: 1.1635591e+09 | EF44: 55847640 | EG44: 19397573 | EH44: 41713128 | EI44: 2401686.9 | EJ44: 8859257 | EK44: 11995150 | EL44: 2.991362e+08 | EM44: 2.1314112e+08 | EO44: 321068000 | EP44: 2.5686954e+08 | ER44: 1858430137 | ES44: 5.2224588e+08 | ET44: 7.4318011e+09 | EV44: 21196422 | EW44: 1500000.1 | EX44: 43227920 | EY44: 412710005 | EZ44: 903205291 | FA44: 31486050 | FC44: 897490884 | FD44: 86110703 | FF44: 21418314 | FG44: 80566905 | FI44: 95402000 | FJ44: 145224115 | FL44: 2.9739394e+08 | FM44: 2.2487586e+08 | FO44: 103087690 | FQ44: 20581132 | FR44: 530488172 | FV44: 114235925 | FW44: 2.5502787e+08 | FZ44: 92317938 | GA44: 2.5029608e+08 | GB44: 60463086 | GC44: 15871076 | GD44: 1131714.3 | GE44: 77510551 | GH44: 41382672 | GM44: 152919559993 | GP44: 20957300 | GQ44: 367789686 | GS44: 36206149 | GT44: 105995231 | GU44: 5.0731045e+08 | GV44: 2.3875866e+08 | GW44: 1.2001079e+08 | GX44: 1.2351429e+09 | GY44: 1872434085 | GZ44: 2481620632 | HC44: 216418132 | HF44: 1610924588 | HG44: 185290190 | HH44: 314394600 | HI44: 1424000 | HJ44: 408140272 | HK44: 42831792 | HL44: 1125000 | HN44: 16581312 | HO44: 133002330 | HP44: 40768251 | HQ44: 863847918 | HR44: 34355764 | HS44: 118567750 | HT44: 376885678 | HU44: 76694750 | HV44: 44161254 | HW44: 92500000 | HX44: 431654975 | HY44: 41121991 | HZ44: 26910620 | IA44: 41562200 | IB44: 8406458 | IC44: 52426622 | ID44: 60503109 | IE44: 99917562 | IF44: 31625098 | IG44: 82999184 | IH44: 3053222 | IK44: 32546403 | IL44: 10384927 | IM44: 790422279 | IO44: 25499724 | IS44: 24852366 | IU44: 238605648 | IX44: 18000000 | JB44: 425667104 | JD44: 2392309 | JE44: 52520803 | JH44: 52944054 | JI44: 11454629 | JK44: 32250000 | JL44: 40989133 | JM44: 3305897700 | JN44: 237600982 | JO44: 88563852 | JP44: 101170028 | JQ44: 5108761 | JT44: 17941191239 | JW44: 3.3159495e+09 | JX44: 123735000 | JY44: 245359087 | JZ44: 3.6850435e+09 | KC44: 3.2762448e+08 | KD44: 3.2762448e+08 | KG44: 38769273 | KH44: 509359502 | KI44: 2.6090543e+09 | KJ44: 1070500 | KK44: 31151.85 | KN44: 3.1582847e+09 | KQ44: 41065421 | KR44: 6.8731471e+09 | KT44: 440895111 | KV44: 2.7190976e+09 | KW44: 3084599.2 | KZ44: 1250000000 | LB44: 154400000 | LC44: 2055546.4 | LE44: 1.4642061e+10 | LH44: - | LI44: - | LJ44: =LE44+KD44+JZ44+JT44 -> 36595920590
A45: July | B45: 205703910143 | C45: 159437200710 | D45: 46266709433 | F45: 21836035047 | G45: 4753631259 | H45: 450453819 | I45: 27040120125 | J45: 19226589307 | L45: 1138639499 | M45: 11290004427 | N45: -10151364928 | P45: 9075224380 | T45: 9075224380 | X45: 9075224380 | AD45: 2.6938625e+10 | AE45: 5.7829806e+10 | AG45: -3.2589749e+08 | AH45: 12160161889 | AI45: 7.3733007e+10 | AJ45: - | AL45: 33055660368 | AM45: 10264338467 | AN45: 213655702013 | AP45: - | AQ45: 123556282777 | AR45: 6892407759 | AU45: 1712002768 | AV45: 132160693304 | AW45: 345816395318 | BA45: 15825657130 | BC45: - | BD45: - | BE45: 4145159320 | BF45: 1098160751 | BI45: 219978025 | BJ45: - | BK45: 189797864493 | BL45: 211086819720 | BN45: 7176083875 | BP45: - | BQ45: 6458132901 | BR45: - | BS45: 13634216776 | BT45: 224721036496 | BV45: 68245000000 | BW45: - | BX45: 9075224380 | BY45: 41337870802 | BZ45: -541805960 | CA45: - | CB45: 2979069600 | CC45: 1.2109536e+11 | CD45: 3.458164e+11 | CF45: July | DQ45: July | DR45: 17412574075 | DS45: 2.0589891e+11 | DT45: -2.24622e+08 | DU45: -875000 | DV45: 223085988235 | DZ45: 166073071216 | EA45: 919103000 | EB45: 340420384 | EC45: -100000 | EE45: 1372786610 | EF45: 60783669 | EG45: 20814440 | EH45: 54346081 | EI45: 7802895 | EJ45: 11997530 | EK45: 13657579 | EL45: 360133870 | EM45: 246664769 | EO45: 382768000 | EP45: 270200130 | ER45: 2167207153 | ES45: 563581876 | ET45: 8912818063 | EV45: 37076714 | EW45: 1500000 | EX45: 128782866 | EY45: 487735853 | EZ45: 1055658327 | FA45: 34123946 | FC45: 1052934489 | FD45: 98979101 | FF45: 33978461 | FG45: 82705696 | FI45: 107402000 | FJ45: 187868065 | FL45: 350843648 | FM45: 268260916 | FO45: 112338940 | FQ45: 8316644 | FR45: 601246247 | FV45: 129455675 | FW45: 405184440 | FX45: 52035000 | FZ45: 113746287 | GA45: 293119554 | GB45: 69556091 | GC45: 16226456 | GD45: 1131714 | GE45: 141408284 | GH45: 51794826 | GM45: 176812907952 | GQ45: 816701388 | GR45: 424470747 | GS45: 41928341 | GT45: 155573936 | GU45: 590128948 | GV45: 279619524 | GW45: 142129291 | GX45: 1441270918 | GY45: 2184506432 | GZ45: 2926934967 | HC45: 229364305 | HF45: 1610924588 | HG45: 214503601 | HH45: 379075269 | HI45: 4858821 | HJ45: 482949184 | HK45: 43211792 | HL45: 1725000 | HN45: 16581312 | HO45: 180085043 | HP45: 57144021 | HQ45: 1020015414 | HR45: 52955819 | HS45: 120587750 | HT45: 435716535 | HU45: 142069750 | HV45: 118680904 | HW45: 185000000 | HX45: 431654975 | HY45: 71029277 | HZ45: 35712987 | IA45: 49954678 | IB45: 14098258 | IC45: 74507336 | ID45: 85613709 | IE45: 117619373 | IF45: 36165845 | IG45: 145887972 | IH45: 8203832 | IK45: 34696403 | IL45: 12454789 | IM45: 871066499 | IO45: 25499724 | IP45: 74000000 | IS45: 24852366 | IT45: 58783784 | IU45: 278373256 | IX45: 67650000 | JB45: 503167104 | JD45: 3992309 | JE45: 58006503 | JH45: 61845698 | JI45: 11454629 | JK45: 32250000 | JL45: 40989133 | JM45: 3840249896 | JN45: 272100914 | JO45: 118123362 | JP45: 101170028 | JQ45: 5146761 | JT45: 21865035000 | JW45: 4275290650 | JX45: 145735000 | JY45: 332605609 | JZ45: 4753631259 | KC45: 450453819 | KD45: 450453819 | KG45: 49366996 | KH45: 526359502 | KI45: 10404841 | KJ45: 1070500 | KK45: 33113 | KL45: 19994031 | KN45: 607228983 | KQ45: 49459480 | KR45: 8.3951251e+09 | KT45: 440895111 | KW45: 3089445 | KZ45: 1700000000 | LB45: 167969190 | LC45: 2055546 | LE45: 10758593911 | LH45: - | LI45: - | LJ45: =LE45+KD45+JZ45+JT45 -> 37827713989
A46: August | B46: 267029890830 | C46: 208275379546 | D46: 58754511284 | F46: 25270272652 | G46: 5872187152 | H46: 593381999 | I46: 31735841803 | J46: 27018669481 | L46: 1263627517 | M46: 13396348576 | N46: -12132721059 | P46: 14885948422 | T46: 14885948422 | X46: 14885948422 | AD46: 29892210244 | AJ46: - | AU46: 1712002768 | CF46: August | DQ46: August | DT46: -229225150 | DU46: -875000 | DV46: 277910905262 | DZ46: 193941527069 | EA46: 1236599000 | EB46: 446362304 | EC46: -100000 | EE46: 1583444601 | EF46: 69236010 | EG46: 40952921 | EH46: 54829758 | EI46: 8879462 | EJ46: 12439259 | EK46: 20979527 | EL46: 444935060 | EM46: 279583156 | EO46: 465868000 | EP46: 307581385 | ER46: 2532556684 | ES46: 625194676 | ET46: 10023431182 | EV46: 99890029 | EW46: 1500000 | EX46: 137619868 | EY46: 566232743 | EZ46: 1209636091 | FA46: 34549017 | FC46: 1283329544 | FD46: 113446352 | FF46: 36756261 | FG46: 85636977 | FI46: 131412000 | FJ46: 231975090 | FL46: 383878938 | FM46: 308667446 | FO46: 135526615 | FQ46: 41853270 | FR46: 646700247 | FV46: 134608675 | FW46: 497415691 | FX46: 91035000 | FZ46: 138463275 | GA46: 422115961 | GB46: 81963960 | GC46: 21874167 | GD46: 2891714 | GE46: 186506879 | GH46: 63517123 | GM46: 219150612186 | GQ46: 1303161906 | GR46: 481151808 | GS46: 52723121 | GT46: 191928421 | GU46: 672947444 | GV46: 321354630 | GW46: 164247792 | GX46: 1647398907 | GY46: 2496578779 | GZ46: 3380502761 | HC46: 258722822 | HF46: 1610924588 | HG46: 245038691 | HH46: 444681864 | HI46: 9070621 | HJ46: 542985440 | HK46: 45279792 | HL46: 1725000 | HN46: 16581312 | HO46: 227485754 | HP46: 64296471 | HQ46: 1186484703 | HR46: 59715864 | HS46: 133222250 | HT46: 512723907 | HU46: 195894750 | HV46: 128563904 | HW46: 185000000 | HX46: 431654975 | HY46: 79955447 | HZ46: 45658606 | IA46: 52832031 | IB46: 15985658 | IC46: 99674367 | ID46: 102429663 | IE46: 128477100 | IF46: 40774117 | IG46: 161979472 | IH46: 13454634 | IK46: 35013070 | IL46: 29248591 | IM46: 975508925 | IO46: 37945878 | IP46: 187774079 | IS46: 24852366 | IT46: 117342343 | IU46: 318140864 | IX46: 67850000 | JB46: 559467104 | JD46: 3992309 | JE46: 58006503 | JF46: 1695327 | JH46: 70747342 | JI46: 11454629 | JK46: 32250000 | JL46: 40989133 | JM46: 4382316146 | JN46: 307011601 | JO46: 119376475 | JP46: 159623788 | JQ46: 5396761 | JT46: 25299272605 | JW46: 5321107590 | JX46: 162735000 | JY46: 388344562 | JZ46: 5872187152 | KC46: 593381999 | KD46: 593381999 | KG46: 61126386 | KH46: 543360202 | KI46: 3549474412 | KJ46: 1070500 | KK46: 34691 | KL46: 49103781 | KN46: 4204169972 | KQ46: 57786010 | KR46: 1.019806e+10 | KT46: 735976187 | KV46: 3471952972 | KW46: 3090756 | KZ46: 1700000000 | LB46: 167969190 | LC46: 2055546 | LE46: 16336891031 | LH46: - | LI46: - | LJ46: =LE46+KD46+JZ46+JT46 -> 48101732787
A47: September | B47: 311914729969 | C47: 247065741443 | D47: 64848988526 | F47: 29228621765 | G47: 6393287929 | H47: 677713099 | I47: 36299622793 | J47: 28549365733 | L47: 1585798464 | M47: 15584844810 | N47: -13999046346 | P47: 14550319387 | Q47: 0 | S47: 0 | T47: 14550319387 | X47: 14550319387 | AD47: 9260523364 | AE47: 108235307430 | AG47: -325897486 | AH47: 12513931889 | AI47: 72678939342 | AJ47: - | AL47: 17478731307 | AM47: 12208543201 | AN47: 232050079047 | AQ47: 124901778938 | AR47: 6830367469 | AU47: 1712002768 | AV47: 145433198911 | AW47: 365494228221 | BA47: 24591271235 | BE47: 5601444248 | BF47: 906419751 | BI47: 153423760 | BK47: 194502473897 | BL47: 225755032891 | BN47: 7176083875 | BQ47: 5992657627 | BS47: 13168741502 | BT47: 238923774393 | BV47: 68245000000 | BX47: 14550319387 | BY47: 41337870802 | BZ47: -541805960 | CB47: 2979069600 | CC47: 126570453829 | CD47: 365494228222 | CF47: September | DQ47: September | DT47: -237237672 | DU47: -875000 | DV47: 322498145375 | DZ47: 229747480909 | EA47: 1236599000 | EB47: 446362304 | EC47: -100000 | EE47: 1794667398 | EF47: 73611112 | EG47: 44991652 | EH47: 55666735 | EI47: 12135888 | EJ47: 14774524 | EK47: 40601888 | EL47: 464699884 | EM47: 313058877 | EO47: 506168000 | EP47: 284052767 | ER47: 2876563724 | ES47: 803383901 | ET47: 10496962176 | EV47: 131614273 | EW47: 1500000 | EX47: 145246865 | EY47: 646271250 | EZ47: 1363575439 | FA47: 35103098 | FC47: 1483066135 | FD47: 128660981 | FF47: 41843261 | FG47: 89000651 | FI47: 155553500 | FJ47: 298058240 | FL47: 499347703 | FM47: 389760569 | FO47: 165348065 | FQ47: 51168301 | FR47: 851232747 | FV47: 253608425 | FW47: 520291092 | FX47: 117035000 | FZ47: 147757275 | GA47: 481570853 | GB47: 87750322 | GC47: 30987970 | GD47: 2891714 | GE47: 236235451 | GH47: 77890389 | GM47: 257644050308 | GQ47: 1699651576 | GR47: 537832869 | GS47: 67260151 | GT47: 191928421 | GU47: 755765939 | GV47: 364356733 | GW47: 186366293 | GX47: 1853526895 | GY47: 2808651126 | GZ47: 3859231074 | HC47: 282547888 | HF47: 1610924588 | HG47: 275551692 | HH47: 500336125 | HI47: 9500621 | HJ47: 595511956 | HK47: 55779792 | HL47: 1725000 | HN47: 19084021 | HO47: 296286288 | HP47: 70224481 | HQ47: 1868427063 | HR47: 67544365 | HS47: 188450950 | HT47: 576597946 | HU47: 256094750 | HV47: 128953904 | HW47: 185000000 | HX47: 431654975 | HY47: 88544211 | HZ47: 48756084 | IA47: 56000331 | IB47: 17979458 | IC47: 110178767 | ID47: 115110071 | IE47: 139331127 | IF47: 44852591 | IG47: 170522072 | IH47: 16954634 | IK47: 41794737 | IL47: 33695213 | IM47: 1070569291 | IO47: 75000463 | IP47: 287774079 | IS47: 24852366 | IT47: 125900902 | IU47: 357908472 | IX47: 67850000 | JB47: 761067104 | JD47: 3992309 | JE47: 121999752 | JF47: 1840327 | JH47: 79648986 | JI47: 11454629 | JK47: 32250000 | JL47: 40989133 | JM47: 4909736526 | JN47: 339671065 | JO47: 128915651 | JP47: 167623788 | JQ47: 15590136 | JR47: 4500000 | JT47: 29257621758 | JW47: 5756846818 | JX47: 201078400 | JY47: 435362711 | JZ47: 6393287929 | KC47: 677713099 | KD47: 677713099 | KG47: 69155467 | KH47: 548360202 | KI47: 918070006 | KJ47: 1070500 | KK47: 38507 | KL47: 49103781 | KN47: 1585798464 | KQ47: 65312679 | KR47: 1.2150815e+10 | KT47: 964190125 | KV47: 531410517 | KW47: 3092134 | KZ47: 1700000000 | LB47: 167969190 | LC47: 2055546 | LE47: 15584844810 | LH47: - | LI47: - | LJ47: =LE47+KD47+JZ47+JT47 -> 51913467596
A48: October | AD48: 25771866000 | CF48: October | DQ48: October | DT48: -263082722 | DU48: -875000 | DV48: 366245153037 | DZ48: 264527826647 | EA48: 1378599000 | EB48: 446362304 | EC48: -100000 | EE48: 2014761881 | EF48: 88806146 | EG48: 48882243 | EH48: 56009159 | EI48: 13715228 | EJ48: 19336421 | EK48: 45205134 | EL48: 485633867 | EM48: 347124265 | EO48: 567868000 | EP48: -88195824 | EQ48: -60608243 | ER48: 3162909243 | ES48: 874346161 | ET48: 12466619466 | EV48: 137333515 | EW48: 1500000 | EX48: 169926498 | EY48: 724826225 | EZ48: 1518709590 | FA48: 47140054 | FC48: 1560989899 | FD48: 144872253 | FF48: 45279913 | FG48: 89311718 | FI48: 167603500 | FJ48: 344486840 | FL48: 499347703 | FM48: 389760569 | FO48: 196450708 | FQ48: 51216031 | FR48: 944298597 | FV48: 272866550 | FW48: 532041233 | FX48: 190535000 | FZ48: 154709030 | GA48: 517405952 | GB48: 97498691 | GC48: 33099477 | GD48: 3509103 | GE48: 245637003 | GF48: 21931872 | GG48: 9500000 | GH48: 90228494 | GM48: 295597117115 | GQ48: 2041335928 | GR48: 594513930 | GS48: 81359679 | GT48: 230109738 | GU48: 839896935 | GV48: 408513824 | GW48: 208484794 | GX48: 2076289728 | GY48: 3120723473 | GZ48: 4322393005 | HC48: 289443892 | HF48: 1610924588 | HG48: 305007392 | HH48: 555846209 | HI48: 9500621 | HJ48: 669904404 | HK48: 56337792 | HL48: 5257000 | HN48: 21586730 | HO48: 400022106 | HP48: 72564331 | HQ48: 2123200140 | HR48: 71143865 | HS48: 223221950 | HT48: 643471985 | HU48: 282947250 | HV48: 128953904 | HW48: 185000000 | HX48: 431654975 | HY48: 97067762 | HZ48: 68635038 | IA48: 59893384 | IB48: 22636158 | IC48: 119956517 | ID48: 140141834 | IE48: 149929916 | IF48: 47772110 | IG48: 177373572 | IH48: 21954634 | IK48: 91887296 | IL48: 39710979 | IM48: 1184766113 | IO48: 91830463 | IP48: 414333579 | IQ48: 130222000 | IS48: 24852366 | IT48: 129729731 | IU48: 397676080 | IX48: 73350000 | JB48: 841367104 | JD48: 4236309 | JE48: 157582473 | JH48: 88550630 | JI48: 11454629 | JK48: 32250000 | JL48: 40989133 | JM48: 5411563161 | JN48: 370053416 | JO48: 144290478 | JP48: 238360782 | JQ48: 15590136 | JR48: 13500000 | JT48: 32863117951 | JW48: 6293355982 | JX48: 220578400 | JY48: 484934011 | JZ48: 6998868393 | KC48: 789685236 | KD48: 789685236 | KG48: 77631029 | KH48: 1011860252 | KI48: 918070006 | KJ48: 1070500 | KK48: 90172 | KL48: 49103781 | KN48: 2057825741 | KQ48: 77146640 | KR48: 1.3876116e+10 | KT48: 1104604315 | KU48: 17150133 | KV48: 558706525 | KW48: 3096024 | KZ48: 1700000000 | LB48: 167969190 | LC48: 3305546 | LE48: 17508094423 | LH48: 9137025 | LI48: 9137025 | LJ48: =LE48+KD48+JZ48+JT48 -> 58159766003
A49: November | AD49: 24295973394 | CF49: November | DQ49: November | DR49: 397658050368 | DT49: -360884713 | DU49: -875000 | DV49: 397296290655 | DZ49: 284324003837 | EA49: 1558767000 | EB49: 446782304 | EC49: -100000 | EE49: 2236947525 | EF49: 104878121 | EG49: 56525528 | EH49: 61353208 | EI49: 16570458 | EJ49: 34395945 | EK49: 51787320 | EL49: 485769531 | EM49: 381481235 | EO49: 629568000 | EP49: -85619065 | EQ49: -59940623 | ER49: 3549069251 | ES49: 1037734302 | ET49: 14424645776 | EV49: 140213515 | EW49: 1500000 | EX49: 175518398 | EY49: 802826801 | EZ49: 1682674789 | FA49: 59110595 | FC49: 1737619089 | FD49: 161826385 | FF49: 46697913 | FG49: 90233056 | FI49: 203626000 | FJ49: 375631803 | FL49: 511262453 | FM49: 425182224 | FO49: 215146158 | FQ49: 52327290 | FR49: 1143003497 | FV49: 289765425 | FW49: 564224142 | FX49: 190535000 | FZ49: 193787377 | GA49: 598302611 | GB49: 100551898 | GC49: 34194935 | GD49: 5964427 | GE49: 294163007 | GF49: 40256588 | GG49: 9500000 | GH49: 100062608 | GI49: 396000000 | GM49: 319896327636 | GQ49: 2556225784 | GR49: 651194991 | GS49: 92806953 | GT49: 231362338 | GU49: 922152930 | GV49: 453631492 | GW49: 230603295 | GX49: 2299052561 | GY49: 3432795820 | GZ49: 4791263157 | HC49: 328680666 | HF49: 1610924588 | HG49: 336072338 | HH49: 610302595 | HI49: 9850621 | HJ49: 734546616 | HK49: 56337792 | HL49: 5257000 | HN49: 24089439 | HO49: 449024010 | HP49: 79982819 | HQ49: 2290931729 | HR49: 72463865 | HS49: 374724950 | HT49: 712669357 | HU49: 342297250 | HV49: 128953904 | HW49: 185000000 | HX49: 431654975 | HY49: 99957942 | HZ49: 81532529 | IA49: 62665034 | IB49: 25708396 | IC49: 134533216 | ID49: 158515198 | IE49: 164296436 | IF49: 51161095 | IG49: 199983172 | IH49: 23704634 | IK49: 92053963 | IL49: 41109729 | IM49: 1284576472 | IO49: 117042894 | IP49: 414333579 | IQ49: 131396300 | IS49: 24852366 | IT49: 129729731 | IU49: 437443688 | IX49: 109350000 | JB49: 892817104 | JD49: 4236309 | JE49: 179503850 | JH49: 97452274 | JI49: 11454629 | JK49: 32250000 | JL49: 40989133 | JM49: 5928476490 | JN49: 398043651 | JO49: 147350478 | JP49: 279258223 | JQ49: 15590136 | JR49: 13500000 | JT49: 36269722487 | JW49: 7656763215 | JX49: 280078400 | JY49: 552255290 | JZ49: 8489096905 | KC49: 892351422 | KD49: 892351422 | KG49: 90861669 | KH49: 1017409202 | KI49: 921870732 | KJ49: 1070500 | KK49: 109233 | KL49: 49103781 | KN49: 2080425118 | KQ49: 85243984 | KR49: 1.5496172e+10 | KT49: 1236718505 | KU49: 17150133 | KV49: 558706525 | KW49: 3096878 | KZ49: 1700000000 | LB49: 167969190 | LC49: 3305546 | LE49: 19268362317 | LH49: 9504525 | LI49: 9504525 | LJ49: =LE49+KD49+JZ49+JT49 -> 64919533131
A50: December | B50: 421126840396 | C50: 339699711199 | D50: 81427129197 | F50: 43797431309 | G50: 4954583955 | I50: 48752015264 | J50: 32675113933 | L50: 3250898372 | M50: 21360691248 | N50: -18109792876 | P50: 14565321057 | Q50: 4484319020 | R50: 671286653 | S50: 3813032367 | T50: 10752288690 | V50: -2616980500 | X50: 8135308190 | AD50: 50189674314 | AE50: 52359271094 | AH50: 9991605728 | AI50: 69526001377 | AL50: 24000790325 | AM50: 4078437036 | AN50: 210145779874 | AQ50: 124443908268 | AR50: 7020005378 | AS50: 215650415 | AT50: 2254920523 | AU50: 3097703639 | AV50: 137032188223 | AW50: 347177968097 | BA50: 22279823661 | BE50: 2922304253 | BF50: 1136790000 | BG50: 75972481 | BI50: 247602110 | BK50: 178805104117 | BL50: 205467596622 | BN50: 10371362209 | BQ50: 11577858681 | BS50: 21949220890 | BT50: 227416817512 | BV50: 68245000000 | BY50: 50279132592 | BZ50: -3110625307 | CA50: 4347643300 | CC50: 119761150585 | CD50: 347177968097 | CF50: December | DQ50: December | DR50: 421572205450 | DT50: -444490055 | DU50: -875000 | DV50: 421126840395 | DZ50: 294943425242 | EA50: 1558767000 | EB50: 446782304 | EC50: -100000 | EE50: 2458310633 | EF50: 112008905 | EG50: 56750020 | EH50: 69479992 | EI50: 25601578 | EJ50: 39545991 | EK50: 56458096 | EL50: 487533795 | EM50: 415876747 | EO50: 704245061 | EP50: -140215189 | EQ50: -56040585 | ER50: 3886975165 | ES50: 1048027429 | ET50: 16618671501 | EV50: 141398515 | EW50: 1500000 | EX50: 210858736 | EY50: 879467214 | EZ50: 1845723017 | FA50: 72437315 | FC50: 1897519439 | FD50: 184575232 | FF50: 53134587 | FG50: 90410391 | FI50: 242926000 | FJ50: 393575803 | FL50: 511262453 | FM50: 425182224 | FO50: 242007888 | FQ50: 54301157 | FR50: 1315816997 | FV50: 310588613 | FW50: 668409846 | FX50: 200535000 | FZ50: 207208727 | GA50: 748005076 | GB50: 104181340 | GC50: 40511428 | GD50: 9943113 | GE50: 398252378 | GF50: 80495764 | GG50: 9500000 | GH50: 125853193 | GI50: 396000000 | GM50: 334593685130 | GQ50: 3202336066 | GR50: 707876052 | GS50: 107585296 | GT50: 263224324 | GU50: 1004408926 | GV50: 500237800 | GW50: 252721797 | GX50: 2528776389 | GY50: 3854868167 | GZ50: 5279482810 | HC50: 350633578 | HF50: 1701726900 | HG50: 367729521 | HH50: 663814726 | HI50: 9978521 | HJ50: 797062856 | HK50: 88416792 | HL50: 5257000 | HN50: 26592148 | HO50: 517679054 | HP50: 84027689 | HQ50: 2474071141 | HR50: 79529485 | HS50: 377575237 | HT50: 771752468 | HU50: 346832250 | HV50: 128953904 | HW50: 185000000 | HX50: 431654975 | HY50: 112391006 | HZ50: 89574654 | IA50: 73348509 | IB50: 28134095 | IC50: 163245706 | ID50: 171810058 | IE50: 180354523 | IF50: 56029035 | IG50: 223035672 | IH50: 26204634 | IK50: 96820630 | IL50: 49922575 | IM50: 1387101727 | IO50: 117042894 | IP50: 415387613 | IQ50: 131811300 | IS50: 25757840 | IT50: 137387389 | IU50: 477211296 | IX50: 109350000 | JB50: 942817104 | JD50: 4236309 | JE50: 207247080 | JH50: 106353918 | JI50: 11912629 | JK50: 32250000 | JL50: 74311133 | JM50: 6444156373 | JN50: 429527878 | JO50: 152839237 | JP50: 320835190 | JQ50: 43665561 | JR50: 22500000 | JT50: 39949527073 | JW50: 9119164904 | JX50: 334078400 | JY50: 632298151 | JZ50: 10085541455 | KC50: 1011041871 | KD50: 1011041871 | KG50: 99379224 | KH50: 1223232280 | KI50: 1068891617 | KJ50: 1070500 | KK50: 114310 | KL50: 49103781 | KN50: 2441791713 | KQ50: 99381651 | KR50: 1.6875984e+10 | KT50: 1449122695 | KU50: 17150133 | KV50: 559274515 | KW50: 3099583 | KZ50: 1700000000 | LB50: 167969190 | LC50: 3305546 | LE50: 20875287741 | LH50: 4406748565 | LI50: 4406748565 | LJ50: =LE50+KD50+JZ50+JT50 -> 71921398140
A53: Laba Rugi Konsolidasi up to month X in 2024 | AB53: Neraca Konsolidasi up to month x in 2024 | CF53: Arus Kas Konsolidasi up to month X in 2024 | DQ53: Monthly CALK Konsolidasi up to month X 2024
B54: Penjualan | C54: Harga Pokok Penjualan | D54: Laba Kotor | E54: Beban Usaha | F54: Beban Umum dan Administrasi | G54: Beban Penjualan dan Pemasaran | H54: Beban Analisa Lab | I54: Jumlah Beban Usaha | J54: Laba Usaha | K54: Pendapatan (Beban) Lain-lain | L54: Pendapatan Lain-lain | M54: Beban Diluar Usaha Lainnya | N54: Jumlah Pendapatan (Beban) Lain-lain | P54: Laba Sebelum Pajak | Q54: Beban Pajak Penghasilan (Pajak Kini) | R54: Pajak tangguhan | S54: Jumlah Beban Pajak | T54: Laba Bersih Setelah Pajak | U54: Penghasilan Komprehensif Lain | V54: Keuntungan/Kerugian aktuarial | W54: atas liabilitas imbalan kerja | X54: Jumlah Penghasilan (Rugi) Komprehensif Lain | AB54: ASET | AC54: Aset Lancar | AD54: Kas dan Setara Kas | AE54: Piutang Usaha | AF54: Anjak Piutang | AG54: Cadangan Kerugian Piutang Tak Tertagih | AH54: Piutang Lain Pihak Terkait | AI54: Persediaan | AJ54: Persediaan dalam Proses | AK54: Persediaan Barang Dagang | AL54: Biaya Dibayar Dimuka | AM54: Pajak Dibayar Dimuka | AN54: Jumlah Aset Lancar | AO54: Aset Tidak Lancar | AP54: Investasi | AQ54: Aset Tetap | AR54: Aset Tidak Lancar Lainnya | AS54: Aset tidak berwujud - bersih | AT54: Pekerjaan dalam proses konstruksi | AU54: Aset Pajak Tangguhan | AV54: Jumlah Aset Tidak Lancar | AW54: Jumlah Aset | AY54: LIABILITAS DAN EKUITAS | AZ54: Liabilitas Lancar | BA54: Hutang Usaha | BC54: Barang yang belum terinvoice | BD54: Persediaan Barang Diterima Belum di BAST (LPB) | BE54: Hutang Pajak | BF54: Uang Muka Penjualan | BG54: Akrual | BH54: Pendapatan diterima dimuka | BI54: Hutang Lain-Lain | BJ54: Hutang Bunga Bank | BK54: Hutang Bank Jangka Pendek | BL54: Jumlah Liabilitas Lancar | BM54: Liabilitas Tidak Lancar | BN54: Hutang Bank Jangka Panjang | BO54: Hutang Leasing | BP54: Hutang Pemegang Saham | BQ54: Hutang Imbalan Pasca Kerja | BR54: Liabilitas pajak tangguhan | BS54: Jumlah Liabilitas Tidak Lancar | BT54: Jumlah Liabilitas | BU54: Ekuitas | BV54: Modal Disetor | BW54: Saldo Laba | BX54: Laba-Rugi Periode Berjalan | BY54: Laba-Rugi Ditahan | BZ54: Akumulasi penghasilan komprehensif lain | CA54: Kepentingan non pengendali - Rugi/Laba | CB54: Kepentingan non pengendali - Modal | CC54: Jumlah Ekuitas | CD54: Jumlah Liabilitas dan Ekuitas | CG54: Arus Kas dari Aktivitas Operasi | CH54: Laba (rugi) bersih | CI54: Penyesuaian : | CJ54: Penyusutan | CK54: Akumulasi Komprehensif Lain | CM54: Penurunan (Kenaikan) : | CN54: Piutang usaha | CO54: Anjak Piutang | CP54: Piutang Afiliasi & Lainnya | CQ54: Biaya dibayar dimuka | CR54: Pajak dibayar dimuka | CS54: Persediaan | CT54: Kenaikan (Penurunan) : | CU54: Utang Usaha | CV54: Hutang Afiliasi & Lainnya | CW54: Utang Pajak | CX54: Uang Muka Penjualan | CY54: Biaya yg masih harus dibayar | CZ54: Hutang jangka Panjang | DA54: Kas Bersih yang digunakan untuk Aktivitas Operasi | DB54: Arus Kas dari Aktivitas Investasi : | DC54: (Penambahan) Pengurangan Aset Tetap | DD54: (Penambahan) Pengurangan Investasi | DE54: (Penambahan) Pengurangan Konstruksi Dalam Pengerjaan | DF54: Kas Bersih yang diperoleh/ digunakan untuk Aktivitas Investasi | DG54: Arus Kas dari Aktivitas Pendanaan : | DH54: Utang Bank | DI54: Modal di setor | DJ54: Kas Bersih yang diperoleh/ digunakan untuk Aktivitas Pendanaan | DK54: Kenaikan Kas & Setara Kas | DL54: Kas & Setara Kas awal periode | DM54: Kas & Setara Kas akhir periode | DR54: Penjualan Afiliasi | DS54: Penjualan Non Afiliasi | DT54: Retur Penjualan | DU54: Diskon Penjualan | DV54: Jumlah Penjualan | DX54: BEBAN POKOK PENJUALAN | DY54: Harga Pokok Penjualan Afiliasi | DZ54: Harga Pokok Penjualan Non Afiliasi | EA54: Beban Bea Masuk Import | EB54: Beban Clearance Impor | EC54: Potongan Pembelian | ED54: Retur Pembelian | EE54: Beban Penyusutan Mesin | EF54: Beban Pemeliharaan Mesin Ew | EG54: Beban Pemeliharaan Mesin Line 1 | EH54: Beban Pemeliharaan Mesin Line 2 | EI54: Beban Pemeliharaan Mesin Line 3 | EJ54: Beban Pemeliharaan Mesin Line 4 | EK54: Beban Pemeliharaan Mesin Line 5 | EL54: Beban Pemeliharaan Mesin Copper Sulphate | EM54: Beban Penyusutan Peralatan Pabrik | EN54: Beban Pemeliharaan Mesin Mixing | EO54: Beban Sewa Kendaraan | EP54: Selisih Stock Opname | EQ54: Selisih Timbang | ER54: Beban Tenaga Kerja Langsung | ES54: Beban Transportasi Bahan Baku | ET54: Beban Transportasi Produk Jadi | EV54: Beban Pemeliharaan Kendaraan Pabrik | EW54: Beban Pemeliharaan Aset Pabrik | EX54: Beban Rumah Tangga Pabrik | EY54: Beban Gaji Staff Pabrik | EZ54: Beban Tenaga Kerja Tidak Langsung | FA54: Beban Pemeliharaan Mesin Pramaterial | FB54: Beban Operasional | FC54: Beban Listrik Pabrik | FD54: Beban Listrik Pabrik (Gudang Timur) | FE54: Beban Listrik Pabrik (Tengah) | FF54: Beban Transportasi Lainnya | FG54: Beban Perlengkapan Pabrik | FH54: Beban Telepon Pabrik | FI54: Beban Bbm Pabrik | FJ54: Beban Bongkar | FK54: Beban Qc Produk | FL54: Beban Transportasi Impor | FM54: Beban Gudang Pelabuhan | FN54: Beban Administrasi Pabean | FO54: Beban Muat | FP54: Beban Royalti Merk | FQ54: Beban Klaim | FR54: Beban Gaji PHL | FS54: Beban Operasional Kebun | FT54: Beban Perlengkapan Kebun | FU54: Beban Bbm Kebun | FV54: Beban Asuransi Pengiriman | FW54: Beban Sample | FX54: Beban Demplot | FY54: Beban Jasa Maklon | FZ54: Beban Pemeliharaan Bangunan Pabrik | GA54: Beban Pemeliharaan Sarana Prasarana Pabrik | GB54: Beban Perlengkapan Mekanik | GC54: Beban Perlengkapan Elektrikal | GD54: Beban Pemeliharaan Mesin Crf | GE54: Beban Riset Dan Percobaan Lapangan | GF54: Beban Pemeliharaan Mesin Copper Sulphate Line 2 | GG54: Beban Pemeliharaan Aset Lab | GH54: Beban Operasional Gudang | GI54: Beban Uji Dosis (Internal) | GJ54: Beban Perlengkapan Lab | GK54: Beban Kerugian Bibit Afkir | GL54: Beban Pemeliharaan Mesin NPK | GM54: Jumlah Harga Pokok Penjualan | GO54: BEBAN UMUM DAN ADMINISTRASI | GP54: Beban Administrasi Dan Umum | GQ54: Beban Pelatihan | GR54: Beban Pelatihan Internal | GS54: Beban Perlengkapan Kantor | GT54: Beban Hse | GU54: Beban Penyusutan Kendaraan | GV54: Beban Penyusutan Inventaris Kantor | GW54: Beban Amortisasi Ditangguhkan SHGB | GX54: Beban Penyusutan Bangunan | GY54: Beban Gaji BOD | GZ54: Beban Gaji Staff Kantor | HA54: Beban Tunjangan Keluarga | HB54: Bebang Tunjangan Kemahalan | HC54: Tunjangan Lembur | HD54: Beban Tunjangan Kinerja | HE54: Beban Bonus | HF54: Tunjangan Hari Raya - THR | HG54: Beban Asuransi - BPJS KES | HH54: Beban Asuransi - BPJS TK | HI54: Beban Pemeliharaan Aset Kantor | HJ54: Beban Rumah Tangga Kantor | HK54: Beban Pengembangan System/Software | HL54: Beban Kompensasi Ganti Rugi | HM54: Beban Koreksi Fiskal | HN54: Beban Asuransi Kebakaran | HO54: Beban Pemeliharaan Kendaraan Kantor | HP54: Beban Bbm Kantor | HQ54: Beban Perjalanan Dinas Kantor | HR54: Beban Perjalanan Dinas Tamu | HS54: Beban Obat/Pengobatan | HT54: Beban Sewa | HU54: Biaya Legal Dan Perijinan | HV54: Beban Rakor | HW54: Beban Audit | HX54: Beban Perayaan Hari Besar | HY54: Beban Atk Kantor | HZ54: Beban Internet/Vsat | IA54: Beban Cetak/Fotocopy | IB54: Beban Air Minum Kantor | IC54: Beban Konsumsi Dan Oleh-Oleh Tamu | ID54: Beban Kirim Paket (Sampel/Dokumen) | IE54: Beban Listrik Kantor | IF54: Beban Telepon Kantor | IG54: Pajak Kendaraan & PBB | IH54: Beban Suka/Duka | II54: Beban Bunga Imbalan Kerja | IJ54: Beban Kerugian Aktuaria | IK54: Beban Pph 4 Ayat 2 | IL54: Beban Pph Pasal 23 | IM54: Beban Pph Pasal 21 | IN54: Beban Pph 25 | IO54: Beban Pinalti Pajak | IP54: Beban Pph Pasal 29 | IQ54: Beban Olahraga Dan Rekreasi | IR54: Biaya Kaizen | IS54: Beban Pemutusan Hubungan Kerja | IT54: Beban Apraisal | IU54: Beban Konsultan Keuangan | IV54: Beban Bphtb | IW54: Beban Kerugian Investasi | IX54: Beban Apresiasi Karyawan | IY54: Beban Imbalan Pasca Kerja | IZ54: Beban Notaris | JA54: Beban Gaji Staff Laboratorium | JB54: Beban Csr (Corporate Social Responsibility) | JC54: Beban Cadangan Kerugian Piutang Tak Tertagih | JD54: Beban Brand Development | JE54: Beban Ppn Tidak Bisa Dikreditkan | JF54: Beban Operasional Direksi | JG54: Beban Asuransi Managemen | JH54: Beban Penyusutan Software | JI54: Beban Rekrutmen | JJ54: Beban Rups | JK54: Beban Aktuaria | JL54: Beban Riset Corporate & Strategy | JM54: Beban Gaji Managemen | JN54: Beban Gaji Principal | JO54: Beban Sarana Prasarana Kantor | JP54: Beban Outsourcing | JQ54: Biaya Pemeliharaan Bangunan Kantor | JR54: Beban Beasiswa | JS54: Beban Kesejahteraan Karyawan | JT54: Jumlah Beban Administrasi dan Umum | JV54: BEBAN PENJUALAN DAN PEMASARAN | JW54: Beban Operasional Pemasaran | JX54: Beban Relasi | JY54: Beban Promosi | JZ54: Jumlah Beban Penjualan dan Pemasaran | KB54: BEBAN ANALISA LAB | KC54: Beban Analisa Lab | KD54: Jumlah Analisa Lab | KF54: PENDAPATAN | KG54: Pendapatan Jasa Giro | KH54: Pendapatan Lain-Lain | KI54: Pendapatan Selisih Lebih Kurs | KJ54: Pendapatan Aval | KK54: Pendapatan Selisih Koma | KL54: Pendapatan Klaim | KM54: Pendapatan Jasa Maklon | KN54: Jumlah Pendapatan | KP54: BEBAN DILUAR USAHA | KQ54: Beban Adm Bank | KR54: Beban Marjin Pinjaman | KT54: Beban Administrasi Kredit - Mk | KU54: Beban Pengikatan Kredit | KV54: Beban Selisih Kurang Kurs | KW54: Beban Selisih Koma | KX54: Beban Market Place | KY54: Beban Lain-Lain | KZ54: Beban Zakat | LA54: Beban Infak | LB54: Beban Qurban | LC54: Beban Administrasi Kredit - LC/SKBDN | LD54: Beban Kerugian Penjualan Aset | LE54: Jumlah Beban Diluar Usaha | LG54: PAJAK PENGHASILAN | LH54: Beban Pajak Penghasilan | LI54: Jumlah Pajak Penghasilan | LJ54: Jumlah Beban
A55: January | B55: 4.7252005e+10 | C55: 3.9500561e+10 | D55: =B55-C55 -> 7751443615 | F55: 2.1482043e+09 | G55: 152624453 | H55: 50539695 | I55: =SUM(F55:H55) -> 2351368485 | J55: =D55-I55 -> 5400075130 | L55: 2.045808e+08 | M55: 1.0319597e+09 | N55: =L55-M55 -> -8.273789e+08 | P55: =J55+N55 -> 4572696225 | T55: =P55-S55 -> 4572696225 | X55: =T55+W55 -> 4572696225 | AD55: 12626666563 | AE55: 50811719218 | AG55: -100319905 | AH55: 8491920776 | AI55: 88636029556 | AL55: 2354431162 | AM55: 10584647021 | AN55: 173405094392 | AP55: - | AQ55: 108345190885 | AR55: 4849798649 | AU55: 1361708691 | AV55: 114556698225 | AW55: 287961792618 | BA55: 35305343431 | BC55: 557008923 | BD55: - | BE55: 6396668048 | BF55: - | BI55: 2225327351 | BJ55: - | BK55: 124382874005 | BL55: 168867221758 | BN55: - | BO55: 190865004 | BP55: - | BQ55: 5983834871 | BR55: - | BS55: 6174699875 | BT55: 175041921633 | BV55: 68245000000 | BW55: - | BX55: 4572696225 | BY55: 38088897514 | BZ55: -656444657 | CA55: - | CB55: 2669721904 | CC55: 112919870986 | CD55: 287961792619 | CF55: January | DQ55: January | DR55: 36716705750 | DS55: 10535299123 | DT55: - | DU55: - | DV55: 47252004873 | DY55: 30281340480 | DZ55: 8709123266 | EA55: 137747000 | EB55: - | EC55: - | ED55: - | EE55: 145058946 | EF55: 139998 | EG55: 45600698 | EH55: 4412286 | EI55: - | EJ55: 2980377 | EK55: 232055 | EL55: 18581232 | EM55: 30042266 | EN55: - | EO55: 29563266 | EP55: -126312 | ER55: 169286797 | ES55: 12475000 | ET55: 702201140 | EV55: 82203 | EW55: 40301306 | EX55: 1754000 | EY55: 147839571 | EZ55: 224026390 | FA55: 33608777 | FB55: 30318880 | FC55: 13519152 | FD55: 30712574 | FE55: 41170691 | FF55: 1172981 | FG55: 10000155 | FI55: 9950000 | FJ55: 5450485 | FO55: 17998675 | FR55: 21905625 | FS55: 799000 | FT55: 1429000 | FU55: 2010000 | FV55: 47824855 | GM55: 40970532815 | GQ55: 71185302 | GS55: 13198005 | GT55: 21485538 | GU55: 72958023 | GV55: 29190083 | GW55: 15685925 | GX55: 174100508 | GY55: 131657205 | GZ55: 646896591 | HC55: 24496707 | HG55: 25123325 | HH55: 47709136 | HI55: 328008408 | HJ55: 41965846 | HO55: 30373000 | HP55: 4053720 | HQ55: 146067363 | HR55: 1300000 | HT55: 118147880 | HU55: 34192385 | HW55: - | HX55: 11719431 | HY55: 10189430 | HZ55: 2343451 | IA55: 16086250 | IB55: 1517300 | IC55: 9159412 | ID55: 8375700 | IE55: 12581897 | IF55: 2414286 | IG55: 7901500 | IK55: 15171237 | IM55: 9686814 | JB55: 2000000 | JD55: 440000 | JE55: 5323356 | JF55: 52976074 | JT55: 2145681087 | JW55: 126369376 | JX55: 20002500 | JY55: 5000000 | JZ55: 151371876 | KC55: 55576849 | KD55: 55576849 | KG55: 5317659 | KH55: 17013610 | KI55: 178662605 | KJ55: 2870500 | KK55: 24948 | KN55: 203889322 | KQ55: 4291018 | KR55: 984171013 | KT55: 10688853 | KV55: 23625600 | KW55: 83117 | KY55: 9100100 | LE55: 1031959701 | LJ55: =LE55+KD55+JZ55+JT55 -> 3384589513
A56: February | B56: 7.2975719e+10 | C56: 5.9574609e+10 | D56: =B56-C56 -> 13401110087 | F56: 4.1607708e+09 | G56: 270999451 | H56: 96869945 | I56: =SUM(F56:H56) -> 4528640222 | J56: =D56-I56 -> 8872469865 | L56: 2.290476e+08 | M56: 2.3859463e+09 | N56: =L56-M56 -> -2156898747 | P56: =J56+N56 -> 6715571118 | T56: =P56-S56 -> 6715571118 | X56: =T56+W56 -> 6715571118 | AD56: 5259679858 | AE56: 50535551910 | AG56: -100319905 | AH56: 9134110581 | AI56: 84137970277 | AL56: 9303703904 | AM56: 9810362398 | AN56: 168081059023 | AP56: - | AQ56: 108660844053 | AR56: 4864706810 | AU56: 1361708691 | AV56: 114887259553 | AW56: 282968318576 | BA56: 33792928453 | BC56: 557008923 | BD56: - | BE56: 4349255562 | BF56: 163350000 | BI56: 2231368104 | BJ56: - | BK56: 120682247783 | BL56: 161776158824 | BN56: - | BO56: 145579004 | BP56: - | BQ56: 5983834871 | BR56: - | BS56: 6129413875 | BT56: 167905572699 | BV56: 68245000000 | BW56: - | BX56: 6715571118 | BY56: 38088897514 | BZ56: -656444657 | CA56: - | CB56: 2669721904 | CC56: 115062745879 | CD56: 282968318578 | CF56: February | DQ56: February | DR56: 41561007880 | DS56: 31227258080 | DV56: 72788265960 | DY56: 30781212558 | DZ56: 25988957393 | EA56: 137747000 | EB56: 7390800 | EE56: 289923674 | EF56: 242601 | EG56: 45666751 | EH56: 5731245 | EI56: 1455983 | EJ56: 3711921 | EK56: 17438040 | EL56: 47071521 | EM56: 60417864 | EO56: 81432654 | EP56: -126312 | ER56: 372167117 | ES56: 68960000 | ET56: 2415858703 | EV56: 16438450 | EW56: 82388368 | EX56: 7145800 | EY56: 274882228 | EZ56: 472221982 | FA56: 58039123 | FB56: 52161179 | FC56: 37250273 | FD56: 65708110 | FE56: 82979121 | FF56: 5567442 | FG56: 28127305 | FI56: 9950000 | FJ56: 11531607 | FL56: 20131988 | FM56: 5679320 | FO56: 24355735 | FR56: 21905625 | FS56: 919000 | FT56: 1429000 | FU56: 2535000 | FV56: 370721585 | GM56: 61977327755 | GQ56: 85685302 | GS56: 14361505 | GT56: 22986538 | GU56: 145916045 | GV56: 58181808 | GW56: 31371850 | GX56: 348201015 | GY56: 380391666 | GZ56: 1182557688 | HC56: 46436037 | HG56: 50153122 | HH56: 99628714 | HI56: 354729331 | HJ56: 92994256 | HK56: 266200 | HL56: 63334998 | HP56: 13570538 | HQ56: 473819666 | HR56: 14200000 | HT56: 122086383 | HU56: 55684770 | HX56: 11719431 | HY56: 12614730 | HZ56: 4676778 | IA56: 20173910 | IB56: 2673800 | IC56: 10732712 | ID56: 9768700 | IE56: 26605535 | IF56: 5463321 | IG56: 22658600 | IH56: 4000000 | IK56: 63334324 | IL56: 13266525 | IM56: 86806503 | IO56: 7500000 | IP56: 118455700 | IQ56: 700000 | JB56: 5350000 | JD56: 440000 | JE56: 17159906 | JF56: 63439174 | JH56: 3125000 | JT56: 4167222081 | JW56: 409260456 | JX56: 36502500 | JY56: 14175000 | JZ56: 459937956 | KC56: 107108978 | KD56: 107108978 | KG56: 15971161 | KH56: 29118620 | KI56: 183241355 | KJ56: 2870500 | KK56: 24988 | KN56: 231226624 | KQ56: 10432195 | KR56: 1993892040 | KT56: 21377706 | KV56: 49936050 | KW56: 83250 | KY56: 10200100 | KZ56: 300000000 | LE56: 2385921341 | LJ56: =LE56+KD56+JZ56+JT56 -> 7120190356
A57: March | B57: 8.4013598e+10 | C57: 6.8374079e+10 | D57: =B57-C57 -> 15639519473 | F57: 6.9958668e+09 | G57: 443824922 | H57: 1.0700675e+08 | I57: =SUM(F57:H57) -> 7546698500 | J57: =D57-I57 -> 8092820973 | L57: 3.6713581e+08 | M57: 3.8213581e+09 | N57: =L57-M57 -> -3454222277 | P57: =J57+N57 -> 4638598696 | T57: =P57-S57 -> 4638598696 | X57: =T57+W57 -> 4638598696 | AD57: 23899144420 | AE57: 39032051700 | AG57: -100319905 | AH57: 9724235283 | AI57: 69803584632 | AL57: 12759563100 | AM57: 8466909666 | AN57: 163585168896 | AP57: - | AQ57: 109638141974 | AR57: 4847614970 | AU57: 1361708691 | AV57: 115847465635 | AW57: 279432634532 | BA57: 35195731150 | BC57: 557008923 | BD57: - | BE57: 4595814339 | BF57: - | BI57: 2235990229 | BJ57: - | BK57: 117762025561 | BL57: 160346570201 | BN57: - | BO57: 121456004 | BP57: - | BQ57: 5983834871 | BR57: - | BS57: 6105290875 | BT57: 166451861076 | BV57: 68245000000 | BW57: - | BX57: 4633598696 | BY57: 38088897514 | BZ57: -656444657 | CA57: - | CB57: 2669721904 | CC57: 112980773457 | CD57: 279432634533 | CF57: March | DQ57: March | DR57: 20566684881 | DS57: 63538025530 | DV57: 84104710410 | DY57: 8030679682 | DZ57: 54390804716 | EA57: 276725000 | EB57: 7390800 | EE57: 436080068 | EF57: 19166100 | EG57: 45866751 | EH57: 5756244 | EI57: 1700512 | EJ57: 3711921 | EK57: 31398472 | EL57: 133014074 | EM57: 90793463 | EO57: 139895920 | EP57: 31518108 | ER57: 522371774 | ES57: 78660000 | ET57: 4767229905 | EV57: 20313450 | EW57: 75015219 | EX57: 41681550 | EY57: 393338435 | EZ57: 743099109 | FA57: 71758105 | FB57: 57821633 | FC57: 56827966 | FD57: 89042635 | FE57: 120571666 | FF57: 10348052 | FG57: 50619827 | FI57: 19194917 | FJ57: 29587756 | FL57: 20131988 | FM57: 5679320 | FO57: 27520285 | FR57: 21905625 | FS57: 919000 | FT57: 1608000 | FU57: 6443000 | FV57: 370721585 | FW57: 7788057 | GM57: 71254700688 | GQ57: 524821535 | GS57: 24981100 | GT57: 51088428 | GU57: 218874068 | GV57: 88485092 | GW57: 47057775 | GX57: 522505461 | GY57: 549754104 | GZ57: 1832916766 | HC57: 62131419 | HG57: 77640915 | HH57: 155453671 | HI57: 378757822 | HJ57: 397569173 | HK57: 532600 | HL57: 1050000 | HO57: 83864952 | HP57: 25812298 | HQ57: 868573532 | HR57: 16365000 | HT57: 52503050 | HU57: 92720611 | HW57: 6097500 | HX57: 24920831 | HY57: 24176050 | HZ57: 6581778 | IA57: 21834910 | IB57: 3540800 | IC57: 14218712 | ID57: 13494510 | IE57: 37901319 | IF57: 9611263 | IG57: 30819900 | IH57: 5200000 | IJ57: 6000000 | IK57: 90443398 | IL57: 13266525 | IM57: 173361676 | IO57: 50086901 | IP57: 118455700 | IQ57: 700000 | IT57: 35500000 | IX57: 10882500 | JB57: 18100000 | JD57: 440000 | JE57: 41091122 | JF57: 132234474 | JH57: 6250000 | JK57: 26250000 | JT57: 6994919241 | JW57: 763701624 | JX57: 58009000 | JY57: 14175000 | JZ57: 835885624 | KC57: 122929003 | KD57: 122929003 | KG57: 25828012 | KH57: 60476470 | KI57: 260979323 | KJ57: 5005900 | KK57: 25137 | KM57: 12000000 | KN57: 364314842 | KQ57: 17311385 | KR57: 2996592249 | KT57: 32066559 | KV57: 131730066 | KW57: 83913 | KY57: 10800100 | KZ57: 631458819 | LA57: 1315000 | LE57: 3821358092 | LJ57: =LE57+KD57+JZ57+JT57 -> 11775091960
A58: April | B58: 1.0413147e+11 | C58: 8.4446293e+10 | D58: =B58-C58 -> 19685181030 | F58: 1.0219875e+10 | G58: 787997674 | H58: 1.4036938e+08 | I58: =SUM(F58:H58) -> 11148242062 | J58: =D58-I58 -> 8536938968 | L58: 1.904755e+09 | M58: 4.9314171e+09 | N58: =L58-M58 -> -3026662101 | P58: =J58+N58 -> 5510276867 | T58: =P58-S58 -> 5510276867 | X58: =T58+W58 -> 5510276867 | AD58: 14943144612 | AE58: 38456572443 | AG58: -100319905 | AH58: 9293011078 | AI58: 65296751541 | AL58: 14423069545 | AM58: 8065197439 | AN58: 150377426752 | AP58: - | AQ58: 109529781729 | AR58: 4863839047 | AU58: 1361708691 | AV58: 115755329467 | AW58: 266132756220 | BA58: 25089842485 | BC58: 459773194 | BD58: - | BE58: 3746915251 | BF58: - | BI58: 2238235448 | BK58: 114657503339 | BL58: 146192269717 | BN58: - | BO58: 104200004 | BP58: - | BQ58: 5983834871 | BR58: - | BS58: 6088034875 | BT58: 152280304592 | BV58: 68245000000 | BW58: - | BX58: 5505276867 | BY58: 38088897514 | BZ58: -656444657 | CA58: - | CB58: 2669721904 | CC58: 113852451628 | CD58: 266132756220 | CF58: April | DQ58: April | DR58: 21786077250 | DS58: 82436509286 | DV58: 104222586535 | DY58: 6897791380 | DZ58: 69504366123 | EA58: 276725000 | EB58: 12270850 | EE58: 582435223 | EF58: 27820789 | EG58: 45866751 | EH58: 5756244 | EI58: 2804316 | EJ58: 4959121 | EK58: 32407271 | EL58: 158149087 | EM58: 121169062 | EO58: 169459186 | EP58: 31518108 | ER58: 726071170 | ES58: 111510000 | ET58: 6643731198 | EV58: 43647679 | EW58: 79045850 | EX58: 48208214 | EY58: 506541042 | EZ58: 1003127790 | FA58: 72092073 | FB58: 72994001 | FC58: 82749517 | FD58: 150780156 | FE58: 158722358 | FF58: 12289352 | FG58: 59729406 | FI58: 22456917 | FJ58: 102732021 | FL58: 30057388 | FM58: 15784347 | FO58: 41833170 | FS58: 7658100 | FT58: 1608000 | FU58: 11317000 | FV58: 109391880 | FW58: 14650107 | GM58: 88002227246 | GQ58: 529593479 | GR58: 448100 | GS58: 31726600 | GT58: 66621688 | GU58: 291832090 | GV58: 119794863 | GW58: 62743700 | GX58: 697069582 | GY58: 798488566 | GZ58: 2373804002 | HC58: 86828731 | HF58: 1132314778 | HG58: 104148914 | HH58: 213596622 | HI58: 387970422 | HJ58: 436371805 | HK58: 6610200 | HL58: 1050000 | HN58: 4145328 | HO58: 110830952 | HP58: 31904448 | HQ58: 949722165 | HR58: 22502500 | HT58: 120751569 | HU58: 146112996 | HW58: 6097500 | HX58: 47664831 | HY58: 31273812 | HZ58: 9009274 | IA58: 14118910 | IB58: 4315800 | IC58: 18931862 | ID58: 19332910 | IE58: 50005210 | IF58: 11989622 | IG58: 45867000 | IH58: 7200000 | IJ58: 6000000 | IK58: 99290582 | IL58: 15250975 | IM58: 260586610 | IO58: 53079829 | IP58: 118455700 | IQ58: 1400000 | IS58: 13309890 | IT58: 35500000 | IX58: 10882500 | IZ58: 7625000 | JB58: 22100000 | JC58: 354814357 | JD58: 12440000 | JE58: 44097554 | JF58: 142638074 | JH58: 6250000 | JK58: 26250000 | JT58: 10222761902 | JW58: 1415447795 | JX58: 79509000 | JY58: 14175000 | JZ58: 1509131795 | KC58: 165253423 | KD58: 165253423 | KG58: 34814379 | KH58: 1589109152 | KI58: 260979323 | KJ58: 5005900 | KK58: 25241 | KM58: 12000000 | KN58: 1901933995 | KQ58: 23756324 | KR58: 3945720061 | KT58: 78172079 | KV58: 239609917 | KW58: 84769 | KY58: 10800100 | KZ58: 631458819 | LA58: 1815000 | LE58: 4931417069 | LJ58: =LE58+KD58+JZ58+JT58 -> 16828564189
A59: May | B59: 1.1966412e+11 | C59: 9.5642048e+10 | D59: =B59-C59 -> 24022073368 | F59: 1.302492e+10 | G59: 2209792569 | H59: 1.1145528e+08 | I59: =SUM(F59:H59) -> 15346167688 | J59: =D59-I59 -> 8675905680 | L59: 2.1430119e+09 | M59: 6.1656661e+09 | N59: =L59-M59 -> -4022654179 | P59: =J59+N59 -> 4653251501 | T59: =P59-S59 -> 4653251501 | X59: =T59+W59 -> 4653251501 | AD59: 1277712271 | AE59: 65009465320 | AG59: -100319905 | AH59: 8346091567 | AI59: 56376094050 | AL59: 6603882834 | AM59: 7630873196 | AN59: 145143799333 | AP59: - | AQ59: 108486721301 | AR59: 4841755125 | AU59: 1361708691 | AV59: 114690185116 | AW59: 259833984450 | BA59: 23330519035 | BC59: 378012091 | BD59: - | BE59: 4790271520 | BF59: - | BI59: 2239895550 | BK59: 109949081117 | BL59: 140687779313 | BN59: - | BO59: 86944004 | BP59: - | BQ59: 5983834871 | BR59: - | BS59: 6070778875 | BT59: 146758558188 | BV59: 68245000000 | BW59: - | BX59: 4648251501 | BY59: 38168897514 | BZ59: -656444657 | CA59: - | CB59: 2669721904 | CC59: 113075426262 | CD59: 259833984450 | CF59: May | DQ59: May | KR59: 4852593255 | LJ59: =LE59+KD59+JZ59+JT59 -> 0
A60: June | B60: 1.3717626e+11 | C60: 1.0963665e+11 | D60: =B60-C60 -> 27539616483 | F60: 1.4465713e+10 | G60: 2644427977 | H60: 154131622 | I60: =SUM(F60:H60) -> 17264272915 | J60: =D60-I60 -> 10275343568 | L60: 2172990663 | M60: 7314174501 | N60: =L60-M60 -> -5141183838 | P60: =J60+N60 -> 5134159730 | T60: =P60-S60 -> 5134159730 | X60: =T60+W60 -> 5134159730 | AD60: 9282558949 | AE60: 64342179664 | AG60: -100319905 | AH60: 8553979090 | AI60: 53146940174 | AL60: 3728106741 | AM60: 5606778405 | AN60: 144560223118 | AP60: - | AQ60: 109344547471 | AR60: 4819671202 | AU60: 1361708691 | AV60: 115525927364 | AW60: 260086150481 | BA60: 23389050206 | BC60: - | BD60: - | BE60: 2929239813 | BF60: 17972973 | BI60: 2249178731 | BK60: 111970858895 | BL60: 140556300617 | BN60: - | BO60: 69680504 | BQ60: 5983834871 | BS60: 6053515375 | BT60: 146609815992 | BV60: 68245000000 | BW60: - | BX60: 5129159730 | BY60: 38088897514 | BZ60: -656444657 | CA60: - | CB60: 2669721904 | CC60: 113476334491 | CD60: 260086150483 | CF60: June | DQ60: June
A61: July | B61: 1.5367608e+11 | C61: 1.2327019e+11 | D61: =B61-C61 -> 30405893330 | F61: 1.6274541e+10 | G61: 2998872307 | H61: 3.8491942e+08 | I61: =SUM(F61:H61) -> 19658332763 | J61: =D61-I61 -> 10747560567 | L61: 2.2035302e+09 | M61: 8.5051266e+09 | N61: =L61-M61 -> -6301596422 | P61: =J61+N61 -> 4445964145 | T61: =P61-S61 -> 4445964145 | X61: =T61+W61 -> 4445964145 | AD61: 9707484302 | AE61: 47857623182 | AG61: -100319905 | AH61: 8277072882 | AI61: 54064469311 | AL61: 5131419450 | AM61: 6361864750 | AN61: 131299613971 | AP61: - | AQ61: 112442055090 | AR61: 4797587279 | AU61: 1361708691 | AV61: 118601351061 | AW61: 249900965032 | BA61: 17110339790 | BC61: 0 | BD61: - | BE61: 2363787873 | BF61: 16500000 | BI61: 2263494684 | BJ61: - | BK61: 111970858895 | BL61: 133724981242 | BN61: 4986517807 | BO61: 52424504 | BP61: - | BQ61: 5983834871 | BR61: - | BS61: 11022777182 | BT61: 144747758424 | BV61: 68245000000 | BW61: - | BX61: 4440964145 | BY61: 38088897514 | BZ61: -656444657 | CA61: - | CB61: 2669721904 | CC61: 112788138906 | CD61: 257535897330 | CF61: July | DQ61: July | DT61: -78820000 | DU61: -243750 | DV61: 153797596984 | DY61: 108006541675 | EA61: 460785000 | EB61: 39941700 | EE61: 1025761034 | EF61: 47486547 | EG61: 63037593 | EH61: 27687823 | EI61: 23200173 | EJ61: 25307012 | EK61: 54402203 | EL61: 92172226 | EM61: 212946196 | EO61: 307699014 | EP61: -6806106 | ER61: 1345144443 | ES61: 256107500 | ET61: 11601398206 | EV61: 73558741 | EW61: 61289761 | EX61: 157070360 | EY61: 844772762 | EZ61: 1813032835 | FA61: 93915671 | FC61: 136423200 | FD61: 311962877 | FE61: 235288037 | FF61: 1900541222 | FG61: 154427380 | FI61: 35744917 | FJ61: 170334253 | FL61: 104167814 | FM61: 132163891 | FO61: 100849006 | FQ61: 193281000000000 | FT61: 1608000 | FU61: 11317000 | FV61: 114234895 | FW61: 46837341 | GM61: 130082545483 | GQ61: 588347906 | GR61: 39406433 | GS61: 42480282 | GT61: 100494252 | GU61: 514310325 | GV61: 215841953 | GW61: 108508599 | GX61: 1229225784 | GY61: 1506986719 | GZ61: 4127515340 | HC61: 137516422 | HF61: 1132314778 | HG61: 189950077 | HH61: 394830706 | HI61: 78878580 | HJ61: 774886067 | HK61: 4491653 | HL61: 6947500 | HN61: 16581312 | HO61: 192435016 | HP61: 45129588 | HQ61: 1572084274 | HR61: 36633700 | HT61: 172057126 | HU61: 280390151 | HV61: 34465470 | HW61: 113597500 | HX61: 310092694 | HY61: 141175335 | HZ61: 22105116 | IA61: 18926917 | IB61: 8340800 | IC61: 59236631 | ID61: 35835607 | IE61: 85788932 | IF61: 20712340 | IG61: 102752056 | IH61: 19802721 | IK61: 140189090 | IL61: 18533975 | IM61: 746788770 | IO61: 157125755 | IP61: 118455700 | IQ61: 2688000 | IS61: 27626235 | IT61: 106196209 | IV61: 97280000 | IX61: 35482500 | JB61: 68205000 | JC61: 354814357 | JD61: 12440000 | JE61: 58532239 | JH61: 30905833 | JI61: 310000 | JJ61: 6500000 | JK61: 32250000 | JT61: 16495400325 | JW61: 1839947921 | JX61: 129509000 | JY61: 25198500 | JZ61: 1994655421 | KC61: 413519909 | KD61: 413519909 | KG61: 51501721 | KH61: 1657035617 | KI61: 473439697 | KJ61: 6705900 | KK61: 26314 | KM61: 12000000 | KN61: 2200709250 | KQ61: 38671127 | KR61: 6706224303 | KT61: 319943377 | KU61: 100000000 | KV61: 337312433 | KW61: 5582 | KY61: 10800100 | KZ61: 880000000 | LA61: 1815000 | LB61: 103260000 | LE61: 8498031922 | LJ61: =LE61+KD61+JZ61+JT61 -> 27401607577
A62: August | B62: 1.8923096e+11 | C62: 1.5149815e+11 | D62: =B62-C62 -> 37732815544 | F62: 1.832173e+10 | G62: 3234791625 | H62: 4.7415742e+08 | I62: =SUM(F62:H62) -> 22030678676 | J62: =D62-I62 -> 15702136868 | L62: 2.3862204e+09 | M62: 9.7379454e+09 | N62: =L62-M62 -> -7351724961 | P62: =J62+N62 -> 8350411907 | T62: =P62-S62 -> 8350411907 | X62: =T62+W62 -> 8350411907 | AD62: 8714244528 | AE62: 42098796324 | AG62: -100319905 | AH62: 8793905498 | AI62: 62063383425 | AL62: 7925004232 | AM62: 9878624436 | AN62: 139373638538 | AP62: - | AQ62: 114755418765 | AR62: 4806836690 | AU62: 1361708691 | AV62: 120923964146 | AW62: 260297602684 | BA62: 21500769351 | BC62: - | BD62: - | BE62: 4870153694 | BF62: 59945946 | BI62: 2195168548 | BJ62: - | BK62: 103973704301 | BL62: 132599741839 | BN62: 4986517807 | BO62: 34921500 | BP62: - | BQ62: 5983834871 | BR62: - | BS62: 11005274178 | BT62: 143605016017 | BV62: 68245000000 | BW62: - | BX62: 8345411907 | BY62: 38088897514 | BZ62: -656444657 | CA62: - | CB62: 2669721904 | CC62: 116692586668 | CD62: 260297602686 | CF62: August | DQ62: August | DR62: 189440525163 | DT62: -209317345 | DU62: -243750 | DV62: 189230964068 | DY62: 134809653663 | EA62: 460785000 | EB62: 51142200 | EE62: 1175858044 | EF62: 48989272 | EG62: 65747982 | EH62: 33048598 | EI62: 23988066 | EJ62: 27076624 | EK62: 61178842 | EL62: 146742200 | EM62: 243554284 | EO62: 349921463 | EP62: -3051700 | ER62: 1570184385 | ES62: 317385000 | ET62: 13582767640 | EV62: 76215816 | EW62: 76649778 | EX62: 178805258 | EY62: 956663898 | EZ62: 2090504104 | FA62: 100482409 | FB62: -1603658 | FC62: 150134575 | FD62: 379556183 | FE62: 274898420 | FF62: 1901106928 | FG62: 181959996 | FI62: 63119917 | FJ62: 217282513 | FL62: 108805069 | FM62: 135547007 | FO62: 127788021 | FQ62: 60273382 | FT62: 1608000 | FU62: 11317000 | FV62: 170752939 | FW62: 61858945 | FY62: 5951250 | GM62: 160294649313 | GQ62: 624156979 | GR62: 117323099 | GS62: 44134982 | GT62: 103843252 | GU62: 595112097 | GV62: 248669519 | GW62: 124192209 | GX62: 1415499098 | GY62: 1793186414 | GZ62: 4673042304 | HC62: 154566635 | HF62: 1132314778 | HG62: 219038735 | HH62: 460611321 | HI62: 82103580 | HJ62: 928229683 | HK62: 4491653 | HL62: 6947500 | HN62: 20726640 | HO62: 241441439 | HP62: 62997496 | HQ62: 1639899751 | HR62: 36633700 | HT62: 190001574 | HU62: 286290151 | HV62: 34731710 | HW62: 113597500 | HX62: 310092694 | HY62: 144795290 | HZ62: 24264404 | IA62: 24589437 | IB62: 9272800 | IC62: 60342831 | ID62: 40327407 | IE62: 97728095 | IF62: 24445434 | IG62: 116008056 | IH62: 22802721 | IK62: 170685124 | IL62: 20117317 | IM62: 834318008 | IO62: 296835755 | IP62: 118455700 | IQ62: 2848000 | IS62: 27626235 | IT62: 180207020 | IV62: 97280000 | IX62: 35482500 | JB62: 95967000 | JC62: 354814357 | JD62: 12440000 | JE62: 62125161 | JH62: 37460417 | JI62: 2410000 | JJ62: 6500000 | JK62: 32250000 | JT62: 18616275562 | JW62: 2167237703 | JX62: 164874820 | JY62: 25198500 | JZ62: 2357311023 | KC62: 525971423 | KD62: 525971423 | KG62: 55690098 | KH62: 1671759152 | KI62: 637217777 | KJ62: 6705900 | KK62: 26536 | KM62: 12000000 | KN62: 2383399462 | KQ62: 44147829 | KR62: 8505102979 | KT62: 357052900 | KU62: 100000000 | KV62: 574422704 | KW62: 7821 | KY62: 100 | KZ62: 880000000 | LB62: 103260000 | LD62: 8306250 | LJ62: =LE62+KD62+JZ62+JT62 -> 21499558008
A63: September | B63: 2.0983519e+11 | C63: 1.6547761e+11 | D63: =B63-C63 -> 44357579700 | F63: 2.0818445e+10 | G63: 3.4684227e+09 | H63: 5.1447652e+08 | I63: =SUM(F63:H63) -> 24801344283 | J63: =D63-I63 -> 19556235417 | L63: 3.400678e+09 | M63: 1.1660353e+10 | N63: =L63-M63 -> -8259674976 | P63: =J63+N63 -> 11296560441 | T63: =P63-S63 -> 11296560441 | X63: =T63+W63 -> 11296560441 | AD63: 13962356696 | AE63: 60984624343 | AG63: -100319905 | AH63: 9076377408 | AI63: 48284077916 | AL63: 3302491968 | AM63: 9481367099 | AN63: 144990975525 | AP63: - | AQ63: 115886894780 | AR63: 4784086100 | AU63: 1361708691 | AV63: 122032689571 | AW63: 267023665096 | BA63: 12940759169 | BC63: - | BD63: - | BE63: 5461165165 | BF63: 61449999 | BI63: 1559438405 | BJ63: - | BK63: 114347942004 | BL63: 134370754742 | BN63: 6999992283 | BO63: 29923000 | BP63: - | BQ63: 5983834871 | BR63: - | BS63: 13013750154 | BT63: 147384504896 | BV63: 68245000000 | BW63: - | BX63: 11291985441 | BY63: 38088897514 | BZ63: -656444657 | CA63: - | CB63: 2669721904 | CC63: 119639160202 | CD63: 267023665098 | CF63: September | DQ63: September | DR63: 210139904128 | DT63: -325268694 | DU63: -243750 | DV63: 209814391684 | DY63: 146946922402 | EA63: 460785000 | EB63: 60469400 | EE63: 1327505513 | EF63: 61143776 | EG63: 69230143 | EH63: 33686023 | EI63: 25282084 | EJ63: 35408079 | EK63: 65696365 | EL63: 153322044 | EM63: 274568087 | EO63: 373574524 | EP63: 58985300 | ER63: 2621134545 | ES63: 451980625 | ET63: 15133496567 | EV63: 81019595 | EW63: 77924939 | EX63: 198616193 | EY63: 1068630684 | EZ63: 1579233779 | FA63: 105527510 | FC63: 171434292 | FD63: 443050239 | FE63: 332891102 | FF63: 1968492650 | FG63: 220764479 | FI63: 72399917 | FJ63: 255984431 | FL63: 134343047 | FM63: 154989623 | FO63: 167705334 | FQ63: 363382 | FT63: 1608000 | FU63: 11317000 | FV63: 179755439 | FW63: 213913197 | FY63: 7951250 | GM63: 175601106557 | GQ63: 880348949 | GR63: 116874999 | GS63: 53890326 | GT63: 141227053 | GU63: 673509351 | GV63: 282125338 | GW63: 139875818 | GX63: 1601752638 | GY63: 2041760876 | GZ63: 5261121037 | HC63: 170424189 | HF63: 1132314778 | HG63: 247901860 | HH63: 524319139 | HI63: 282397480 | HJ63: 1019379677 | HK63: 4780253 | HL63: 26302600 | HN63: 24871968 | HO63: 282570271 | HP63: 73607713 | HQ63: 1758806854 | HR63: 39233700 | HT63: 235660767 | HU63: 312590151 | HV63: 34731710 | HW63: 113597500 | HX63: 310092694 | HY63: 67050575 | HZ63: 27568362 | IA63: 28383937 | IB63: 11108799 | IC63: 63206731 | ID63: 49066137 | IE63: 108942026 | IF63: 28489391 | IG63: 132000356 | IH63: 22932721 | IK63: 198318281 | IL63: 24962353 | IM63: 923004833 | IO63: 446168375 | IP63: 118455700 | IQ63: 3550500 | IS63: 27626235 | IT63: 206783597 | IV63: 97280000 | IX63: 35482500 | JB63: 80662800 | JC63: 354814357 | JD63: 12440000 | JE63: 64775432 | JH63: 44015000 | JI63: 7619550 | JJ63: 6500000 | JK63: 32250000 | JT63: 24399115984 | JW63: 2423479739 | JX63: 188374820 | JY63: 31524700 | JZ63: 2643379259 | KC63: 525196562 | KD63: 525196562 | KG63: 58452980 | KH63: 1911875099 | KI63: 1311131014 | KJ63: 10783300 | KK63: 87240 | KM63: 12000000 | KN63: 3304329632 | KQ63: 51658725 | KR63: 8505102979 | KT63: 398462423 | KU63: 100000000 | KV63: 1455400079 | KW63: 9129 | KZ63: 880000000 | LB63: 103260000 | LD63: 8306250 | LE63: 11502199584 | LJ63: =LE63+KD63+JZ63+JT63 -> 39069891389
A64: October | B64: 2.3136628e+11 | C64: 1.8247086e+11 | D64: =B64-C64 -> 48895420179 | F64: 2.324174e+10 | G64: 4.0284631e+09 | H64: 5.8950066e+08 | I64: =SUM(F64:H64) -> 27859703519 | J64: =D64-I64 -> 21035716660 | L64: 4.9902981e+09 | M64: 1.4301151e+10 | N64: =L64-M64 -> -9310852576 | P64: =J64+N64 -> 11724864084 | T64: =P64-S64 -> 11724864084 | X64: =T64+W64 -> 11724864084 | AD64: 28529710039 | AE64: 46007563485 | AG64: -100319905 | AH64: 10170623902 | AI64: 40327695593 | AL64: 2868744909 | AM64: 7226467375 | AN64: 135030485397 | AP64: - | AQ64: 116536733010 | AR64: 4761335511 | AU64: 1361708691 | AV64: 122659777212 | AW64: 257690262610 | BA64: 7956781710 | BE64: 2991886489 | BF64: 266447333 | BI64: 1546355538 | BK64: 111945719707 | BL64: 124707190777 | BN64: 6906848618 | BO64: 24924500 | BQ64: 5983834871 | BR64: - | BS64: 12915607989 | BT64: 137622798766 | BV64: 68245000000 | BW64: - | BX64: 11720289084 | BY64: 38088897514 | BZ64: -656444657 | CA64: - | CB64: 2669721904 | CC64: 120067463845 | CD64: 257690262611 | CF64: October | DQ64: October | KR64: 10431484129 | LJ64: =LE64+KD64+JZ64+JT64 -> 0
A65: November | B65: 2.4320517e+11 | C65: 1.9285512e+11 | D65: =B65-C65 -> 50350051535 | F65: 2.5544706e+10 | G65: 4.4108666e+09 | H65: 6.2724654e+08 | I65: =SUM(F65:H65) -> 30582818774 | J65: =D65-I65 -> 19767232762 | L65: 7.1433903e+09 | M65: 1.5676596e+10 | N65: =L65-M65 -> -8533205328 | P65: =J65+N65 -> 11234027434 | T65: =P65-S65 -> 11234027434 | X65: =T65+W65 -> 11234027434 | AD65: 20534450597 | AE65: 35517471629 | AG65: -100319905 | AH65: 11224914420 | AI65: 46443048510 | AL65: 5383126703 | AM65: 7497396016 | AN65: 126500087970 | AP65: - | AQ65: 116975846931 | AR65: 4768753672 | AU65: 1361708691 | AV65: 123106309293 | AW65: 249606397263 | BA65: 6837045463 | BC65: - | BD65: - | BE65: 1982081266 | BF65: 211886936 | BI65: 28107609 | BJ65: - | BK65: 106135497635 | BL65: 115194618909 | BN65: 8826815289 | BO65: 19926000 | BP65: - | BQ65: 5983834871 | BR65: - | BS65: 14830576160 | BT65: 130025195070 | BV65: 68245000000 | BW65: - | BX65: 11234027434 | BY65: 38088897514 | BZ65: -656444657 | CA65: - | CB65: 2669721904 | CC65: 119581202195 | CD65: 249606397265 | CF65: November | DQ65: November | KR65: 11384323625 | LJ65: =LE65+KD65+JZ65+JT65 -> 0
A66: December | B66: 248584198721 | C66: 196819803443 | D66: =B66-C66 -> 51764395278 | F66: 29986519436 | G66: 4662752842 | I66: 34649272278 | J66: 17115123000 | L66: 4248871561 | M66: 15513093348 | N66: -11264221787 | P66: 5850901213 | Q66: 2619816448 | R66: 335575531 | S66: 2284240917 | T66: 3566660296 | V66: 114638697 | X66: 3681298993 | AD66: 13453685239 | AE66: 20486932453 | AH66: 12125091334 | AI66: 58866109711 | AL66: 8731412515 | AM66: 4582719436 | AN66: 118245950688 | AP66: - | AQ66: 112900204621 | AR66: 5523726416 | AS66: 299645414 | AT66: 4740907338 | AU66: 1712002771 | AV66: 125176486560 | AW66: 243422437248 | BA66: 10637120798 | BE66: 389939346 | BF66: 269670250 | BG66: 91652875 | BI66: 165256678 | BJ66: - | BK66: 105476695895 | BL66: 117030335842 | BN66: 7176685529 | BO66: 14927500 | BQ66: 7184014624 | BR66: - | BS66: 14375627653 | BT66: 131405963495 | BV66: 68245000000 | BW66: - | BY66: 41334210113 | BZ66: -541805960 | CB66: 2979069600 | CC66: 112016473753 | CD66: 243422437248 | CF66: December | DQ66: December | LJ66: =LE66+KD66+JZ66+JT66 -> 0
A69: Laba Rugi Konsolidasi up to month X in 2023 | AB69: Neraca Konsolidasi up to month x in 2023 | CF69: Arus Kas Konsolidasi up to month X in 2023 | DQ69: Monthly CALK Konsolidasi up to month X 2023
B70: Penjualan | C70: Harga Pokok Penjualan | D70: Laba Kotor | E70: Beban Usaha | F70: Beban Umum dan Administrasi | G70: Beban Penjualan dan Pemasaran | H70: Beban Analisa Lab | I70: Jumlah Beban Usaha | J70: Laba Usaha | K70: Pendapatan (Beban) Lain-lain | L70: Pendapatan Lain-lain | M70: Beban Diluar Usaha Lainnya | N70: Jumlah Pendapatan (Beban) Lain-lain | P70: Laba Sebelum Pajak | Q70: Beban Pajak Penghasilan (Pajak Kini) | R70: Pajak tangguhan | S70: Jumlah Beban Pajak | T70: Laba Bersih Setelah Pajak | U70: Penghasilan Komprehensif Lain | V70: Keuntungan/Kerugian aktuarial | W70: atas liabilitas imbalan kerja | X70: Jumlah Penghasilan (Rugi) Komprehensif Lain | AB70: ASET | AC70: Aset Lancar | AD70: Kas dan Setara Kas | AE70: Piutang Usaha | AF70: Anjak Piutang | AG70: Cadangan Kerugian Piutang Tak Tertagih | AH70: Piutang Lain Pihak Terkait | AI70: Persediaan | AJ70: Persediaan dalam Proses | AK70: Persediaan Barang Dagang | AL70: Biaya Dibayar Dimuka | AM70: Pajak Dibayar Dimuka | AN70: Jumlah Aset Lancar | AO70: Aset Tidak Lancar | AP70: Investasi | AQ70: Aset Tetap | AR70: Aset Tidak Lancar Lainnya | AS70: Aset tidak berwujud - bersih | AT70: Pekerjaan dalam proses konstruksi | AU70: Aset Pajak Tangguhan | AV70: Jumlah Aset Tidak Lancar | AW70: Jumlah Aset | AY70: LIABILITAS DAN EKUITAS | AZ70: Liabilitas Lancar | BA70: Hutang Usaha | BC70: Barang yang belum terinvoice | BD70: Persediaan Barang Diterima Belum di BAST (LPB) | BE70: Hutang Pajak | BF70: Uang Muka Penjualan | BG70: Akrual | BH70: Pendapatan diterima dimuka | BI70: Hutang Lain-Lain | BJ70: Hutang Bunga Bank | BK70: Hutang Bank Jangka Pendek | BL70: Jumlah Liabilitas Lancar | BM70: Liabilitas Tidak Lancar | BN70: Hutang Bank Jangka Panjang | BO70: Hutang Leasing | BP70: Hutang Pemegang Saham | BQ70: Hutang Imbalan Pasca Kerja | BR70: Liabilitas pajak tangguhan | BS70: Jumlah Liabilitas Tidak Lancar | BT70: Jumlah Liabilitas | BU70: Ekuitas | BV70: Modal Disetor | BW70: Saldo Laba | BX70: Laba-Rugi Periode Berjalan | BY70: Laba-Rugi Ditahan | BZ70: Akumulasi penghasilan komprehensif lain | CA70: Kepentingan non pengendali - Rugi/Laba | CB70: Kepentingan non pengendali - Modal | CC70: Jumlah Ekuitas | CD70: Jumlah Liabilitas dan Ekuitas | CG70: Arus Kas dari Aktivitas Operasi | CH70: Laba (rugi) bersih | CI70: Penyesuaian : | CJ70: Penyusutan | CK70: Akumulasi Komprehensif Lain | CM70: Penurunan (Kenaikan) : | CN70: Piutang usaha | CO70: Anjak Piutang | CP70: Piutang Afiliasi & Lainnya | CQ70: Biaya dibayar dimuka | CR70: Pajak dibayar dimuka | CS70: Persediaan | CT70: Kenaikan (Penurunan) : | CU70: Utang Usaha | CV70: Hutang Afiliasi & Lainnya | CW70: Utang Pajak | CX70: Uang Muka Penjualan | CY70: Biaya yg masih harus dibayar | CZ70: Hutang jangka Panjang | DA70: Kas Bersih yang digunakan untuk Aktivitas Operasi | DB70: Arus Kas dari Aktivitas Investasi : | DC70: (Penambahan) Pengurangan Aset Tetap | DD70: (Penambahan) Pengurangan Investasi | DE70: (Penambahan) Pengurangan Konstruksi Dalam Pengerjaan | DF70: Kas Bersih yang diperoleh/ digunakan untuk Aktivitas Investasi | DG70: Arus Kas dari Aktivitas Pendanaan : | DH70: Utang Bank | DI70: Modal di setor | DJ70: Kas Bersih yang diperoleh/ digunakan untuk Aktivitas Pendanaan | DK70: Kenaikan Kas & Setara Kas | DL70: Kas & Setara Kas awal periode | DM70: Kas & Setara Kas akhir periode | DR70: Penjualan Afiliasi | DS70: Penjualan Non Afiliasi | DT70: Retur Penjualan | DU70: Diskon Penjualan | DV70: Jumlah Penjualan | DX70: BEBAN POKOK PENJUALAN | DY70: Harga Pokok Penjualan | DZ70: Harga Pokok Penjualan Non Afiliasi | EA70: Beban Bea Masuk Import | EB70: Beban Clearance Impor | EC70: Potongan Pembelian | ED70: Retur Pembelian | EE70: Beban Penyusutan Mesin | EF70: Beban Pemeliharaan Mesin Ew | EG70: Beban Pemeliharaan Mesin Line 1 | EH70: Beban Pemeliharaan Mesin Line 2 | EI70: Beban Pemeliharaan Mesin Line 3 | EJ70: Beban Pemeliharaan Mesin Line 4 | EK70: Beban Pemeliharaan Mesin Line 5 | EL70: Beban Pemeliharaan Mesin Copper Sulphate | EM70: Beban Penyusutan Peralatan Pabrik | EN70: Beban Pemeliharaan Mesin Mixing | EO70: Beban Sewa Kendaraan | EP70: Selisih Stock Opname | EQ70: Selisih Timbang | ER70: Beban Tenaga Kerja Langsung | ES70: Beban Transportasi Bahan Baku | ET70: Beban Transportasi Produk Jadi | EV70: Beban Pemeliharaan Kendaraan Pabrik | EW70: Beban Pemeliharaan Aset Pabrik | EX70: Beban Rumah Tangga Pabrik | EY70: Beban Gaji Staff Pabrik | EZ70: Beban Tenaga Kerja Tidak Langsung | FA70: Beban Pemeliharaan Mesin Pramaterial | FB70: Beban Operasional | FC70: Beban Listrik Pabrik | FD70: Beban Listrik Pabrik (Gudang Timur) | FE70: Beban Listrik Pabrik (Tengah) | FF70: Beban Transportasi Lainnya | FG70: Beban Perlengkapan Pabrik | FH70: Beban Telepon Pabrik | FI70: Beban Bbm Pabrik | FJ70: Beban Bongkar | FK70: Beban Qc Produk | FL70: Beban Transportasi Impor | FM70: Beban Gudang Pelabuhan | FN70: Beban Administrasi Pabean | FO70: Beban Muat | FP70: Beban Royalti Merk | FQ70: Beban Klaim | FR70: Beban Gaji PHL | FS70: Beban Operasional Kebun | FT70: Beban Perlengkapan Kebun | FU70: Beban Bbm Kebun | FV70: Beban Asuransi Pengiriman | FW70: Beban Sample | FX70: Beban Demplot | FY70: Beban Jasa Maklon | FZ70: Beban Pemeliharaan Bangunan Pabrik | GA70: Beban Pemeliharaan Sarana Prasarana Pabrik | GB70: Beban Perlengkapan Mekanik | GC70: Beban Perlengkapan Elektrikal | GD70: Beban Pemeliharaan Mesin Crf | GE70: Beban Riset Dan Percobaan Lapangan | GF70: Beban Pemeliharaan Mesin Copper Sulphate Line 2 | GG70: Beban Pemeliharaan Aset Lab | GH70: Beban Operasional Gudang | GI70: Beban Uji Dosis (Internal) | GJ70: Beban Perlengkapan Lab | GK70: Beban Kerugian Bibit Afkir | GL70: Beban Pemeliharaan Mesin NPK | GM70: Jumlah Harga Pokok Penjualan | GO70: BEBAN UMUM DAN ADMINISTRASI | GP70: Beban Administrasi Dan Umum | GQ70: Beban Pelatihan | GR70: Beban Pelatihan Internal | GS70: Beban Perlengkapan Kantor | GT70: Beban Hse | GU70: Beban Penyusutan Kendaraan | GV70: Beban Penyusutan Inventaris Kantor | GW70: Beban Amortisasi Ditangguhkan SHGB | GX70: Beban Penyusutan Bangunan | GY70: Beban Gaji BOD | GZ70: Beban Gaji Staff Kantor | HA70: Beban Tunjangan Keluarga | HB70: Bebang Tunjangan Kemahalan | HC70: Tunjangan Lembur | HD70: Beban Tunjangan Kinerja | HE70: Beban Bonus | HF70: Tunjangan Hari Raya - THR | HG70: Beban Asuransi - BPJS KES | HH70: Beban Asuransi - BPJS TK | HI70: Beban Pemeliharaan Aset Kantor | HJ70: Beban Rumah Tangga Kantor | HK70: Beban Pengembangan System/Software | HL70: Beban Kompensasi Ganti Rugi | HM70: Beban Koreksi Fiskal | HN70: Beban Asuransi Kebakaran | HO70: Beban Pemeliharaan Kendaraan Kantor | HP70: Beban Bbm Kantor | HQ70: Beban Perjalanan Dinas Kantor | HR70: Beban Perjalanan Dinas Tamu | HS70: Beban Obat/Pengobatan | HT70: Beban Sewa | HU70: Biaya Legal Dan Perijinan | HV70: Beban Rakor | HW70: Beban Audit | HX70: Beban Perayaan Hari Besar | HY70: Beban Atk Kantor | HZ70: Beban Internet/Vsat | IA70: Beban Cetak/Fotocopy | IB70: Beban Air Minum Kantor | IC70: Beban Konsumsi Dan Oleh-Oleh Tamu | ID70: Beban Kirim Paket (Sampel/Dokumen) | IE70: Beban Listrik Kantor | IF70: Beban Telepon Kantor | IG70: Pajak Kendaraan & PBB | IH70: Beban Suka/Duka | II70: Beban Bunga Imbalan Kerja | IJ70: Beban Kerugian Aktuaria | IK70: Beban Pph 4 Ayat 2 | IL70: Beban Pph Pasal 23 | IM70: Beban Pph Pasal 21 | IN70: Beban Pph 25 | IO70: Beban Pinalti Pajak | IP70: Beban Pph Pasal 29 | IQ70: Beban Olahraga Dan Rekreasi | IR70: Biaya Kaizen | IS70: Beban Pemutusan Hubungan Kerja | IT70: Beban Apraisal | IU70: Beban Konsultan Keuangan | IV70: Beban Bphtb | IW70: Beban Kerugian Investasi | IX70: Beban Apresiasi Karyawan | IY70: Beban Imbalan Pasca Kerja | IZ70: Beban Notaris | JA70: Beban Gaji Staff Laboratorium | JB70: Beban Csr (Corporate Social Responsibility) | JC70: Beban Cadangan Kerugian Piutang Tak Tertagih | JD70: Beban Brand Development | JE70: Beban Ppn Tidak Bisa Dikreditkan | JF70: Beban Operasional Direksi | JG70: Beban Asuransi Managemen | JH70: Beban Penyusutan Software | JI70: Beban Rekrutmen | JJ70: Beban Rups | JK70: Beban Aktuaria | JL70: Beban Riset Corporate & Strategy | JM70: Beban Gaji Managemen | JN70: Beban Gaji Principal | JO70: Beban Sarana Prasarana Kantor | JP70: Beban Outsourcing | JQ70: Biaya Pemeliharaan Bangunan Kantor | JR70: Beban Beasiswa | JS70: Beban Kesejahteraan Karyawan | JT70: Jumlah Beban Administrasi dan Umum | JV70: BEBAN PENJUALAN DAN PEMASARAN | JW70: Beban Operasional Pemasaran | JX70: Beban Relasi | JY70: Beban Promosi | JZ70: Jumlah Beban Penjualan dan Pemasaran | KB70: BEBAN ANALISA LAB | KC70: Beban Analisa Lab | KD70: Jumlah Analisa Lab | KF70: PENDAPATAN | KG70: Pendapatan Jasa Giro | KH70: Pendapatan Lain-Lain | KI70: Pendapatan Selisih Lebih Kurs | KJ70: Pendapatan Aval | KK70: Pendapatan Selisih Koma | KL70: Pendapatan Klaim | KM70: Pendapatan Jasa Maklon | KN70: Jumlah Pendapatan | KP70: BEBAN DILUAR USAHA | KQ70: Beban Adm Bank | KR70: Beban Marjin Pinjaman | KT70: Beban Administrasi Kredit - Mk | KU70: Beban Pengikatan Kredit | KV70: Beban Selisih Kurang Kurs | KW70: Beban Selisih Koma | KX70: Beban Market Place | KY70: Beban Lain-Lain | KZ70: Beban Zakat | LA70: Beban Infak | LB70: Beban Qurban | LC70: Beban Administrasi Kredit - LC/SKBDN | LD70: Beban Kerugian Penjualan Aset | LE70: Jumlah Beban Diluar Usaha | LG70: PAJAK PENGHASILAN | LH70: Beban Pajak Penghasilan | LI70: Jumlah Pajak Penghasilan | LJ70: Jumlah Beban
A71: January | B71: 1.4402405e+10 | C71: 1.1338011e+10 | D71: =B71-C71 -> 3064393327 | F71: 1962242313 | G71: 580833939 | I71: =SUM(F71:H71) -> 2543076252 | J71: =D71-I71 -> 5.2131707e+08 | L71: 1.5922322e+08 | M71: 7.0911344e+08 | N71: =L71-M71 -> -5.4989022e+08 | P71: =J71+N71 -> -28573141 | T71: =P71-S71 -> -28573141 | X71: =T71-W71 -> -28573141 | AD71: 29481353313 | AE71: 34826715531 | AG71: -2963308220 | AH71: 14814138402 | AI71: 45954281520 | AL71: 9886089919 | AM71: 2414988217 | AN71: 152648391197 | AP71: - | AQ71: 27434369327 | AR71: 193650142 | AU71: 898449450 | AV71: 28526468919 | AW71: 181174860116 | BA71: 36626395187 | BC71: 1759103024 | BD71: - | BE71: 3379852846 | BF71: 357927000 | BI71: 8092318165 | BJ71: - | BK71: 90372709582 | BL71: 140588305803 | BN71: - | BO71: 129766000 | BQ71: 4348075409 | BR71: 1686636 | BS71: 4479528045 | BT71: 145067833848 | BV71: 1290000000 | BX71: -28573141 | BY71: 34906015399 | BZ71: -60415989 | CC71: 36107026269 | CD71: 181174860117 | CF71: January | DQ71: January | GM71: 1.1338011e+10 | LJ71: =LE71+KD71+JZ71+JT71 -> 0
A72: February | B72: 3.6607209e+10 | C72: 2.9409341e+10 | D72: =B72-C72 -> 7197867378 | F72: 3.6788788e+09 | G72: 916754623 | I72: =SUM(F72:H72) -> 4595633452 | J72: =D72-I72 -> 2602233926 | L72: 6.2140595e+08 | M72: 1.4294484e+09 | N72: =L72-M72 -> -8.0804249e+08 | P72: =J72+N72 -> 1794191433 | T72: =P72-S72 -> 1794191433 | X72: =T72-W72 -> 1794191433 | AD72: 25069927710 | AE72: 32690399579 | AG72: -2963308220 | AH72: 8692719065 | AI72: 51411790508 | AJ72: - | AL72: 11650816318 | AM72: 5062950646 | AN72: 145543153807 | AP72: - | AQ72: 27633590302 | AR72: 191795975 | AU72: 898449450 | AV72: 28723835727 | AW72: 174266989534 | BA72: 35849529904 | BC72: 3473013315 | BD72: - | BE72: 4713596312 | BF72: 181000000 | BI72: 1591309071 | BJ72: - | BK72: 86054213046 | BL72: 131862661648 | BN72: - | BO72: 124775000 | BQ72: 4348075409 | BR72: 1686636 | BS72: 4474537045 | BT72: 136337198693 | BV72: 1290000000 | BX72: 1794191433 | BY72: 34906015399 | BZ72: -60415989 | CC72: 37929790843 | CD72: 174266989535 | CF72: February | DQ72: February | GM72: 2.9409341e+10 | LJ72: =LE72+KD72+JZ72+JT72 -> 0
A73: March | B73: 6.8420097e+10 | C73: 5.4123563e+10 | D73: =B73-C73 -> 14296533751 | F73: 5.2594776e+09 | G73: 1168795421 | I73: =SUM(F73:H73) -> 6428273006 | J73: =D73-I73 -> 7868260745 | L73: 9.9828005e+08 | M73: 2.1595119e+09 | N73: =L73-M73 -> -1161231801 | P73: =J73+N73 -> 6707028944 | T73: =P73-S73 -> 6707028944 | X73: =T73-W73 -> 6707028944 | AD73: 7925524372 | AE73: 53782365654 | AG73: -2963308220 | AH73: 12239926323 | AI73: 45250987781 | AJ73: - | AL73: 5215476319 | AM73: 6740695048 | AN73: 138882765477 | AP73: - | AQ73: 32353833078 | AR73: 189941808 | AU73: 898449450 | AV73: 33442224336 | AW73: 172324989814 | BA73: 22752231823 | BC73: 980201960 | BD73: - | BE73: - | BF73: - | BI73: 12032157640 | BJ73: - | BK73: 88939901995 | BL73: 124704493418 | BN73: - | BO73: 428106000 | BQ73: 4348075409 | BR73: 1686636 | BS73: 4777868045 | BT73: 129482361463 | BV73: 1290000000 | BX73: 6707028944 | BY73: 34906015399 | BZ73: -60415989 | CC73: 42842628354 | CD73: 172324989816 | CF73: March | DQ73: March | GM73: 5.4123563e+10 | LJ73: =LE73+KD73+JZ73+JT73 -> 0
A74: April | B74: 8.3535132e+10 | C74: 6.6838638e+10 | D74: =B74-C74 -> 16696494182 | F74: 8.0477671e+09 | G74: 1645342312 | I74: =SUM(F74:H74) -> 9693109422 | J74: =D74-I74 -> 7003384760 | L74: 8.6148964e+08 | M74: 3.0045125e+09 | N74: =L74-M74 -> -2143022898 | P74: =J74+N74 -> 4860361862 | T74: =P74-S74 -> 4860361862 | X74: =T74-W74 -> 4860361862 | AD74: 12162345378 | AE74: 49542929512 | AG74: -2963308220 | AH74: 12783796671 | AI74: 45468724513 | AL74: 2704538066 | AM74: 4264356710 | AN74: 134654480830 | AQ74: 35031892774 | AR74: 188087641 | AU74: 898449450 | AV74: 36118429865 | AW74: 170772910695 | BA74: 25908061111 | BC74: 885158378 | BD74: - | BE74: 1664719458 | BF74: - | BI74: 8301058658 | BJ74: - | BK74: 87266237773 | BL74: 124025235378 | BN74: - | BO74: 1401952000 | BQ74: 4348075409 | BR74: 1686636 | BS74: 5751714045 | BT74: 129776949423 | BV74: 1290000000 | BW74: - | BX74: 4860361862 | BY74: 34906015399 | BZ74: -60415989 | CC74: 40995961272 | CD74: 170772910695 | CF74: April | DQ74: April | GM74: 6.6838638e+10 | LJ74: =LE74+KD74+JZ74+JT74 -> 0
A75: May | B75: 117100934967 | C75: 95494274588 | D75: =B75-C75 -> 21606660379 | F75: 11512587399 | G75: 1991057304 | I75: =SUM(F75:H75) -> 13503644703 | J75: =D75-I75 -> 8103015676 | L75: 1062474148 | M75: 4579799622 | N75: =L75-M75 -> -3517325474 | P75: =J75+N75 -> 4585690202 | T75: =P75-S75 -> 4585690202 | X75: =T75-W75 -> 4585690202 | AD75: 18945355182 | AE75: 55650638564 | AG75: -2963308219 | AH75: 10069593637 | AI75: 37864128561 | AJ75: - | AL75: 5953334328 | AM75: 5602616765 | AN75: 133307171820 | AP75: - | AQ75: 85928062615 | AR75: 186233474 | AU75: 898449450 | AV75: 87012745539 | AW75: 220319917359 | BA75: 31365498145 | BC75: 1196192968 | BD75: - | BE75: - | BF75: - | BI75: 6490892239 | BJ75: - | BK75: 85505688351 | BL75: 124558271703 | BN75: - | BO75: 354635000 | BQ75: 4348075409 | BR75: 1686636 | BS75: 4704397045 | BT75: 129262668748 | BV75: 51625959000 | BW75: - | BX75: 4585690201 | BY75: 34906015399 | BZ75: -60415989 | CC75: 91057248611 | CD75: 220319917359 | CF75: May | DQ75: May | GM75: 95494274588 | LJ75: =LE75+KD75+JZ75+JT75 -> 0
A76: June | B76: 127045606747 | C76: 98941704459 | D76: =B76-C76 -> 28103902288 | F76: 13288207681 | G76: 2544845940 | I76: =SUM(F76:H76) -> 15833053621 | J76: =D76-I76 -> 12270848667 | L76: 940147855 | M76: 5414574879 | N76: =L76-M76 -> -4474427024 | P76: =J76+N76 -> 7796421643 | T76: =P76-S76 -> 7796421643 | X76: =T76-W76 -> 7796421643 | AD76: 23564993228 | AE76: 43070377221 | AG76: -2963308220 | AH76: 9373377584 | AI76: 45489827177 | AL76: 15695096786 | AM76: 5616313773 | AN76: 142619380681 | AQ76: 85803608759 | AR76: 184379307 | AU76: 898449450 | AV76: 86886437516 | AW76: 229505818197 | BA76: 30937785964 | BC76: 1133556711 | BD76: - | BE76: 2844741160 | BF76: - | BI76: 73374004 | BJ76: - | BK76: 95577004260 | BL76: 130566462099 | BN76: - | BO76: 321614000 | BQ76: 4348075409 | BR76: 1686636 | BS76: 4671376045 | BT76: 135237838144 | BV76: 51625959000 | BX76: 7796421643 | BY76: 34906015399 | BZ76: -60415989 | CC76: 94267980053 | CD76: 229505818197 | CF76: June | DQ76: June | GM76: 98941704459 | LJ76: =LE76+KD76+JZ76+JT76 -> 0
A77: July | B77: 1.4922428e+11 | C77: 1.182656e+11 | D77: =B77-C77 -> 30958679646 | F77: 1.624467e+10 | G77: 2673809299 | H77: 4.2544167e+08 | I77: =SUM(F77:H77) -> 19343920576 | J77: =D77-I77 -> 11614759070 | L77: 8.1146962e+08 | M77: 6.3762155e+09 | N77: =L77-M77 -> -5564745865 | P77: =J77+N77 -> 6050013205 | T77: =P77-S77 -> 6050013205 | X77: =T77-W77 -> 6050013205 | AD77: 7004815965 | AE77: 41239046214 | AG77: -2963308220 | AH77: 10240438548 | AI77: 56251006695 | AJ77: - | AL77: 4445764310 | AM77: 7982238646 | AN77: 126972705289 | AQ77: 87194481127 | AR77: 7470830 | AU77: 898449450 | AV77: 88100401407 | AW77: 215073106696 | BA77: 26074050226 | BC77: 5490240752 | BD77: - | BE77: 3765377219 | BF77: - | BI77: 21571366 | BJ77: - | BK77: 82561940467 | BL77: 117913180030 | BN77: - | BO77: 288593000 | BQ77: 4348075409 | BR77: 1686636 | BS77: 4638355045 | BT77: 122551535075 | BV77: 51625959000 | BW77: - | BX77: 6050013205 | BY77: 34906015399 | BZ77: -60415989 | CC77: 92521571615 | CD77: 215073106690 | CF77: July | DQ77: July | DV77: 149224284170 | DY77: 104648193837 | EE77: 544017673 | EM77: 190113644 | EZ77: 1324632784 | FO77: 63090365 | GM77: 1.182656e+11 | GU77: 348092139 | GV77: 133147019 | GX77: 437794705 | KR77: 5023642322 | LJ77: =LE77+KD77+JZ77+JT77 -> 0
A78: August | B78: 1.7820963e+11 | C78: 1.4010609e+11 | D78: =B78-C78 -> 38103545916 | F78: 1.8772026e+10 | G78: 3429412838 | H78: 4.636164e+08 | I78: =SUM(F78:H78) -> 22665055403 | J78: =D78-I78 -> 15438490514 | L78: 1.1385184e+09 | M78: 7.0872911e+09 | N78: =L78-M78 -> -5948772710 | P78: =J78+N78 -> 9489717804 | T78: =P78-S78 -> 9489717804 | X78: =T78-W78 -> 9489717804 | AD78: 5693624614 | AE78: 49100263429 | AG78: -296117767 | AH78: 10540306517 | AI78: 47142888085 | AJ78: - | AL78: 3457826166 | AM78: 7913394377 | AN78: 126324888551 | AQ78: 111729233374 | AR78: 6812497 | AU78: 898449450 | AV78: 112634495321 | AW78: 238959383872 | BA78: 24384952453 | BC78: 1132396797 | BD78: - | BE78: 4516531172 | BF78: - | BI78: 23650450 | BJ78: - | BK78: 82109838245 | BL78: 112167369117 | BN78: - | BO78: 1480976504 | BQ78: 4348075409 | BR78: 1686636 | BS78: 5830738549 | BT78: 117998107666 | BV78: 76625959000 | BW78: - | BX78: 9489717803 | BY78: 34906015399 | BZ78: -60415989 | CC78: 120961276213 | CD78: 238959383879 | CF78: August | DQ78: August | DV78: 178209633207 | DY78: 140106087292 | EA78: 1017297000 | EB78: 154464800 | EE78: 667978709 | EF78: 23531368 | EG78: 5473326 | EH78: 19894802 | EI78: 28404679 | EJ78: 7934987 | EK78: 24022627 | EL78: 19997067 | EM78: 211037346 | EO78: 129900000 | ER78: 1396597781 | ES78: 842861750 | ET78: 5465167712 | EV78: 24684547 | EW78: 468805433 | EX78: 51761844 | EY78: 1107504000 | EZ78: 1521647021 | FB78: 248473189 | FC78: 203060642 | FD78: 266889652 | FE78: 61631363 | FF78: 30017070 | FG78: 196273074 | FI78: 39931000 | FJ78: 127034631 | FL78: 464424121 | FM78: - | FN78: 847871 | FO78: 71722365 | FP78: - | FQ78: 540529859 | FV78: 29976550 | GE78: 62390592 | GJ78: 67296814 | GM78: 1.4010609e+11 | GQ78: 266424359 | GR78: 12995030 | GT78: 45286397 | HH78: 315719739 | HS78: 17024404 | HX78: 136750775 | IC78: 193219392 | JW78: 3019650912 | JX78: 283862600 | JY78: 62840155 | JZ78: 3429412838 | LJ78: =LE78+KD78+JZ78+JT78 -> 3429412838
A79: September | B79: 195956481653 | C79: 154651513232 | D79: =B79-C79 -> 41304968421 | F79: 18258626106 | G79: 3936534346 | H79: 491730146 | I79: =SUM(F79:H79) -> 22686890598 | J79: =D79-I79 -> 18618077823 | L79: 1391757628 | M79: 7863693238 | N79: =L79-M79 -> -6471935610 | P79: =J79+N79 -> 12146142213 | T79: =P79-S79 -> 12146142213 | X79: =T79-W79 -> 12146142213 | AD79: 8557378107 | AE79: 51930090325 | AG79: -296117767 | AH79: 11142831009 | AI79: 47915792594 | AJ79: - | AL79: 5012848938 | AM79: 7819077468 | AN79: 134854603805 | AP79: 98000000 | AQ79: 112145199869 | AR79: 2852725223 | AU79: 898449450 | AV79: 115994374542 | AW79: 250848978348 | BA79: 22554384782 | BC79: 3095595174 | BD79: - | BE79: 3582659951 | BF79: - | BI79: 178469655 | BJ79: - | BK79: 93119406023 | BL79: 122530515584 | BN79: - | BO79: 357713004 | BQ79: 4348075409 | BR79: 1686636 | BS79: 4707475049 | BT79: 127237990633 | BV79: 76625959000 | BW79: - | BX79: 12146142214 | BY79: 34899302493 | BZ79: -60415989 | CC79: 123610987718 | CD79: 250848978351 | CF79: September | DQ79: September | DV79: 196160417477 | DY79: 154651513233 | EA79: 1017297000 | EB79: 158028400 | EE79: 792516378 | EF79: 38942516 | EG79: 19482481 | EH79: 72849201 | EI79: 30509500 | EL79: 77262331 | EM79: 238296412 | EO79: 194100000 | ER79: 1521461444 | ES79: 871761750 | ET79: 6399539741 | EV79: 26389839 | EW79: 548151836 | EX79: 54016748 | EY79: 1249621835 | EZ79: 1721335198 | FB79: 272728753 | FC79: 222863075 | FD79: 293579565 | FE79: 100978942 | FF79: 32361770 | FG79: 209961021 | FI79: 108546988 | FJ79: 134698381 | FL79: 472053067 | FN79: 847871 | FO79: 75418865 | FQ79: 115755951 | FV79: 72436550 | GE79: 491730146 | GJ79: 69739814 | GM79: 154651513232 | GQ79: 355747573 | GT79: 60903528 | GU79: 465739615 | GV79: 183495396 | GW79: 9523799 | GX79: 15072220 | GY79: 2151984269 | GZ79: 5587445630 | JA79: 477032380 | JW79: 3440538445 | JX79: 327636575 | JY79: 62840155 | JZ79: 3936534346 | KG79: 60501629 | KH79: 507490652 | KI79: 167755883 | KJ79: 51153555 | KK79: 561656870 | KN79: 1391757629 | KQ79: 44733360 | KR79: 6452262326 | LJ79: =LE79+KD79+JZ79+JT79 -> 3936534346
A80: October | B80: 2.1789279e+11 | C80: 1.6755693e+11 | D80: =B80-C80 -> 50335863028 | F80: 2.2386894e+10 | G80: 5019955998 | H80: 5.528061e+08 | I80: =SUM(F80:H80) -> 27959656421 | J80: =D80-I80 -> 22376206607 | L80: 1.5893333e+09 | M80: 8.8622486e+09 | N80: =L80-M80 -> -7272915242 | P80: =J80+N80 -> 15103291364 | T80: =P80-S80 -> 15103291364 | X80: =T80-W80 -> 15103291364 | AD80: 4196530883 | AE80: 50915720363 | AG80: -296117767 | AH80: 8165784699 | AI80: 56212848031 | AJ80: - | AL80: 10689330286 | AM80: 9471578708 | AN80: 142128378332 | AP80: 98000000 | AQ80: 113498414411 | AR80: 3842568100 | AU80: 898449450 | AV80: 118337431961 | AW80: 260465810293 | BA80: 23323943945 | BC80: 2380068225 | BD80: - | BE80: 4386320693 | BF80: 135135135 | BI80: 910486005 | BJ80: - | BK80: 99289483801 | BL80: 130425437804 | BN80: - | BO80: 300162004 | BQ80: 4348075409 | BR80: 1686636 | BS80: 4649924049 | BT80: 135075361853 | BV80: 76210959000 | BW80: - | BX80: 2886254086 | BY80: 46353651338 | BZ80: -60415989 | CC80: 125390448435 | CD80: 260465810288 | CF80: October | DQ80: October | GM80: 1.6755693e+11 | LJ80: =LE80+KD80+JZ80+JT80 -> 0
A81: November | B81: 2.3433637e+11 | C81: 1.7784567e+11 | D81: =B81-C81 -> 56490707517 | F81: 2.3855057e+10 | G81: 5366264360 | H81: 5.8592766e+08 | I81: =SUM(F81:H81) -> 29807248728 | J81: =D81-I81 -> 26683458789 | L81: 1.61363e+09 | M81: 9.8979127e+09 | N81: =L81-M81 -> -8284282707 | P81: =J81+N81 -> 18399176081 | T81: =P81-S81 -> 18399176081 | X81: =T81-W81 -> 18399176081 | AD81: 7877481283 | AE81: 59052811590 | AG81: -296117767 | AH81: 9085119352 | AI81: 60763378161 | AJ81: - | AL81: 5243378416 | AM81: 10430848753 | AN81: 152156899788 | AP81: 98000000 | AQ81: 122594520199 | AR81: 5036225563 | AU81: 898449450 | AV81: 128627195212 | AW81: 280784094999 | BA81: 23558447946 | BC81: 1532511635 | BD81: - | BE81: 4892835138 | BF81: - | BI81: 1677209543 | BJ81: - | BK81: 106467558448 | BL81: 138128562710 | BN81: - | BO81: 281437004 | BQ81: 4348075409 | BR81: 1686636 | BS81: 4631199049 | BT81: 142759761759 | BV81: 85548959000 | BW81: - | BX81: 2612395682 | BY81: 49923394542 | BZ81: -60415989 | CC81: 138024333234 | CD81: 280784094993 | CF81: November | DQ81: November | GM81: 1.7784567e+11 | LJ81: =LE81+KD81+JZ81+JT81 -> 0
A82: December | B82: 257719040082 | C82: 203902207541 | D82: 53816832541 | F82: 26048269354 | G82: 5871257642 | I82: 31919526996 | J82: 21897305545 | L82: 4256275161 | M82: 13006137121 | N82: -8749861960 | P82: 13147443585 | Q82: 3235883452 | R82: 296276853 | S82: 2939606599 | T82: 10207836986 | V82: 592028467 | W82: 76003816 | X82: 9691812335 | AD82: 6773805638 | AE82: 61963843139 | AH82: 8603757128 | AI82: 60746621522 | AJ82: - | AL82: 2800477844 | AM82: 6179246991 | AN82: 147067752262 | AP82: - | AQ82: 106234728383 | AR82: 4275801822 | AS82: 206811997 | AT82: 1172804848 | AU82: 1361708691 | AV82: 113251855741 | AW82: 260319608003 | BA82: 22581638056 | BE82: 2969233204 | BG82: 103663459 | BI82: 2523762420 | BK82: 117588446227 | BL82: 145766743366 | BN82: -- | BO82: 221855004 | BQ82: 5983834871 | BS82: 6205689875 | BT82: 151972433241 | BV82: 68245000000 | BW82: - | BX82: 3217491839 | BY82: 38088897515 | BZ82: -656444657 | CA82: - | CB82: 2669721904 | CC82: 108347174762 | CD82: 260319608003 | CF82: December | DQ82: December | GM82: 203902207541 | LJ82: =LE82+KD82+JZ82+JT82 -> 0
A85: Laba Rugi Konsolidasi up to month X in 2022 | AB85: Neraca Konsolidasi up to month x in 2022 | CF85: Arus Kas Konsolidasi up to month X in 2022 | DQ85: Monthly CALK Konsolidasi up to month X 2022
B86: Penjualan | C86: Harga Pokok Penjualan | D86: Laba Kotor | E86: Beban Usaha | F86: Beban Umum dan Administrasi | G86: Beban Penjualan dan Pemasaran | H86: Beban Analisa Lab | I86: Jumlah Beban Usaha | J86: Laba Usaha | K86: Pendapatan (Beban) Lain-lain | L86: Pendapatan Lain-lain | M86: Beban Diluar Usaha Lainnya | N86: Jumlah Pendapatan (Beban) Lain-lain | P86: Laba Sebelum Pajak | Q86: Beban Pajak Penghasilan (Pajak Kini) | R86: Pajak tangguhan | S86: Jumlah Beban Pajak | T86: Laba Bersih Setelah Pajak | U86: Penghasilan Komprehensif Lain | V86: Keuntungan/Kerugian aktuarial | W86: atas liabilitas imbalan kerja | X86: Jumlah Penghasilan (Rugi) Komprehensif Lain | AB86: ASET | AC86: Aset Lancar | AD86: Kas dan Setara Kas | AE86: Piutang Usaha | AF86: Anjak Piutang | AG86: Cadangan Kerugian Piutang Tak Tertagih | AH86: Piutang Lain Pihak Terkait | AI86: Persediaan | AJ86: Persediaan dalam Proses | AK86: Persediaan Barang Dagang | AL86: Biaya Dibayar Dimuka | AM86: Pajak Dibayar Dimuka | AN86: Jumlah Aset Lancar | AO86: Aset Tidak Lancar | AP86: Investasi | AQ86: Aset Tetap | AR86: Aset Tidak Lancar Lainnya | AS86: Aset tidak berwujud - bersih | AT86: Pekerjaan dalam proses konstruksi | AU86: Aset Pajak Tangguhan | AV86: Jumlah Aset Tidak Lancar | AW86: Jumlah Aset | AY86: LIABILITAS DAN EKUITAS | AZ86: Liabilitas Lancar | BA86: Hutang Usaha | BC86: Barang yang belum terinvoice | BD86: Persediaan Barang Diterima Belum di BAST (LPB) | BE86: Hutang Pajak | BF86: Uang Muka Penjualan | BG86: Akrual | BH86: Pendapatan diterima dimuka | BI86: Hutang Lain-Lain | BJ86: Hutang Bunga Bank | BK86: Hutang Bank Jangka Pendek | BL86: Jumlah Liabilitas Lancar | BM86: Liabilitas Tidak Lancar | BN86: Hutang Bank Jangka Panjang | BO86: Hutang Leasing | BP86: Hutang Pemegang Saham | BQ86: Hutang Imbalan Pasca Kerja | BR86: Liabilitas pajak tangguhan | BS86: Jumlah Liabilitas Tidak Lancar | BT86: Jumlah Liabilitas | BU86: Ekuitas | BV86: Modal Disetor | BW86: Saldo Laba | BX86: Laba-Rugi Periode Berjalan | BY86: Laba-Rugi Ditahan | BZ86: Akumulasi penghasilan komprehensif lain | CA86: Kepentingan non pengendali - Rugi/Laba | CB86: Kepentingan non pengendali - Modal | CC86: Jumlah Ekuitas | CD86: Jumlah Liabilitas dan Ekuitas | CG86: Arus Kas dari Aktivitas Operasi | CH86: Laba (rugi) bersih | CI86: Penyesuaian : | CJ86: Penyusutan | CK86: Akumulasi Komprehensif Lain | CM86: Penurunan (Kenaikan) : | CN86: Piutang usaha | CO86: Anjak Piutang | CP86: Piutang Afiliasi & Lainnya | CQ86: Biaya dibayar dimuka | CR86: Pajak dibayar dimuka | CS86: Persediaan | CT86: Kenaikan (Penurunan) : | CU86: Utang Usaha | CV86: Hutang Afiliasi & Lainnya | CW86: Utang Pajak | CX86: Uang Muka Penjualan | CY86: Biaya yg masih harus dibayar | CZ86: Hutang jangka Panjang | DA86: Kas Bersih yang digunakan untuk Aktivitas Operasi | DB86: Arus Kas dari Aktivitas Investasi : | DC86: (Penambahan) Pengurangan Aset Tetap | DD86: (Penambahan) Pengurangan Investasi | DE86: (Penambahan) Pengurangan Konstruksi Dalam Pengerjaan | DF86: Kas Bersih yang diperoleh/ digunakan untuk Aktivitas Investasi | DG86: Arus Kas dari Aktivitas Pendanaan : | DH86: Utang Bank | DI86: Modal di setor | DJ86: Kas Bersih yang diperoleh/ digunakan untuk Aktivitas Pendanaan | DK86: Kenaikan Kas & Setara Kas | DL86: Kas & Setara Kas awal periode | DM86: Kas & Setara Kas akhir periode | DR86: Penjualan Afiliasi | DS86: Penjualan Non Afiliasi | DT86: Retur Penjualan | DU86: Diskon Penjualan | DV86: Jumlah Penjualan | DX86: BEBAN POKOK PENJUALAN | DY86: Harga Pokok Penjualan Afiliasi | DZ86: Harga Pokok Penjualan Non Afiliasi | EA86: Beban Bea Masuk Import | EB86: Beban Clearance Impor | EC86: Potongan Pembelian | ED86: Retur Pembelian | EE86: Beban Penyusutan Mesin | EF86: Beban Pemeliharaan Mesin Ew | EG86: Beban Pemeliharaan Mesin Line 1 | EH86: Beban Pemeliharaan Mesin Line 2 | EI86: Beban Pemeliharaan Mesin Line 3 | EJ86: Beban Pemeliharaan Mesin Line 4 | EK86: Beban Pemeliharaan Mesin Line 5 | EL86: Beban Pemeliharaan Mesin Copper Sulphate | EM86: Beban Penyusutan Peralatan Pabrik | EN86: Beban Pemeliharaan Mesin Mixing | EO86: Beban Sewa Kendaraan | EP86: Selisih Stock Opname | EQ86: Selisih Timbang | ER86: Beban Tenaga Kerja Langsung | ES86: Beban Transportasi Bahan Baku | ET86: Beban Transportasi Produk Jadi | EV86: Beban Pemeliharaan Kendaraan Pabrik | EW86: Beban Pemeliharaan Aset Pabrik | EX86: Beban Rumah Tangga Pabrik | EY86: Beban Gaji Staff Pabrik | EZ86: Beban Tenaga Kerja Tidak Langsung | FA86: Beban Pemeliharaan Mesin Pramaterial | FB86: Beban Operasional | FC86: Beban Listrik Pabrik | FD86: Beban Listrik Pabrik (Gudang Timur) | FE86: Beban Listrik Pabrik (Tengah) | FF86: Beban Transportasi Lainnya | FG86: Beban Perlengkapan Pabrik | FH86: Beban Telepon Pabrik | FI86: Beban Bbm Pabrik | FJ86: Beban Bongkar | FK86: Beban Qc Produk | FL86: Beban Transportasi Impor | FM86: Beban Gudang Pelabuhan | FN86: Beban Administrasi Pabean | FO86: Beban Muat | FP86: Beban Royalti Merk | FQ86: Beban Klaim | FR86: Beban Gaji PHL | FS86: Beban Operasional Kebun | FT86: Beban Perlengkapan Kebun | FU86: Beban Bbm Kebun | FV86: Beban Asuransi Pengiriman | FW86: Beban Sample | FX86: Beban Demplot | FY86: Beban Jasa Maklon | FZ86: Beban Pemeliharaan Bangunan Pabrik | GA86: Beban Pemeliharaan Sarana Prasarana Pabrik | GB86: Beban Perlengkapan Mekanik | GC86: Beban Perlengkapan Elektrikal | GD86: Beban Pemeliharaan Mesin Crf | GE86: Beban Riset Dan Percobaan Lapangan | GF86: Beban Pemeliharaan Mesin Copper Sulphate Line 2 | GG86: Beban Pemeliharaan Aset Lab | GH86: Beban Operasional Gudang | GI86: Beban Uji Dosis (Internal) | GJ86: Beban Perlengkapan Lab | GK86: Beban Kerugian Bibit Afkir | GL86: Beban Pemeliharaan Mesin NPK | GM86: Jumlah Harga Pokok Penjualan | GO86: BEBAN UMUM DAN ADMINISTRASI | GP86: Beban Administrasi Dan Umum | GQ86: Beban Pelatihan | GR86: Beban Pelatihan Internal | GS86: Beban Perlengkapan Kantor | GT86: Beban Hse | GU86: Beban Penyusutan Kendaraan | GV86: Beban Penyusutan Inventaris Kantor | GW86: Beban Amortisasi Ditangguhkan SHGB | GX86: Beban Penyusutan Bangunan | GY86: Beban Gaji BOD | GZ86: Beban Gaji Staff Kantor | HA86: Beban Tunjangan Keluarga | HB86: Bebang Tunjangan Kemahalan | HC86: Tunjangan Lembur | HD86: Beban Tunjangan Kinerja | HE86: Beban Bonus | HF86: Tunjangan Hari Raya - THR | HG86: Beban Asuransi - BPJS KES | HH86: Beban Asuransi - BPJS TK | HI86: Beban Pemeliharaan Aset Kantor | HJ86: Beban Rumah Tangga Kantor | HK86: Beban Pengembangan System/Software | HL86: Beban Kompensasi Ganti Rugi | HM86: Beban Koreksi Fiskal | HN86: Beban Asuransi Kebakaran | HO86: Beban Pemeliharaan Kendaraan Kantor | HP86: Beban Bbm Kantor | HQ86: Beban Perjalanan Dinas Kantor | HR86: Beban Perjalanan Dinas Tamu | HS86: Beban Obat/Pengobatan | HT86: Beban Sewa | HU86: Biaya Legal Dan Perijinan | HV86: Beban Rakor | HW86: Beban Audit | HX86: Beban Perayaan Hari Besar | HY86: Beban Atk Kantor | HZ86: Beban Internet/Vsat | IA86: Beban Cetak/Fotocopy | IB86: Beban Air Minum Kantor | IC86: Beban Konsumsi Dan Oleh-Oleh Tamu | ID86: Beban Kirim Paket (Sampel/Dokumen) | IE86: Beban Listrik Kantor | IF86: Beban Telepon Kantor | IG86: Pajak Kendaraan & PBB | IH86: Beban Suka/Duka | II86: Beban Bunga Imbalan Kerja | IJ86: Beban Kerugian Aktuaria | IK86: Beban Pph 4 Ayat 2 | IL86: Beban Pph Pasal 23 | IM86: Beban Pph Pasal 21 | IN86: Beban Pph 25 | IO86: Beban Pinalti Pajak | IP86: Beban Pph Pasal 29 | IQ86: Beban Olahraga Dan Rekreasi | IR86: Biaya Kaizen | IS86: Beban Pemutusan Hubungan Kerja | IT86: Beban Apraisal | IU86: Beban Konsultan Keuangan | IV86: Beban Bphtb | IW86: Beban Kerugian Investasi | IX86: Beban Apresiasi Karyawan | IY86: Beban Imbalan Pasca Kerja | IZ86: Beban Notaris | JA86: Beban Gaji Staff Laboratorium | JB86: Beban Csr (Corporate Social Responsibility) | JC86: Beban Cadangan Kerugian Piutang Tak Tertagih | JD86: Beban Brand Development | JE86: Beban Ppn Tidak Bisa Dikreditkan | JF86: Beban Operasional Direksi | JG86: Beban Asuransi Managemen | JH86: Beban Penyusutan Software | JI86: Beban Rekrutmen | JJ86: Beban Rups | JK86: Beban Aktuaria | JL86: Beban Riset Corporate & Strategy | JM86: Beban Gaji Managemen | JN86: Beban Gaji Principal | JO86: Beban Sarana Prasarana Kantor | JP86: Beban Outsourcing | JQ86: Biaya Pemeliharaan Bangunan Kantor | JR86: Beban Beasiswa | JS86: Beban Kesejahteraan Karyawan | JT86: Jumlah Beban Administrasi dan Umum | JV86: BEBAN PENJUALAN DAN PEMASARAN | JW86: Beban Operasional Pemasaran | JX86: Beban Relasi | JY86: Beban Promosi | JZ86: Jumlah Beban Penjualan dan Pemasaran | KB86: BEBAN ANALISA LAB | KC86: Beban Analisa Lab | KD86: Jumlah Analisa Lab | KF86: PENDAPATAN | KG86: Pendapatan Jasa Giro | KH86: Pendapatan Lain-Lain | KI86: Pendapatan Selisih Lebih Kurs | KJ86: Pendapatan Aval | KK86: Pendapatan Selisih Koma | KL86: Pendapatan Klaim | KM86: Pendapatan Jasa Maklon | KN86: Jumlah Pendapatan | KP86: BEBAN DILUAR USAHA | KQ86: Beban Adm Bank | KR86: Beban Marjin Pinjaman | KT86: Beban Administrasi Kredit - Mk | KU86: Beban Pengikatan Kredit | KV86: Beban Selisih Kurang Kurs | KW86: Beban Selisih Koma | KX86: Beban Market Place | KY86: Beban Lain-Lain | KZ86: Beban Zakat | LA86: Beban Infak | LB86: Beban Qurban | LC86: Beban Administrasi Kredit - LC/SKBDN | LD86: Beban Kerugian Penjualan Aset | LE86: Jumlah Beban Diluar Usaha | LG86: PAJAK PENGHASILAN | LH86: Beban Pajak Penghasilan | LI86: Jumlah Pajak Penghasilan | LJ86: Jumlah Beban
A87: January | CF87: January | DQ87: January
A88: February | CF88: February | DQ88: February
A89: March | CF89: March | DQ89: March
A90: April | CF90: April | DQ90: April
A91: May | CF91: May | DQ91: May
A92: June | CF92: June | DQ92: June
A93: July | CF93: July | DQ93: July
A94: August | CF94: August | DQ94: August
A95: September | CF95: September | DQ95: September
A96: October | CF96: October | DQ96: October
A97: November | CF97: November | DQ97: November
A98: December | B98: 284561861389 | C98: -218011356270 | D98: 66550505119 | E98: -12032172861 | F98: -27466314457 | J98: 27052017801 | L98: 3233317723 | M98: -16238268902 | N98: -13004951179 | P98: 14047066622 | Q98: -4912641992 | R98: 879722406 | S98: -4032919586 | T98: 10014147036 | U98: -60415989 | X98: 9953731047 | AD98: 30395708480 | AE98: 53144410766 | AH98: 6276716575 | AI98: 45477484262 | AL98: 10040843554 | AM98: 4968299386 | AP98: 1700000000 | AQ98: 25793737156 | AS98: 195504309 | AT98: 1176828294 | AU98: 896762814 | AV98: 29762832573 | AW98: 180066295596 | BA98: 36643819128 | BE98: 6431205767 | BG98: 61400000 | BI98: 683106458 | BL98: 43819531353 | BN98: 94286048804 | BO98: 134757000 | BQ98: 4348075410 | BS98: 98768881214 | BT98: 142588412567 | BV98: 1000000000 | BW98: 34919471652 | BZ98: -60415989 | CA98: 1618827366 | CC98: 37477883029 | CD98: 180066295596 | CF98: December | CG98: 2597819082 | DK98: 4921918506 | DL98: 25473789974 | DM98: 30395708480 | DQ98: December | DV98: 284561861389 | EA98: 3591618000 | EE98: 865612588 | EY98: 12894909608 | FB98: 7431197081 | FF98: 54781345 | FQ98: 515792775 | GQ98: 4432445317 | II98: 234824900 | IJ98: 9256546 | IW98: 896346000 | JC98: 2963308218 | JY98: 56421020 | KI98: 2494060197 | KJ98: 67127060 | KK98: 82670 | KM98: 284110000 | KQ98: 54276141 | KR98: 9219810208 | KV98: 1146847624 | KZ98: 1146847624 | LA98: 250203068 | LB98: 108000000 | LH98: 1145405419
A101: Laba Rugi Konsolidasi up to month X in 2021 | AB101: Neraca Konsolidasi up to month x in 2021 | CF101: Arus Kas Konsolidasi up to month X in 2021 | DQ101: Monthly CALK Konsolidasi up to month X 2021
